Workbook

Sheet Dashboard
A1: RETIREMENT DASHBOARD — 30-Year, 3-Bucket Plan (Age 62 → 92)
B3: Key Metrics
B4: Total Corpus Today (Gold ₹1Cr + Cash ₹1Cr) | E4: Monthly Income — Year 1 | H4: Safe Withdrawal Rate — Year 1
B5: =Corpus -> 20000000 | E5: =MonthlyExp -> 50000 | H5: =(MonthlyExp*12)/Corpus -> 0.03
B7: Retirement Duration | E7: Current Age → Age at Year 30 | H7: Inflation Rate Assumed
B8: =RetYears -> 30 | E8: =Age&" → "&(Age+RetYears) -> 62 → 92 | H8: =Inflation -> 0.07
B10: Bucket 1 Initial (Yrs 1-5, Liquid/FD) | E10: Bucket 2 Initial (Yrs 6-15, Debt/Hybrid) | H10: Bucket 3 Initial (Yrs 16-30, Equity+Gold)
B11: =Corpus*B1Pct -> 3000000 | E11: =Corpus*B2Pct -> 7000000 | H11: =Corpus*B3Pct -> 10000000
B13: Projected Corpus after 30 Years | E13: Overall Plan Health (Year 30) | H13: Avg. Withdrawal Rate (30-yr avg)
B14: ='Annual Summary'!J31 -> 1.957027e+08 | E14: ='Annual Summary'!L31 -> GREEN | H14: =AVERAGE('Annual Summary'!K2:K31) -> 0.027506031
B16: Charts
B17: See charts below — Corpus Growth · Nominal vs Real Income · Bucket Balances · Withdrawal vs Return

Sheet Advisor Mode
A1: ADVISOR MODE — Change these values, the entire plan updates automatically
B3: Change ONLY the yellow cells below. Every sheet in this workbook
B4: (Dashboard, 30-Year Engine, Scenarios, Monte Carlo) recalculates from these.
B6: Current Age (yrs) | C6: 62 | E6: Named ranges used across workbook: Age, Corpus, MonthlyExp, Inflation, GrowthReturn, RetYears
B7: Total Retirement Corpus, ₹ (Gold ₹1 Cr + Cash ₹1 Cr) | C7: 20000000
B8: Desired Monthly Expense — today's value, ₹ | C8: 50000
B9: Expected Inflation Rate | C9: 0.07
B10: Expected Return — Growth/Equity Bucket (Bucket 3) | C10: 0.11
B11: Retirement Duration (Years) | C11: 30
B13: These 5 (+ age) are the ONLY cells you should ever need to touch:
B14: 1) Total Corpus 2) Monthly Expense 3) Inflation 4) Expected Return 5) Retirement Years
B17: Example: if your corpus grows from ₹2 Cr to ₹3 Cr in future, just update C7 — Bucket splits,
B18: the 30-year cash-flow, scenarios and Monte Carlo results will all re-size automatically.

Sheet Assumptions
A1: ASSUMPTIONS — 3-Bucket Allocation, Returns & Scenario Settings
B3: Bucket Allocation (% of Total Corpus) — editable
B4: Bucket 1 — Income Bucket (Yrs 1-5) % | C4: 0.15
B5: Bucket 2 — Refill Bucket (Yrs 6-15) % | C5: 0.35
B6: Bucket 3 — Growth Bucket (Yrs 16-30) % | C6: 0.5
B7: Check — must equal 100% | C7: =C4+C5+C6 -> 1
B9: Bucket Return Offsets vs Growth Rate (Advisor Mode C10) — editable
B10: Bucket 1 offset (Liquid/FD, safest) | C10: -0.04
B11: Bucket 2 offset (Debt/Hybrid) | C11: -0.02
B12: Bucket 3 offset (Equity + Gold, full growth rate) | C12: 0
B14: Resulting Bucket Returns (calculated, linked to Advisor Mode)
B15: Bucket 1 Return p.a. (FD / Liquid Fund) | C15: =GrowthReturn+C10 -> 0.07
B16: Bucket 2 Return p.a. (Debt / Hybrid Fund) | C16: =GrowthReturn+C11 -> 0.09
B17: Bucket 3 Return p.a. (Equity + Gold) | C17: =GrowthReturn+C12 -> 0.11
B19: Bucket Refill Schedule (fixed, per your design)
B20: Bucket 2 → Bucket 1 refills at End of Year | C20: 5, 10, 15, 20, 25
B21: Bucket 3 → Bucket 2 refills at End of Year | C21: 15, 20, 25
B22: Bucket 1 always holds ~5 years of expenses in reserve
B24: Scenario Analysis — Return Delta Applied to Blended Portfolio
B25: Weak / Bad Market Case — return delta | C25: -0.02
B26: Expected / Normal Case — return delta | C26: 0
B27: Best Case — return delta | C27: 0.02
B29: Monte Carlo Volatility Assumptions (std. deviation p.a.) — editable
B30: Bucket 1 Std. Deviation | C30: 0.01
B31: Bucket 2 Std. Deviation | C31: 0.05
B32: Bucket 3 Std. Deviation | C32: 0.16
B34: Safe Withdrawal Rate (SWR) Health-Check Bands
B35: Green: Annual Withdrawal / Opening Corpus ≤ | C35: 0.04
B36: Yellow: up to | C36: 0.06
B37: Red: above Yellow threshold
B39: → See 'Instrument Guide' sheet for which actual instruments to hold in each Bucket.

Sheet Monthly Engine
A1: Month | B1: Year | C1: Age | D1: Monthly Expense (inflated) | E1: B1 Opening | F1: B1 Return | G1: B1 Withdrawal | H1: Transfer Trigger Amt | I1: B1 Transfer In | J1: B1 Closing | K1: B2 Opening | L1: B2 Return | M1: B2 Transfer Out | N1: B2 Transfer In | O1: B2 Closing | P1: B3 Opening | Q1: B3 Return | R1: B3 Transfer Out | S1: B3 Closing | T1: Total Corpus
A2: 1 | B2: =ROUNDUP(A2/12,0) -> 1 | C2: =Age+B2-1 -> 62 | D2: =MonthlyExp*(1+Inflation)^(B2-1) -> 50000 | E2: =Corpus*B1Pct -> 3000000 | F2: =E2*B1Ret/12 -> 17500 | G2: =D2 -> 50000 | H2: 0 | I2: =H2 -> 0 | J2: =E2+F2-G2+I2 -> 2967500 | K2: =Corpus*B2Pct -> 7000000 | L2: =K2*B2Ret/12 -> 52500 | M2: =-I2 -> 0 | N2: 0 | O2: =K2+L2+M2+N2 -> 7052500 | P2: =Corpus*B3Pct -> 10000000 | Q2: =P2*B3Ret/12 -> 91666.667 | R2: =-N2 -> 0 | S2: =P2+Q2+R2 -> 10091667 | T2: =J2+O2+S2 -> 20111667
A3: 2 | B3: =ROUNDUP(A3/12,0) -> 1 | C3: =Age+B3-1 -> 62 | D3: =MonthlyExp*(1+Inflation)^(B3-1) -> 50000 | E3: =J2 -> 2967500 | F3: =E3*B1Ret/12 -> 17310.417 | G3: =D3 -> 50000 | H3: 0 | I3: =H3 -> 0 | J3: =E3+F3-G3+I3 -> 2934810.4 | K3: =O2 -> 7052500 | L3: =K3*B2Ret/12 -> 52893.75 | M3: =-I3 -> 0 | N3: 0 | O3: =K3+L3+M3+N3 -> 7105393.8 | P3: =S2 -> 10091667 | Q3: =P3*B3Ret/12 -> 92506.944 | R3: =-N3 -> 0 | S3: =P3+Q3+R3 -> 10184174 | T3: =J3+O3+S3 -> 20224378
A4: 3 | B4: =ROUNDUP(A4/12,0) -> 1 | C4: =Age+B4-1 -> 62 | D4: =MonthlyExp*(1+Inflation)^(B4-1) -> 50000 | E4: =J3 -> 2934810.4 | F4: =E4*B1Ret/12 -> 17119.727 | G4: =D4 -> 50000 | H4: 0 | I4: =H4 -> 0 | J4: =E4+F4-G4+I4 -> 2901930.1 | K4: =O3 -> 7105393.8 | L4: =K4*B2Ret/12 -> 53290.453 | M4: =-I4 -> 0 | N4: 0 | O4: =K4+L4+M4+N4 -> 7158684.2 | P4: =S3 -> 10184174 | Q4: =P4*B3Ret/12 -> 93354.925 | R4: =-N4 -> 0 | S4: =P4+Q4+R4 -> 10277529 | T4: =J4+O4+S4 -> 20338143
A5: 4 | B5: =ROUNDUP(A5/12,0) -> 1 | C5: =Age+B5-1 -> 62 | D5: =MonthlyExp*(1+Inflation)^(B5-1) -> 50000 | E5: =J4 -> 2901930.1 | F5: =E5*B1Ret/12 -> 16927.926 | G5: =D5 -> 50000 | H5: 0 | I5: =H5 -> 0 | J5: =E5+F5-G5+I5 -> 2868858.1 | K5: =O4 -> 7158684.2 | L5: =K5*B2Ret/12 -> 53690.132 | M5: =-I5 -> 0 | N5: 0 | O5: =K5+L5+M5+N5 -> 7212374.3 | P5: =S4 -> 10277529 | Q5: =P5*B3Ret/12 -> 94210.678 | R5: =-N5 -> 0 | S5: =P5+Q5+R5 -> 10371739 | T5: =J5+O5+S5 -> 20452972
A6: 5 | B6: =ROUNDUP(A6/12,0) -> 1 | C6: =Age+B6-1 -> 62 | D6: =MonthlyExp*(1+Inflation)^(B6-1) -> 50000 | E6: =J5 -> 2868858.1 | F6: =E6*B1Ret/12 -> 16735.005 | G6: =D6 -> 50000 | H6: 0 | I6: =H6 -> 0 | J6: =E6+F6-G6+I6 -> 2835593.1 | K6: =O5 -> 7212374.3 | L6: =K6*B2Ret/12 -> 54092.808 | M6: =-I6 -> 0 | N6: 0 | O6: =K6+L6+M6+N6 -> 7266467.1 | P6: =S5 -> 10371739 | Q6: =P6*B3Ret/12 -> 95074.276 | R6: =-N6 -> 0 | S6: =P6+Q6+R6 -> 10466813 | T6: =J6+O6+S6 -> 20568874
A7: 6 | B7: =ROUNDUP(A7/12,0) -> 1 | C7: =Age+B7-1 -> 62 | D7: =MonthlyExp*(1+Inflation)^(B7-1) -> 50000 | E7: =J6 -> 2835593.1 | F7: =E7*B1Ret/12 -> 16540.96 | G7: =D7 -> 50000 | H7: 0 | I7: =H7 -> 0 | J7: =E7+F7-G7+I7 -> 2802134 | K7: =O6 -> 7266467.1 | L7: =K7*B2Ret/12 -> 54498.504 | M7: =-I7 -> 0 | N7: 0 | O7: =K7+L7+M7+N7 -> 7320965.6 | P7: =S6 -> 10466813 | Q7: =P7*B3Ret/12 -> 95945.79 | R7: =-N7 -> 0 | S7: =P7+Q7+R7 -> 10562759 | T7: =J7+O7+S7 -> 20685859
A8: 7 | B8: =ROUNDUP(A8/12,0) -> 1 | C8: =Age+B8-1 -> 62 | D8: =MonthlyExp*(1+Inflation)^(B8-1) -> 50000 | E8: =J7 -> 2802134 | F8: =E8*B1Ret/12 -> 16345.782 | G8: =D8 -> 50000 | H8: 0 | I8: =H8 -> 0 | J8: =E8+F8-G8+I8 -> 2768479.8 | K8: =O7 -> 7320965.6 | L8: =K8*B2Ret/12 -> 54907.242 | M8: =-I8 -> 0 | N8: 0 | O8: =K8+L8+M8+N8 -> 7375872.9 | P8: =S7 -> 10562759 | Q8: =P8*B3Ret/12 -> 96825.293 | R8: =-N8 -> 0 | S8: =P8+Q8+R8 -> 10659585 | T8: =J8+O8+S8 -> 20803937
A9: 8 | B9: =ROUNDUP(A9/12,0) -> 1 | C9: =Age+B9-1 -> 62 | D9: =MonthlyExp*(1+Inflation)^(B9-1) -> 50000 | E9: =J8 -> 2768479.8 | F9: =E9*B1Ret/12 -> 16149.466 | G9: =D9 -> 50000 | H9: 0 | I9: =H9 -> 0 | J9: =E9+F9-G9+I9 -> 2734629.3 | K9: =O8 -> 7375872.9 | L9: =K9*B2Ret/12 -> 55319.047 | M9: =-I9 -> 0 | N9: 0 | O9: =K9+L9+M9+N9 -> 7431191.9 | P9: =S8 -> 10659585 | Q9: =P9*B3Ret/12 -> 97712.859 | R9: =-N9 -> 0 | S9: =P9+Q9+R9 -> 10757297 | T9: =J9+O9+S9 -> 20923119
A10: 9 | B10: =ROUNDUP(A10/12,0) -> 1 | C10: =Age+B10-1 -> 62 | D10: =MonthlyExp*(1+Inflation)^(B10-1) -> 50000 | E10: =J9 -> 2734629.3 | F10: =E10*B1Ret/12 -> 15952.004 | G10: =D10 -> 50000 | H10: 0 | I10: =H10 -> 0 | J10: =E10+F10-G10+I10 -> 2700581.3 | K10: =O9 -> 7431191.9 | L10: =K10*B2Ret/12 -> 55733.94 | M10: =-I10 -> 0 | N10: 0 | O10: =K10+L10+M10+N10 -> 7486925.9 | P10: =S9 -> 10757297 | Q10: =P10*B3Ret/12 -> 98608.56 | R10: =-N10 -> 0 | S10: =P10+Q10+R10 -> 10855906 | T10: =J10+O10+S10 -> 21043413
A11: 10 | B11: =ROUNDUP(A11/12,0) -> 1 | C11: =Age+B11-1 -> 62 | D11: =MonthlyExp*(1+Inflation)^(B11-1) -> 50000 | E11: =J10 -> 2700581.3 | F11: =E11*B1Ret/12 -> 15753.391 | G11: =D11 -> 50000 | H11: 0 | I11: =H11 -> 0 | J11: =E11+F11-G11+I11 -> 2666334.7 | K11: =O10 -> 7486925.9 | L11: =K11*B2Ret/12 -> 56151.944 | M11: =-I11 -> 0 | N11: 0 | O11: =K11+L11+M11+N11 -> 7543077.8 | P11: =S10 -> 10855906 | Q11: =P11*B3Ret/12 -> 99512.472 | R11: =-N11 -> 0 | S11: =P11+Q11+R11 -> 10955418 | T11: =J11+O11+S11 -> 21164831
A12: 11 | B12: =ROUNDUP(A12/12,0) -> 1 | C12: =Age+B12-1 -> 62 | D12: =MonthlyExp*(1+Inflation)^(B12-1) -> 50000 | E12: =J11 -> 2666334.7 | F12: =E12*B1Ret/12 -> 15553.619 | G12: =D12 -> 50000 | H12: 0 | I12: =H12 -> 0 | J12: =E12+F12-G12+I12 -> 2631888.3 | K12: =O11 -> 7543077.8 | L12: =K12*B2Ret/12 -> 56573.084 | M12: =-I12 -> 0 | N12: 0 | O12: =K12+L12+M12+N12 -> 7599650.9 | P12: =S11 -> 10955418 | Q12: =P12*B3Ret/12 -> 100424.67 | R12: =-N12 -> 0 | S12: =P12+Q12+R12 -> 11055843 | T12: =J12+O12+S12 -> 21287382
A13: 12 | B13: =ROUNDUP(A13/12,0) -> 1 | C13: =Age+B13-1 -> 62 | D13: =MonthlyExp*(1+Inflation)^(B13-1) -> 50000 | E13: =J12 -> 2631888.3 | F13: =E13*B1Ret/12 -> 15352.682 | G13: =D13 -> 50000 | H13: 0 | I13: =H13 -> 0 | J13: =E13+F13-G13+I13 -> 2597241 | K13: =O12 -> 7599650.9 | L13: =K13*B2Ret/12 -> 56997.382 | M13: =-I13 -> 0 | N13: 0 | O13: =K13+L13+M13+N13 -> 7656648.3 | P13: =S12 -> 11055843 | Q13: =P13*B3Ret/12 -> 101345.23 | R13: =-N13 -> 0 | S13: =P13+Q13+R13 -> 11157188 | T13: =J13+O13+S13 -> 21411078
A14: 13 | B14: =ROUNDUP(A14/12,0) -> 2 | C14: =Age+B14-1 -> 63 | D14: =MonthlyExp*(1+Inflation)^(B14-1) -> 53500 | E14: =J13 -> 2597241 | F14: =E14*B1Ret/12 -> 15150.572 | G14: =D14 -> 53500 | H14: 0 | I14: =H14 -> 0 | J14: =E14+F14-G14+I14 -> 2558891.6 | K14: =O13 -> 7656648.3 | L14: =K14*B2Ret/12 -> 57424.862 | M14: =-I14 -> 0 | N14: 0 | O14: =K14+L14+M14+N14 -> 7714073.1 | P14: =S13 -> 11157188 | Q14: =P14*B3Ret/12 -> 102274.23 | R14: =-N14 -> 0 | S14: =P14+Q14+R14 -> 11259463 | T14: =J14+O14+S14 -> 21532427
... A60: 59 | B60: =ROUNDUP(A60/12,0) -> 5 | C60: =Age+B60-1 -> 66 | D60: =MonthlyExp*(1+Inflation)^(B60-1) -> 65539.8 | E60: =J59 -> 302341.63 | F60: =E60*B1Ret/12 -> 1763.6595 | G60: =D60 -> 65539.8 | H60: 0 | I60: =H60 -> 0 | J60: =E60+F60-G60+I60 -> 238565.49 | K60: =O59 -> 10797202 | L60: =K60*B2Ret/12 -> 80979.014 | M60: =-I60 -> 0 | N60: 0 | O60: =K60+L60+M60+N60 -> 10878181 | P60: =S59 -> 16976495 | Q60: =P60*B3Ret/12 -> 155617.87 | R60: =-N60 -> 0 | S60: =P60+Q60+R60 -> 17132113 | T60: =J60+O60+S60 -> 28248859
A61: 60 | B61: =ROUNDUP(A61/12,0) -> 5 | C61: =Age+B61-1 -> 66 | D61: =MonthlyExp*(1+Inflation)^(B61-1) -> 65539.8 | E61: =J60 -> 238565.49 | F61: =E61*B1Ret/12 -> 1391.632 | G61: =D61 -> 65539.8 | H61: =MAX(SUM(D62:D121)-(E61+F61-G61),0) -> 4665008 | I61: =H61 -> 4665008 | J61: =E61+F61-G61+I61 -> 4839425.4 | K61: =O60 -> 10878181 | L61: =K61*B2Ret/12 -> 81586.356 | M61: =-I61 -> -4665008 | N61: 0 | O61: =K61+L61+M61+N61 -> 6294759.1 | P61: =S60 -> 17132113 | Q61: =P61*B3Ret/12 -> 157044.37 | R61: =-N61 -> 0 | S61: =P61+Q61+R61 -> 17289157 | T61: =J61+O61+S61 -> 28423342
A62: 61 | B62: =ROUNDUP(A62/12,0) -> 6 | C62: =Age+B62-1 -> 67 | D62: =MonthlyExp*(1+Inflation)^(B62-1) -> 70127.587 | E62: =J61 -> 4839425.4 | F62: =E62*B1Ret/12 -> 28229.981 | G62: =D62 -> 70127.587 | H62: 0 | I62: =H62 -> 0 | J62: =E62+F62-G62+I62 -> 4797527.8 | K62: =O61 -> 6294759.1 | L62: =K62*B2Ret/12 -> 47210.694 | M62: =-I62 -> 0 | N62: 0 | O62: =K62+L62+M62+N62 -> 6341969.8 | P62: =S61 -> 17289157 | Q62: =P62*B3Ret/12 -> 158483.94 | R62: =-N62 -> 0 | S62: =P62+Q62+R62 -> 17447641 | T62: =J62+O62+S62 -> 28587139
A63: 62 | B63: =ROUNDUP(A63/12,0) -> 6 | C63: =Age+B63-1 -> 67 | D63: =MonthlyExp*(1+Inflation)^(B63-1) -> 70127.587 | E63: =J62 -> 4797527.8 | F63: =E63*B1Ret/12 -> 27985.579 | G63: =D63 -> 70127.587 | H63: 0 | I63: =H63 -> 0 | J63: =E63+F63-G63+I63 -> 4755385.8 | K63: =O62 -> 6341969.8 | L63: =K63*B2Ret/12 -> 47564.774 | M63: =-I63 -> 0 | N63: 0 | O63: =K63+L63+M63+N63 -> 6389534.6 | P63: =S62 -> 17447641 | Q63: =P63*B3Ret/12 -> 159936.71 | R63: =-N63 -> 0 | S63: =P63+Q63+R63 -> 17607578 | T63: =J63+O63+S63 -> 28752498
A64: 63 | B64: =ROUNDUP(A64/12,0) -> 6 | C64: =Age+B64-1 -> 67 | D64: =MonthlyExp*(1+Inflation)^(B64-1) -> 70127.587 | E64: =J63 -> 4755385.8 | F64: =E64*B1Ret/12 -> 27739.75 | G64: =D64 -> 70127.587 | H64: 0 | I64: =H64 -> 0 | J64: =E64+F64-G64+I64 -> 4712997.9 | K64: =O63 -> 6389534.6 | L64: =K64*B2Ret/12 -> 47921.51 | M64: =-I64 -> 0 | N64: 0 | O64: =K64+L64+M64+N64 -> 6437456.1 | P64: =S63 -> 17607578 | Q64: =P64*B3Ret/12 -> 161402.8 | R64: =-N64 -> 0 | S64: =P64+Q64+R64 -> 17768981 | T64: =J64+O64+S64 -> 28919435
A65: 64 | B65: =ROUNDUP(A65/12,0) -> 6 | C65: =Age+B65-1 -> 67 | D65: =MonthlyExp*(1+Inflation)^(B65-1) -> 70127.587 | E65: =J64 -> 4712997.9 | F65: =E65*B1Ret/12 -> 27492.488 | G65: =D65 -> 70127.587 | H65: 0 | I65: =H65 -> 0 | J65: =E65+F65-G65+I65 -> 4670362.8 | K65: =O64 -> 6437456.1 | L65: =K65*B2Ret/12 -> 48280.921 | M65: =-I65 -> 0 | N65: 0 | O65: =K65+L65+M65+N65 -> 6485737 | P65: =S64 -> 17768981 | Q65: =P65*B3Ret/12 -> 162882.32 | R65: =-N65 -> 0 | S65: =P65+Q65+R65 -> 17931863 | T65: =J65+O65+S65 -> 29087963
A66: 65 | B66: =ROUNDUP(A66/12,0) -> 6 | C66: =Age+B66-1 -> 67 | D66: =MonthlyExp*(1+Inflation)^(B66-1) -> 70127.587 | E66: =J65 -> 4670362.8 | F66: =E66*B1Ret/12 -> 27243.783 | G66: =D66 -> 70127.587 | H66: 0 | I66: =H66 -> 0 | J66: =E66+F66-G66+I66 -> 4627479 | K66: =O65 -> 6485737 | L66: =K66*B2Ret/12 -> 48643.028 | M66: =-I66 -> 0 | N66: 0 | O66: =K66+L66+M66+N66 -> 6534380.1 | P66: =S65 -> 17931863 | Q66: =P66*B3Ret/12 -> 164375.41 | R66: =-N66 -> 0 | S66: =P66+Q66+R66 -> 18096238 | T66: =J66+O66+S66 -> 29258098
A67: 66 | B67: =ROUNDUP(A67/12,0) -> 6 | C67: =Age+B67-1 -> 67 | D67: =MonthlyExp*(1+Inflation)^(B67-1) -> 70127.587 | E67: =J66 -> 4627479 | F67: =E67*B1Ret/12 -> 26993.628 | G67: =D67 -> 70127.587 | H67: 0 | I67: =H67 -> 0 | J67: =E67+F67-G67+I67 -> 4584345.1 | K67: =O66 -> 6534380.1 | L67: =K67*B2Ret/12 -> 49007.85 | M67: =-I67 -> 0 | N67: 0 | O67: =K67+L67+M67+N67 -> 6583387.9 | P67: =S66 -> 18096238 | Q67: =P67*B3Ret/12 -> 165882.19 | R67: =-N67 -> 0 | S67: =P67+Q67+R67 -> 18262121 | T67: =J67+O67+S67 -> 29429854
A68: 67 | B68: =ROUNDUP(A68/12,0) -> 6 | C68: =Age+B68-1 -> 67 | D68: =MonthlyExp*(1+Inflation)^(B68-1) -> 70127.587 | E68: =J67 -> 4584345.1 | F68: =E68*B1Ret/12 -> 26742.013 | G68: =D68 -> 70127.587 | H68: 0 | I68: =H68 -> 0 | J68: =E68+F68-G68+I68 -> 4540959.5 | K68: =O67 -> 6583387.9 | L68: =K68*B2Ret/12 -> 49375.409 | M68: =-I68 -> 0 | N68: 0 | O68: =K68+L68+M68+N68 -> 6632763.3 | P68: =S67 -> 18262121 | Q68: =P68*B3Ret/12 -> 167402.77 | R68: =-N68 -> 0 | S68: =P68+Q68+R68 -> 18429523 | T68: =J68+O68+S68 -> 29603246
A69: 68 | B69: =ROUNDUP(A69/12,0) -> 6 | C69: =Age+B69-1 -> 67 | D69: =MonthlyExp*(1+Inflation)^(B69-1) -> 70127.587 | E69: =J68 -> 4540959.5 | F69: =E69*B1Ret/12 -> 26488.93 | G69: =D69 -> 70127.587 | H69: 0 | I69: =H69 -> 0 | J69: =E69+F69-G69+I69 -> 4497320.8 | K69: =O68 -> 6632763.3 | L69: =K69*B2Ret/12 -> 49745.725 | M69: =-I69 -> 0 | N69: 0 | O69: =K69+L69+M69+N69 -> 6682509.1 | P69: =S68 -> 18429523 | Q69: =P69*B3Ret/12 -> 168937.3 | R69: =-N69 -> 0 | S69: =P69+Q69+R69 -> 18598461 | T69: =J69+O69+S69 -> 29778291
A70: 69 | B70: =ROUNDUP(A70/12,0) -> 6 | C70: =Age+B70-1 -> 67 | D70: =MonthlyExp*(1+Inflation)^(B70-1) -> 70127.587 | E70: =J69 -> 4497320.8 | F70: =E70*B1Ret/12 -> 26234.372 | G70: =D70 -> 70127.587 | H70: 0 | I70: =H70 -> 0 | J70: =E70+F70-G70+I70 -> 4453427.6 | K70: =O69 -> 6682509.1 | L70: =K70*B2Ret/12 -> 50118.818 | M70: =-I70 -> 0 | N70: 0 | O70: =K70+L70+M70+N70 -> 6732627.9 | P70: =S69 -> 18598461 | Q70: =P70*B3Ret/12 -> 170485.89 | R70: =-N70 -> 0 | S70: =P70+Q70+R70 -> 18768947 | T70: =J70+O70+S70 -> 29955002
A71: 70 | B71: =ROUNDUP(A71/12,0) -> 6 | C71: =Age+B71-1 -> 67 | D71: =MonthlyExp*(1+Inflation)^(B71-1) -> 70127.587 | E71: =J70 -> 4453427.6 | F71: =E71*B1Ret/12 -> 25978.328 | G71: =D71 -> 70127.587 | H71: 0 | I71: =H71 -> 0 | J71: =E71+F71-G71+I71 -> 4409278.4 | K71: =O70 -> 6732627.9 | L71: =K71*B2Ret/12 -> 50494.709 | M71: =-I71 -> 0 | N71: 0 | O71: =K71+L71+M71+N71 -> 6783122.6 | P71: =S70 -> 18768947 | Q71: =P71*B3Ret/12 -> 172048.68 | R71: =-N71 -> 0 | S71: =P71+Q71+R71 -> 18940995 | T71: =J71+O71+S71 -> 30133396
A72: 71 | B72: =ROUNDUP(A72/12,0) -> 6 | C72: =Age+B72-1 -> 67 | D72: =MonthlyExp*(1+Inflation)^(B72-1) -> 70127.587 | E72: =J71 -> 4409278.4 | F72: =E72*B1Ret/12 -> 25720.79 | G72: =D72 -> 70127.587 | H72: 0 | I72: =H72 -> 0 | J72: =E72+F72-G72+I72 -> 4364871.6 | K72: =O71 -> 6783122.6 | L72: =K72*B2Ret/12 -> 50873.419 | M72: =-I72 -> 0 | N72: 0 | O72: =K72+L72+M72+N72 -> 6833996 | P72: =S71 -> 18940995 | Q72: =P72*B3Ret/12 -> 173625.79 | R72: =-N72 -> 0 | S72: =P72+Q72+R72 -> 19114621 | T72: =J72+O72+S72 -> 30313489
A73: 72 | B73: =ROUNDUP(A73/12,0) -> 6 | C73: =Age+B73-1 -> 67 | D73: =MonthlyExp*(1+Inflation)^(B73-1) -> 70127.587 | E73: =J72 -> 4364871.6 | F73: =E73*B1Ret/12 -> 25461.751 | G73: =D73 -> 70127.587 | H73: 0 | I73: =H73 -> 0 | J73: =E73+F73-G73+I73 -> 4320205.7 | K73: =O72 -> 6833996 | L73: =K73*B2Ret/12 -> 51254.97 | M73: =-I73 -> 0 | N73: 0 | O73: =K73+L73+M73+N73 -> 6885251 | P73: =S72 -> 19114621 | Q73: =P73*B3Ret/12 -> 175217.36 | R73: =-N73 -> 0 | S73: =P73+Q73+R73 -> 19289838 | T73: =J73+O73+S73 -> 30495295
... A120: 119 | B120: =ROUNDUP(A120/12,0) -> 10 | C120: =Age+B120-1 -> 71 | D120: =MonthlyExp*(1+Inflation)^(B120-1) -> 91922.961 | E120: =J119 -> 1309305 | F120: =E120*B1Ret/12 -> 7637.6127 | G120: =D120 -> 91922.961 | H120: 0 | I120: =H120 -> 0 | J120: =E120+F120-G120+I120 -> 1225019.7 | K120: =O119 -> 9709397.8 | L120: =K120*B2Ret/12 -> 72820.484 | M120: =-I120 -> 0 | N120: 0 | O120: =K120+L120+M120+N120 -> 9782218.3 | P120: =S119 -> 29350929 | Q120: =P120*B3Ret/12 -> 269050.19 | R120: =-N120 -> 0 | S120: =P120+Q120+R120 -> 29619980 | T120: =J120+O120+S120 -> 40627218
A121: 120 | B121: =ROUNDUP(A121/12,0) -> 10 | C121: =Age+B121-1 -> 71 | D121: =MonthlyExp*(1+Inflation)^(B121-1) -> 91922.961 | E121: =J120 -> 1225019.7 | F121: =E121*B1Ret/12 -> 7145.9482 | G121: =D121 -> 91922.961 | H121: =MAX(SUM(D122:D181)-(E121+F121-G121),0) -> 5647301.7 | I121: =H121 -> 5647301.7 | J121: =E121+F121-G121+I121 -> 6787544.4 | K121: =O120 -> 9782218.3 | L121: =K121*B2Ret/12 -> 73366.637 | M121: =-I121 -> -5647301.7 | N121: 0 | O121: =K121+L121+M121+N121 -> 4208283.2 | P121: =S120 -> 29619980 | Q121: =P121*B3Ret/12 -> 271516.48 | R121: =-N121 -> 0 | S121: =P121+Q121+R121 -> 29891496 | T121: =J121+O121+S121 -> 40887324
A122: 121 | B122: =ROUNDUP(A122/12,0) -> 11 | C122: =Age+B122-1 -> 72 | D122: =MonthlyExp*(1+Inflation)^(B122-1) -> 98357.568 | E122: =J121 -> 6787544.4 | F122: =E122*B1Ret/12 -> 39594.009 | G122: =D122 -> 98357.568 | H122: 0 | I122: =H122 -> 0 | J122: =E122+F122-G122+I122 -> 6728780.9 | K122: =O121 -> 4208283.2 | L122: =K122*B2Ret/12 -> 31562.124 | M122: =-I122 -> 0 | N122: 0 | O122: =K122+L122+M122+N122 -> 4239845.3 | P122: =S121 -> 29891496 | Q122: =P122*B3Ret/12 -> 274005.38 | R122: =-N122 -> 0 | S122: =P122+Q122+R122 -> 30165501 | T122: =J122+O122+S122 -> 41134128
A123: 122 | B123: =ROUNDUP(A123/12,0) -> 11 | C123: =Age+B123-1 -> 72 | D123: =MonthlyExp*(1+Inflation)^(B123-1) -> 98357.568 | E123: =J122 -> 6728780.9 | F123: =E123*B1Ret/12 -> 39251.222 | G123: =D123 -> 98357.568 | H123: 0 | I123: =H123 -> 0 | J123: =E123+F123-G123+I123 -> 6669674.5 | K123: =O122 -> 4239845.3 | L123: =K123*B2Ret/12 -> 31798.84 | M123: =-I123 -> 0 | N123: 0 | O123: =K123+L123+M123+N123 -> 4271644.2 | P123: =S122 -> 30165501 | Q123: =P123*B3Ret/12 -> 276517.1 | R123: =-N123 -> 0 | S123: =P123+Q123+R123 -> 30442019 | T123: =J123+O123+S123 -> 41383337
A124: 123 | B124: =ROUNDUP(A124/12,0) -> 11 | C124: =Age+B124-1 -> 72 | D124: =MonthlyExp*(1+Inflation)^(B124-1) -> 98357.568 | E124: =J123 -> 6669674.5 | F124: =E124*B1Ret/12 -> 38906.435 | G124: =D124 -> 98357.568 | H124: 0 | I124: =H124 -> 0 | J124: =E124+F124-G124+I124 -> 6610223.4 | K124: =O123 -> 4271644.2 | L124: =K124*B2Ret/12 -> 32037.331 | M124: =-I124 -> 0 | N124: 0 | O124: =K124+L124+M124+N124 -> 4303681.5 | P124: =S123 -> 30442019 | Q124: =P124*B3Ret/12 -> 279051.84 | R124: =-N124 -> 0 | S124: =P124+Q124+R124 -> 30721070 | T124: =J124+O124+S124 -> 41634975
A125: 124 | B125: =ROUNDUP(A125/12,0) -> 11 | C125: =Age+B125-1 -> 72 | D125: =MonthlyExp*(1+Inflation)^(B125-1) -> 98357.568 | E125: =J124 -> 6610223.4 | F125: =E125*B1Ret/12 -> 38559.636 | G125: =D125 -> 98357.568 | H125: 0 | I125: =H125 -> 0 | J125: =E125+F125-G125+I125 -> 6550425.5 | K125: =O124 -> 4303681.5 | L125: =K125*B2Ret/12 -> 32277.611 | M125: =-I125 -> 0 | N125: 0 | O125: =K125+L125+M125+N125 -> 4335959.1 | P125: =S124 -> 30721070 | Q125: =P125*B3Ret/12 -> 281609.81 | R125: =-N125 -> 0 | S125: =P125+Q125+R125 -> 31002680 | T125: =J125+O125+S125 -> 41889065
A126: 125 | B126: =ROUNDUP(A126/12,0) -> 11 | C126: =Age+B126-1 -> 72 | D126: =MonthlyExp*(1+Inflation)^(B126-1) -> 98357.568 | E126: =J125 -> 6550425.5 | F126: =E126*B1Ret/12 -> 38210.815 | G126: =D126 -> 98357.568 | H126: 0 | I126: =H126 -> 0 | J126: =E126+F126-G126+I126 -> 6490278.7 | K126: =O125 -> 4335959.1 | L126: =K126*B2Ret/12 -> 32519.693 | M126: =-I126 -> 0 | N126: 0 | O126: =K126+L126+M126+N126 -> 4368478.8 | P126: =S125 -> 31002680 | Q126: =P126*B3Ret/12 -> 284191.23 | R126: =-N126 -> 0 | S126: =P126+Q126+R126 -> 31286871 | T126: =J126+O126+S126 -> 42145629
A127: 126 | B127: =ROUNDUP(A127/12,0) -> 11 | C127: =Age+B127-1 -> 72 | D127: =MonthlyExp*(1+Inflation)^(B127-1) -> 98357.568 | E127: =J126 -> 6490278.7 | F127: =E127*B1Ret/12 -> 37859.959 | G127: =D127 -> 98357.568 | H127: 0 | I127: =H127 -> 0 | J127: =E127+F127-G127+I127 -> 6429781.1 | K127: =O126 -> 4368478.8 | L127: =K127*B2Ret/12 -> 32763.591 | M127: =-I127 -> 0 | N127: 0 | O127: =K127+L127+M127+N127 -> 4401242.4 | P127: =S126 -> 31286871 | Q127: =P127*B3Ret/12 -> 286796.32 | R127: =-N127 -> 0 | S127: =P127+Q127+R127 -> 31573668 | T127: =J127+O127+S127 -> 42404691
A128: 127 | B128: =ROUNDUP(A128/12,0) -> 11 | C128: =Age+B128-1 -> 72 | D128: =MonthlyExp*(1+Inflation)^(B128-1) -> 98357.568 | E128: =J127 -> 6429781.1 | F128: =E128*B1Ret/12 -> 37507.056 | G128: =D128 -> 98357.568 | H128: 0 | I128: =H128 -> 0 | J128: =E128+F128-G128+I128 -> 6368930.6 | K128: =O127 -> 4401242.4 | L128: =K128*B2Ret/12 -> 33009.318 | M128: =-I128 -> 0 | N128: 0 | O128: =K128+L128+M128+N128 -> 4434251.7 | P128: =S127 -> 31573668 | Q128: =P128*B3Ret/12 -> 289425.29 | R128: =-N128 -> 0 | S128: =P128+Q128+R128 -> 31863093 | T128: =J128+O128+S128 -> 42666275
A129: 128 | B129: =ROUNDUP(A129/12,0) -> 11 | C129: =Age+B129-1 -> 72 | D129: =MonthlyExp*(1+Inflation)^(B129-1) -> 98357.568 | E129: =J128 -> 6368930.6 | F129: =E129*B1Ret/12 -> 37152.095 | G129: =D129 -> 98357.568 | H129: 0 | I129: =H129 -> 0 | J129: =E129+F129-G129+I129 -> 6307725.1 | K129: =O128 -> 4434251.7 | L129: =K129*B2Ret/12 -> 33256.888 | M129: =-I129 -> 0 | N129: 0 | O129: =K129+L129+M129+N129 -> 4467508.6 | P129: =S128 -> 31863093 | Q129: =P129*B3Ret/12 -> 292078.35 | R129: =-N129 -> 0 | S129: =P129+Q129+R129 -> 32155171 | T129: =J129+O129+S129 -> 42930405
A130: 129 | B130: =ROUNDUP(A130/12,0) -> 11 | C130: =Age+B130-1 -> 72 | D130: =MonthlyExp*(1+Inflation)^(B130-1) -> 98357.568 | E130: =J129 -> 6307725.1 | F130: =E130*B1Ret/12 -> 36795.063 | G130: =D130 -> 98357.568 | H130: 0 | I130: =H130 -> 0 | J130: =E130+F130-G130+I130 -> 6246162.6 | K130: =O129 -> 4467508.6 | L130: =K130*B2Ret/12 -> 33506.315 | M130: =-I130 -> 0 | N130: 0 | O130: =K130+L130+M130+N130 -> 4501014.9 | P130: =S129 -> 32155171 | Q130: =P130*B3Ret/12 -> 294755.74 | R130: =-N130 -> 0 | S130: =P130+Q130+R130 -> 32449927 | T130: =J130+O130+S130 -> 43197105
A131: 130 | B131: =ROUNDUP(A131/12,0) -> 11 | C131: =Age+B131-1 -> 72 | D131: =MonthlyExp*(1+Inflation)^(B131-1) -> 98357.568 | E131: =J130 -> 6246162.6 | F131: =E131*B1Ret/12 -> 36435.949 | G131: =D131 -> 98357.568 | H131: 0 | I131: =H131 -> 0 | J131: =E131+F131-G131+I131 -> 6184241 | K131: =O130 -> 4501014.9 | L131: =K131*B2Ret/12 -> 33757.612 | M131: =-I131 -> 0 | N131: 0 | O131: =K131+L131+M131+N131 -> 4534772.5 | P131: =S130 -> 32449927 | Q131: =P131*B3Ret/12 -> 297457.66 | R131: =-N131 -> 0 | S131: =P131+Q131+R131 -> 32747385 | T131: =J131+O131+S131 -> 43466398
A132: 131 | B132: =ROUNDUP(A132/12,0) -> 11 | C132: =Age+B132-1 -> 72 | D132: =MonthlyExp*(1+Inflation)^(B132-1) -> 98357.568 | E132: =J131 -> 6184241 | F132: =E132*B1Ret/12 -> 36074.739 | G132: =D132 -> 98357.568 | H132: 0 | I132: =H132 -> 0 | J132: =E132+F132-G132+I132 -> 6121958.2 | K132: =O131 -> 4534772.5 | L132: =K132*B2Ret/12 -> 34010.794 | M132: =-I132 -> 0 | N132: 0 | O132: =K132+L132+M132+N132 -> 4568783.3 | P132: =S131 -> 32747385 | Q132: =P132*B3Ret/12 -> 300184.36 | R132: =-N132 -> 0 | S132: =P132+Q132+R132 -> 33047569 | T132: =J132+O132+S132 -> 43738311
A133: 132 | B133: =ROUNDUP(A133/12,0) -> 11 | C133: =Age+B133-1 -> 72 | D133: =MonthlyExp*(1+Inflation)^(B133-1) -> 98357.568 | E133: =J132 -> 6121958.2 | F133: =E133*B1Ret/12 -> 35711.423 | G133: =D133 -> 98357.568 | H133: 0 | I133: =H133 -> 0 | J133: =E133+F133-G133+I133 -> 6059312 | K133: =O132 -> 4568783.3 | L133: =K133*B2Ret/12 -> 34265.875 | M133: =-I133 -> 0 | N133: 0 | O133: =K133+L133+M133+N133 -> 4603049.2 | P133: =S132 -> 33047569 | Q133: =P133*B3Ret/12 -> 302936.05 | R133: =-N133 -> 0 | S133: =P133+Q133+R133 -> 33350505 | T133: =J133+O133+S133 -> 44012866
... A180: 179 | B180: =ROUNDUP(A180/12,0) -> 15 | C180: =Age+B180-1 -> 76 | D180: =MonthlyExp*(1+Inflation)^(B180-1) -> 128926.71 | E180: =J179 -> 1836368.1 | F180: =E180*B1Ret/12 -> 10712.147 | G180: =D180 -> 128926.71 | H180: 0 | I180: =H180 -> 0 | J180: =E180+F180-G180+I180 -> 1718153.5 | K180: =O179 -> 6491097.6 | L180: =K180*B2Ret/12 -> 48683.232 | M180: =-I180 -> 0 | N180: 0 | O180: =K180+L180+M180+N180 -> 6539780.8 | P180: =S179 -> 50745283 | Q180: =P180*B3Ret/12 -> 465165.1 | R180: =-N180 -> 0 | S180: =P180+Q180+R180 -> 51210449 | T180: =J180+O180+S180 -> 59468383
A181: 180 | B181: =ROUNDUP(A181/12,0) -> 15 | C181: =Age+B181-1 -> 76 | D181: =MonthlyExp*(1+Inflation)^(B181-1) -> 128926.71 | E181: =J180 -> 1718153.5 | F181: =E181*B1Ret/12 -> 10022.562 | G181: =D181 -> 128926.71 | H181: =MAX(SUM(D182:D241)-(E181+F181-G181),0) -> 7920632.8 | I181: =H181 -> 7920632.8 | J181: =E181+F181-G181+I181 -> 9519882.2 | K181: =O180 -> 6539780.8 | L181: =K181*B2Ret/12 -> 49048.356 | M181: =-I181 -> -7920632.8 | N181: =H181 -> 7920632.8 | O181: =K181+L181+M181+N181 -> 6588829.2 | P181: =S180 -> 51210449 | Q181: =P181*B3Ret/12 -> 469429.11 | R181: =-N181 -> -7920632.8 | S181: =P181+Q181+R181 -> 43759245 | T181: =J181+O181+S181 -> 59867956
A182: 181 | B182: =ROUNDUP(A182/12,0) -> 16 | C182: =Age+B182-1 -> 77 | D182: =MonthlyExp*(1+Inflation)^(B182-1) -> 137951.58 | E182: =J181 -> 9519882.2 | F182: =E182*B1Ret/12 -> 55532.646 | G182: =D182 -> 137951.58 | H182: 0 | I182: =H182 -> 0 | J182: =E182+F182-G182+I182 -> 9437463.3 | K182: =O181 -> 6588829.2 | L182: =K182*B2Ret/12 -> 49416.219 | M182: =-I182 -> 0 | N182: 0 | O182: =K182+L182+M182+N182 -> 6638245.4 | P182: =S181 -> 43759245 | Q182: =P182*B3Ret/12 -> 401126.41 | R182: =-N182 -> 0 | S182: =P182+Q182+R182 -> 44160371 | T182: =J182+O182+S182 -> 60236080
A183: 182 | B183: =ROUNDUP(A183/12,0) -> 16 | C183: =Age+B183-1 -> 77 | D183: =MonthlyExp*(1+Inflation)^(B183-1) -> 137951.58 | E183: =J182 -> 9437463.3 | F183: =E183*B1Ret/12 -> 55051.869 | G183: =D183 -> 137951.58 | H183: 0 | I183: =H183 -> 0 | J183: =E183+F183-G183+I183 -> 9354563.5 | K183: =O182 -> 6638245.4 | L183: =K183*B2Ret/12 -> 49786.84 | M183: =-I183 -> 0 | N183: 0 | O183: =K183+L183+M183+N183 -> 6688032.2 | P183: =S182 -> 44160371 | Q183: =P183*B3Ret/12 -> 404803.4 | R183: =-N183 -> 0 | S183: =P183+Q183+R183 -> 44565175 | T183: =J183+O183+S183 -> 60607770
A184: 183 | B184: =ROUNDUP(A184/12,0) -> 16 | C184: =Age+B184-1 -> 77 | D184: =MonthlyExp*(1+Inflation)^(B184-1) -> 137951.58 | E184: =J183 -> 9354563.5 | F184: =E184*B1Ret/12 -> 54568.287 | G184: =D184 -> 137951.58 | H184: 0 | I184: =H184 -> 0 | J184: =E184+F184-G184+I184 -> 9271180.3 | K184: =O183 -> 6688032.2 | L184: =K184*B2Ret/12 -> 50160.242 | M184: =-I184 -> 0 | N184: 0 | O184: =K184+L184+M184+N184 -> 6738192.5 | P184: =S183 -> 44565175 | Q184: =P184*B3Ret/12 -> 408514.1 | R184: =-N184 -> 0 | S184: =P184+Q184+R184 -> 44973689 | T184: =J184+O184+S184 -> 60983061
A185: 184 | B185: =ROUNDUP(A185/12,0) -> 16 | C185: =Age+B185-1 -> 77 | D185: =MonthlyExp*(1+Inflation)^(B185-1) -> 137951.58 | E185: =J184 -> 9271180.3 | F185: =E185*B1Ret/12 -> 54081.885 | G185: =D185 -> 137951.58 | H185: 0 | I185: =H185 -> 0 | J185: =E185+F185-G185+I185 -> 9187310.6 | K185: =O184 -> 6738192.5 | L185: =K185*B2Ret/12 -> 50536.444 | M185: =-I185 -> 0 | N185: 0 | O185: =K185+L185+M185+N185 -> 6788728.9 | P185: =S184 -> 44973689 | Q185: =P185*B3Ret/12 -> 412258.81 | R185: =-N185 -> 0 | S185: =P185+Q185+R185 -> 45385948 | T185: =J185+O185+S185 -> 61361987
A186: 185 | B186: =ROUNDUP(A186/12,0) -> 16 | C186: =Age+B186-1 -> 77 | D186: =MonthlyExp*(1+Inflation)^(B186-1) -> 137951.58 | E186: =J185 -> 9187310.6 | F186: =E186*B1Ret/12 -> 53592.645 | G186: =D186 -> 137951.58 | H186: 0 | I186: =H186 -> 0 | J186: =E186+F186-G186+I186 -> 9102951.6 | K186: =O185 -> 6788728.9 | L186: =K186*B2Ret/12 -> 50915.467 | M186: =-I186 -> 0 | N186: 0 | O186: =K186+L186+M186+N186 -> 6839644.4 | P186: =S185 -> 45385948 | Q186: =P186*B3Ret/12 -> 416037.85 | R186: =-N186 -> 0 | S186: =P186+Q186+R186 -> 45801985 | T186: =J186+O186+S186 -> 61744581
A187: 186 | B187: =ROUNDUP(A187/12,0) -> 16 | C187: =Age+B187-1 -> 77 | D187: =MonthlyExp*(1+Inflation)^(B187-1) -> 137951.58 | E187: =J186 -> 9102951.6 | F187: =E187*B1Ret/12 -> 53100.551 | G187: =D187 -> 137951.58 | H187: 0 | I187: =H187 -> 0 | J187: =E187+F187-G187+I187 -> 9018100.6 | K187: =O186 -> 6839644.4 | L187: =K187*B2Ret/12 -> 51297.333 | M187: =-I187 -> 0 | N187: 0 | O187: =K187+L187+M187+N187 -> 6890941.7 | P187: =S186 -> 45801985 | Q187: =P187*B3Ret/12 -> 419851.53 | R187: =-N187 -> 0 | S187: =P187+Q187+R187 -> 46221837 | T187: =J187+O187+S187 -> 62130879
A188: 187 | B188: =ROUNDUP(A188/12,0) -> 16 | C188: =Age+B188-1 -> 77 | D188: =MonthlyExp*(1+Inflation)^(B188-1) -> 137951.58 | E188: =J187 -> 9018100.6 | F188: =E188*B1Ret/12 -> 52605.587 | G188: =D188 -> 137951.58 | H188: 0 | I188: =H188 -> 0 | J188: =E188+F188-G188+I188 -> 8932754.6 | K188: =O187 -> 6890941.7 | L188: =K188*B2Ret/12 -> 51682.063 | M188: =-I188 -> 0 | N188: 0 | O188: =K188+L188+M188+N188 -> 6942623.8 | P188: =S187 -> 46221837 | Q188: =P188*B3Ret/12 -> 423700.17 | R188: =-N188 -> 0 | S188: =P188+Q188+R188 -> 46645537 | T188: =J188+O188+S188 -> 62520916
A189: 188 | B189: =ROUNDUP(A189/12,0) -> 16 | C189: =Age+B189-1 -> 77 | D189: =MonthlyExp*(1+Inflation)^(B189-1) -> 137951.58 | E189: =J188 -> 8932754.6 | F189: =E189*B1Ret/12 -> 52107.735 | G189: =D189 -> 137951.58 | H189: 0 | I189: =H189 -> 0 | J189: =E189+F189-G189+I189 -> 8846910.8 | K189: =O188 -> 6942623.8 | L189: =K189*B2Ret/12 -> 52069.678 | M189: =-I189 -> 0 | N189: 0 | O189: =K189+L189+M189+N189 -> 6994693.5 | P189: =S188 -> 46645537 | Q189: =P189*B3Ret/12 -> 427584.09 | R189: =-N189 -> 0 | S189: =P189+Q189+R189 -> 47073121 | T189: =J189+O189+S189 -> 62914725
A190: 189 | B190: =ROUNDUP(A190/12,0) -> 16 | C190: =Age+B190-1 -> 77 | D190: =MonthlyExp*(1+Inflation)^(B190-1) -> 137951.58 | E190: =J189 -> 8846910.8 | F190: =E190*B1Ret/12 -> 51606.98 | G190: =D190 -> 137951.58 | H190: 0 | I190: =H190 -> 0 | J190: =E190+F190-G190+I190 -> 8760566.2 | K190: =O189 -> 6994693.5 | L190: =K190*B2Ret/12 -> 52460.201 | M190: =-I190 -> 0 | N190: 0 | O190: =K190+L190+M190+N190 -> 7047153.7 | P190: =S189 -> 47073121 | Q190: =P190*B3Ret/12 -> 431503.61 | R190: =-N190 -> 0 | S190: =P190+Q190+R190 -> 47504625 | T190: =J190+O190+S190 -> 63312345
A191: 190 | B191: =ROUNDUP(A191/12,0) -> 16 | C191: =Age+B191-1 -> 77 | D191: =MonthlyExp*(1+Inflation)^(B191-1) -> 137951.58 | E191: =J190 -> 8760566.2 | F191: =E191*B1Ret/12 -> 51103.303 | G191: =D191 -> 137951.58 | H191: 0 | I191: =H191 -> 0 | J191: =E191+F191-G191+I191 -> 8673717.9 | K191: =O190 -> 7047153.7 | L191: =K191*B2Ret/12 -> 52853.652 | M191: =-I191 -> 0 | N191: 0 | O191: =K191+L191+M191+N191 -> 7100007.3 | P191: =S190 -> 47504625 | Q191: =P191*B3Ret/12 -> 435459.06 | R191: =-N191 -> 0 | S191: =P191+Q191+R191 -> 47940084 | T191: =J191+O191+S191 -> 63713809
A192: 191 | B192: =ROUNDUP(A192/12,0) -> 16 | C192: =Age+B192-1 -> 77 | D192: =MonthlyExp*(1+Inflation)^(B192-1) -> 137951.58 | E192: =J191 -> 8673717.9 | F192: =E192*B1Ret/12 -> 50596.688 | G192: =D192 -> 137951.58 | H192: 0 | I192: =H192 -> 0 | J192: =E192+F192-G192+I192 -> 8586363 | K192: =O191 -> 7100007.3 | L192: =K192*B2Ret/12 -> 53250.055 | M192: =-I192 -> 0 | N192: 0 | O192: =K192+L192+M192+N192 -> 7153257.4 | P192: =S191 -> 47940084 | Q192: =P192*B3Ret/12 -> 439450.77 | R192: =-N192 -> 0 | S192: =P192+Q192+R192 -> 48379535 | T192: =J192+O192+S192 -> 64119155
A193: 192 | B193: =ROUNDUP(A193/12,0) -> 16 | C193: =Age+B193-1 -> 77 | D193: =MonthlyExp*(1+Inflation)^(B193-1) -> 137951.58 | E193: =J192 -> 8586363 | F193: =E193*B1Ret/12 -> 50087.118 | G193: =D193 -> 137951.58 | H193: 0 | I193: =H193 -> 0 | J193: =E193+F193-G193+I193 -> 8498498.6 | K193: =O192 -> 7153257.4 | L193: =K193*B2Ret/12 -> 53649.43 | M193: =-I193 -> 0 | N193: 0 | O193: =K193+L193+M193+N193 -> 7206906.8 | P193: =S192 -> 48379535 | Q193: =P193*B3Ret/12 -> 443479.07 | R193: =-N193 -> 0 | S193: =P193+Q193+R193 -> 48823014 | T193: =J193+O193+S193 -> 64528419
... A240: 239 | B240: =ROUNDUP(A240/12,0) -> 20 | C240: =Age+B240-1 -> 81 | D240: =MonthlyExp*(1+Inflation)^(B240-1) -> 180826.38 | E240: =J239 -> 2575601.2 | F240: =E240*B1Ret/12 -> 15024.34 | G240: =D240 -> 180826.38 | H240: 0 | I240: =H240 -> 0 | J240: =E240+F240-G240+I240 -> 2409799.2 | K240: =O239 -> 10162988 | L240: =K240*B2Ret/12 -> 76222.412 | M240: =-I240 -> 0 | N240: 0 | O240: =K240+L240+M240+N240 -> 10239211 | P240: =S239 -> 74287860 | Q240: =P240*B3Ret/12 -> 680972.05 | R240: =-N240 -> 0 | S240: =P240+Q240+R240 -> 74968832 | T240: =J240+O240+S240 -> 87617842
A241: 240 | B241: =ROUNDUP(A241/12,0) -> 20 | C241: =Age+B241-1 -> 81 | D241: =MonthlyExp*(1+Inflation)^(B241-1) -> 180826.38 | E241: =J240 -> 2409799.2 | F241: =E241*B1Ret/12 -> 14057.162 | G241: =D241 -> 180826.38 | H241: =MAX(SUM(D242:D301)-(E241+F241-G241),0) -> 11109097 | I241: =H241 -> 11109097 | J241: =E241+F241-G241+I241 -> 13352127 | K241: =O240 -> 10239211 | L241: =K241*B2Ret/12 -> 76794.081 | M241: =-I241 -> -11109097 | N241: =H241 -> 11109097 | O241: =K241+L241+M241+N241 -> 10316005 | P241: =S240 -> 74968832 | Q241: =P241*B3Ret/12 -> 687214.3 | R241: =-N241 -> -11109097 | S241: =P241+Q241+R241 -> 64546949 | T241: =J241+O241+S241 -> 88215082
A242: 241 | B242: =ROUNDUP(A242/12,0) -> 21 | C242: =Age+B242-1 -> 82 | D242: =MonthlyExp*(1+Inflation)^(B242-1) -> 193484.22 | E242: =J241 -> 13352127 | F242: =E242*B1Ret/12 -> 77887.409 | G242: =D242 -> 193484.22 | H242: 0 | I242: =H242 -> 0 | J242: =E242+F242-G242+I242 -> 13236530 | K242: =O241 -> 10316005 | L242: =K242*B2Ret/12 -> 77370.036 | M242: =-I242 -> 0 | N242: 0 | O242: =K242+L242+M242+N242 -> 10393375 | P242: =S241 -> 64546949 | Q242: =P242*B3Ret/12 -> 591680.37 | R242: =-N242 -> 0 | S242: =P242+Q242+R242 -> 65138630 | T242: =J242+O242+S242 -> 88768535
A243: 242 | B243: =ROUNDUP(A243/12,0) -> 21 | C243: =Age+B243-1 -> 82 | D243: =MonthlyExp*(1+Inflation)^(B243-1) -> 193484.22 | E243: =J242 -> 13236530 | F243: =E243*B1Ret/12 -> 77213.094 | G243: =D243 -> 193484.22 | H243: 0 | I243: =H243 -> 0 | J243: =E243+F243-G243+I243 -> 13120259 | K243: =O242 -> 10393375 | L243: =K243*B2Ret/12 -> 77950.311 | M243: =-I243 -> 0 | N243: 0 | O243: =K243+L243+M243+N243 -> 10471325 | P243: =S242 -> 65138630 | Q243: =P243*B3Ret/12 -> 597104.11 | R243: =-N243 -> 0 | S243: =P243+Q243+R243 -> 65735734 | T243: =J243+O243+S243 -> 89327318
A244: 243 | B244: =ROUNDUP(A244/12,0) -> 21 | C244: =Age+B244-1 -> 82 | D244: =MonthlyExp*(1+Inflation)^(B244-1) -> 193484.22 | E244: =J243 -> 13120259 | F244: =E244*B1Ret/12 -> 76534.846 | G244: =D244 -> 193484.22 | H244: 0 | I244: =H244 -> 0 | J244: =E244+F244-G244+I244 -> 13003310 | K244: =O243 -> 10471325 | L244: =K244*B2Ret/12 -> 78534.939 | M244: =-I244 -> 0 | N244: 0 | O244: =K244+L244+M244+N244 -> 10549860 | P244: =S243 -> 65735734 | Q244: =P244*B3Ret/12 -> 602577.56 | R244: =-N244 -> 0 | S244: =P244+Q244+R244 -> 66338312 | T244: =J244+O244+S244 -> 89891482
A245: 244 | B245: =ROUNDUP(A245/12,0) -> 21 | C245: =Age+B245-1 -> 82 | D245: =MonthlyExp*(1+Inflation)^(B245-1) -> 193484.22 | E245: =J244 -> 13003310 | F245: =E245*B1Ret/12 -> 75852.641 | G245: =D245 -> 193484.22 | H245: 0 | I245: =H245 -> 0 | J245: =E245+F245-G245+I245 -> 12885678 | K245: =O244 -> 10549860 | L245: =K245*B2Ret/12 -> 79123.951 | M245: =-I245 -> 0 | N245: 0 | O245: =K245+L245+M245+N245 -> 10628984 | P245: =S244 -> 66338312 | Q245: =P245*B3Ret/12 -> 608101.19 | R245: =-N245 -> 0 | S245: =P245+Q245+R245 -> 66946413 | T245: =J245+O245+S245 -> 90461075
A246: 245 | B246: =ROUNDUP(A246/12,0) -> 21 | C246: =Age+B246-1 -> 82 | D246: =MonthlyExp*(1+Inflation)^(B246-1) -> 193484.22 | E246: =J245 -> 12885678 | F246: =E246*B1Ret/12 -> 75166.457 | G246: =D246 -> 193484.22 | H246: 0 | I246: =H246 -> 0 | J246: =E246+F246-G246+I246 -> 12767361 | K246: =O245 -> 10628984 | L246: =K246*B2Ret/12 -> 79717.38 | M246: =-I246 -> 0 | N246: 0 | O246: =K246+L246+M246+N246 -> 10708701 | P246: =S245 -> 66946413 | Q246: =P246*B3Ret/12 -> 613675.45 | R246: =-N246 -> 0 | S246: =P246+Q246+R246 -> 67560088 | T246: =J246+O246+S246 -> 91036150
A247: 246 | B247: =ROUNDUP(A247/12,0) -> 21 | C247: =Age+B247-1 -> 82 | D247: =MonthlyExp*(1+Inflation)^(B247-1) -> 193484.22 | E247: =J246 -> 12767361 | F247: =E247*B1Ret/12 -> 74476.27 | G247: =D247 -> 193484.22 | H247: 0 | I247: =H247 -> 0 | J247: =E247+F247-G247+I247 -> 12648353 | K247: =O246 -> 10708701 | L247: =K247*B2Ret/12 -> 80315.261 | M247: =-I247 -> 0 | N247: 0 | O247: =K247+L247+M247+N247 -> 10789017 | P247: =S246 -> 67560088 | Q247: =P247*B3Ret/12 -> 619300.81 | R247: =-N247 -> 0 | S247: =P247+Q247+R247 -> 68179389 | T247: =J247+O247+S247 -> 91616758
A248: 247 | B248: =ROUNDUP(A248/12,0) -> 21 | C248: =Age+B248-1 -> 82 | D248: =MonthlyExp*(1+Inflation)^(B248-1) -> 193484.22 | E248: =J247 -> 12648353 | F248: =E248*B1Ret/12 -> 73782.057 | G248: =D248 -> 193484.22 | H248: 0 | I248: =H248 -> 0 | J248: =E248+F248-G248+I248 -> 12528650 | K248: =O247 -> 10789017 | L248: =K248*B2Ret/12 -> 80917.625 | M248: =-I248 -> 0 | N248: 0 | O248: =K248+L248+M248+N248 -> 10869934 | P248: =S247 -> 68179389 | Q248: =P248*B3Ret/12 -> 624977.73 | R248: =-N248 -> 0 | S248: =P248+Q248+R248 -> 68804367 | T248: =J248+O248+S248 -> 92202951
A249: 248 | B249: =ROUNDUP(A249/12,0) -> 21 | C249: =Age+B249-1 -> 82 | D249: =MonthlyExp*(1+Inflation)^(B249-1) -> 193484.22 | E249: =J248 -> 12528650 | F249: =E249*B1Ret/12 -> 73083.794 | G249: =D249 -> 193484.22 | H249: 0 | I249: =H249 -> 0 | J249: =E249+F249-G249+I249 -> 12408250 | K249: =O248 -> 10869934 | L249: =K249*B2Ret/12 -> 81524.507 | M249: =-I249 -> 0 | N249: 0 | O249: =K249+L249+M249+N249 -> 10951459 | P249: =S248 -> 68804367 | Q249: =P249*B3Ret/12 -> 630706.69 | R249: =-N249 -> 0 | S249: =P249+Q249+R249 -> 69435073 | T249: =J249+O249+S249 -> 92794782
A250: 249 | B250: =ROUNDUP(A250/12,0) -> 21 | C250: =Age+B250-1 -> 82 | D250: =MonthlyExp*(1+Inflation)^(B250-1) -> 193484.22 | E250: =J249 -> 12408250 | F250: =E250*B1Ret/12 -> 72381.458 | G250: =D250 -> 193484.22 | H250: 0 | I250: =H250 -> 0 | J250: =E250+F250-G250+I250 -> 12287147 | K250: =O249 -> 10951459 | L250: =K250*B2Ret/12 -> 82135.941 | M250: =-I250 -> 0 | N250: 0 | O250: =K250+L250+M250+N250 -> 11033595 | P250: =S249 -> 69435073 | Q250: =P250*B3Ret/12 -> 636488.17 | R250: =-N250 -> 0 | S250: =P250+Q250+R250 -> 70071562 | T250: =J250+O250+S250 -> 93392304
A251: 250 | B251: =ROUNDUP(A251/12,0) -> 21 | C251: =Age+B251-1 -> 82 | D251: =MonthlyExp*(1+Inflation)^(B251-1) -> 193484.22 | E251: =J250 -> 12287147 | F251: =E251*B1Ret/12 -> 71675.026 | G251: =D251 -> 193484.22 | H251: 0 | I251: =H251 -> 0 | J251: =E251+F251-G251+I251 -> 12165338 | K251: =O250 -> 11033595 | L251: =K251*B2Ret/12 -> 82751.961 | M251: =-I251 -> 0 | N251: 0 | O251: =K251+L251+M251+N251 -> 11116347 | P251: =S250 -> 70071562 | Q251: =P251*B3Ret/12 -> 642322.65 | R251: =-N251 -> 0 | S251: =P251+Q251+R251 -> 70713884 | T251: =J251+O251+S251 -> 93995569
A252: 251 | B252: =ROUNDUP(A252/12,0) -> 21 | C252: =Age+B252-1 -> 82 | D252: =MonthlyExp*(1+Inflation)^(B252-1) -> 193484.22 | E252: =J251 -> 12165338 | F252: =E252*B1Ret/12 -> 70964.472 | G252: =D252 -> 193484.22 | H252: 0 | I252: =H252 -> 0 | J252: =E252+F252-G252+I252 -> 12042818 | K252: =O251 -> 11116347 | L252: =K252*B2Ret/12 -> 83372.601 | M252: =-I252 -> 0 | N252: 0 | O252: =K252+L252+M252+N252 -> 11199719 | P252: =S251 -> 70713884 | Q252: =P252*B3Ret/12 -> 648210.61 | R252: =-N252 -> 0 | S252: =P252+Q252+R252 -> 71362095 | T252: =J252+O252+S252 -> 94604632
A253: 252 | B253: =ROUNDUP(A253/12,0) -> 21 | C253: =Age+B253-1 -> 82 | D253: =MonthlyExp*(1+Inflation)^(B253-1) -> 193484.22 | E253: =J252 -> 12042818 | F253: =E253*B1Ret/12 -> 70249.773 | G253: =D253 -> 193484.22 | H253: 0 | I253: =H253 -> 0 | J253: =E253+F253-G253+I253 -> 11919584 | K253: =O252 -> 11199719 | L253: =K253*B2Ret/12 -> 83997.895 | M253: =-I253 -> 0 | N253: 0 | O253: =K253+L253+M253+N253 -> 11283717 | P253: =S252 -> 71362095 | Q253: =P253*B3Ret/12 -> 654152.54 | R253: =-N253 -> 0 | S253: =P253+Q253+R253 -> 72016247 | T253: =J253+O253+S253 -> 95219548
... A300: 299 | B300: =ROUNDUP(A300/12,0) -> 25 | C300: =Age+B300-1 -> 86 | D300: =MonthlyExp*(1+Inflation)^(B300-1) -> 253618.35 | E300: =J299 -> 3612413.9 | F300: =E300*B1Ret/12 -> 21072.414 | G300: =D300 -> 253618.35 | H300: 0 | I300: =H300 -> 0 | J300: =E300+F300-G300+I300 -> 3379868 | K300: =O299 -> 15911998 | L300: =K300*B2Ret/12 -> 119339.99 | M300: =-I300 -> 0 | N300: 0 | O300: =K300+L300+M300+N300 -> 16031338 | P300: =S299 -> 1.095781e+08 | Q300: =P300*B3Ret/12 -> 1004465.9 | R300: =-N300 -> 0 | S300: =P300+Q300+R300 -> 1.1058256e+08 | T300: =J300+O300+S300 -> 1.2999377e+08
A301: 300 | B301: =ROUNDUP(A301/12,0) -> 25 | C301: =Age+B301-1 -> 86 | D301: =MonthlyExp*(1+Inflation)^(B301-1) -> 253618.35 | E301: =J300 -> 3379868 | F301: =E301*B1Ret/12 -> 19715.897 | G301: =D301 -> 253618.35 | H301: =MAX(SUM(D302:D361)-(E301+F301-G301),0) -> 15581084 | I301: =H301 -> 15581084 | J301: =E301+F301-G301+I301 -> 18727049 | K301: =O300 -> 16031338 | L301: =K301*B2Ret/12 -> 120235.03 | M301: =-I301 -> -15581084 | N301: =H301 -> 15581084 | O301: =K301+L301+M301+N301 -> 16151573 | P301: =S300 -> 1.1058256e+08 | Q301: =P301*B3Ret/12 -> 1013673.5 | R301: =-N301 -> -15581084 | S301: =P301+Q301+R301 -> 96015153 | T301: =J301+O301+S301 -> 1.3089377e+08
A302: 301 | B302: =ROUNDUP(A302/12,0) -> 26 | C302: =Age+B302-1 -> 87 | D302: =MonthlyExp*(1+Inflation)^(B302-1) -> 271371.63 | E302: =J301 -> 18727049 | F302: =E302*B1Ret/12 -> 109241.12 | G302: =D302 -> 271371.63 | H302: 0 | I302: =H302 -> 0 | J302: =E302+F302-G302+I302 -> 18564919 | K302: =O301 -> 16151573 | L302: =K302*B2Ret/12 -> 121136.8 | M302: =-I302 -> 0 | N302: 0 | O302: =K302+L302+M302+N302 -> 16272710 | P302: =S301 -> 96015153 | Q302: =P302*B3Ret/12 -> 880138.9 | R302: =-N302 -> 0 | S302: =P302+Q302+R302 -> 96895292 | T302: =J302+O302+S302 -> 1.3173292e+08
A303: 302 | B303: =ROUNDUP(A303/12,0) -> 26 | C303: =Age+B303-1 -> 87 | D303: =MonthlyExp*(1+Inflation)^(B303-1) -> 271371.63 | E303: =J302 -> 18564919 | F303: =E303*B1Ret/12 -> 108295.36 | G303: =D303 -> 271371.63 | H303: 0 | I303: =H303 -> 0 | J303: =E303+F303-G303+I303 -> 18401842 | K303: =O302 -> 16272710 | L303: =K303*B2Ret/12 -> 122045.32 | M303: =-I303 -> 0 | N303: 0 | O303: =K303+L303+M303+N303 -> 16394755 | P303: =S302 -> 96895292 | Q303: =P303*B3Ret/12 -> 888206.84 | R303: =-N303 -> 0 | S303: =P303+Q303+R303 -> 97783498 | T303: =J303+O303+S303 -> 1.325801e+08
A304: 303 | B304: =ROUNDUP(A304/12,0) -> 26 | C304: =Age+B304-1 -> 87 | D304: =MonthlyExp*(1+Inflation)^(B304-1) -> 271371.63 | E304: =J303 -> 18401842 | F304: =E304*B1Ret/12 -> 107344.08 | G304: =D304 -> 271371.63 | H304: 0 | I304: =H304 -> 0 | J304: =E304+F304-G304+I304 -> 18237815 | K304: =O303 -> 16394755 | L304: =K304*B2Ret/12 -> 122960.66 | M304: =-I304 -> 0 | N304: 0 | O304: =K304+L304+M304+N304 -> 16517716 | P304: =S303 -> 97783498 | Q304: =P304*B3Ret/12 -> 896348.74 | R304: =-N304 -> 0 | S304: =P304+Q304+R304 -> 98679847 | T304: =J304+O304+S304 -> 1.3343538e+08
A305: 304 | B305: =ROUNDUP(A305/12,0) -> 26 | C305: =Age+B305-1 -> 87 | D305: =MonthlyExp*(1+Inflation)^(B305-1) -> 271371.63 | E305: =J304 -> 18237815 | F305: =E305*B1Ret/12 -> 106387.25 | G305: =D305 -> 271371.63 | H305: 0 | I305: =H305 -> 0 | J305: =E305+F305-G305+I305 -> 18072830 | K305: =O304 -> 16517716 | L305: =K305*B2Ret/12 -> 123882.87 | M305: =-I305 -> 0 | N305: 0 | O305: =K305+L305+M305+N305 -> 16641599 | P305: =S304 -> 98679847 | Q305: =P305*B3Ret/12 -> 904565.27 | R305: =-N305 -> 0 | S305: =P305+Q305+R305 -> 99584412 | T305: =J305+O305+S305 -> 1.3429884e+08
A306: 305 | B306: =ROUNDUP(A306/12,0) -> 26 | C306: =Age+B306-1 -> 87 | D306: =MonthlyExp*(1+Inflation)^(B306-1) -> 271371.63 | E306: =J305 -> 18072830 | F306: =E306*B1Ret/12 -> 105424.84 | G306: =D306 -> 271371.63 | H306: 0 | I306: =H306 -> 0 | J306: =E306+F306-G306+I306 -> 17906884 | K306: =O305 -> 16641599 | L306: =K306*B2Ret/12 -> 124811.99 | M306: =-I306 -> 0 | N306: 0 | O306: =K306+L306+M306+N306 -> 16766411 | P306: =S305 -> 99584412 | Q306: =P306*B3Ret/12 -> 912857.11 | R306: =-N306 -> 0 | S306: =P306+Q306+R306 -> 1.0049727e+08 | T306: =J306+O306+S306 -> 1.3517056e+08
A307: 306 | B307: =ROUNDUP(A307/12,0) -> 26 | C307: =Age+B307-1 -> 87 | D307: =MonthlyExp*(1+Inflation)^(B307-1) -> 271371.63 | E307: =J306 -> 17906884 | F307: =E307*B1Ret/12 -> 104456.82 | G307: =D307 -> 271371.63 | H307: 0 | I307: =H307 -> 0 | J307: =E307+F307-G307+I307 -> 17739969 | K307: =O306 -> 16766411 | L307: =K307*B2Ret/12 -> 125748.08 | M307: =-I307 -> 0 | N307: 0 | O307: =K307+L307+M307+N307 -> 16892159 | P307: =S306 -> 1.0049727e+08 | Q307: =P307*B3Ret/12 -> 921224.97 | R307: =-N307 -> 0 | S307: =P307+Q307+R307 -> 1.0141849e+08 | T307: =J307+O307+S307 -> 1.3605062e+08
A308: 307 | B308: =ROUNDUP(A308/12,0) -> 26 | C308: =Age+B308-1 -> 87 | D308: =MonthlyExp*(1+Inflation)^(B308-1) -> 271371.63 | E308: =J307 -> 17739969 | F308: =E308*B1Ret/12 -> 103483.15 | G308: =D308 -> 271371.63 | H308: 0 | I308: =H308 -> 0 | J308: =E308+F308-G308+I308 -> 17572080 | K308: =O307 -> 16892159 | L308: =K308*B2Ret/12 -> 126691.19 | M308: =-I308 -> 0 | N308: 0 | O308: =K308+L308+M308+N308 -> 17018850 | P308: =S307 -> 1.0141849e+08 | Q308: =P308*B3Ret/12 -> 929669.53 | R308: =-N308 -> 0 | S308: =P308+Q308+R308 -> 1.0234816e+08 | T308: =J308+O308+S308 -> 1.3693909e+08
A309: 308 | B309: =ROUNDUP(A309/12,0) -> 26 | C309: =Age+B309-1 -> 87 | D309: =MonthlyExp*(1+Inflation)^(B309-1) -> 271371.63 | E309: =J308 -> 17572080 | F309: =E309*B1Ret/12 -> 102503.8 | G309: =D309 -> 271371.63 | H309: 0 | I309: =H309 -> 0 | J309: =E309+F309-G309+I309 -> 17403213 | K309: =O308 -> 17018850 | L309: =K309*B2Ret/12 -> 127641.37 | M309: =-I309 -> 0 | N309: 0 | O309: =K309+L309+M309+N309 -> 17146491 | P309: =S308 -> 1.0234816e+08 | Q309: =P309*B3Ret/12 -> 938191.5 | R309: =-N309 -> 0 | S309: =P309+Q309+R309 -> 1.0328636e+08 | T309: =J309+O309+S309 -> 1.3783606e+08
A310: 309 | B310: =ROUNDUP(A310/12,0) -> 26 | C310: =Age+B310-1 -> 87 | D310: =MonthlyExp*(1+Inflation)^(B310-1) -> 271371.63 | E310: =J309 -> 17403213 | F310: =E310*B1Ret/12 -> 101518.74 | G310: =D310 -> 271371.63 | H310: 0 | I310: =H310 -> 0 | J310: =E310+F310-G310+I310 -> 17233360 | K310: =O309 -> 17146491 | L310: =K310*B2Ret/12 -> 128598.68 | M310: =-I310 -> 0 | N310: 0 | O310: =K310+L310+M310+N310 -> 17275090 | P310: =S309 -> 1.0328636e+08 | Q310: =P310*B3Ret/12 -> 946791.59 | R310: =-N310 -> 0 | S310: =P310+Q310+R310 -> 1.0423315e+08 | T310: =J310+O310+S310 -> 1.387416e+08
A311: 310 | B311: =ROUNDUP(A311/12,0) -> 26 | C311: =Age+B311-1 -> 87 | D311: =MonthlyExp*(1+Inflation)^(B311-1) -> 271371.63 | E311: =J310 -> 17233360 | F311: =E311*B1Ret/12 -> 100527.93 | G311: =D311 -> 271371.63 | H311: 0 | I311: =H311 -> 0 | J311: =E311+F311-G311+I311 -> 17062516 | K311: =O310 -> 17275090 | L311: =K311*B2Ret/12 -> 129563.18 | M311: =-I311 -> 0 | N311: 0 | O311: =K311+L311+M311+N311 -> 17404653 | P311: =S310 -> 1.0423315e+08 | Q311: =P311*B3Ret/12 -> 955470.52 | R311: =-N311 -> 0 | S311: =P311+Q311+R311 -> 1.0518862e+08 | T311: =J311+O311+S311 -> 1.3965579e+08
A312: 311 | B312: =ROUNDUP(A312/12,0) -> 26 | C312: =Age+B312-1 -> 87 | D312: =MonthlyExp*(1+Inflation)^(B312-1) -> 271371.63 | E312: =J311 -> 17062516 | F312: =E312*B1Ret/12 -> 99531.343 | G312: =D312 -> 271371.63 | H312: 0 | I312: =H312 -> 0 | J312: =E312+F312-G312+I312 -> 16890676 | K312: =O311 -> 17404653 | L312: =K312*B2Ret/12 -> 130534.9 | M312: =-I312 -> 0 | N312: 0 | O312: =K312+L312+M312+N312 -> 17535188 | P312: =S311 -> 1.0518862e+08 | Q312: =P312*B3Ret/12 -> 964228.99 | R312: =-N312 -> 0 | S312: =P312+Q312+R312 -> 1.0615285e+08 | T312: =J312+O312+S312 -> 1.4057871e+08
A313: 312 | B313: =ROUNDUP(A313/12,0) -> 26 | C313: =Age+B313-1 -> 87 | D313: =MonthlyExp*(1+Inflation)^(B313-1) -> 271371.63 | E313: =J312 -> 16890676 | F313: =E313*B1Ret/12 -> 98528.941 | G313: =D313 -> 271371.63 | H313: 0 | I313: =H313 -> 0 | J313: =E313+F313-G313+I313 -> 16717833 | K313: =O312 -> 17535188 | L313: =K313*B2Ret/12 -> 131513.91 | M313: =-I313 -> 0 | N313: 0 | O313: =K313+L313+M313+N313 -> 17666702 | P313: =S312 -> 1.0615285e+08 | Q313: =P313*B3Ret/12 -> 973067.76 | R313: =-N313 -> 0 | S313: =P313+Q313+R313 -> 1.0712591e+08 | T313: =J313+O313+S313 -> 1.4151045e+08
... A361: 360 | B361: =ROUNDUP(A361/12,0) -> 30 | C361: =Age+B361-1 -> 91 | D361: =MonthlyExp*(1+Inflation)^(B361-1) -> 355712.85 | E361: =J360 -> 4740439.7 | F361: =E361*B1Ret/12 -> 27652.565 | G361: =D361 -> 355712.85 | H361: 0 | I361: =H361 -> 0 | J361: =E361+F361-G361+I361 -> 4412379.4 | K361: =O360 -> 25099962 | L361: =K361*B2Ret/12 -> 188249.71 | M361: =-I361 -> 0 | N361: 0 | O361: =K361+L361+M361+N361 -> 25288211 | P361: =S360 -> 1.6449424e+08 | Q361: =P361*B3Ret/12 -> 1507863.9 | R361: =-N361 -> 0 | S361: =P361+Q361+R361 -> 1.6600211e+08 | T361: =J361+O361+S361 -> 1.957027e+08

Sheet Annual Summary
A1: Year | B1: Age | C1: Opening Total Corpus | D1: Annual Withdrawal (inflation-adjusted) | E1: Avg Monthly Income that Year | F1: Investment Return (the year) | G1: Bucket 1 Closing | H1: Bucket 2 Closing | I1: Bucket 3 Closing | J1: Closing Total Corpus | K1: Withdrawal Rate (of Opening Corpus) | L1: Health Status
A2: 1 | B2: =Age+A2-1 -> 62 | C2: =Corpus -> 20000000 | D2: =SUMIFS('Monthly Engine'!$D:$D,'Monthly Engine'!$B:$B,A2) -> 600000 | E2: =D2/12 -> 50000 | F2: =J2-C2+D2 -> 2011077.6 | G2: ='Monthly Engine'!J13 -> 2597241 | H2: ='Monthly Engine'!O13 -> 7656648.3 | I2: ='Monthly Engine'!S13 -> 11157188 | J2: =G2+H2+I2 -> 21411078 | K2: =D2/C2 -> 0.03 | L2: =IF(K2<=GreenBand,"GREEN",IF(K2<=YellowBand,"YELLOW","RED")) -> GREEN
A3: 2 | B3: =Age+A3-1 -> 63 | C3: =J2 -> 21411078 | D3: =SUMIFS('Monthly Engine'!$D:$D,'Monthly Engine'!$B:$B,A3) -> 642000 | E3: =D3/12 -> 53500 | F3: =J3-C3+D3 -> 2176094.7 | G3: ='Monthly Engine'!J25 -> 2121992.4 | H3: ='Monthly Engine'!O25 -> 8374894.7 | I3: ='Monthly Engine'!S25 -> 12448285 | J3: =G3+H3+I3 -> 22945172 | K3: =D3/C3 -> 0.029984479 | L3: =IF(K3<=GreenBand,"GREEN",IF(K3<=YellowBand,"YELLOW","RED")) -> GREEN
A4: 3 | B4: =Age+A4-1 -> 64 | C4: =J3 -> 22945172 | D4: =SUMIFS('Monthly Engine'!$D:$D,'Monthly Engine'!$B:$B,A4) -> 686940 | E4: =D4/12 -> 57245 | F4: =J4-C4+D4 -> 2357049.4 | G4: ='Monthly Engine'!J37 -> 1565977.9 | H4: ='Monthly Engine'!O37 -> 9160517.6 | I4: ='Monthly Engine'!S37 -> 13888786 | J4: =G4+H4+I4 -> 24615282 | K4: =D4/C4 -> 0.029938324 | L4: =IF(K4<=GreenBand,"GREEN",IF(K4<=YellowBand,"YELLOW","RED")) -> GREEN
A5: 4 | B5: =Age+A5-1 -> 65 | C5: =J4 -> 24615282 | D5: =SUMIFS('Monthly Engine'!$D:$D,'Monthly Engine'!$B:$B,A5) -> 735025.8 | E5: =D5/12 -> 61252.15 | F5: =J5-C5+D5 -> 2555671.9 | G5: ='Monthly Engine'!J49 -> 920110.06 | H5: ='Monthly Engine'!O49 -> 10019837 | I5: ='Monthly Engine'!S49 -> 15495980 | J5: =G5+H5+I5 -> 26435928 | K5: =D5/C5 -> 0.029860548 | L5: =IF(K5<=GreenBand,"GREEN",IF(K5<=YellowBand,"YELLOW","RED")) -> GREEN
A6: 5 | B6: =Age+A6-1 -> 66 | C6: =J5 -> 26435928 | D6: =SUMIFS('Monthly Engine'!$D:$D,'Monthly Engine'!$B:$B,A6) -> 786477.61 | E6: =D6/12 -> 65539.8 | F6: =J6-C6+D6 -> 2773891.6 | G6: ='Monthly Engine'!J61 -> 4839425.4 | H6: ='Monthly Engine'!O61 -> 6294759.1 | I6: ='Monthly Engine'!S61 -> 17289157 | J6: =G6+H6+I6 -> 28423342 | K6: =D6/C6 -> 0.029750331 | L6: =IF(K6<=GreenBand,"GREEN",IF(K6<=YellowBand,"YELLOW","RED")) -> GREEN
A7: 6 | B7: =Age+A7-1 -> 67 | C7: =J6 -> 28423342 | D7: =SUMIFS('Monthly Engine'!$D:$D,'Monthly Engine'!$B:$B,A7) -> 841531.04 | E7: =D7/12 -> 70127.587 | F7: =J7-C7+D7 -> 2913484.4 | G7: ='Monthly Engine'!J73 -> 4320205.7 | H7: ='Monthly Engine'!O73 -> 6885251 | I7: ='Monthly Engine'!S73 -> 19289838 | J7: =G7+H7+I7 -> 30495295 | K7: =D7/C7 -> 0.029607041 | L7: =IF(K7<=GreenBand,"GREEN",IF(K7<=YellowBand,"YELLOW","RED")) -> GREEN
A8: 7 | B8: =Age+A8-1 -> 68 | C8: =J7 -> 30495295 | D8: =SUMIFS('Monthly Engine'!$D:$D,'Monthly Engine'!$B:$B,A8) -> 900438.21 | E8: =D8/12 -> 75036.518 | F8: =J8-C8+D8 -> 3160931.5 | G8: ='Monthly Engine'!J85 -> 3702617.3 | H8: ='Monthly Engine'!O85 -> 7531135 | I8: ='Monthly Engine'!S85 -> 21522036 | J8: =G8+H8+I8 -> 32755788 | K8: =D8/C8 -> 0.029527119 | L8: =IF(K8<=GreenBand,"GREEN",IF(K8<=YellowBand,"YELLOW","RED")) -> GREEN
A9: 8 | B9: =Age+A9-1 -> 69 | C9: =J8 -> 32755788 | D9: =SUMIFS('Monthly Engine'!$D:$D,'Monthly Engine'!$B:$B,A9) -> 963468.89 | E9: =D9/12 -> 80289.074 | F9: =J9-C9+D9 -> 3433119.6 | G9: ='Monthly Engine'!J97 -> 2975290.6 | H9: ='Monthly Engine'!O97 -> 8237607.4 | I9: ='Monthly Engine'!S97 -> 24012541 | J9: =G9+H9+I9 -> 35225439 | K9: =D9/C9 -> 0.029413699 | L9: =IF(K9<=GreenBand,"GREEN",IF(K9<=YellowBand,"YELLOW","RED")) -> GREEN
A10: 9 | B10: =Age+A10-1 -> 70 | C10: =J9 -> 35225439 | D10: =SUMIFS('Monthly Engine'!$D:$D,'Monthly Engine'!$B:$B,A10) -> 1030911.7 | E10: =D10/12 -> 85909.309 | F10: =J10-C10+D10 -> 3732805 | G10: ='Monthly Engine'!J109 -> 2125736.2 | H10: ='Monthly Engine'!O109 -> 9010351.8 | I10: ='Monthly Engine'!S109 -> 26791244 | J10: =G10+H10+I10 -> 37927332 | K10: =D10/C10 -> 0.029266114 | L10: =IF(K10<=GreenBand,"GREEN",IF(K10<=YellowBand,"YELLOW","RED")) -> GREEN
A11: 10 | B11: =Age+A11-1 -> 71 | C11: =J10 -> 37927332 | D11: =SUMIFS('Monthly Engine'!$D:$D,'Monthly Engine'!$B:$B,A11) -> 1103075.5 | E11: =D11/12 -> 91922.961 | F11: =J11-C11+D11 -> 4063066.8 | G11: ='Monthly Engine'!J121 -> 6787544.4 | H11: ='Monthly Engine'!O121 -> 4208283.2 | I11: ='Monthly Engine'!S121 -> 29891496 | J11: =G11+H11+I11 -> 40887324 | K11: =D11/C11 -> 0.029083921 | L11: =IF(K11<=GreenBand,"GREEN",IF(K11<=YellowBand,"YELLOW","RED")) -> GREEN
A12: 11 | B12: =Age+A12-1 -> 72 | C12: =J11 -> 40887324 | D12: =SUMIFS('Monthly Engine'!$D:$D,'Monthly Engine'!$B:$B,A12) -> 1180290.8 | E12: =D12/12 -> 98357.568 | F12: =J12-C12+D12 -> 4305833.5 | G12: ='Monthly Engine'!J133 -> 6059312 | H12: ='Monthly Engine'!O133 -> 4603049.2 | I12: ='Monthly Engine'!S133 -> 33350505 | J12: =G12+H12+I12 -> 44012866 | K12: =D12/C12 -> 0.028866913 | L12: =IF(K12<=GreenBand,"GREEN",IF(K12<=YellowBand,"YELLOW","RED")) -> GREEN
A13: 12 | B13: =Age+A13-1 -> 73 | C13: =J12 -> 44012866 | D13: =SUMIFS('Monthly Engine'!$D:$D,'Monthly Engine'!$B:$B,A13) -> 1262911.2 | E13: =D13/12 -> 105242.6 | F13: =J13-C13+D13 -> 4687790.9 | G13: ='Monthly Engine'!J145 -> 5193112.3 | H13: ='Monthly Engine'!O145 -> 5034847 | I13: ='Monthly Engine'!S145 -> 37209787 | J13: =G13+H13+I13 -> 47437746 | K13: =D13/C13 -> 0.028694136 | L13: =IF(K13<=GreenBand,"GREEN",IF(K13<=YellowBand,"YELLOW","RED")) -> GREEN
A14: 13 | B14: =Age+A14-1 -> 74 | C14: =J13 -> 47437746 | D14: =SUMIFS('Monthly Engine'!$D:$D,'Monthly Engine'!$B:$B,A14) -> 1351315 | E14: =D14/12 -> 112609.58 | F14: =J14-C14+D14 -> 5109378.2 | G14: ='Monthly Engine'!J157 -> 4172999 | H14: ='Monthly Engine'!O157 -> 5507150.3 | I14: ='Monthly Engine'!S157 -> 41515660 | J14: =G14+H14+I14 -> 51195809 | K14: =D14/C14 -> 0.02848607 | L14: =IF(K14<=GreenBand,"GREEN",IF(K14<=YellowBand,"YELLOW","RED")) -> GREEN
A15: 14 | B15: =Age+A15-1 -> 75 | C15: =J14 -> 51195809 | D15: =SUMIFS('Monthly Engine'!$D:$D,'Monthly Engine'!$B:$B,A15) -> 1445907 | E15: =D15/12 -> 120492.25 | F15: =J15-C15+D15 -> 5575115.5 | G15: ='Monthly Engine'!J169 -> 2981454.9 | H15: ='Monthly Engine'!O169 -> 6023759 | I15: ='Monthly Engine'!S169 -> 46319804 | J15: =G15+H15+I15 -> 55325018 | K15: =D15/C15 -> 0.028242683 | L15: =IF(K15<=GreenBand,"GREEN",IF(K15<=YellowBand,"YELLOW","RED")) -> GREEN
A16: 15 | B16: =Age+A16-1 -> 76 | C16: =J15 -> 55325018 | D16: =SUMIFS('Monthly Engine'!$D:$D,'Monthly Engine'!$B:$B,A16) -> 1547120.5 | E16: =D16/12 -> 128926.71 | F16: =J16-C16+D16 -> 6090058.8 | G16: ='Monthly Engine'!J181 -> 9519882.2 | H16: ='Monthly Engine'!O181 -> 6588829.2 | I16: ='Monthly Engine'!S181 -> 43759245 | J16: =G16+H16+I16 -> 59867956 | K16: =D16/C16 -> 0.027964211 | L16: =IF(K16<=GreenBand,"GREEN",IF(K16<=YellowBand,"YELLOW","RED")) -> GREEN
A17: 16 | B17: =Age+A17-1 -> 77 | C17: =J16 -> 59867956 | D17: =SUMIFS('Monthly Engine'!$D:$D,'Monthly Engine'!$B:$B,A17) -> 1655418.9 | E17: =D17/12 -> 137951.58 | F17: =J17-C17+D17 -> 6315881.8 | G17: ='Monthly Engine'!J193 -> 8498498.6 | H17: ='Monthly Engine'!O193 -> 7206906.8 | I17: ='Monthly Engine'!S193 -> 48823014 | J17: =G17+H17+I17 -> 64528419 | K17: =D17/C17 -> 0.027651168 | L17: =IF(K17<=GreenBand,"GREEN",IF(K17<=YellowBand,"YELLOW","RED")) -> GREEN
A18: 17 | B18: =Age+A18-1 -> 78 | C18: =J17 -> 64528419 | D18: =SUMIFS('Monthly Engine'!$D:$D,'Monthly Engine'!$B:$B,A18) -> 1771298.2 | E18: =D18/12 -> 147608.19 | F18: =J18-C18+D18 -> 6882208.2 | G18: ='Monthly Engine'!J205 -> 7283608.7 | H18: ='Monthly Engine'!O205 -> 7882964.4 | I18: ='Monthly Engine'!S205 -> 54472756 | J18: =G18+H18+I18 -> 69639329 | K18: =D18/C18 -> 0.027449894 | L18: =IF(K18<=GreenBand,"GREEN",IF(K18<=YellowBand,"YELLOW","RED")) -> GREEN
A19: 18 | B19: =Age+A19-1 -> 79 | C19: =J18 -> 69639329 | D19: =SUMIFS('Monthly Engine'!$D:$D,'Monthly Engine'!$B:$B,A19) -> 1895289.1 | E19: =D19/12 -> 157940.76 | F19: =J19-C19+D19 -> 7507527.8 | G19: ='Monthly Engine'!J217 -> 5852847 | H19: ='Monthly Engine'!O217 -> 8622440.8 | I19: ='Monthly Engine'!S217 -> 60776280 | J19: =G19+H19+I19 -> 75251568 | K19: =D19/C19 -> 0.027215787 | L19: =IF(K19<=GreenBand,"GREEN",IF(K19<=YellowBand,"YELLOW","RED")) -> GREEN
A20: 19 | B20: =Age+A20-1 -> 80 | C20: =J19 -> 75251568 | D20: =SUMIFS('Monthly Engine'!$D:$D,'Monthly Engine'!$B:$B,A20) -> 2027959.4 | E20: =D20/12 -> 168996.61 | F20: =J20-C20+D20 -> 8198562 | G20: ='Monthly Engine'!J229 -> 4181644.8 | H20: ='Monthly Engine'!O229 -> 9431285.2 | I20: ='Monthly Engine'!S229 -> 67809240 | J20: =G20+H20+I20 -> 81422170 | K20: =D20/C20 -> 0.026949065 | L20: =IF(K20<=GreenBand,"GREEN",IF(K20<=YellowBand,"YELLOW","RED")) -> GREEN
A21: 20 | B21: =Age+A21-1 -> 81 | C21: =J20 -> 81422170 | D21: =SUMIFS('Monthly Engine'!$D:$D,'Monthly Engine'!$B:$B,A21) -> 2169916.5 | E21: =D21/12 -> 180826.38 | F21: =J21-C21+D21 -> 8962827.7 | G21: ='Monthly Engine'!J241 -> 13352127 | H21: ='Monthly Engine'!O241 -> 10316005 | I21: ='Monthly Engine'!S241 -> 64546949 | J21: =G21+H21+I21 -> 88215082 | K21: =D21/C21 -> 0.026650193 | L21: =IF(K21<=GreenBand,"GREEN",IF(K21<=YellowBand,"YELLOW","RED")) -> GREEN
A22: 21 | B22: =Age+A22-1 -> 82 | C22: =J21 -> 88215082 | D22: =SUMIFS('Monthly Engine'!$D:$D,'Monthly Engine'!$B:$B,A22) -> 2321810.7 | E22: =D22/12 -> 193484.22 | F22: =J22-C22+D22 -> 9326277.6 | G22: ='Monthly Engine'!J253 -> 11919584 | H22: ='Monthly Engine'!O253 -> 11283717 | I22: ='Monthly Engine'!S253 -> 72016247 | J22: =G22+H22+I22 -> 95219548 | K22: =D22/C22 -> 0.026319884 | L22: =IF(K22<=GreenBand,"GREEN",IF(K22<=YellowBand,"YELLOW","RED")) -> GREEN
A23: 22 | B23: =Age+A23-1 -> 83 | C23: =J22 -> 95219548 | D23: =SUMIFS('Monthly Engine'!$D:$D,'Monthly Engine'!$B:$B,A23) -> 2484337.4 | E23: =D23/12 -> 207028.12 | F23: =J23-C23+D23 -> 10172518 | G23: ='Monthly Engine'!J265 -> 10215638 | H23: ='Monthly Engine'!O265 -> 12342208 | I23: ='Monthly Engine'!S265 -> 80349884 | J23: =G23+H23+I23 -> 1.0290773e+08 | K23: =D23/C23 -> 0.026090624 | L23: =IF(K23<=GreenBand,"GREEN",IF(K23<=YellowBand,"YELLOW","RED")) -> GREEN
A24: 23 | B24: =Age+A24-1 -> 84 | C24: =J23 -> 1.0290773e+08 | D24: =SUMIFS('Monthly Engine'!$D:$D,'Monthly Engine'!$B:$B,A24) -> 2658241 | E24: =D24/12 -> 221520.09 | F24: =J24-C24+D24 -> 11107303 | G24: ='Monthly Engine'!J277 -> 8208920.6 | H24: ='Monthly Engine'!O277 -> 13499992 | I24: ='Monthly Engine'!S277 -> 89647879 | J24: =G24+H24+I24 -> 1.1135679e+08 | K24: =D24/C24 -> 0.025831306 | L24: =IF(K24<=GreenBand,"GREEN",IF(K24<=YellowBand,"YELLOW","RED")) -> GREEN
A25: 24 | B25: =Age+A25-1 -> 85 | C25: =J24 -> 1.1135679e+08 | D25: =SUMIFS('Monthly Engine'!$D:$D,'Monthly Engine'!$B:$B,A25) -> 2844317.9 | E25: =D25/12 -> 237026.49 | F25: =J25-C25+D25 -> 12140711 | G25: ='Monthly Engine'!J289 -> 5864973.1 | H25: ='Monthly Engine'!O289 -> 14766384 | I25: ='Monthly Engine'!S289 -> 1.0002183e+08 | J25: =G25+H25+I25 -> 1.2065318e+08 | K25: =D25/C25 -> 0.025542384 | L25: =IF(K25<=GreenBand,"GREEN",IF(K25<=YellowBand,"YELLOW","RED")) -> GREEN
A26: 25 | B26: =Age+A26-1 -> 86 | C26: =J25 -> 1.2065318e+08 | D26: =SUMIFS('Monthly Engine'!$D:$D,'Monthly Engine'!$B:$B,A26) -> 3043420.2 | E26: =D26/12 -> 253618.35 | F26: =J26-C26+D26 -> 13284011 | G26: ='Monthly Engine'!J301 -> 18727049 | H26: ='Monthly Engine'!O301 -> 16151573 | I26: ='Monthly Engine'!S301 -> 96015153 | J26: =G26+H26+I26 -> 1.3089377e+08 | K26: =D26/C26 -> 0.025224533 | L26: =IF(K26<=GreenBand,"GREEN",IF(K26<=YellowBand,"YELLOW","RED")) -> GREEN
A27: 26 | B27: =Age+A27-1 -> 87 | C27: =J26 -> 1.3089377e+08 | D27: =SUMIFS('Monthly Engine'!$D:$D,'Monthly Engine'!$B:$B,A27) -> 3256459.6 | E27: =D27/12 -> 271371.63 | F27: =J27-C27+D27 -> 13873134 | G27: ='Monthly Engine'!J313 -> 16717833 | H27: ='Monthly Engine'!O313 -> 17666702 | I27: ='Monthly Engine'!S313 -> 1.0712591e+08 | J27: =G27+H27+I27 -> 1.4151045e+08 | K27: =D27/C27 -> 0.024878644 | L27: =IF(K27<=GreenBand,"GREEN",IF(K27<=YellowBand,"YELLOW","RED")) -> GREEN
A28: 27 | B28: =Age+A28-1 -> 88 | C28: =J27 -> 1.4151045e+08 | D28: =SUMIFS('Monthly Engine'!$D:$D,'Monthly Engine'!$B:$B,A28) -> 3484411.8 | E28: =D28/12 -> 290367.65 | F28: =J28-C28+D28 -> 15148284 | G28: ='Monthly Engine'!J325 -> 14327961 | H28: ='Monthly Engine'!O325 -> 19323960 | I28: ='Monthly Engine'!S325 -> 1.195224e+08 | J28: =G28+H28+I28 -> 1.5317432e+08 | K28: =D28/C28 -> 0.024623 | L28: =IF(K28<=GreenBand,"GREEN",IF(K28<=YellowBand,"YELLOW","RED")) -> GREEN
A29: 28 | B29: =Age+A29-1 -> 89 | C29: =J28 -> 1.5317432e+08 | D29: =SUMIFS('Monthly Engine'!$D:$D,'Monthly Engine'!$B:$B,A29) -> 3728320.6 | E29: =D29/12 -> 310693.38 | F29: =J29-C29+D29 -> 16557510 | G29: ='Monthly Engine'!J337 -> 11513436 | H29: ='Monthly Engine'!O337 -> 21136681 | I29: ='Monthly Engine'!S337 -> 1.3335339e+08 | J29: =G29+H29+I29 -> 1.6600351e+08 | K29: =D29/C29 -> 0.024340376 | L29: =IF(K29<=GreenBand,"GREEN",IF(K29<=YellowBand,"YELLOW","RED")) -> GREEN
A30: 29 | B30: =Age+A30-1 -> 90 | C30: =J29 -> 1.6600351e+08 | D30: =SUMIFS('Monthly Engine'!$D:$D,'Monthly Engine'!$B:$B,A30) -> 3989303 | E30: =D30/12 -> 332441.92 | F30: =J30-C30+D30 -> 18116061 | G30: ='Monthly Engine'!J349 -> 8225928.2 | H30: ='Monthly Engine'!O349 -> 23119448 | I30: ='Monthly Engine'!S349 -> 1.4878489e+08 | J30: =G30+H30+I30 -> 1.8013027e+08 | K30: =D30/C30 -> 0.024031438 | L30: =IF(K30<=GreenBand,"GREEN",IF(K30<=YellowBand,"YELLOW","RED")) -> GREEN
A31: 30 | B31: =Age+A31-1 -> 91 | C31: =J30 -> 1.8013027e+08 | D31: =SUMIFS('Monthly Engine'!$D:$D,'Monthly Engine'!$B:$B,A31) -> 4268554.2 | E31: =D31/12 -> 355712.85 | F31: =J31-C31+D31 -> 19840984 | G31: ='Monthly Engine'!J361 -> 4412379.4 | H31: ='Monthly Engine'!O361 -> 25288211 | I31: ='Monthly Engine'!S361 -> 1.6600211e+08 | J31: =G31+H31+I31 -> 1.957027e+08 | K31: =D31/C31 -> 0.02369704 | L31: =IF(K31<=GreenBand,"GREEN",IF(K31<=YellowBand,"YELLOW","RED")) -> GREEN
A33: Note: Health Status compares each year's Withdrawal Rate to the SWR bands set in Assumptions (green ≤ 4%, yellow ≤ 6%, red above).

Sheet Scenario Analysis
A1: SCENARIO ANALYSIS — Worst / Expected / Best Case (simplified blended-portfolio view)
B3: Note: This sheet uses ONE blended portfolio return (weighted avg of the 3 buckets) applied annually — a simplified approximation for quick comparison. The detailed, accurate model is the 3-bucket 'Monthly Engine' + 'Annual Summary'.
B5: Blended Portfolio Return (Expected) | C5: =B1Pct*B1Ret+B2Pct*B2Ret+B3Pct*B3Ret -> 0.097
A7: Year | B7: Age | C7: Weak Case Closing Corpus | D7: Weak Case Annual Withdrawal | E7: Expected Case Closing Corpus | F7: Expected Case Annual Withdrawal | G7: Best Case Closing Corpus | H7: Best Case Annual Withdrawal
A8: 1 | B8: =Age+A8-1 -> 62 | C8: =(Corpus-D8)*(1+$C$5+Assumptions!$C$25) -> 20893800 | D8: =MonthlyExp*12*(1+Inflation)^(A8-1) -> 600000 | E8: =(Corpus-F8)*(1+$C$5+Assumptions!$C$26) -> 21281800 | F8: =MonthlyExp*12*(1+Inflation)^(A8-1) -> 600000 | G8: =(Corpus-H8)*(1+$C$5+Assumptions!$C$27) -> 21669800 | H8: =MonthlyExp*12*(1+Inflation)^(A8-1) -> 600000
A9: 2 | B9: =Age+A9-1 -> 63 | C9: =(C8-D9)*(1+$C$5+Assumptions!$C$25) -> 21811189 | D9: =MonthlyExp*12*(1+Inflation)^(A9-1) -> 642000 | E9: =(E8-F9)*(1+$C$5+Assumptions!$C$26) -> 22641861 | F9: =MonthlyExp*12*(1+Inflation)^(A9-1) -> 642000 | G9: =(G8-H9)*(1+$C$5+Assumptions!$C$27) -> 23488053 | H9: =MonthlyExp*12*(1+Inflation)^(A9-1) -> 642000
A10: 3 | B10: =Age+A10-1 -> 64 | C10: =(C9-D10)*(1+$C$5+Assumptions!$C$25) -> 22750816 | D10: =MonthlyExp*12*(1+Inflation)^(A10-1) -> 686940 | E10: =(E9-F10)*(1+$C$5+Assumptions!$C$26) -> 24084548 | F10: =MonthlyExp*12*(1+Inflation)^(A10-1) -> 686940 | G10: =(G9-H10)*(1+$C$5+Assumptions!$C$27) -> 25468843 | H10: =MonthlyExp*12*(1+Inflation)^(A10-1) -> 686940
A11: 4 | B11: =Age+A11-1 -> 65 | C11: =(C10-D11)*(1+$C$5+Assumptions!$C$25) -> 23711006 | D11: =MonthlyExp*12*(1+Inflation)^(A11-1) -> 735025.8 | E11: =(E10-F11)*(1+$C$5+Assumptions!$C$26) -> 25614426 | F11: =MonthlyExp*12*(1+Inflation)^(A11-1) -> 735025.8 | G11: =(G10-H11)*(1+$C$5+Assumptions!$C$27) -> 27627674 | H11: =MonthlyExp*12*(1+Inflation)^(A11-1) -> 735025.8
A12: 5 | B12: =Age+A12-1 -> 66 | C12: =(C11-D12)*(1+$C$5+Assumptions!$C$25) -> 24689717 | D12: =MonthlyExp*12*(1+Inflation)^(A12-1) -> 786477.61 | E12: =(E11-F12)*(1+$C$5+Assumptions!$C$26) -> 27236259 | F12: =MonthlyExp*12*(1+Inflation)^(A12-1) -> 786477.61 | G12: =(G11-H12)*(1+$C$5+Assumptions!$C$27) -> 29981616 | H12: =MonthlyExp*12*(1+Inflation)^(A12-1) -> 786477.61
A13: 6 | B13: =Age+A13-1 -> 67 | C13: =(C12-D13)*(1+$C$5+Assumptions!$C$25) -> 25684496 | D13: =MonthlyExp*12*(1+Inflation)^(A13-1) -> 841531.04 | E13: =(E12-F13)*(1+$C$5+Assumptions!$C$26) -> 28955017 | F13: =MonthlyExp*12*(1+Inflation)^(A13-1) -> 841531.04 | G13: =(G12-H13)*(1+$C$5+Assumptions!$C$27) -> 32549475 | H13: =MonthlyExp*12*(1+Inflation)^(A13-1) -> 841531.04
A14: 7 | B14: =Age+A14-1 -> 68 | C14: =(C13-D14)*(1+$C$5+Assumptions!$C$25) -> 26692430 | D14: =MonthlyExp*12*(1+Inflation)^(A14-1) -> 900438.21 | E14: =(E13-F14)*(1+$C$5+Assumptions!$C$26) -> 30775873 | F14: =MonthlyExp*12*(1+Inflation)^(A14-1) -> 900438.21 | G14: =(G13-H14)*(1+$C$5+Assumptions!$C$27) -> 35351974 | H14: =MonthlyExp*12*(1+Inflation)^(A14-1) -> 900438.21
A15: 8 | B15: =Age+A15-1 -> 69 | C15: =(C14-D15)*(1+$C$5+Assumptions!$C$25) -> 27710091 | D15: =MonthlyExp*12*(1+Inflation)^(A15-1) -> 963468.89 | E15: =(E14-F15)*(1+$C$5+Assumptions!$C$26) -> 32704207 | F15: =MonthlyExp*12*(1+Inflation)^(A15-1) -> 963468.89 | G15: =(G14-H15)*(1+$C$5+Assumptions!$C$27) -> 38411960 | H15: =MonthlyExp*12*(1+Inflation)^(A15-1) -> 963468.89
A16: 9 | B16: =Age+A16-1 -> 70 | C16: =(C15-D16)*(1+$C$5+Assumptions!$C$25) -> 28733477 | D16: =MonthlyExp*12*(1+Inflation)^(A16-1) -> 1030911.7 | E16: =(E15-F16)*(1+$C$5+Assumptions!$C$26) -> 34745605 | F16: =MonthlyExp*12*(1+Inflation)^(A16-1) -> 1030911.7 | G16: =(G15-H16)*(1+$C$5+Assumptions!$C$27) -> 41754631 | H16: =MonthlyExp*12*(1+Inflation)^(A16-1) -> 1030911.7
A17: 10 | B17: =Age+A17-1 -> 71 | C17: =(C16-D17)*(1+$C$5+Assumptions!$C$25) -> 29757942 | D17: =MonthlyExp*12*(1+Inflation)^(A17-1) -> 1103075.5 | E17: =(E16-F17)*(1+$C$5+Assumptions!$C$26) -> 36905855 | F17: =MonthlyExp*12*(1+Inflation)^(A17-1) -> 1103075.5 | G17: =(G16-H17)*(1+$C$5+Assumptions!$C$27) -> 45407787 | H17: =MonthlyExp*12*(1+Inflation)^(A17-1) -> 1103075.5
A18: 11 | B18: =Age+A18-1 -> 72 | C18: =(C17-D18)*(1+$C$5+Assumptions!$C$25) -> 30778130 | D18: =MonthlyExp*12*(1+Inflation)^(A18-1) -> 1180290.8 | E18: =(E17-F18)*(1+$C$5+Assumptions!$C$26) -> 39190943 | F18: =MonthlyExp*12*(1+Inflation)^(A18-1) -> 1180290.8 | G18: =(G17-H18)*(1+$C$5+Assumptions!$C$27) -> 49402114 | H18: =MonthlyExp*12*(1+Inflation)^(A18-1) -> 1180290.8
A19: 12 | B19: =Age+A19-1 -> 73 | C19: =(C18-D19)*(1+$C$5+Assumptions!$C$25) -> 31787891 | D19: =MonthlyExp*12*(1+Inflation)^(A19-1) -> 1262911.2 | E19: =(E18-F19)*(1+$C$5+Assumptions!$C$26) -> 41607051 | F19: =MonthlyExp*12*(1+Inflation)^(A19-1) -> 1262911.2 | G19: =(G18-H19)*(1+$C$5+Assumptions!$C$27) -> 53771489 | H19: =MonthlyExp*12*(1+Inflation)^(A19-1) -> 1262911.2
A20: 13 | B20: =Age+A20-1 -> 74 | C20: =(C19-D20)*(1+$C$5+Assumptions!$C$25) -> 32780192 | D20: =MonthlyExp*12*(1+Inflation)^(A20-1) -> 1351315 | E20: =(E19-F20)*(1+$C$5+Assumptions!$C$26) -> 44160543 | F20: =MonthlyExp*12*(1+Inflation)^(A20-1) -> 1351315 | G20: =(G19-H20)*(1+$C$5+Assumptions!$C$27) -> 58553335 | H20: =MonthlyExp*12*(1+Inflation)^(A20-1) -> 1351315
... A37: 30 | B37: =Age+A37-1 -> 91 | C37: =(C36-D37)*(1+$C$5+Assumptions!$C$25) -> 33305257 | D37: =MonthlyExp*12*(1+Inflation)^(A37-1) -> 4268554.2 | E37: =(E36-F37)*(1+$C$5+Assumptions!$C$26) -> 1.1518933e+08 | F37: =MonthlyExp*12*(1+Inflation)^(A37-1) -> 4268554.2 | G37: =(G36-H37)*(1+$C$5+Assumptions!$C$27) -> 2.6723376e+08 | H37: =MonthlyExp*12*(1+Inflation)^(A37-1) -> 4268554.2
B39: Ending Corpus after 30 Years: | C39: =C37 -> 33305257 | E39: =E37 -> 1.1518933e+08 | G39: =G37 -> 2.6723376e+08
B40: Corpus Lasts Full 30 Years? | C40: =IF(MIN(C8:C37)>0,"YES","NO") -> YES | E40: =IF(MIN(E8:E37)>0,"YES","NO") -> YES | G40: =IF(MIN(G8:G37)>0,"YES","NO") -> YES

Sheet Monte Carlo
A1: MONTE CARLO SIMULATION — Probability Analysis (40 random trials, press F9 to resample)
B3: Each trial draws a random annual portfolio return every year (Normal distribution, mean = blended expected return, std. dev. = blended volatility from Assumptions) and applies it to the same withdrawal schedule as the Expected Case. Corpus is floored at ₹0 (cannot go negative).
B6: Blended Expected Return | C6: =B1Pct*B1Ret+B2Pct*B2Ret+B3Pct*B3Ret -> 0.097 | D6: Blended Volatility (std dev, approx.) | E6: =SQRT((B1Pct*Assumptions!$C$30)^2+(B2Pct*Assumptions!$C$31)^2+(B3Pct*Assumptions!$C$32)^2) -> 0.081905433
A8: Trial # | B8: Year 0 | C8: Yr 1 | D8: Yr 2 | E8: Yr 3 | F8: Yr 4 | G8: Yr 5 | H8: Yr 6 | I8: Yr 7 | J8: Yr 8 | K8: Yr 9 | L8: Yr 10 | M8: Yr 11 | N8: Yr 12 | O8: Yr 13 | P8: Yr 14 | Q8: Yr 15 | R8: Yr 16 | S8: Yr 17 | T8: Yr 18 | U8: Yr 19 | V8: Yr 20 | W8: Yr 21 | X8: Yr 22 | Y8: Yr 23 | Z8: Yr 24 | AA8: Yr 25 | AB8: Yr 26 | AC8: Yr 27 | AD8: Yr 28 | AE8: Yr 29 | AF8: Yr 30
A9: 1 | B9: =Corpus -> 20000000 | C9: =MAX(B9*(1+NORMINV(RAND(),$C$6,$E$6))-MonthlyExp*12*(1+Inflation)^(1-1),0) -> 21042407 | D9: =MAX(C9*(1+NORMINV(RAND(),$C$6,$E$6))-MonthlyExp*12*(1+Inflation)^(2-1),0) -> 21464807 | E9: =MAX(D9*(1+NORMINV(RAND(),$C$6,$E$6))-MonthlyExp*12*(1+Inflation)^(3-1),0) -> 23123505 | F9: =MAX(E9*(1+NORMINV(RAND(),$C$6,$E$6))-MonthlyExp*12*(1+Inflation)^(4-1),0) -> 23335189 | G9: =MAX(F9*(1+NORMINV(RAND(),$C$6,$E$6))-MonthlyExp*12*(1+Inflation)^(5-1),0) -> 21680300 | H9: =MAX(G9*(1+NORMINV(RAND(),$C$6,$E$6))-MonthlyExp*12*(1+Inflation)^(6-1),0) -> 23613216 | I9: =MAX(H9*(1+NORMINV(RAND(),$C$6,$E$6))-MonthlyExp*12*(1+Inflation)^(7-1),0) -> 25001599 | J9: =MAX(I9*(1+NORMINV(RAND(),$C$6,$E$6))-MonthlyExp*12*(1+Inflation)^(8-1),0) -> 28027599 | K9: =MAX(J9*(1+NORMINV(RAND(),$C$6,$E$6))-MonthlyExp*12*(1+Inflation)^(9-1),0) -> 31190971 | L9: =MAX(K9*(1+NORMINV(RAND(),$C$6,$E$6))-MonthlyExp*12*(1+Inflation)^(10-1),0) -> 32500616 | M9: =MAX(L9*(1+NORMINV(RAND(),$C$6,$E$6))-MonthlyExp*12*(1+Inflation)^(11-1),0) -> 35565178 | N9: =MAX(M9*(1+NORMINV(RAND(),$C$6,$E$6))-MonthlyExp*12*(1+Inflation)^(12-1),0) -> 35709514 | O9: =MAX(N9*(1+NORMINV(RAND(),$C$6,$E$6))-MonthlyExp*12*(1+Inflation)^(13-1),0) -> 29383458 | P9: =MAX(O9*(1+NORMINV(RAND(),$C$6,$E$6))-MonthlyExp*12*(1+Inflation)^(14-1),0) -> 30046338 | Q9: =MAX(P9*(1+NORMINV(RAND(),$C$6,$E$6))-MonthlyExp*12*(1+Inflation)^(15-1),0) -> 29765285 | R9: =MAX(Q9*(1+NORMINV(RAND(),$C$6,$E$6))-MonthlyExp*12*(1+Inflation)^(16-1),0) -> 34342416 | S9: =MAX(R9*(1+NORMINV(RAND(),$C$6,$E$6))-MonthlyExp*12*(1+Inflation)^(17-1),0) -> 35589235 | T9: =MAX(S9*(1+NORMINV(RAND(),$C$6,$E$6))-MonthlyExp*12*(1+Inflation)^(18-1),0) -> 36358974 | U9: =MAX(T9*(1+NORMINV(RAND(),$C$6,$E$6))-MonthlyExp*12*(1+Inflation)^(19-1),0) -> 41879900 | V9: =MAX(U9*(1+NORMINV(RAND(),$C$6,$E$6))-MonthlyExp*12*(1+Inflation)^(20-1),0) -> 38797759 | W9: =MAX(V9*(1+NORMINV(RAND(),$C$6,$E$6))-MonthlyExp*12*(1+Inflation)^(21-1),0) -> 42226484 | X9: =MAX(W9*(1+NORMINV(RAND(),$C$6,$E$6))-MonthlyExp*12*(1+Inflation)^(22-1),0) -> 46148197 | Y9: =MAX(X9*(1+NORMINV(RAND(),$C$6,$E$6))-MonthlyExp*12*(1+Inflation)^(23-1),0) -> 42465586 | Z9: =MAX(Y9*(1+NORMINV(RAND(),$C$6,$E$6))-MonthlyExp*12*(1+Inflation)^(24-1),0) -> 39540427 | AA9: =MAX(Z9*(1+NORMINV(RAND(),$C$6,$E$6))-MonthlyExp*12*(1+Inflation)^(25-1),0) -> 43397607 | AB9: =MAX(AA9*(1+NORMINV(RAND(),$C$6,$E$6))-MonthlyExp*12*(1+Inflation)^(26-1),0) -> 51284322 | AC9: =MAX(AB9*(1+NORMINV(RAND(),$C$6,$E$6))-MonthlyExp*12*(1+Inflation)^(27-1),0) -> 48392876 | AD9: =MAX(AC9*(1+NORMINV(RAND(),$C$6,$E$6))-MonthlyExp*12*(1+Inflation)^(28-1),0) -> 49594197 | AE9: =MAX(AD9*(1+NORMINV(RAND(),$C$6,$E$6))-MonthlyExp*12*(1+Inflation)^(29-1),0) -> 58080027 | AF9: =MAX(AE9*(1+NORMINV(RAND(),$C$6,$E$6))-MonthlyExp*12*(1+Inflation)^(30-1),0) -> 55651651
A10: 2 | B10: =Corpus -> 20000000 | C10: =MAX(B10*(1+NORMINV(RAND(),$C$6,$E$6))-MonthlyExp*12*(1+Inflation)^(1-1),0) -> 21087293 | D10: =MAX(C10*(1+NORMINV(RAND(),$C$6,$E$6))-MonthlyExp*12*(1+Inflation)^(2-1),0) -> 25694380 | E10: =MAX(D10*(1+NORMINV(RAND(),$C$6,$E$6))-MonthlyExp*12*(1+Inflation)^(3-1),0) -> 26494553 | F10: =MAX(E10*(1+NORMINV(RAND(),$C$6,$E$6))-MonthlyExp*12*(1+Inflation)^(4-1),0) -> 28652704 | G10: =MAX(F10*(1+NORMINV(RAND(),$C$6,$E$6))-MonthlyExp*12*(1+Inflation)^(5-1),0) -> 29294270 | H10: =MAX(G10*(1+NORMINV(RAND(),$C$6,$E$6))-MonthlyExp*12*(1+Inflation)^(6-1),0) -> 30651537 | I10: =MAX(H10*(1+NORMINV(RAND(),$C$6,$E$6))-MonthlyExp*12*(1+Inflation)^(7-1),0) -> 30033240 | J10: =MAX(I10*(1+NORMINV(RAND(),$C$6,$E$6))-MonthlyExp*12*(1+Inflation)^(8-1),0) -> 36478639 | K10: =MAX(J10*(1+NORMINV(RAND(),$C$6,$E$6))-MonthlyExp*12*(1+Inflation)^(9-1),0) -> 37217126 | L10: =MAX(K10*(1+NORMINV(RAND(),$C$6,$E$6))-MonthlyExp*12*(1+Inflation)^(10-1),0) -> 38377530 | M10: =MAX(L10*(1+NORMINV(RAND(),$C$6,$E$6))-MonthlyExp*12*(1+Inflation)^(11-1),0) -> 35293489 | N10: =MAX(M10*(1+NORMINV(RAND(),$C$6,$E$6))-MonthlyExp*12*(1+Inflation)^(12-1),0) -> 37095333 | O10: =MAX(N10*(1+NORMINV(RAND(),$C$6,$E$6))-MonthlyExp*12*(1+Inflation)^(13-1),0) -> 42844509 | P10: =MAX(O10*(1+NORMINV(RAND(),$C$6,$E$6))-MonthlyExp*12*(1+Inflation)^(14-1),0) -> 46658766 | Q10: =MAX(P10*(1+NORMINV(RAND(),$C$6,$E$6))-MonthlyExp*12*(1+Inflation)^(15-1),0) -> 58595069 | R10: =MAX(Q10*(1+NORMINV(RAND(),$C$6,$E$6))-MonthlyExp*12*(1+Inflation)^(16-1),0) -> 64536365 | S10: =MAX(R10*(1+NORMINV(RAND(),$C$6,$E$6))-MonthlyExp*12*(1+Inflation)^(17-1),0) -> 66685779 | T10: =MAX(S10*(1+NORMINV(RAND(),$C$6,$E$6))-MonthlyExp*12*(1+Inflation)^(18-1),0) -> 69624589 | U10: =MAX(T10*(1+NORMINV(RAND(),$C$6,$E$6))-MonthlyExp*12*(1+Inflation)^(19-1),0) -> 67169342 | V10: =MAX(U10*(1+NORMINV(RAND(),$C$6,$E$6))-MonthlyExp*12*(1+Inflation)^(20-1),0) -> 49338110 | W10: =MAX(V10*(1+NORMINV(RAND(),$C$6,$E$6))-MonthlyExp*12*(1+Inflation)^(21-1),0) -> 56260847 | X10: =MAX(W10*(1+NORMINV(RAND(),$C$6,$E$6))-MonthlyExp*12*(1+Inflation)^(22-1),0) -> 62292110 | Y10: =MAX(X10*(1+NORMINV(RAND(),$C$6,$E$6))-MonthlyExp*12*(1+Inflation)^(23-1),0) -> 64451739 | Z10: =MAX(Y10*(1+NORMINV(RAND(),$C$6,$E$6))-MonthlyExp*12*(1+Inflation)^(24-1),0) -> 71553736 | AA10: =MAX(Z10*(1+NORMINV(RAND(),$C$6,$E$6))-MonthlyExp*12*(1+Inflation)^(25-1),0) -> 70061463 | AB10: =MAX(AA10*(1+NORMINV(RAND(),$C$6,$E$6))-MonthlyExp*12*(1+Inflation)^(26-1),0) -> 77794610 | AC10: =MAX(AB10*(1+NORMINV(RAND(),$C$6,$E$6))-MonthlyExp*12*(1+Inflation)^(27-1),0) -> 85398967 | AD10: =MAX(AC10*(1+NORMINV(RAND(),$C$6,$E$6))-MonthlyExp*12*(1+Inflation)^(28-1),0) -> 88695129 | AE10: =MAX(AD10*(1+NORMINV(RAND(),$C$6,$E$6))-MonthlyExp*12*(1+Inflation)^(29-1),0) -> 93860328 | AF10: =MAX(AE10*(1+NORMINV(RAND(),$C$6,$E$6))-MonthlyExp*12*(1+Inflation)^(30-1),0) -> 1.1432185e+08
A11: 3 | B11: =Corpus -> 20000000 | C11: =MAX(B11*(1+NORMINV(RAND(),$C$6,$E$6))-MonthlyExp*12*(1+Inflation)^(1-1),0) -> 23987539 | D11: =MAX(C11*(1+NORMINV(RAND(),$C$6,$E$6))-MonthlyExp*12*(1+Inflation)^(2-1),0) -> 26762291 | E11: =MAX(D11*(1+NORMINV(RAND(),$C$6,$E$6))-MonthlyExp*12*(1+Inflation)^(3-1),0) -> 28662027 | F11: =MAX(E11*(1+NORMINV(RAND(),$C$6,$E$6))-MonthlyExp*12*(1+Inflation)^(4-1),0) -> 31289607 | G11: =MAX(F11*(1+NORMINV(RAND(),$C$6,$E$6))-MonthlyExp*12*(1+Inflation)^(5-1),0) -> 34119792 | H11: =MAX(G11*(1+NORMINV(RAND(),$C$6,$E$6))-MonthlyExp*12*(1+Inflation)^(6-1),0) -> 36702352 | I11: =MAX(H11*(1+NORMINV(RAND(),$C$6,$E$6))-MonthlyExp*12*(1+Inflation)^(7-1),0) -> 41825068 | J11: =MAX(I11*(1+NORMINV(RAND(),$C$6,$E$6))-MonthlyExp*12*(1+Inflation)^(8-1),0) -> 43964298 | K11: =MAX(J11*(1+NORMINV(RAND(),$C$6,$E$6))-MonthlyExp*12*(1+Inflation)^(9-1),0) -> 50475081 | L11: =MAX(K11*(1+NORMINV(RAND(),$C$6,$E$6))-MonthlyExp*12*(1+Inflation)^(10-1),0) -> 54546040 | M11: =MAX(L11*(1+NORMINV(RAND(),$C$6,$E$6))-MonthlyExp*12*(1+Inflation)^(11-1),0) -> 60459801 | N11: =MAX(M11*(1+NORMINV(RAND(),$C$6,$E$6))-MonthlyExp*12*(1+Inflation)^(12-1),0) -> 69615160 | O11: =MAX(N11*(1+NORMINV(RAND(),$C$6,$E$6))-MonthlyExp*12*(1+Inflation)^(13-1),0) -> 79340579 | P11: =MAX(O11*(1+NORMINV(RAND(),$C$6,$E$6))-MonthlyExp*12*(1+Inflation)^(14-1),0) -> 79333424 | Q11: =MAX(P11*(1+NORMINV(RAND(),$C$6,$E$6))-MonthlyExp*12*(1+Inflation)^(15-1),0) -> 93344113 | R11: =MAX(Q11*(1+NORMINV(RAND(),$C$6,$E$6))-MonthlyExp*12*(1+Inflation)^(16-1),0) -> 1.0943407e+08 | S11: =MAX(R11*(1+NORMINV(RAND(),$C$6,$E$6))-MonthlyExp*12*(1+Inflation)^(17-1),0) -> 1.239596e+08 | T11: =MAX(S11*(1+NORMINV(RAND(),$C$6,$E$6))-MonthlyExp*12*(1+Inflation)^(18-1),0) -> 1.1541557e+08 | U11: =MAX(T11*(1+NORMINV(RAND(),$C$6,$E$6))-MonthlyExp*12*(1+Inflation)^(19-1),0) -> 1.2621285e+08 | V11: =MAX(U11*(1+NORMINV(RAND(),$C$6,$E$6))-MonthlyExp*12*(1+Inflation)^(20-1),0) -> 1.30787e+08 | W11: =MAX(V11*(1+NORMINV(RAND(),$C$6,$E$6))-MonthlyExp*12*(1+Inflation)^(21-1),0) -> 1.2551702e+08 | X11: =MAX(W11*(1+NORMINV(RAND(),$C$6,$E$6))-MonthlyExp*12*(1+Inflation)^(22-1),0) -> 1.3063681e+08 | Y11: =MAX(X11*(1+NORMINV(RAND(),$C$6,$E$6))-MonthlyExp*12*(1+Inflation)^(23-1),0) -> 1.3361503e+08 | Z11: =MAX(Y11*(1+NORMINV(RAND(),$C$6,$E$6))-MonthlyExp*12*(1+Inflation)^(24-1),0) -> 1.3975435e+08 | AA11: =MAX(Z11*(1+NORMINV(RAND(),$C$6,$E$6))-MonthlyExp*12*(1+Inflation)^(25-1),0) -> 1.4629701e+08 | AB11: =MAX(AA11*(1+NORMINV(RAND(),$C$6,$E$6))-MonthlyExp*12*(1+Inflation)^(26-1),0) -> 1.427657e+08 | AC11: =MAX(AB11*(1+NORMINV(RAND(),$C$6,$E$6))-MonthlyExp*12*(1+Inflation)^(27-1),0) -> 1.3493392e+08 | AD11: =MAX(AC11*(1+NORMINV(RAND(),$C$6,$E$6))-MonthlyExp*12*(1+Inflation)^(28-1),0) -> 1.334897e+08 | AE11: =MAX(AD11*(1+NORMINV(RAND(),$C$6,$E$6))-MonthlyExp*12*(1+Inflation)^(29-1),0) -> 1.3187251e+08 | AF11: =MAX(AE11*(1+NORMINV(RAND(),$C$6,$E$6))-MonthlyExp*12*(1+Inflation)^(30-1),0) -> 1.4400093e+08
A12: 4 | B12: =Corpus -> 20000000 | C12: =MAX(B12*(1+NORMINV(RAND(),$C$6,$E$6))-MonthlyExp*12*(1+Inflation)^(1-1),0) -> 20291985 | D12: =MAX(C12*(1+NORMINV(RAND(),$C$6,$E$6))-MonthlyExp*12*(1+Inflation)^(2-1),0) -> 23601955 | E12: =MAX(D12*(1+NORMINV(RAND(),$C$6,$E$6))-MonthlyExp*12*(1+Inflation)^(3-1),0) -> 24366722 | F12: =MAX(E12*(1+NORMINV(RAND(),$C$6,$E$6))-MonthlyExp*12*(1+Inflation)^(4-1),0) -> 27609447 | G12: =MAX(F12*(1+NORMINV(RAND(),$C$6,$E$6))-MonthlyExp*12*(1+Inflation)^(5-1),0) -> 30188770 | H12: =MAX(G12*(1+NORMINV(RAND(),$C$6,$E$6))-MonthlyExp*12*(1+Inflation)^(6-1),0) -> 29831617 | I12: =MAX(H12*(1+NORMINV(RAND(),$C$6,$E$6))-MonthlyExp*12*(1+Inflation)^(7-1),0) -> 34201786 | J12: =MAX(I12*(1+NORMINV(RAND(),$C$6,$E$6))-MonthlyExp*12*(1+Inflation)^(8-1),0) -> 33463147 | K12: =MAX(J12*(1+NORMINV(RAND(),$C$6,$E$6))-MonthlyExp*12*(1+Inflation)^(9-1),0) -> 39667618 | L12: =MAX(K12*(1+NORMINV(RAND(),$C$6,$E$6))-MonthlyExp*12*(1+Inflation)^(10-1),0) -> 39557273 | M12: =MAX(L12*(1+NORMINV(RAND(),$C$6,$E$6))-MonthlyExp*12*(1+Inflation)^(11-1),0) -> 42687474 | N12: =MAX(M12*(1+NORMINV(RAND(),$C$6,$E$6))-MonthlyExp*12*(1+Inflation)^(12-1),0) -> 44854845 | O12: =MAX(N12*(1+NORMINV(RAND(),$C$6,$E$6))-MonthlyExp*12*(1+Inflation)^(13-1),0) -> 47479851 | P12: =MAX(O12*(1+NORMINV(RAND(),$C$6,$E$6))-MonthlyExp*12*(1+Inflation)^(14-1),0) -> 48797330 | Q12: =MAX(P12*(1+NORMINV(RAND(),$C$6,$E$6))-MonthlyExp*12*(1+Inflation)^(15-1),0) -> 50563135 | R12: =MAX(Q12*(1+NORMINV(RAND(),$C$6,$E$6))-MonthlyExp*12*(1+Inflation)^(16-1),0) -> 52304848 | S12: =MAX(R12*(1+NORMINV(RAND(),$C$6,$E$6))-MonthlyExp*12*(1+Inflation)^(17-1),0) -> 52072362 | T12: =MAX(S12*(1+NORMINV(RAND(),$C$6,$E$6))-MonthlyExp*12*(1+Inflation)^(18-1),0) -> 51754605 | U12: =MAX(T12*(1+NORMINV(RAND(),$C$6,$E$6))-MonthlyExp*12*(1+Inflation)^(19-1),0) -> 55987372 | V12: =MAX(U12*(1+NORMINV(RAND(),$C$6,$E$6))-MonthlyExp*12*(1+Inflation)^(20-1),0) -> 62196057 | W12: =MAX(V12*(1+NORMINV(RAND(),$C$6,$E$6))-MonthlyExp*12*(1+Inflation)^(21-1),0) -> 64705316 | X12: =MAX(W12*(1+NORMINV(RAND(),$C$6,$E$6))-MonthlyExp*12*(1+Inflation)^(22-1),0) -> 67450803 | Y12: =MAX(X12*(1+NORMINV(RAND(),$C$6,$E$6))-MonthlyExp*12*(1+Inflation)^(23-1),0) -> 63478297 | Z12: =MAX(Y12*(1+NORMINV(RAND(),$C$6,$E$6))-MonthlyExp*12*(1+Inflation)^(24-1),0) -> 68085724 | AA12: =MAX(Z12*(1+NORMINV(RAND(),$C$6,$E$6))-MonthlyExp*12*(1+Inflation)^(25-1),0) -> 67584200 | AB12: =MAX(AA12*(1+NORMINV(RAND(),$C$6,$E$6))-MonthlyExp*12*(1+Inflation)^(26-1),0) -> 78802001 | AC12: =MAX(AB12*(1+NORMINV(RAND(),$C$6,$E$6))-MonthlyExp*12*(1+Inflation)^(27-1),0) -> 74525515 | AD12: =MAX(AC12*(1+NORMINV(RAND(),$C$6,$E$6))-MonthlyExp*12*(1+Inflation)^(28-1),0) -> 84243624 | AE12: =MAX(AD12*(1+NORMINV(RAND(),$C$6,$E$6))-MonthlyExp*12*(1+Inflation)^(29-1),0) -> 89836224 | AF12: =MAX(AE12*(1+NORMINV(RAND(),$C$6,$E$6))-MonthlyExp*12*(1+Inflation)^(30-1),0) -> 90668516
A13: 5 | B13: =Corpus -> 20000000 | C13: =MAX(B13*(1+NORMINV(RAND(),$C$6,$E$6))-MonthlyExp*12*(1+Inflation)^(1-1),0) -> 19757891 | D13: =MAX(C13*(1+NORMINV(RAND(),$C$6,$E$6))-MonthlyExp*12*(1+Inflation)^(2-1),0) -> 20357465 | E13: =MAX(D13*(1+NORMINV(RAND(),$C$6,$E$6))-MonthlyExp*12*(1+Inflation)^(3-1),0) -> 20842481 | F13: =MAX(E13*(1+NORMINV(RAND(),$C$6,$E$6))-MonthlyExp*12*(1+Inflation)^(4-1),0) -> 18390143 | G13: =MAX(F13*(1+NORMINV(RAND(),$C$6,$E$6))-MonthlyExp*12*(1+Inflation)^(5-1),0) -> 20943617 | H13: =MAX(G13*(1+NORMINV(RAND(),$C$6,$E$6))-MonthlyExp*12*(1+Inflation)^(6-1),0) -> 20256562 | I13: =MAX(H13*(1+NORMINV(RAND(),$C$6,$E$6))-MonthlyExp*12*(1+Inflation)^(7-1),0) -> 22157798 | J13: =MAX(I13*(1+NORMINV(RAND(),$C$6,$E$6))-MonthlyExp*12*(1+Inflation)^(8-1),0) -> 26185626 | K13: =MAX(J13*(1+NORMINV(RAND(),$C$6,$E$6))-MonthlyExp*12*(1+Inflation)^(9-1),0) -> 29265677 | L13: =MAX(K13*(1+NORMINV(RAND(),$C$6,$E$6))-MonthlyExp*12*(1+Inflation)^(10-1),0) -> 32121254 | M13: =MAX(L13*(1+NORMINV(RAND(),$C$6,$E$6))-MonthlyExp*12*(1+Inflation)^(11-1),0) -> 32175815 | N13: =MAX(M13*(1+NORMINV(RAND(),$C$6,$E$6))-MonthlyExp*12*(1+Inflation)^(12-1),0) -> 32933019 | O13: =MAX(N13*(1+NORMINV(RAND(),$C$6,$E$6))-MonthlyExp*12*(1+Inflation)^(13-1),0) -> 34416997 | P13: =MAX(O13*(1+NORMINV(RAND(),$C$6,$E$6))-MonthlyExp*12*(1+Inflation)^(14-1),0) -> 41257551 | Q13: =MAX(P13*(1+NORMINV(RAND(),$C$6,$E$6))-MonthlyExp*12*(1+Inflation)^(15-1),0) -> 40943104 | R13: =MAX(Q13*(1+NORMINV(RAND(),$C$6,$E$6))-MonthlyExp*12*(1+Inflation)^(16-1),0) -> 34596561 | S13: =MAX(R13*(1+NORMINV(RAND(),$C$6,$E$6))-MonthlyExp*12*(1+Inflation)^(17-1),0) -> 35982583 | T13: =MAX(S13*(1+NORMINV(RAND(),$C$6,$E$6))-MonthlyExp*12*(1+Inflation)^(18-1),0) -> 35342567 | U13: =MAX(T13*(1+NORMINV(RAND(),$C$6,$E$6))-MonthlyExp*12*(1+Inflation)^(19-1),0) -> 37619652 | V13: =MAX(U13*(1+NORMINV(RAND(),$C$6,$E$6))-MonthlyExp*12*(1+Inflation)^(20-1),0) -> 38933130 | W13: =MAX(V13*(1+NORMINV(RAND(),$C$6,$E$6))-MonthlyExp*12*(1+Inflation)^(21-1),0) -> 39781386 | X13: =MAX(W13*(1+NORMINV(RAND(),$C$6,$E$6))-MonthlyExp*12*(1+Inflation)^(22-1),0) -> 40454159 | Y13: =MAX(X13*(1+NORMINV(RAND(),$C$6,$E$6))-MonthlyExp*12*(1+Inflation)^(23-1),0) -> 40919931 | Z13: =MAX(Y13*(1+NORMINV(RAND(),$C$6,$E$6))-MonthlyExp*12*(1+Inflation)^(24-1),0) -> 41296155 | AA13: =MAX(Z13*(1+NORMINV(RAND(),$C$6,$E$6))-MonthlyExp*12*(1+Inflation)^(25-1),0) -> 44225580 | AB13: =MAX(AA13*(1+NORMINV(RAND(),$C$6,$E$6))-MonthlyExp*12*(1+Inflation)^(26-1),0) -> 38483132 | AC13: =MAX(AB13*(1+NORMINV(RAND(),$C$6,$E$6))-MonthlyExp*12*(1+Inflation)^(27-1),0) -> 32984092 | AD13: =MAX(AC13*(1+NORMINV(RAND(),$C$6,$E$6))-MonthlyExp*12*(1+Inflation)^(28-1),0) -> 31106320 | AE13: =MAX(AD13*(1+NORMINV(RAND(),$C$6,$E$6))-MonthlyExp*12*(1+Inflation)^(29-1),0) -> 30978463 | AF13: =MAX(AE13*(1+NORMINV(RAND(),$C$6,$E$6))-MonthlyExp*12*(1+Inflation)^(30-1),0) -> 25817732
A14: 6 | B14: =Corpus -> 20000000 | C14: =MAX(B14*(1+NORMINV(RAND(),$C$6,$E$6))-MonthlyExp*12*(1+Inflation)^(1-1),0) -> 20237808 | D14: =MAX(C14*(1+NORMINV(RAND(),$C$6,$E$6))-MonthlyExp*12*(1+Inflation)^(2-1),0) -> 24758461 | E14: =MAX(D14*(1+NORMINV(RAND(),$C$6,$E$6))-MonthlyExp*12*(1+Inflation)^(3-1),0) -> 25123110 | F14: =MAX(E14*(1+NORMINV(RAND(),$C$6,$E$6))-MonthlyExp*12*(1+Inflation)^(4-1),0) -> 24794034 | G14: =MAX(F14*(1+NORMINV(RAND(),$C$6,$E$6))-MonthlyExp*12*(1+Inflation)^(5-1),0) -> 27122096 | H14: =MAX(G14*(1+NORMINV(RAND(),$C$6,$E$6))-MonthlyExp*12*(1+Inflation)^(6-1),0) -> 31101582 | I14: =MAX(H14*(1+NORMINV(RAND(),$C$6,$E$6))-MonthlyExp*12*(1+Inflation)^(7-1),0) -> 30954259 | J14: =MAX(I14*(1+NORMINV(RAND(),$C$6,$E$6))-MonthlyExp*12*(1+Inflation)^(8-1),0) -> 34868245 | K14: =MAX(J14*(1+NORMINV(RAND(),$C$6,$E$6))-MonthlyExp*12*(1+Inflation)^(9-1),0) -> 32969233 | L14: =MAX(K14*(1+NORMINV(RAND(),$C$6,$E$6))-MonthlyExp*12*(1+Inflation)^(10-1),0) -> 38364817 | M14: =MAX(L14*(1+NORMINV(RAND(),$C$6,$E$6))-MonthlyExp*12*(1+Inflation)^(11-1),0) -> 40223262 | N14: =MAX(M14*(1+NORMINV(RAND(),$C$6,$E$6))-MonthlyExp*12*(1+Inflation)^(12-1),0) -> 43979087 | O14: =MAX(N14*(1+NORMINV(RAND(),$C$6,$E$6))-MonthlyExp*12*(1+Inflation)^(13-1),0) -> 48769587 | P14: =MAX(O14*(1+NORMINV(RAND(),$C$6,$E$6))-MonthlyExp*12*(1+Inflation)^(14-1),0) -> 51344995 | Q14: =MAX(P14*(1+NORMINV(RAND(),$C$6,$E$6))-MonthlyExp*12*(1+Inflation)^(15-1),0) -> 50930007 | R14: =MAX(Q14*(1+NORMINV(RAND(),$C$6,$E$6))-MonthlyExp*12*(1+Inflation)^(16-1),0) -> 56329685 | S14: =MAX(R14*(1+NORMINV(RAND(),$C$6,$E$6))-MonthlyExp*12*(1+Inflation)^(17-1),0) -> 63711732 | T14: =MAX(S14*(1+NORMINV(RAND(),$C$6,$E$6))-MonthlyExp*12*(1+Inflation)^(18-1),0) -> 66499536 | U14: =MAX(T14*(1+NORMINV(RAND(),$C$6,$E$6))-MonthlyExp*12*(1+Inflation)^(19-1),0) -> 68388417 | V14: =MAX(U14*(1+NORMINV(RAND(),$C$6,$E$6))-MonthlyExp*12*(1+Inflation)^(20-1),0) -> 76010815 | W14: =MAX(V14*(1+NORMINV(RAND(),$C$6,$E$6))-MonthlyExp*12*(1+Inflation)^(21-1),0) -> 73271040 | X14: =MAX(W14*(1+NORMINV(RAND(),$C$6,$E$6))-MonthlyExp*12*(1+Inflation)^(22-1),0) -> 78619658 | Y14: =MAX(X14*(1+NORMINV(RAND(),$C$6,$E$6))-MonthlyExp*12*(1+Inflation)^(23-1),0) -> 84013326 | Z14: =MAX(Y14*(1+NORMINV(RAND(),$C$6,$E$6))-MonthlyExp*12*(1+Inflation)^(24-1),0) -> 99277472 | AA14: =MAX(Z14*(1+NORMINV(RAND(),$C$6,$E$6))-MonthlyExp*12*(1+Inflation)^(25-1),0) -> 1.1699911e+08 | AB14: =MAX(AA14*(1+NORMINV(RAND(),$C$6,$E$6))-MonthlyExp*12*(1+Inflation)^(26-1),0) -> 1.3539924e+08 | AC14: =MAX(AB14*(1+NORMINV(RAND(),$C$6,$E$6))-MonthlyExp*12*(1+Inflation)^(27-1),0) -> 1.2830928e+08 | AD14: =MAX(AC14*(1+NORMINV(RAND(),$C$6,$E$6))-MonthlyExp*12*(1+Inflation)^(28-1),0) -> 1.2116153e+08 | AE14: =MAX(AD14*(1+NORMINV(RAND(),$C$6,$E$6))-MonthlyExp*12*(1+Inflation)^(29-1),0) -> 1.1909705e+08 | AF14: =MAX(AE14*(1+NORMINV(RAND(),$C$6,$E$6))-MonthlyExp*12*(1+Inflation)^(30-1),0) -> 1.3535317e+08
A15: 7 | B15: =Corpus -> 20000000 | C15: =MAX(B15*(1+NORMINV(RAND(),$C$6,$E$6))-MonthlyExp*12*(1+Inflation)^(1-1),0) -> 16808277 | D15: =MAX(C15*(1+NORMINV(RAND(),$C$6,$E$6))-MonthlyExp*12*(1+Inflation)^(2-1),0) -> 15431197 | E15: =MAX(D15*(1+NORMINV(RAND(),$C$6,$E$6))-MonthlyExp*12*(1+Inflation)^(3-1),0) -> 17017037 | F15: =MAX(E15*(1+NORMINV(RAND(),$C$6,$E$6))-MonthlyExp*12*(1+Inflation)^(4-1),0) -> 15581183 | G15: =MAX(F15*(1+NORMINV(RAND(),$C$6,$E$6))-MonthlyExp*12*(1+Inflation)^(5-1),0) -> 14525585 | H15: =MAX(G15*(1+NORMINV(RAND(),$C$6,$E$6))-MonthlyExp*12*(1+Inflation)^(6-1),0) -> 16852129 | I15: =MAX(H15*(1+NORMINV(RAND(),$C$6,$E$6))-MonthlyExp*12*(1+Inflation)^(7-1),0) -> 18936068 | J15: =MAX(I15*(1+NORMINV(RAND(),$C$6,$E$6))-MonthlyExp*12*(1+Inflation)^(8-1),0) -> 19064539 | K15: =MAX(J15*(1+NORMINV(RAND(),$C$6,$E$6))-MonthlyExp*12*(1+Inflation)^(9-1),0) -> 22664645 | L15: =MAX(K15*(1+NORMINV(RAND(),$C$6,$E$6))-MonthlyExp*12*(1+Inflation)^(10-1),0) -> 22466010 | M15: =MAX(L15*(1+NORMINV(RAND(),$C$6,$E$6))-MonthlyExp*12*(1+Inflation)^(11-1),0) -> 25541088 | N15: =MAX(M15*(1+NORMINV(RAND(),$C$6,$E$6))-MonthlyExp*12*(1+Inflation)^(12-1),0) -> 27434489 | O15: =MAX(N15*(1+NORMINV(RAND(),$C$6,$E$6))-MonthlyExp*12*(1+Inflation)^(13-1),0) -> 30506837 | P15: =MAX(O15*(1+NORMINV(RAND(),$C$6,$E$6))-MonthlyExp*12*(1+Inflation)^(14-1),0) -> 32658204 | Q15: =MAX(P15*(1+NORMINV(RAND(),$C$6,$E$6))-MonthlyExp*12*(1+Inflation)^(15-1),0) -> 38144469 | R15: =MAX(Q15*(1+NORMINV(RAND(),$C$6,$E$6))-MonthlyExp*12*(1+Inflation)^(16-1),0) -> 40043901 | S15: =MAX(R15*(1+NORMINV(RAND(),$C$6,$E$6))-MonthlyExp*12*(1+Inflation)^(17-1),0) -> 35901344 | T15: =MAX(S15*(1+NORMINV(RAND(),$C$6,$E$6))-MonthlyExp*12*(1+Inflation)^(18-1),0) -> 34608294 | U15: =MAX(T15*(1+NORMINV(RAND(),$C$6,$E$6))-MonthlyExp*12*(1+Inflation)^(19-1),0) -> 32682796 | V15: =MAX(U15*(1+NORMINV(RAND(),$C$6,$E$6))-MonthlyExp*12*(1+Inflation)^(20-1),0) -> 33435460 | W15: =MAX(V15*(1+NORMINV(RAND(),$C$6,$E$6))-MonthlyExp*12*(1+Inflation)^(21-1),0) -> 32518695 | X15: =MAX(W15*(1+NORMINV(RAND(),$C$6,$E$6))-MonthlyExp*12*(1+Inflation)^(22-1),0) -> 32024715 | Y15: =MAX(X15*(1+NORMINV(RAND(),$C$6,$E$6))-MonthlyExp*12*(1+Inflation)^(23-1),0) -> 29360384 | Z15: =MAX(Y15*(1+NORMINV(RAND(),$C$6,$E$6))-MonthlyExp*12*(1+Inflation)^(24-1),0) -> 30313579 | AA15: =MAX(Z15*(1+NORMINV(RAND(),$C$6,$E$6))-MonthlyExp*12*(1+Inflation)^(25-1),0) -> 28762273 | AB15: =MAX(AA15*(1+NORMINV(RAND(),$C$6,$E$6))-MonthlyExp*12*(1+Inflation)^(26-1),0) -> 23261468 | AC15: =MAX(AB15*(1+NORMINV(RAND(),$C$6,$E$6))-MonthlyExp*12*(1+Inflation)^(27-1),0) -> 21718365 | AD15: =MAX(AC15*(1+NORMINV(RAND(),$C$6,$E$6))-MonthlyExp*12*(1+Inflation)^(28-1),0) -> 23223891 | AE15: =MAX(AD15*(1+NORMINV(RAND(),$C$6,$E$6))-MonthlyExp*12*(1+Inflation)^(29-1),0) -> 20783598 | AF15: =MAX(AE15*(1+NORMINV(RAND(),$C$6,$E$6))-MonthlyExp*12*(1+Inflation)^(30-1),0) -> 19464679
A16: 8 | B16: =Corpus -> 20000000 | C16: =MAX(B16*(1+NORMINV(RAND(),$C$6,$E$6))-MonthlyExp*12*(1+Inflation)^(1-1),0) -> 22067236 | D16: =MAX(C16*(1+NORMINV(RAND(),$C$6,$E$6))-MonthlyExp*12*(1+Inflation)^(2-1),0) -> 24046678 | E16: =MAX(D16*(1+NORMINV(RAND(),$C$6,$E$6))-MonthlyExp*12*(1+Inflation)^(3-1),0) -> 20907332 | F16: =MAX(E16*(1+NORMINV(RAND(),$C$6,$E$6))-MonthlyExp*12*(1+Inflation)^(4-1),0) -> 23075474 | G16: =MAX(F16*(1+NORMINV(RAND(),$C$6,$E$6))-MonthlyExp*12*(1+Inflation)^(5-1),0) -> 21570039 | H16: =MAX(G16*(1+NORMINV(RAND(),$C$6,$E$6))-MonthlyExp*12*(1+Inflation)^(6-1),0) -> 24451962 | I16: =MAX(H16*(1+NORMINV(RAND(),$C$6,$E$6))-MonthlyExp*12*(1+Inflation)^(7-1),0) -> 23565973 | J16: =MAX(I16*(1+NORMINV(RAND(),$C$6,$E$6))-MonthlyExp*12*(1+Inflation)^(8-1),0) -> 22651542 | K16: =MAX(J16*(1+NORMINV(RAND(),$C$6,$E$6))-MonthlyExp*12*(1+Inflation)^(9-1),0) -> 28432841 | L16: =MAX(K16*(1+NORMINV(RAND(),$C$6,$E$6))-MonthlyExp*12*(1+Inflation)^(10-1),0) -> 30740438 | M16: =MAX(L16*(1+NORMINV(RAND(),$C$6,$E$6))-MonthlyExp*12*(1+Inflation)^(11-1),0) -> 31328550 | N16: =MAX(M16*(1+NORMINV(RAND(),$C$6,$E$6))-MonthlyExp*12*(1+Inflation)^(12-1),0) -> 33604095 | O16: =MAX(N16*(1+NORMINV(RAND(),$C$6,$E$6))-MonthlyExp*12*(1+Inflation)^(13-1),0) -> 38265026 | P16: =MAX(O16*(1+NORMINV(RAND(),$C$6,$E$6))-MonthlyExp*12*(1+Inflation)^(14-1),0) -> 44547538 | Q16: =MAX(P16*(1+NORMINV(RAND(),$C$6,$E$6))-MonthlyExp*12*(1+Inflation)^(15-1),0) -> 46296034 | R16: =MAX(Q16*(1+NORMINV(RAND(),$C$6,$E$6))-MonthlyExp*12*(1+Inflation)^(16-1),0) -> 49124683 | S16: =MAX(R16*(1+NORMINV(RAND(),$C$6,$E$6))-MonthlyExp*12*(1+Inflation)^(17-1),0) -> 55781083 | T16: =MAX(S16*(1+NORMINV(RAND(),$C$6,$E$6))-MonthlyExp*12*(1+Inflation)^(18-1),0) -> 66841339 | U16: =MAX(T16*(1+NORMINV(RAND(),$C$6,$E$6))-MonthlyExp*12*(1+Inflation)^(19-1),0) -> 57737639 | V16: =MAX(U16*(1+NORMINV(RAND(),$C$6,$E$6))-MonthlyExp*12*(1+Inflation)^(20-1),0) -> 58879051 | W16: =MAX(V16*(1+NORMINV(RAND(),$C$6,$E$6))-MonthlyExp*12*(1+Inflation)^(21-1),0) -> 72252163 | X16: =MAX(W16*(1+NORMINV(RAND(),$C$6,$E$6))-MonthlyExp*12*(1+Inflation)^(22-1),0) -> 72141399 | Y16: =MAX(X16*(1+NORMINV(RAND(),$C$6,$E$6))-MonthlyExp*12*(1+Inflation)^(23-1),0) -> 75576491 | Z16: =MAX(Y16*(1+NORMINV(RAND(),$C$6,$E$6))-MonthlyExp*12*(1+Inflation)^(24-1),0) -> 76541791 | AA16: =MAX(Z16*(1+NORMINV(RAND(),$C$6,$E$6))-MonthlyExp*12*(1+Inflation)^(25-1),0) -> 81462664 | AB16: =MAX(AA16*(1+NORMINV(RAND(),$C$6,$E$6))-MonthlyExp*12*(1+Inflation)^(26-1),0) -> 83683610 | AC16: =MAX(AB16*(1+NORMINV(RAND(),$C$6,$E$6))-MonthlyExp*12*(1+Inflation)^(27-1),0) -> 95050965 | AD16: =MAX(AC16*(1+NORMINV(RAND(),$C$6,$E$6))-MonthlyExp*12*(1+Inflation)^(28-1),0) -> 87257475 | AE16: =MAX(AD16*(1+NORMINV(RAND(),$C$6,$E$6))-MonthlyExp*12*(1+Inflation)^(29-1),0) -> 91113860 | AF16: =MAX(AE16*(1+NORMINV(RAND(),$C$6,$E$6))-MonthlyExp*12*(1+Inflation)^(30-1),0) -> 1.1072509e+08
A17: 9 | B17: =Corpus -> 20000000 | C17: =MAX(B17*(1+NORMINV(RAND(),$C$6,$E$6))-MonthlyExp*12*(1+Inflation)^(1-1),0) -> 20765322 | D17: =MAX(C17*(1+NORMINV(RAND(),$C$6,$E$6))-MonthlyExp*12*(1+Inflation)^(2-1),0) -> 22146231 | E17: =MAX(D17*(1+NORMINV(RAND(),$C$6,$E$6))-MonthlyExp*12*(1+Inflation)^(3-1),0) -> 25087788 | F17: =MAX(E17*(1+NORMINV(RAND(),$C$6,$E$6))-MonthlyExp*12*(1+Inflation)^(4-1),0) -> 26621393 | G17: =MAX(F17*(1+NORMINV(RAND(),$C$6,$E$6))-MonthlyExp*12*(1+Inflation)^(5-1),0) -> 24254221 | H17: =MAX(G17*(1+NORMINV(RAND(),$C$6,$E$6))-MonthlyExp*12*(1+Inflation)^(6-1),0) -> 25928301 | I17: =MAX(H17*(1+NORMINV(RAND(),$C$6,$E$6))-MonthlyExp*12*(1+Inflation)^(7-1),0) -> 28729572 | J17: =MAX(I17*(1+NORMINV(RAND(),$C$6,$E$6))-MonthlyExp*12*(1+Inflation)^(8-1),0) -> 29582286 | K17: =MAX(J17*(1+NORMINV(RAND(),$C$6,$E$6))-MonthlyExp*12*(1+Inflation)^(9-1),0) -> 33658260 | L17: =MAX(K17*(1+NORMINV(RAND(),$C$6,$E$6))-MonthlyExp*12*(1+Inflation)^(10-1),0) -> 32392085 | M17: =MAX(L17*(1+NORMINV(RAND(),$C$6,$E$6))-MonthlyExp*12*(1+Inflation)^(11-1),0) -> 29207139 | N17: =MAX(M17*(1+NORMINV(RAND(),$C$6,$E$6))-MonthlyExp*12*(1+Inflation)^(12-1),0) -> 30327476 | O17: =MAX(N17*(1+NORMINV(RAND(),$C$6,$E$6))-MonthlyExp*12*(1+Inflation)^(13-1),0) -> 32171104 | P17: =MAX(O17*(1+NORMINV(RAND(),$C$6,$E$6))-MonthlyExp*12*(1+Inflation)^(14-1),0) -> 35882871 | Q17: =MAX(P17*(1+NORMINV(RAND(),$C$6,$E$6))-MonthlyExp*12*(1+Inflation)^(15-1),0) -> 40229620 | R17: =MAX(Q17*(1+NORMINV(RAND(),$C$6,$E$6))-MonthlyExp*12*(1+Inflation)^(16-1),0) -> 43825169 | S17: =MAX(R17*(1+NORMINV(RAND(),$C$6,$E$6))-MonthlyExp*12*(1+Inflation)^(17-1),0) -> 50142773 | T17: =MAX(S17*(1+NORMINV(RAND(),$C$6,$E$6))-MonthlyExp*12*(1+Inflation)^(18-1),0) -> 47434666 | U17: =MAX(T17*(1+NORMINV(RAND(),$C$6,$E$6))-MonthlyExp*12*(1+Inflation)^(19-1),0) -> 48614789 | V17: =MAX(U17*(1+NORMINV(RAND(),$C$6,$E$6))-MonthlyExp*12*(1+Inflation)^(20-1),0) -> 52097072 | W17: =MAX(V17*(1+NORMINV(RAND(),$C$6,$E$6))-MonthlyExp*12*(1+Inflation)^(21-1),0) -> 54621602 | X17: =MAX(W17*(1+NORMINV(RAND(),$C$6,$E$6))-MonthlyExp*12*(1+Inflation)^(22-1),0) -> 59910421 | Y17: =MAX(X17*(1+NORMINV(RAND(),$C$6,$E$6))-MonthlyExp*12*(1+Inflation)^(23-1),0) -> 66355413 | Z17: =MAX(Y17*(1+NORMINV(RAND(),$C$6,$E$6))-MonthlyExp*12*(1+Inflation)^(24-1),0) -> 59505762 | AA17: =MAX(Z17*(1+NORMINV(RAND(),$C$6,$E$6))-MonthlyExp*12*(1+Inflation)^(25-1),0) -> 68987802 | AB17: =MAX(AA17*(1+NORMINV(RAND(),$C$6,$E$6))-MonthlyExp*12*(1+Inflation)^(26-1),0) -> 64984904 | AC17: =MAX(AB17*(1+NORMINV(RAND(),$C$6,$E$6))-MonthlyExp*12*(1+Inflation)^(27-1),0) -> 70229202 | AD17: =MAX(AC17*(1+NORMINV(RAND(),$C$6,$E$6))-MonthlyExp*12*(1+Inflation)^(28-1),0) -> 64962813 | AE17: =MAX(AD17*(1+NORMINV(RAND(),$C$6,$E$6))-MonthlyExp*12*(1+Inflation)^(29-1),0) -> 64278063 | AF17: =MAX(AE17*(1+NORMINV(RAND(),$C$6,$E$6))-MonthlyExp*12*(1+Inflation)^(30-1),0) -> 66242255
A18: 10 | B18: =Corpus -> 20000000 | C18: =MAX(B18*(1+NORMINV(RAND(),$C$6,$E$6))-MonthlyExp*12*(1+Inflation)^(1-1),0) -> 20349809 | D18: =MAX(C18*(1+NORMINV(RAND(),$C$6,$E$6))-MonthlyExp*12*(1+Inflation)^(2-1),0) -> 21242288 | E18: =MAX(D18*(1+NORMINV(RAND(),$C$6,$E$6))-MonthlyExp*12*(1+Inflation)^(3-1),0) -> 24539689 | F18: =MAX(E18*(1+NORMINV(RAND(),$C$6,$E$6))-MonthlyExp*12*(1+Inflation)^(4-1),0) -> 25995581 | G18: =MAX(F18*(1+NORMINV(RAND(),$C$6,$E$6))-MonthlyExp*12*(1+Inflation)^(5-1),0) -> 28414785 | H18: =MAX(G18*(1+NORMINV(RAND(),$C$6,$E$6))-MonthlyExp*12*(1+Inflation)^(6-1),0) -> 28343122 | I18: =MAX(H18*(1+NORMINV(RAND(),$C$6,$E$6))-MonthlyExp*12*(1+Inflation)^(7-1),0) -> 30517955 | J18: =MAX(I18*(1+NORMINV(RAND(),$C$6,$E$6))-MonthlyExp*12*(1+Inflation)^(8-1),0) -> 32968577 | K18: =MAX(J18*(1+NORMINV(RAND(),$C$6,$E$6))-MonthlyExp*12*(1+Inflation)^(9-1),0) -> 34420895 | L18: =MAX(K18*(1+NORMINV(RAND(),$C$6,$E$6))-MonthlyExp*12*(1+Inflation)^(10-1),0) -> 39144023 | M18: =MAX(L18*(1+NORMINV(RAND(),$C$6,$E$6))-MonthlyExp*12*(1+Inflation)^(11-1),0) -> 43010105 | N18: =MAX(M18*(1+NORMINV(RAND(),$C$6,$E$6))-MonthlyExp*12*(1+Inflation)^(12-1),0) -> 44923782 | O18: =MAX(N18*(1+NORMINV(RAND(),$C$6,$E$6))-MonthlyExp*12*(1+Inflation)^(13-1),0) -> 49204446 | P18: =MAX(O18*(1+NORMINV(RAND(),$C$6,$E$6))-MonthlyExp*12*(1+Inflation)^(14-1),0) -> 53892074 | Q18: =MAX(P18*(1+NORMINV(RAND(),$C$6,$E$6))-MonthlyExp*12*(1+Inflation)^(15-1),0) -> 60856856 | R18: =MAX(Q18*(1+NORMINV(RAND(),$C$6,$E$6))-MonthlyExp*12*(1+Inflation)^(16-1),0) -> 61507125 | S18: =MAX(R18*(1+NORMINV(RAND(),$C$6,$E$6))-MonthlyExp*12*(1+Inflation)^(17-1),0) -> 62496119 | T18: =MAX(S18*(1+NORMINV(RAND(),$C$6,$E$6))-MonthlyExp*12*(1+Inflation)^(18-1),0) -> 62044737 | U18: =MAX(T18*(1+NORMINV(RAND(),$C$6,$E$6))-MonthlyExp*12*(1+Inflation)^(19-1),0) -> 56818650 | V18: =MAX(U18*(1+NORMINV(RAND(),$C$6,$E$6))-MonthlyExp*12*(1+Inflation)^(20-1),0) -> 58961511 | W18: =MAX(V18*(1+NORMINV(RAND(),$C$6,$E$6))-MonthlyExp*12*(1+Inflation)^(21-1),0) -> 72260132 | X18: =MAX(W18*(1+NORMINV(RAND(),$C$6,$E$6))-MonthlyExp*12*(1+Inflation)^(22-1),0) -> 75625636 | Y18: =MAX(X18*(1+NORMINV(RAND(),$C$6,$E$6))-MonthlyExp*12*(1+Inflation)^(23-1),0) -> 70878015 | Z18: =MAX(Y18*(1+NORMINV(RAND(),$C$6,$E$6))-MonthlyExp*12*(1+Inflation)^(24-1),0) -> 75739180 | AA18: =MAX(Z18*(1+NORMINV(RAND(),$C$6,$E$6))-MonthlyExp*12*(1+Inflation)^(25-1),0) -> 79527333 | AB18: =MAX(AA18*(1+NORMINV(RAND(),$C$6,$E$6))-MonthlyExp*12*(1+Inflation)^(26-1),0) -> 84930389 | AC18: =MAX(AB18*(1+NORMINV(RAND(),$C$6,$E$6))-MonthlyExp*12*(1+Inflation)^(27-1),0) -> 87252542 | AD18: =MAX(AC18*(1+NORMINV(RAND(),$C$6,$E$6))-MonthlyExp*12*(1+Inflation)^(28-1),0) -> 88127901 | AE18: =MAX(AD18*(1+NORMINV(RAND(),$C$6,$E$6))-MonthlyExp*12*(1+Inflation)^(29-1),0) -> 85974303 | AF18: =MAX(AE18*(1+NORMINV(RAND(),$C$6,$E$6))-MonthlyExp*12*(1+Inflation)^(30-1),0) -> 80679640
A19: 11 | B19: =Corpus -> 20000000 | C19: =MAX(B19*(1+NORMINV(RAND(),$C$6,$E$6))-MonthlyExp*12*(1+Inflation)^(1-1),0) -> 21187137 | D19: =MAX(C19*(1+NORMINV(RAND(),$C$6,$E$6))-MonthlyExp*12*(1+Inflation)^(2-1),0) -> 24654508 | E19: =MAX(D19*(1+NORMINV(RAND(),$C$6,$E$6))-MonthlyExp*12*(1+Inflation)^(3-1),0) -> 22812306 | F19: =MAX(E19*(1+NORMINV(RAND(),$C$6,$E$6))-MonthlyExp*12*(1+Inflation)^(4-1),0) -> 26375121 | G19: =MAX(F19*(1+NORMINV(RAND(),$C$6,$E$6))-MonthlyExp*12*(1+Inflation)^(5-1),0) -> 28769187 | H19: =MAX(G19*(1+NORMINV(RAND(),$C$6,$E$6))-MonthlyExp*12*(1+Inflation)^(6-1),0) -> 32156952 | I19: =MAX(H19*(1+NORMINV(RAND(),$C$6,$E$6))-MonthlyExp*12*(1+Inflation)^(7-1),0) -> 35457815 | J19: =MAX(I19*(1+NORMINV(RAND(),$C$6,$E$6))-MonthlyExp*12*(1+Inflation)^(8-1),0) -> 34630361 | K19: =MAX(J19*(1+NORMINV(RAND(),$C$6,$E$6))-MonthlyExp*12*(1+Inflation)^(9-1),0) -> 32063035 | L19: =MAX(K19*(1+NORMINV(RAND(),$C$6,$E$6))-MonthlyExp*12*(1+Inflation)^(10-1),0) -> 27471913 | M19: =MAX(L19*(1+NORMINV(RAND(),$C$6,$E$6))-MonthlyExp*12*(1+Inflation)^(11-1),0) -> 26349888 | N19: =MAX(M19*(1+NORMINV(RAND(),$C$6,$E$6))-MonthlyExp*12*(1+Inflation)^(12-1),0) -> 27368704 | O19: =MAX(N19*(1+NORMINV(RAND(),$C$6,$E$6))-MonthlyExp*12*(1+Inflation)^(13-1),0) -> 27272651 | P19: =MAX(O19*(1+NORMINV(RAND(),$C$6,$E$6))-MonthlyExp*12*(1+Inflation)^(14-1),0) -> 26537368 | Q19: =MAX(P19*(1+NORMINV(RAND(),$C$6,$E$6))-MonthlyExp*12*(1+Inflation)^(15-1),0) -> 25829734 | R19: =MAX(Q19*(1+NORMINV(RAND(),$C$6,$E$6))-MonthlyExp*12*(1+Inflation)^(16-1),0) -> 26703135 | S19: =MAX(R19*(1+NORMINV(RAND(),$C$6,$E$6))-MonthlyExp*12*(1+Inflation)^(17-1),0) -> 27848461 | T19: =MAX(S19*(1+NORMINV(RAND(),$C$6,$E$6))-MonthlyExp*12*(1+Inflation)^(18-1),0) -> 30970310 | U19: =MAX(T19*(1+NORMINV(RAND(),$C$6,$E$6))-MonthlyExp*12*(1+Inflation)^(19-1),0) -> 31912888 | V19: =MAX(U19*(1+NORMINV(RAND(),$C$6,$E$6))-MonthlyExp*12*(1+Inflation)^(20-1),0) -> 35228399 | W19: =MAX(V19*(1+NORMINV(RAND(),$C$6,$E$6))-MonthlyExp*12*(1+Inflation)^(21-1),0) -> 34392692 | X19: =MAX(W19*(1+NORMINV(RAND(),$C$6,$E$6))-MonthlyExp*12*(1+Inflation)^(22-1),0) -> 33377625 | Y19: =MAX(X19*(1+NORMINV(RAND(),$C$6,$E$6))-MonthlyExp*12*(1+Inflation)^(23-1),0) -> 28970744 | Z19: =MAX(Y19*(1+NORMINV(RAND(),$C$6,$E$6))-MonthlyExp*12*(1+Inflation)^(24-1),0) -> 28450647 | AA19: =MAX(Z19*(1+NORMINV(RAND(),$C$6,$E$6))-MonthlyExp*12*(1+Inflation)^(25-1),0) -> 28960874 | AB19: =MAX(AA19*(1+NORMINV(RAND(),$C$6,$E$6))-MonthlyExp*12*(1+Inflation)^(26-1),0) -> 33343293 | AC19: =MAX(AB19*(1+NORMINV(RAND(),$C$6,$E$6))-MonthlyExp*12*(1+Inflation)^(27-1),0) -> 35046586 | AD19: =MAX(AC19*(1+NORMINV(RAND(),$C$6,$E$6))-MonthlyExp*12*(1+Inflation)^(28-1),0) -> 34394888 | AE19: =MAX(AD19*(1+NORMINV(RAND(),$C$6,$E$6))-MonthlyExp*12*(1+Inflation)^(29-1),0) -> 37060341 | AF19: =MAX(AE19*(1+NORMINV(RAND(),$C$6,$E$6))-MonthlyExp*12*(1+Inflation)^(30-1),0) -> 36580822
A20: 12 | B20: =Corpus -> 20000000 | C20: =MAX(B20*(1+NORMINV(RAND(),$C$6,$E$6))-MonthlyExp*12*(1+Inflation)^(1-1),0) -> 20234746 | D20: =MAX(C20*(1+NORMINV(RAND(),$C$6,$E$6))-MonthlyExp*12*(1+Inflation)^(2-1),0) -> 20374684 | E20: =MAX(D20*(1+NORMINV(RAND(),$C$6,$E$6))-MonthlyExp*12*(1+Inflation)^(3-1),0) -> 21591101 | F20: =MAX(E20*(1+NORMINV(RAND(),$C$6,$E$6))-MonthlyExp*12*(1+Inflation)^(4-1),0) -> 23038988 | G20: =MAX(F20*(1+NORMINV(RAND(),$C$6,$E$6))-MonthlyExp*12*(1+Inflation)^(5-1),0) -> 26332624 | H20: =MAX(G20*(1+NORMINV(RAND(),$C$6,$E$6))-MonthlyExp*12*(1+Inflation)^(6-1),0) -> 29589885 | I20: =MAX(H20*(1+NORMINV(RAND(),$C$6,$E$6))-MonthlyExp*12*(1+Inflation)^(7-1),0) -> 30267032 | J20: =MAX(I20*(1+NORMINV(RAND(),$C$6,$E$6))-MonthlyExp*12*(1+Inflation)^(8-1),0) -> 27990895 | K20: =MAX(J20*(1+NORMINV(RAND(),$C$6,$E$6))-MonthlyExp*12*(1+Inflation)^(9-1),0) -> 27829189 | L20: =MAX(K20*(1+NORMINV(RAND(),$C$6,$E$6))-MonthlyExp*12*(1+Inflation)^(10-1),0) -> 30160507 | M20: =MAX(L20*(1+NORMINV(RAND(),$C$6,$E$6))-MonthlyExp*12*(1+Inflation)^(11-1),0) -> 27612047 | N20: =MAX(M20*(1+NORMINV(RAND(),$C$6,$E$6))-MonthlyExp*12*(1+Inflation)^(12-1),0) -> 29318671 | O20: =MAX(N20*(1+NORMINV(RAND(),$C$6,$E$6))-MonthlyExp*12*(1+Inflation)^(13-1),0) -> 28635337 | P20: =MAX(O20*(1+NORMINV(RAND(),$C$6,$E$6))-MonthlyExp*12*(1+Inflation)^(14-1),0) -> 27503861 | Q20: =MAX(P20*(1+NORMINV(RAND(),$C$6,$E$6))-MonthlyExp*12*(1+Inflation)^(15-1),0) -> 29495377 | R20: =MAX(Q20*(1+NORMINV(RAND(),$C$6,$E$6))-MonthlyExp*12*(1+Inflation)^(16-1),0) -> 28977369 | S20: =MAX(R20*(1+NORMINV(RAND(),$C$6,$E$6))-MonthlyExp*12*(1+Inflation)^(17-1),0) -> 27591314 | T20: =MAX(S20*(1+NORMINV(RAND(),$C$6,$E$6))-MonthlyExp*12*(1+Inflation)^(18-1),0) -> 28794672 | U20: =MAX(T20*(1+NORMINV(RAND(),$C$6,$E$6))-MonthlyExp*12*(1+Inflation)^(19-1),0) -> 30786273 | V20: =MAX(U20*(1+NORMINV(RAND(),$C$6,$E$6))-MonthlyExp*12*(1+Inflation)^(20-1),0) -> 32888608 | W20: =MAX(V20*(1+NORMINV(RAND(),$C$6,$E$6))-MonthlyExp*12*(1+Inflation)^(21-1),0) -> 35099231 | X20: =MAX(W20*(1+NORMINV(RAND(),$C$6,$E$6))-MonthlyExp*12*(1+Inflation)^(22-1),0) -> 33835819 | Y20: =MAX(X20*(1+NORMINV(RAND(),$C$6,$E$6))-MonthlyExp*12*(1+Inflation)^(23-1),0) -> 36009143 | Z20: =MAX(Y20*(1+NORMINV(RAND(),$C$6,$E$6))-MonthlyExp*12*(1+Inflation)^(24-1),0) -> 34990115 | AA20: =MAX(Z20*(1+NORMINV(RAND(),$C$6,$E$6))-MonthlyExp*12*(1+Inflation)^(25-1),0) -> 30914956 | AB20: =MAX(AA20*(1+NORMINV(RAND(),$C$6,$E$6))-MonthlyExp*12*(1+Inflation)^(26-1),0) -> 27056790 | AC20: =MAX(AB20*(1+NORMINV(RAND(),$C$6,$E$6))-MonthlyExp*12*(1+Inflation)^(27-1),0) -> 23833817 | AD20: =MAX(AC20*(1+NORMINV(RAND(),$C$6,$E$6))-MonthlyExp*12*(1+Inflation)^(28-1),0) -> 22400869 | AE20: =MAX(AD20*(1+NORMINV(RAND(),$C$6,$E$6))-MonthlyExp*12*(1+Inflation)^(29-1),0) -> 23381399 | AF20: =MAX(AE20*(1+NORMINV(RAND(),$C$6,$E$6))-MonthlyExp*12*(1+Inflation)^(30-1),0) -> 20451362
... A48: 40 | B48: =Corpus -> 20000000 | C48: =MAX(B48*(1+NORMINV(RAND(),$C$6,$E$6))-MonthlyExp*12*(1+Inflation)^(1-1),0) -> 20821568 | D48: =MAX(C48*(1+NORMINV(RAND(),$C$6,$E$6))-MonthlyExp*12*(1+Inflation)^(2-1),0) -> 21349136 | E48: =MAX(D48*(1+NORMINV(RAND(),$C$6,$E$6))-MonthlyExp*12*(1+Inflation)^(3-1),0) -> 21093119 | F48: =MAX(E48*(1+NORMINV(RAND(),$C$6,$E$6))-MonthlyExp*12*(1+Inflation)^(4-1),0) -> 20599296 | G48: =MAX(F48*(1+NORMINV(RAND(),$C$6,$E$6))-MonthlyExp*12*(1+Inflation)^(5-1),0) -> 22582125 | H48: =MAX(G48*(1+NORMINV(RAND(),$C$6,$E$6))-MonthlyExp*12*(1+Inflation)^(6-1),0) -> 18902408 | I48: =MAX(H48*(1+NORMINV(RAND(),$C$6,$E$6))-MonthlyExp*12*(1+Inflation)^(7-1),0) -> 18519600 | J48: =MAX(I48*(1+NORMINV(RAND(),$C$6,$E$6))-MonthlyExp*12*(1+Inflation)^(8-1),0) -> 18380775 | K48: =MAX(J48*(1+NORMINV(RAND(),$C$6,$E$6))-MonthlyExp*12*(1+Inflation)^(9-1),0) -> 17917556 | L48: =MAX(K48*(1+NORMINV(RAND(),$C$6,$E$6))-MonthlyExp*12*(1+Inflation)^(10-1),0) -> 18637757 | M48: =MAX(L48*(1+NORMINV(RAND(),$C$6,$E$6))-MonthlyExp*12*(1+Inflation)^(11-1),0) -> 20129719 | N48: =MAX(M48*(1+NORMINV(RAND(),$C$6,$E$6))-MonthlyExp*12*(1+Inflation)^(12-1),0) -> 21374729 | O48: =MAX(N48*(1+NORMINV(RAND(),$C$6,$E$6))-MonthlyExp*12*(1+Inflation)^(13-1),0) -> 22381406 | P48: =MAX(O48*(1+NORMINV(RAND(),$C$6,$E$6))-MonthlyExp*12*(1+Inflation)^(14-1),0) -> 23508191 | Q48: =MAX(P48*(1+NORMINV(RAND(),$C$6,$E$6))-MonthlyExp*12*(1+Inflation)^(15-1),0) -> 25323137 | R48: =MAX(Q48*(1+NORMINV(RAND(),$C$6,$E$6))-MonthlyExp*12*(1+Inflation)^(16-1),0) -> 22603270 | S48: =MAX(R48*(1+NORMINV(RAND(),$C$6,$E$6))-MonthlyExp*12*(1+Inflation)^(17-1),0) -> 22324989 | T48: =MAX(S48*(1+NORMINV(RAND(),$C$6,$E$6))-MonthlyExp*12*(1+Inflation)^(18-1),0) -> 19943862 | U48: =MAX(T48*(1+NORMINV(RAND(),$C$6,$E$6))-MonthlyExp*12*(1+Inflation)^(19-1),0) -> 16240110 | V48: =MAX(U48*(1+NORMINV(RAND(),$C$6,$E$6))-MonthlyExp*12*(1+Inflation)^(20-1),0) -> 17698669 | W48: =MAX(V48*(1+NORMINV(RAND(),$C$6,$E$6))-MonthlyExp*12*(1+Inflation)^(21-1),0) -> 15220128 | X48: =MAX(W48*(1+NORMINV(RAND(),$C$6,$E$6))-MonthlyExp*12*(1+Inflation)^(22-1),0) -> 14024783 | Y48: =MAX(X48*(1+NORMINV(RAND(),$C$6,$E$6))-MonthlyExp*12*(1+Inflation)^(23-1),0) -> 12597615 | Z48: =MAX(Y48*(1+NORMINV(RAND(),$C$6,$E$6))-MonthlyExp*12*(1+Inflation)^(24-1),0) -> 13242993 | AA48: =MAX(Z48*(1+NORMINV(RAND(),$C$6,$E$6))-MonthlyExp*12*(1+Inflation)^(25-1),0) -> 11322775 | AB48: =MAX(AA48*(1+NORMINV(RAND(),$C$6,$E$6))-MonthlyExp*12*(1+Inflation)^(26-1),0) -> 8340636.8 | AC48: =MAX(AB48*(1+NORMINV(RAND(),$C$6,$E$6))-MonthlyExp*12*(1+Inflation)^(27-1),0) -> 5190608.8 | AD48: =MAX(AC48*(1+NORMINV(RAND(),$C$6,$E$6))-MonthlyExp*12*(1+Inflation)^(28-1),0) -> 1826154.3 | AE48: =MAX(AD48*(1+NORMINV(RAND(),$C$6,$E$6))-MonthlyExp*12*(1+Inflation)^(29-1),0) -> 0 | AF48: =MAX(AE48*(1+NORMINV(RAND(),$C$6,$E$6))-MonthlyExp*12*(1+Inflation)^(30-1),0) -> 0
B50: Results Summary (based on the trials above)
B51: Probability of Success (corpus > ₹0 after 30 yrs) | D51: =COUNTIF(AF9:AF48,">0")/40 -> 0.975
B52: Median Ending Corpus (Year 30) | D52: =MEDIAN(AF9:AF48) -> 96936914
B53: 10th Percentile Ending Corpus (weak-market tail) | D53: =PERCENTILE(AF9:AF48,0.1) -> 28765780
B54: 90th Percentile Ending Corpus (strong-market tail) | D54: =PERCENTILE(AF9:AF48,0.9) -> 2.4534188e+08
B55: Best Trial — Ending Corpus | D55: =MAX(AF9:AF48) -> 3.6807052e+08
B56: Worst Trial — Ending Corpus | D56: =MIN(AF9:AF48) -> 0

Sheet Instrument Guide
A1: INSTRUMENT GUIDE — What to hold in each Bucket (India, indicative)
B3: Indicative categories only — actual scheme selection, expense ratio and taxation should be checked with a SEBI-registered adviser. Returns shown are typical historical ranges, NOT guaranteed.
B5: BUCKET 1 — Income Bucket (Years 1-5) | Safety & Liquidity first
B6: Instrument | C6: Suggested % of this Bucket | D6: Typical Return p.a. | E6: Why
B7: Senior Citizen Savings Scheme (SCSS) | C7: 0.3 | D7: ~8.2% | E7: Govt-backed, quarterly payout, max ₹30L/person
B8: Post Office Monthly Income Scheme (POMIS) | C8: 0.2 | D8: ~7.4% | E8: Govt-backed, fixed monthly income
B9: Bank FD (senior citizen rate, laddered) | C9: 0.3 | D9: ~7.0-7.5% | E9: Simple, fully liquid on maturity ladder
B10: Liquid / Overnight Mutual Fund | C10: 0.2 | D10: ~6.5-7.0% | E10: For the monthly SWP - instant liquidity
B12: BUCKET 2 — Refill Bucket (Years 6-15) | Moderate, steady growth
B13: Instrument | C13: Suggested % of this Bucket | D13: Typical Return p.a. | E13: Why
B14: Banking & PSU Debt Fund | C14: 0.3 | D14: ~7.5-8.5% | E14: High credit quality, low volatility
B15: Target Maturity Debt Fund (matched to horizon) | C15: 0.3 | D15: ~7.5-8.0% | E15: Predictable, tax-efficient over 5+ yrs
B16: Conservative Hybrid Fund (75-90% debt) | C16: 0.25 | D16: ~9.0-10.0% | E16: Small equity kicker for slightly higher return
B17: Balanced Advantage Fund (BAF) | C17: 0.15 | D17: ~9.0-11.0% | E17: Auto equity-debt rebalancing, smooths volatility
B19: BUCKET 3 — Growth Bucket (Years 16-30) | Equity + Gold for long-term growth
B20: Instrument | C20: Suggested % of this Bucket | D20: Typical Return p.a. | E20: Why
B21: Nifty 50 / Sensex Index Fund | C21: 0.35 | D21: ~11-12% | E21: Low-cost, long-term equity core
B22: Flexicap / Large & Midcap Mutual Fund | C22: 0.25 | D22: ~12-14% | E22: Higher growth potential, 15-yr+ horizon
B23: Sovereign Gold Bonds (convert existing physical gold) | C23: 0.25 | D23: ~8-10% | E23: Extra 2.5% interest vs physical gold, no GST/making charges
B24: Equity-oriented Hybrid Fund | C24: 0.15 | D24: ~10-11% | E24: Slightly lower volatility than pure equity
B26: Note: % columns are indicative sub-allocation WITHIN each bucket, not of total corpus.
B27: Rebalance/review once a year, and always re-check current rates before investing.

Sheet Delayed SWP Option
A1: DELAYED SWP OPTION — Growth Fund for 5 Years, then Withdraw (vs the 3-Bucket Plan)
B3: Assumes full corpus is put in ONE growth-oriented fund for the first 5 years with NO withdrawal (monthly expenses funded from elsewhere during this period). SWP then starts in Year 6, using the same inflation-adjusted withdrawal schedule as the main plan. Two variants shown: (A) stays 100% in the growth fund throughout, and (B) at Year 5 carves out a safety Buffer into liquid/FD before SWP starts.
B6: Buffer carved out at Year 5, for Variant B (editable) | D6: 0.2
A8: Year | B8: Age | C8: Annual Withdrawal | D8: A: Growth Fund Opening | E8: A: Return | F8: A: Closing (Total) | G8: B: Buffer Opening | H8: B: Buffer Return | I8: B: Buffer Closing | J8: B: Growth Opening | K8: B: Growth Return | L8: B: Shortfall (helper) | M8: B: Growth Closing | N8: B: Closing (Total) | O8: 3-Bucket Plan Closing (ref)
A9: 1 | B9: =Age+A9-1 -> 62 | C9: =IF(A9<=5,0,MonthlyExp*12*(1+Inflation)^(A9-1)) -> 0 | D9: =Corpus -> 20000000 | E9: =D9*GrowthReturn -> 2200000 | F9: =D9+E9-C9 -> 22200000 | G9: 0 | H9: =G9*B1Ret -> 0 | I9: =MAX(G9+H9-C9,0) -> 0 | J9: =Corpus -> 20000000 | K9: =J9*GrowthReturn -> 2200000 | L9: =MAX(C9-(G9+H9),0) -> 0 | M9: =J9+K9-L9 -> 22200000 | N9: =I9+M9 -> 22200000 | O9: ='Annual Summary'!J2 -> 21411078
A10: 2 | B10: =Age+A10-1 -> 63 | C10: =IF(A10<=5,0,MonthlyExp*12*(1+Inflation)^(A10-1)) -> 0 | D10: =F9 -> 22200000 | E10: =D10*GrowthReturn -> 2442000 | F10: =D10+E10-C10 -> 24642000 | G10: 0 | H10: =G10*B1Ret -> 0 | I10: =MAX(G10+H10-C10,0) -> 0 | J10: =M9 -> 22200000 | K10: =J10*GrowthReturn -> 2442000 | L10: =MAX(C10-(G10+H10),0) -> 0 | M10: =J10+K10-L10 -> 24642000 | N10: =I10+M10 -> 24642000 | O10: ='Annual Summary'!J3 -> 22945172
A11: 3 | B11: =Age+A11-1 -> 64 | C11: =IF(A11<=5,0,MonthlyExp*12*(1+Inflation)^(A11-1)) -> 0 | D11: =F10 -> 24642000 | E11: =D11*GrowthReturn -> 2710620 | F11: =D11+E11-C11 -> 27352620 | G11: 0 | H11: =G11*B1Ret -> 0 | I11: =MAX(G11+H11-C11,0) -> 0 | J11: =M10 -> 24642000 | K11: =J11*GrowthReturn -> 2710620 | L11: =MAX(C11-(G11+H11),0) -> 0 | M11: =J11+K11-L11 -> 27352620 | N11: =I11+M11 -> 27352620 | O11: ='Annual Summary'!J4 -> 24615282
A12: 4 | B12: =Age+A12-1 -> 65 | C12: =IF(A12<=5,0,MonthlyExp*12*(1+Inflation)^(A12-1)) -> 0 | D12: =F11 -> 27352620 | E12: =D12*GrowthReturn -> 3008788.2 | F12: =D12+E12-C12 -> 30361408 | G12: 0 | H12: =G12*B1Ret -> 0 | I12: =MAX(G12+H12-C12,0) -> 0 | J12: =M11 -> 27352620 | K12: =J12*GrowthReturn -> 3008788.2 | L12: =MAX(C12-(G12+H12),0) -> 0 | M12: =J12+K12-L12 -> 30361408 | N12: =I12+M12 -> 30361408 | O12: ='Annual Summary'!J5 -> 26435928
A13: 5 | B13: =Age+A13-1 -> 66 | C13: =IF(A13<=5,0,MonthlyExp*12*(1+Inflation)^(A13-1)) -> 0 | D13: =F12 -> 30361408 | E13: =D13*GrowthReturn -> 3339754.9 | F13: =D13+E13-C13 -> 33701163 | G13: 0 | H13: =G13*B1Ret -> 0 | I13: =MAX(G13+H13-C13,0) -> 0 | J13: =M12 -> 30361408 | K13: =J13*GrowthReturn -> 3339754.9 | L13: =MAX(C13-(G13+H13),0) -> 0 | M13: =J13+K13-L13 -> 33701163 | N13: =I13+M13 -> 33701163 | O13: ='Annual Summary'!J6 -> 28423342
A14: 6 | B14: =Age+A14-1 -> 67 | C14: =IF(A14<=5,0,MonthlyExp*12*(1+Inflation)^(A14-1)) -> 841531.04 | D14: =F13 -> 33701163 | E14: =D14*GrowthReturn -> 3707127.9 | F14: =D14+E14-C14 -> 36566760 | G14: =M13*$D$6 -> 6740232.6 | H14: =G14*B1Ret -> 471816.28 | I14: =MAX(G14+H14-C14,0) -> 6370517.9 | J14: =M13*(1-$D$6) -> 26960930 | K14: =J14*GrowthReturn -> 2965702.4 | L14: =MAX(C14-(G14+H14),0) -> 0 | M14: =J14+K14-L14 -> 29926633 | N14: =I14+M14 -> 36297151 | O14: ='Annual Summary'!J7 -> 30495295
A15: 7 | B15: =Age+A15-1 -> 68 | C15: =IF(A15<=5,0,MonthlyExp*12*(1+Inflation)^(A15-1)) -> 900438.21 | D15: =F14 -> 36566760 | E15: =D15*GrowthReturn -> 4022343.6 | F15: =D15+E15-C15 -> 39688665 | G15: =I14 -> 6370517.9 | H15: =G15*B1Ret -> 445936.25 | I15: =MAX(G15+H15-C15,0) -> 5916015.9 | J15: =M14 -> 29926633 | K15: =J15*GrowthReturn -> 3291929.6 | L15: =MAX(C15-(G15+H15),0) -> 0 | M15: =J15+K15-L15 -> 33218562 | N15: =I15+M15 -> 39134578 | O15: ='Annual Summary'!J8 -> 32755788
A16: 8 | B16: =Age+A16-1 -> 69 | C16: =IF(A16<=5,0,MonthlyExp*12*(1+Inflation)^(A16-1)) -> 963468.89 | D16: =F15 -> 39688665 | E16: =D16*GrowthReturn -> 4365753.2 | F16: =D16+E16-C16 -> 43090950 | G16: =I15 -> 5916015.9 | H16: =G16*B1Ret -> 414121.11 | I16: =MAX(G16+H16-C16,0) -> 5366668.1 | J16: =M15 -> 33218562 | K16: =J16*GrowthReturn -> 3654041.9 | L16: =MAX(C16-(G16+H16),0) -> 0 | M16: =J16+K16-L16 -> 36872604 | N16: =I16+M16 -> 42239272 | O16: ='Annual Summary'!J9 -> 35225439
A17: 9 | B17: =Age+A17-1 -> 70 | C17: =IF(A17<=5,0,MonthlyExp*12*(1+Inflation)^(A17-1)) -> 1030911.7 | D17: =F16 -> 43090950 | E17: =D17*GrowthReturn -> 4740004.5 | F17: =D17+E17-C17 -> 46800042 | G17: =I16 -> 5366668.1 | H17: =G17*B1Ret -> 375666.77 | I17: =MAX(G17+H17-C17,0) -> 4711423.2 | J17: =M16 -> 36872604 | K17: =J17*GrowthReturn -> 4055986.5 | L17: =MAX(C17-(G17+H17),0) -> 0 | M17: =J17+K17-L17 -> 40928591 | N17: =I17+M17 -> 45640014 | O17: ='Annual Summary'!J10 -> 37927332
A18: 10 | B18: =Age+A18-1 -> 71 | C18: =IF(A18<=5,0,MonthlyExp*12*(1+Inflation)^(A18-1)) -> 1103075.5 | D18: =F17 -> 46800042 | E18: =D18*GrowthReturn -> 5148004.7 | F18: =D18+E18-C18 -> 50844972 | G18: =I17 -> 4711423.2 | H18: =G18*B1Ret -> 329799.62 | I18: =MAX(G18+H18-C18,0) -> 3938147.3 | J18: =M17 -> 40928591 | K18: =J18*GrowthReturn -> 4502145 | L18: =MAX(C18-(G18+H18),0) -> 0 | M18: =J18+K18-L18 -> 45430736 | N18: =I18+M18 -> 49368883 | O18: ='Annual Summary'!J11 -> 40887324
A19: 11 | B19: =Age+A19-1 -> 72 | C19: =IF(A19<=5,0,MonthlyExp*12*(1+Inflation)^(A19-1)) -> 1180290.8 | D19: =F18 -> 50844972 | E19: =D19*GrowthReturn -> 5592946.9 | F19: =D19+E19-C19 -> 55257628 | G19: =I18 -> 3938147.3 | H19: =G19*B1Ret -> 275670.31 | I19: =MAX(G19+H19-C19,0) -> 3033526.8 | J19: =M18 -> 45430736 | K19: =J19*GrowthReturn -> 4997380.9 | L19: =MAX(C19-(G19+H19),0) -> 0 | M19: =J19+K19-L19 -> 50428117 | N19: =I19+M19 -> 53461643 | O19: ='Annual Summary'!J12 -> 44012866
A20: 12 | B20: =Age+A20-1 -> 73 | C20: =IF(A20<=5,0,MonthlyExp*12*(1+Inflation)^(A20-1)) -> 1262911.2 | D20: =F19 -> 55257628 | E20: =D20*GrowthReturn -> 6078339 | F20: =D20+E20-C20 -> 60073056 | G20: =I19 -> 3033526.8 | H20: =G20*B1Ret -> 212346.88 | I20: =MAX(G20+H20-C20,0) -> 1982962.5 | J20: =M19 -> 50428117 | K20: =J20*GrowthReturn -> 5547092.8 | L20: =MAX(C20-(G20+H20),0) -> 0 | M20: =J20+K20-L20 -> 55975210 | N20: =I20+M20 -> 57958172 | O20: ='Annual Summary'!J13 -> 47437746
A21: 13 | B21: =Age+A21-1 -> 74 | C21: =IF(A21<=5,0,MonthlyExp*12*(1+Inflation)^(A21-1)) -> 1351315 | D21: =F20 -> 60073056 | E21: =D21*GrowthReturn -> 6608036.1 | F21: =D21+E21-C21 -> 65329777 | G21: =I20 -> 1982962.5 | H21: =G21*B1Ret -> 138807.37 | I21: =MAX(G21+H21-C21,0) -> 770454.91 | J21: =M20 -> 55975210 | K21: =J21*GrowthReturn -> 6157273.1 | L21: =MAX(C21-(G21+H21),0) -> 0 | M21: =J21+K21-L21 -> 62132483 | N21: =I21+M21 -> 62902938 | O21: ='Annual Summary'!J14 -> 51195809
A22: 14 | B22: =Age+A22-1 -> 75 | C22: =IF(A22<=5,0,MonthlyExp*12*(1+Inflation)^(A22-1)) -> 1445907 | D22: =F21 -> 65329777 | E22: =D22*GrowthReturn -> 7186275.4 | F22: =D22+E22-C22 -> 71070145 | G22: =I21 -> 770454.91 | H22: =G22*B1Ret -> 53931.844 | I22: =MAX(G22+H22-C22,0) -> 0 | J22: =M21 -> 62132483 | K22: =J22*GrowthReturn -> 6834573.1 | L22: =MAX(C22-(G22+H22),0) -> 621520.25 | M22: =J22+K22-L22 -> 68345535 | N22: =I22+M22 -> 68345535 | O22: ='Annual Summary'!J15 -> 55325018
A23: 15 | B23: =Age+A23-1 -> 76 | C23: =IF(A23<=5,0,MonthlyExp*12*(1+Inflation)^(A23-1)) -> 1547120.5 | D23: =F22 -> 71070145 | E23: =D23*GrowthReturn -> 7817716 | F23: =D23+E23-C23 -> 77340741 | G23: =I22 -> 0 | H23: =G23*B1Ret -> 0 | I23: =MAX(G23+H23-C23,0) -> 0 | J23: =M22 -> 68345535 | K23: =J23*GrowthReturn -> 7518008.9 | L23: =MAX(C23-(G23+H23),0) -> 1547120.5 | M23: =J23+K23-L23 -> 74316424 | N23: =I23+M23 -> 74316424 | O23: ='Annual Summary'!J16 -> 59867956
A24: 16 | B24: =Age+A24-1 -> 77 | C24: =IF(A24<=5,0,MonthlyExp*12*(1+Inflation)^(A24-1)) -> 1655418.9 | D24: =F23 -> 77340741 | E24: =D24*GrowthReturn -> 8507481.5 | F24: =D24+E24-C24 -> 84192803 | G24: =I23 -> 0 | H24: =G24*B1Ret -> 0 | I24: =MAX(G24+H24-C24,0) -> 0 | J24: =M23 -> 74316424 | K24: =J24*GrowthReturn -> 8174806.6 | L24: =MAX(C24-(G24+H24),0) -> 1655418.9 | M24: =J24+K24-L24 -> 80835812 | N24: =I24+M24 -> 80835812 | O24: ='Annual Summary'!J17 -> 64528419
A25: 17 | B25: =Age+A25-1 -> 78 | C25: =IF(A25<=5,0,MonthlyExp*12*(1+Inflation)^(A25-1)) -> 1771298.2 | D25: =F24 -> 84192803 | E25: =D25*GrowthReturn -> 9261208.3 | F25: =D25+E25-C25 -> 91682713 | G25: =I24 -> 0 | H25: =G25*B1Ret -> 0 | I25: =MAX(G25+H25-C25,0) -> 0 | J25: =M24 -> 80835812 | K25: =J25*GrowthReturn -> 8891939.3 | L25: =MAX(C25-(G25+H25),0) -> 1771298.2 | M25: =J25+K25-L25 -> 87956453 | N25: =I25+M25 -> 87956453 | O25: ='Annual Summary'!J18 -> 69639329
A26: 18 | B26: =Age+A26-1 -> 79 | C26: =IF(A26<=5,0,MonthlyExp*12*(1+Inflation)^(A26-1)) -> 1895289.1 | D26: =F25 -> 91682713 | E26: =D26*GrowthReturn -> 10085098 | F26: =D26+E26-C26 -> 99872523 | G26: =I25 -> 0 | H26: =G26*B1Ret -> 0 | I26: =MAX(G26+H26-C26,0) -> 0 | J26: =M25 -> 87956453 | K26: =J26*GrowthReturn -> 9675209.8 | L26: =MAX(C26-(G26+H26),0) -> 1895289.1 | M26: =J26+K26-L26 -> 95736373 | N26: =I26+M26 -> 95736373 | O26: ='Annual Summary'!J19 -> 75251568
... A38: 30 | B38: =Age+A38-1 -> 91 | C38: =IF(A38<=5,0,MonthlyExp*12*(1+Inflation)^(A38-1)) -> 4268554.2 | D38: =F37 -> 2.6169691e+08 | E38: =D38*GrowthReturn -> 28786661 | F38: =D38+E38-C38 -> 2.8621502e+08 | G38: =I37 -> 0 | H38: =G38*B1Ret -> 0 | I38: =MAX(G38+H38-C38,0) -> 0 | J38: =M37 -> 2.4866078e+08 | K38: =J38*GrowthReturn -> 27352685 | L38: =MAX(C38-(G38+H38),0) -> 4268554.2 | M38: =J38+K38-L38 -> 2.7174491e+08 | N38: =I38+M38 -> 2.7174491e+08 | O38: ='Annual Summary'!J31 -> 1.957027e+08
B40: Summary Comparison — Expected Case
C41: A: Pure Delayed SWP | E41: B: Delayed SWP + Buffer | G41: 3-Bucket Plan
B42: Ending Corpus after 30 Years | C42: =F38 -> 2.8621502e+08 | E42: =N38 -> 2.7174491e+08 | G42: ='Annual Summary'!J31 -> 1.957027e+08
B43: Minimum Corpus reached, any year | C43: =MIN(F9:F38) -> 22200000 | E43: =MIN(N9:N38) -> 22200000 | G43: =MIN('Annual Summary'!J2:J31) -> 21411078
B44: Ever ran out of money (₹0 or less)? | C44: =IF(MIN(F9:F38)<=0,"YES - RISK","No") -> No | E44: =IF(MIN(N9:N38)<=0,"YES - RISK","No") -> No | G44: =IF(MIN('Annual Summary'!J2:J31)<=0,"YES - RISK","No") -> No
B71: Key takeaway: Variant A has zero cushion when SWP starts in Year 6 — a market dip right then hits the full corpus. Variant B softens that first shock with a small buffer, at the cost of a slightly lower long-run average return on the buffer portion. The 3-Bucket Plan (main model) spreads this protection across the whole 30 years, not just the Year-6 transition.

Sheet Gold as Legacy
A1: GOLD AS LEGACY — Plan Using Only the ₹1 Cr Cash Corpus (Gold left untouched for inheritance)
B3: If Gold is never sold and kept purely as legacy, only the ₹1 Cr Cash corpus funds your retirement. This sheet re-runs the same 3-Bucket logic (annual approximation) on ₹1 Cr alone, so you can see what monthly income it can realistically sustain for 30 years.
B6: Local Inputs for this Scenario (editable)
B7: Cash Corpus Available (₹) — Gold excluded | D7: 10000000
B8: Desired Monthly Income — today's value (₹) | D8: 50000
B9: Alternative / Sustainable Monthly Income to test (₹) | D9: 42000 | F9: ← try reducing this until 'Ever ran out?' below says No
A12: Year | B12: Age | C12: Desired (₹50k-style) Withdrawal | D12: Desired Plan Closing Corpus | E12: Desired Plan Status | F12: Alternative (lower ₹) Withdrawal | G12: Alt Plan Closing Corpus | H12: Alt Plan Status | J12: D:B1 | K12: D:B2 | L12: D:B3 | M12: A:B1 | N12: A:B2 | O12: A:B3
A13: 1 | B13: =Age+A13-1 -> 62 | C13: =$D$8*12*(1+Inflation)^(A13-1) -> 600000 | D13: =J13+K13+L13 -> 10370000 | E13: =IF(D13>0,"OK","OUT OF MONEY") -> OK | F13: =$D$9*12*(1+Inflation)^(A13-1) -> 504000 | G13: =M13+N13+O13 -> 10466000 | H13: =IF(G13>0,"OK","OUT OF MONEY") -> OK | J13: =($D$7*B1Pct)*(1+B1Ret)-C13 -> 1005000 | K13: =($D$7*B2Pct)*(1+B2Ret) -> 3815000 | L13: =($D$7*B3Pct)*(1+B3Ret) -> 5550000 | M13: =($D$7*B1Pct)*(1+B1Ret)-F13 -> 1101000 | N13: =($D$7*B2Pct)*(1+B2Ret) -> 3815000 | O13: =($D$7*B3Pct)*(1+B3Ret) -> 5550000
A14: 2 | B14: =Age+A14-1 -> 63 | C14: =$D$8*12*(1+Inflation)^(A14-1) -> 642000 | D14: =J14+K14+L14 -> 10752200 | E14: =IF(D14>0,"OK","OUT OF MONEY") -> OK | F14: =$D$9*12*(1+Inflation)^(A14-1) -> 539280 | G14: =M14+N14+O14 -> 10957640 | H14: =IF(G14>0,"OK","OUT OF MONEY") -> OK | J14: =(J13)*(1+B1Ret)-C14 -> 433350 | K14: =(K13)*(1+B2Ret) -> 4158350 | L14: =(L13)*(1+B3Ret) -> 6160500 | M14: =(M13)*(1+B1Ret)-F14 -> 638790 | N14: =(N13)*(1+B2Ret) -> 4158350 | O14: =(O13)*(1+B3Ret) -> 6160500
A15: 3 | B15: =Age+A15-1 -> 64 | C15: =$D$8*12*(1+Inflation)^(A15-1) -> 686940 | D15: =J15+K15+L15 -> 11147501 | E15: =IF(D15>0,"OK","OUT OF MONEY") -> OK | F15: =$D$9*12*(1+Inflation)^(A15-1) -> 577029.6 | G15: =M15+N15+O15 -> 11477232 | H15: =IF(G15>0,"OK","OUT OF MONEY") -> OK | J15: =(J14)*(1+B1Ret)-C15 -> -223255.5 | K15: =(K14)*(1+B2Ret) -> 4532601.5 | L15: =(L14)*(1+B3Ret) -> 6838155 | M15: =(M14)*(1+B1Ret)-F15 -> 106475.7 | N15: =(N14)*(1+B2Ret) -> 4532601.5 | O15: =(O14)*(1+B3Ret) -> 6838155
A16: 4 | B16: =Age+A16-1 -> 65 | C16: =$D$8*12*(1+Inflation)^(A16-1) -> 735025.8 | D16: =J16+K16+L16 -> 11556978 | E16: =IF(D16>0,"OK","OUT OF MONEY") -> OK | F16: =$D$9*12*(1+Inflation)^(A16-1) -> 617421.67 | G16: =M16+N16+O16 -> 12027395 | H16: =IF(G16>0,"OK","OUT OF MONEY") -> OK | J16: =(J15)*(1+B1Ret)-C16 -> -973909.19 | K16: =(K15)*(1+B2Ret) -> 4940535.6 | L16: =(L15)*(1+B3Ret) -> 7590352 | M16: =(M15)*(1+B1Ret)-F16 -> -503492.67 | N16: =(N15)*(1+B2Ret) -> 4940535.6 | O16: =(O15)*(1+B3Ret) -> 7590352
A17: 5 | B17: =Age+A17-1 -> 66 | C17: =$D$8*12*(1+Inflation)^(A17-1) -> 786477.61 | D17: =J17+K17+L17 -> 11981914 | E17: =IF(D17>0,"OK","OUT OF MONEY") -> OK | F17: =$D$9*12*(1+Inflation)^(A17-1) -> 660641.19 | G17: =M17+N17+O17 -> 12611096 | H17: =IF(G17>0,"OK","OUT OF MONEY") -> OK | J17: =((J16)*(1+B1Ret)-C17)+(MIN(MAX(($D$8*12*(1+Inflation)^(5+1-1)+$D$8*12*(1+Inflation)^(5+2-1)+$D$8*12*(1+Inflation)^(5+3-1)+$D$8*12*(1+Inflation)^(5+4-1)+$D$8*12*(1+Inflation)^(5+5-1))-((J16)*(1+B1Ret)-C17),0),((K16)*(1+B2Ret)))) -> 3556623.4 | K17: =((K16)*(1+B2Ret))-(MIN(MAX(($D$8*12*(1+Inflation)^(5+1-1)+$D$8*12*(1+Inflation)^(5+2-1)+$D$8*12*(1+Inflation)^(5+3-1)+$D$8*12*(1+Inflation)^(5+4-1)+$D$8*12*(1+Inflation)^(5+5-1))-((J16)*(1+B1Ret)-C17),0),((K16)*(1+B2Ret)))) -> 0 | L17: =(L16)*(1+B3Ret) -> 8425290.8 | M17: =((M16)*(1+B1Ret)-F17)+(MIN(MAX(($D$9*12*(1+Inflation)^(5+1-1)+$D$9*12*(1+Inflation)^(5+2-1)+$D$9*12*(1+Inflation)^(5+3-1)+$D$9*12*(1+Inflation)^(5+4-1)+$D$9*12*(1+Inflation)^(5+5-1))-((M16)*(1+B1Ret)-F17),0),((N16)*(1+B2Ret)))) -> 4065117.3 | N17: =((N16)*(1+B2Ret))-(MIN(MAX(($D$9*12*(1+Inflation)^(5+1-1)+$D$9*12*(1+Inflation)^(5+2-1)+$D$9*12*(1+Inflation)^(5+3-1)+$D$9*12*(1+Inflation)^(5+4-1)+$D$9*12*(1+Inflation)^(5+5-1))-((M16)*(1+B1Ret)-F17),0),((N16)*(1+B2Ret)))) -> 120688.18 | O17: =(O16)*(1+B3Ret) -> 8425290.8
A18: 6 | B18: =Age+A18-1 -> 67 | C18: =$D$8*12*(1+Inflation)^(A18-1) -> 841531.04 | D18: =J18+K18+L18 -> 12316129 | E18: =IF(D18>0,"OK","OUT OF MONEY") -> OK | F18: =$D$9*12*(1+Inflation)^(A18-1) -> 706886.07 | G18: =M18+N18+O18 -> 13126412 | H18: =IF(G18>0,"OK","OUT OF MONEY") -> OK | J18: =(J17)*(1+B1Ret)-C18 -> 2964056 | K18: =(K17)*(1+B2Ret) -> 0 | L18: =(L17)*(1+B3Ret) -> 9352072.8 | M18: =(M17)*(1+B1Ret)-F18 -> 3642789.5 | N18: =(N17)*(1+B2Ret) -> 131550.12 | O18: =(O17)*(1+B3Ret) -> 9352072.8
A19: 7 | B19: =Age+A19-1 -> 68 | C19: =$D$8*12*(1+Inflation)^(A19-1) -> 900438.21 | D19: =J19+K19+L19 -> 12651902 | E19: =IF(D19>0,"OK","OUT OF MONEY") -> OK | F19: =$D$9*12*(1+Inflation)^(A19-1) -> 756368.1 | G19: =M19+N19+O19 -> 13665607 | H19: =IF(G19>0,"OK","OUT OF MONEY") -> OK | J19: =(J18)*(1+B1Ret)-C19 -> 2271101.7 | K19: =(K18)*(1+B2Ret) -> 0 | L19: =(L18)*(1+B3Ret) -> 10380801 | M19: =(M18)*(1+B1Ret)-F19 -> 3141416.6 | N19: =(N18)*(1+B2Ret) -> 143389.63 | O19: =(O18)*(1+B3Ret) -> 10380801
A20: 8 | B20: =Age+A20-1 -> 69 | C20: =$D$8*12*(1+Inflation)^(A20-1) -> 963468.89 | D20: =J20+K20+L20 -> 12989299 | E20: =IF(D20>0,"OK","OUT OF MONEY") -> OK | F20: =$D$9*12*(1+Inflation)^(A20-1) -> 809313.86 | G20: =M20+N20+O20 -> 14230985 | H20: =IF(G20>0,"OK","OUT OF MONEY") -> OK | J20: =(J19)*(1+B1Ret)-C20 -> 1466610 | K20: =(K19)*(1+B2Ret) -> 0 | L20: =(L19)*(1+B3Ret) -> 11522689 | M20: =(M19)*(1+B1Ret)-F20 -> 2552001.9 | N20: =(N19)*(1+B2Ret) -> 156294.7 | O20: =(O19)*(1+B3Ret) -> 11522689
A21: 9 | B21: =Age+A21-1 -> 70 | C21: =$D$8*12*(1+Inflation)^(A21-1) -> 1030911.7 | D21: =J21+K21+L21 -> 13328546 | E21: =IF(D21>0,"OK","OUT OF MONEY") -> OK | F21: =$D$9*12*(1+Inflation)^(A21-1) -> 865965.83 | G21: =M21+N21+O21 -> 14825222 | H21: =IF(G21>0,"OK","OUT OF MONEY") -> OK | J21: =(J20)*(1+B1Ret)-C21 -> 538360.94 | K21: =(K20)*(1+B2Ret) -> 0 | L21: =(L20)*(1+B3Ret) -> 12790185 | M21: =(M20)*(1+B1Ret)-F21 -> 1864676.2 | N21: =(N20)*(1+B2Ret) -> 170361.22 | O21: =(O20)*(1+B3Ret) -> 12790185
A22: 10 | B22: =Age+A22-1 -> 71 | C22: =$D$8*12*(1+Inflation)^(A22-1) -> 1103075.5 | D22: =J22+K22+L22 -> 13670076 | E22: =IF(D22>0,"OK","OUT OF MONEY") -> OK | F22: =$D$9*12*(1+Inflation)^(A22-1) -> 926583.44 | G22: =M22+N22+O22 -> 15451419 | H22: =IF(G22>0,"OK","OUT OF MONEY") -> OK | J22: =((J21)*(1+B1Ret)-C22)+(MIN(MAX(($D$8*12*(1+Inflation)^(10+1-1)+$D$8*12*(1+Inflation)^(10+2-1)+$D$8*12*(1+Inflation)^(10+3-1)+$D$8*12*(1+Inflation)^(10+4-1)+$D$8*12*(1+Inflation)^(10+5-1))-((J21)*(1+B1Ret)-C22),0),((K21)*(1+B2Ret)))) -> -527029.32 | K22: =((K21)*(1+B2Ret))-(MIN(MAX(($D$8*12*(1+Inflation)^(10+1-1)+$D$8*12*(1+Inflation)^(10+2-1)+$D$8*12*(1+Inflation)^(10+3-1)+$D$8*12*(1+Inflation)^(10+4-1)+$D$8*12*(1+Inflation)^(10+5-1))-((J21)*(1+B1Ret)-C22),0),((K21)*(1+B2Ret)))) -> 0 | L22: =(L21)*(1+B3Ret) -> 14197105 | M22: =((M21)*(1+B1Ret)-F22)+(MIN(MAX(($D$9*12*(1+Inflation)^(10+1-1)+$D$9*12*(1+Inflation)^(10+2-1)+$D$9*12*(1+Inflation)^(10+3-1)+$D$9*12*(1+Inflation)^(10+4-1)+$D$9*12*(1+Inflation)^(10+5-1))-((M21)*(1+B1Ret)-F22),0),((N21)*(1+B2Ret)))) -> 1254313.8 | N22: =((N21)*(1+B2Ret))-(MIN(MAX(($D$9*12*(1+Inflation)^(10+1-1)+$D$9*12*(1+Inflation)^(10+2-1)+$D$9*12*(1+Inflation)^(10+3-1)+$D$9*12*(1+Inflation)^(10+4-1)+$D$9*12*(1+Inflation)^(10+5-1))-((M21)*(1+B1Ret)-F22),0),((N21)*(1+B2Ret)))) -> 0 | O22: =(O21)*(1+B3Ret) -> 14197105
A23: 11 | B23: =Age+A23-1 -> 72 | C23: =$D$8*12*(1+Inflation)^(A23-1) -> 1180290.8 | D23: =J23+K23+L23 -> 14014574 | E23: =IF(D23>0,"OK","OUT OF MONEY") -> OK | F23: =$D$9*12*(1+Inflation)^(A23-1) -> 991444.28 | G23: =M23+N23+O23 -> 16109458 | H23: =IF(G23>0,"OK","OUT OF MONEY") -> OK | J23: =(J22)*(1+B1Ret)-C23 -> -1744212.2 | K23: =(K22)*(1+B2Ret) -> 0 | L23: =(L22)*(1+B3Ret) -> 15758786 | M23: =(M22)*(1+B1Ret)-F23 -> 350671.52 | N23: =(N22)*(1+B2Ret) -> 0 | O23: =(O22)*(1+B3Ret) -> 15758786
A24: 12 | B24: =Age+A24-1 -> 73 | C24: =$D$8*12*(1+Inflation)^(A24-1) -> 1262911.2 | D24: =J24+K24+L24 -> 14363035 | E24: =IF(D24>0,"OK","OUT OF MONEY") -> OK | F24: =$D$9*12*(1+Inflation)^(A24-1) -> 1060845.4 | G24: =M24+N24+O24 -> 16806626 | H24: =IF(G24>0,"OK","OUT OF MONEY") -> OK | J24: =(J23)*(1+B1Ret)-C24 -> -3129218.2 | K24: =(K23)*(1+B2Ret) -> 0 | L24: =(L23)*(1+B3Ret) -> 17492253 | M24: =(M23)*(1+B1Ret)-F24 -> -685626.86 | N24: =(N23)*(1+B2Ret) -> 0 | O24: =(O23)*(1+B3Ret) -> 17492253
A25: 13 | B25: =Age+A25-1 -> 74 | C25: =$D$8*12*(1+Inflation)^(A25-1) -> 1351315 | D25: =J25+K25+L25 -> 14716822 | E25: =IF(D25>0,"OK","OUT OF MONEY") -> OK | F25: =$D$9*12*(1+Inflation)^(A25-1) -> 1135104.6 | G25: =M25+N25+O25 -> 17547676 | H25: =IF(G25>0,"OK","OUT OF MONEY") -> OK | J25: =(J24)*(1+B1Ret)-C25 -> -4699578.4 | K25: =(K24)*(1+B2Ret) -> 0 | L25: =(L24)*(1+B3Ret) -> 19416401 | M25: =(M24)*(1+B1Ret)-F25 -> -1868725.3 | N25: =(N24)*(1+B2Ret) -> 0 | O25: =(O24)*(1+B3Ret) -> 19416401
A26: 14 | B26: =Age+A26-1 -> 75 | C26: =$D$8*12*(1+Inflation)^(A26-1) -> 1445907 | D26: =J26+K26+L26 -> 15077749 | E26: =IF(D26>0,"OK","OUT OF MONEY") -> OK | F26: =$D$9*12*(1+Inflation)^(A26-1) -> 1214561.9 | G26: =M26+N26+O26 -> 18338107 | H26: =IF(G26>0,"OK","OUT OF MONEY") -> OK | J26: =(J25)*(1+B1Ret)-C26 -> -6474455.9 | K26: =(K25)*(1+B2Ret) -> 0 | L26: =(L25)*(1+B3Ret) -> 21552205 | M26: =(M25)*(1+B1Ret)-F26 -> -3214098 | N26: =(N25)*(1+B2Ret) -> 0 | O26: =(O25)*(1+B3Ret) -> 21552205
A27: 15 | B27: =Age+A27-1 -> 76 | C27: =$D$8*12*(1+Inflation)^(A27-1) -> 1547120.5 | D27: =J27+K27+L27 -> 15448159 | E27: =IF(D27>0,"OK","OUT OF MONEY") -> OK | F27: =$D$9*12*(1+Inflation)^(A27-1) -> 1299581.2 | G27: =M27+N27+O27 -> 19184281 | H27: =IF(G27>0,"OK","OUT OF MONEY") -> OK | J27: =((J26)*(1+B1Ret)-C27)+(MIN(MAX(($D$8*12*(1+Inflation)^(15+1-1)+$D$8*12*(1+Inflation)^(15+2-1)+$D$8*12*(1+Inflation)^(15+3-1)+$D$8*12*(1+Inflation)^(15+4-1)+$D$8*12*(1+Inflation)^(15+5-1))-((J26)*(1+B1Ret)-C27),0),(((K26)*(1+B2Ret))+(MIN(MAX(($D$8*12*(1+Inflation)^(15+1-1)+$D$8*12*(1+Inflation)^(15+2-1)+$D$8*12*(1+Inflation)^(15+3-1)+$D$8*12*(1+Inflation)^(15+4-1)+$D$8*12*(1+Inflation)^(15+5-1))-((J26)*(1+B1Ret)-C27),0),((L26)*(1+B3Ret))))))) -> 9519882.2 | K27: =(((K26)*(1+B2Ret))+(MIN(MAX(($D$8*12*(1+Inflation)^(15+1-1)+$D$8*12*(1+Inflation)^(15+2-1)+$D$8*12*(1+Inflation)^(15+3-1)+$D$8*12*(1+Inflation)^(15+4-1)+$D$8*12*(1+Inflation)^(15+5-1))-((J26)*(1+B1Ret)-C27),0),((L26)*(1+B3Ret)))))-(MIN(MAX(($D$8*12*(1+Inflation)^(15+1-1)+$D$8*12*(1+Inflation)^(15+2-1)+$D$8*12*(1+Inflation)^(15+3-1)+$D$8*12*(1+Inflation)^(15+4-1)+$D$8*12*(1+Inflation)^(15+5-1))-((J26)*(1+B1Ret)-C27),0),(((K26)*(1+B2Ret))+(MIN(MAX(($D$8*12*(1+Inflation)^(15+1-1)+$D$8*12*(1+Inflation)^(15+2-1)+$D$8*12*(1+Inflation)^(15+3-1)+$D$8*12*(1+Inflation)^(15+4-1)+$D$8*12*(1+Inflation)^(15+5-1))-((J26)*(1+B1Ret)-C27),0),((L26)*(1+B3Ret))))))) -> 0 | L27: =((L26)*(1+B3Ret))-(MIN(MAX(($D$8*12*(1+Inflation)^(15+1-1)+$D$8*12*(1+Inflation)^(15+2-1)+$D$8*12*(1+Inflation)^(15+3-1)+$D$8*12*(1+Inflation)^(15+4-1)+$D$8*12*(1+Inflation)^(15+5-1))-((J26)*(1+B1Ret)-C27),0),((L26)*(1+B3Ret)))) -> 5928276.9 | M27: =((M26)*(1+B1Ret)-F27)+(MIN(MAX(($D$9*12*(1+Inflation)^(15+1-1)+$D$9*12*(1+Inflation)^(15+2-1)+$D$9*12*(1+Inflation)^(15+3-1)+$D$9*12*(1+Inflation)^(15+4-1)+$D$9*12*(1+Inflation)^(15+5-1))-((M26)*(1+B1Ret)-F27),0),(((N26)*(1+B2Ret))+(MIN(MAX(($D$9*12*(1+Inflation)^(15+1-1)+$D$9*12*(1+Inflation)^(15+2-1)+$D$9*12*(1+Inflation)^(15+3-1)+$D$9*12*(1+Inflation)^(15+4-1)+$D$9*12*(1+Inflation)^(15+5-1))-((M26)*(1+B1Ret)-F27),0),((O26)*(1+B3Ret))))))) -> 7996701 | N27: =(((N26)*(1+B2Ret))+(MIN(MAX(($D$9*12*(1+Inflation)^(15+1-1)+$D$9*12*(1+Inflation)^(15+2-1)+$D$9*12*(1+Inflation)^(15+3-1)+$D$9*12*(1+Inflation)^(15+4-1)+$D$9*12*(1+Inflation)^(15+5-1))-((M26)*(1+B1Ret)-F27),0),((O26)*(1+B3Ret)))))-(MIN(MAX(($D$9*12*(1+Inflation)^(15+1-1)+$D$9*12*(1+Inflation)^(15+2-1)+$D$9*12*(1+Inflation)^(15+3-1)+$D$9*12*(1+Inflation)^(15+4-1)+$D$9*12*(1+Inflation)^(15+5-1))-((M26)*(1+B1Ret)-F27),0),(((N26)*(1+B2Ret))+(MIN(MAX(($D$9*12*(1+Inflation)^(15+1-1)+$D$9*12*(1+Inflation)^(15+2-1)+$D$9*12*(1+Inflation)^(15+3-1)+$D$9*12*(1+Inflation)^(15+4-1)+$D$9*12*(1+Inflation)^(15+5-1))-((M26)*(1+B1Ret)-F27),0),((O26)*(1+B3Ret))))))) -> 0 | O27: =((O26)*(1+B3Ret))-(MIN(MAX(($D$9*12*(1+Inflation)^(15+1-1)+$D$9*12*(1+Inflation)^(15+2-1)+$D$9*12*(1+Inflation)^(15+3-1)+$D$9*12*(1+Inflation)^(15+4-1)+$D$9*12*(1+Inflation)^(15+5-1))-((M26)*(1+B1Ret)-F27),0),((O26)*(1+B3Ret)))) -> 11187580
A28: 16 | B28: =Age+A28-1 -> 77 | C28: =$D$8*12*(1+Inflation)^(A28-1) -> 1655418.9 | D28: =J28+K28+L28 -> 15111242 | E28: =IF(D28>0,"OK","OUT OF MONEY") -> OK | F28: =$D$9*12*(1+Inflation)^(A28-1) -> 1390551.9 | G28: =M28+N28+O28 -> 19584132 | H28: =IF(G28>0,"OK","OUT OF MONEY") -> OK | J28: =(J27)*(1+B1Ret)-C28 -> 8530855 | K28: =(K27)*(1+B2Ret) -> 0 | L28: =(L27)*(1+B3Ret) -> 6580387.4 | M28: =(M27)*(1+B1Ret)-F28 -> 7165918.2 | N28: =(N27)*(1+B2Ret) -> 0 | O28: =(O27)*(1+B3Ret) -> 12418214
A29: 17 | B29: =Age+A29-1 -> 78 | C29: =$D$8*12*(1+Inflation)^(A29-1) -> 1771298.2 | D29: =J29+K29+L29 -> 14660947 | E29: =IF(D29>0,"OK","OUT OF MONEY") -> OK | F29: =$D$9*12*(1+Inflation)^(A29-1) -> 1487890.5 | G29: =M29+N29+O29 -> 19963860 | H29: =IF(G29>0,"OK","OUT OF MONEY") -> OK | J29: =(J28)*(1+B1Ret)-C29 -> 7356716.6 | K29: =(K28)*(1+B2Ret) -> 0 | L29: =(L28)*(1+B3Ret) -> 7304230 | M29: =(M28)*(1+B1Ret)-F29 -> 6179642 | N29: =(N28)*(1+B2Ret) -> 0 | O29: =(O28)*(1+B3Ret) -> 13784218
A30: 18 | B30: =Age+A30-1 -> 79 | C30: =$D$8*12*(1+Inflation)^(A30-1) -> 1895289.1 | D30: =J30+K30+L30 -> 14084093 | E30: =IF(D30>0,"OK","OUT OF MONEY") -> OK | F30: =$D$9*12*(1+Inflation)^(A30-1) -> 1592042.9 | G30: =M30+N30+O30 -> 20320656 | H30: =IF(G30>0,"OK","OUT OF MONEY") -> OK | J30: =(J29)*(1+B1Ret)-C30 -> 5976397.7 | K30: =(K29)*(1+B2Ret) -> 0 | L30: =(L29)*(1+B3Ret) -> 8107695.3 | M30: =(M29)*(1+B1Ret)-F30 -> 5020174 | N30: =(N29)*(1+B2Ret) -> 0 | O30: =(O29)*(1+B3Ret) -> 15300482
A31: 19 | B31: =Age+A31-1 -> 80 | C31: =$D$8*12*(1+Inflation)^(A31-1) -> 2027959.4 | D31: =J31+K31+L31 -> 13366328 | E31: =IF(D31>0,"OK","OUT OF MONEY") -> OK | F31: =$D$9*12*(1+Inflation)^(A31-1) -> 1703485.9 | G31: =M31+N31+O31 -> 20651635 | H31: =IF(G31>0,"OK","OUT OF MONEY") -> OK | J31: =(J30)*(1+B1Ret)-C31 -> 4366786.1 | K31: =(K30)*(1+B2Ret) -> 0 | L31: =(L30)*(1+B3Ret) -> 8999541.8 | M31: =(M30)*(1+B1Ret)-F31 -> 3668100.3 | N31: =(N30)*(1+B2Ret) -> 0 | O31: =(O30)*(1+B3Ret) -> 16983535
A32: 20 | B32: =Age+A32-1 -> 81 | C32: =$D$8*12*(1+Inflation)^(A32-1) -> 2169916.5 | D32: =J32+K32+L32 -> 12492036 | E32: =IF(D32>0,"OK","OUT OF MONEY") -> OK | F32: =$D$9*12*(1+Inflation)^(A32-1) -> 1822729.9 | G32: =M32+N32+O32 -> 20953861 | H32: =IF(G32>0,"OK","OUT OF MONEY") -> OK | J32: =((J31)*(1+B1Ret)-C32)+(MIN(MAX(($D$8*12*(1+Inflation)^(20+1-1)+$D$8*12*(1+Inflation)^(20+2-1)+$D$8*12*(1+Inflation)^(20+3-1)+$D$8*12*(1+Inflation)^(20+4-1)+$D$8*12*(1+Inflation)^(20+5-1))-((J31)*(1+B1Ret)-C32),0),(((K31)*(1+B2Ret))+(MIN(MAX(($D$8*12*(1+Inflation)^(20+1-1)+$D$8*12*(1+Inflation)^(20+2-1)+$D$8*12*(1+Inflation)^(20+3-1)+$D$8*12*(1+Inflation)^(20+4-1)+$D$8*12*(1+Inflation)^(20+5-1))-((J31)*(1+B1Ret)-C32),0),((L31)*(1+B3Ret))))))) -> 12492036 | K32: =(((K31)*(1+B2Ret))+(MIN(MAX(($D$8*12*(1+Inflation)^(20+1-1)+$D$8*12*(1+Inflation)^(20+2-1)+$D$8*12*(1+Inflation)^(20+3-1)+$D$8*12*(1+Inflation)^(20+4-1)+$D$8*12*(1+Inflation)^(20+5-1))-((J31)*(1+B1Ret)-C32),0),((L31)*(1+B3Ret)))))-(MIN(MAX(($D$8*12*(1+Inflation)^(20+1-1)+$D$8*12*(1+Inflation)^(20+2-1)+$D$8*12*(1+Inflation)^(20+3-1)+$D$8*12*(1+Inflation)^(20+4-1)+$D$8*12*(1+Inflation)^(20+5-1))-((J31)*(1+B1Ret)-C32),0),(((K31)*(1+B2Ret))+(MIN(MAX(($D$8*12*(1+Inflation)^(20+1-1)+$D$8*12*(1+Inflation)^(20+2-1)+$D$8*12*(1+Inflation)^(20+3-1)+$D$8*12*(1+Inflation)^(20+4-1)+$D$8*12*(1+Inflation)^(20+5-1))-((J31)*(1+B1Ret)-C32),0),((L31)*(1+B3Ret))))))) -> 0 | L32: =((L31)*(1+B3Ret))-(MIN(MAX(($D$8*12*(1+Inflation)^(20+1-1)+$D$8*12*(1+Inflation)^(20+2-1)+$D$8*12*(1+Inflation)^(20+3-1)+$D$8*12*(1+Inflation)^(20+4-1)+$D$8*12*(1+Inflation)^(20+5-1))-((J31)*(1+B1Ret)-C32),0),((L31)*(1+B3Ret)))) -> 0 | M32: =((M31)*(1+B1Ret)-F32)+(MIN(MAX(($D$9*12*(1+Inflation)^(20+1-1)+$D$9*12*(1+Inflation)^(20+2-1)+$D$9*12*(1+Inflation)^(20+3-1)+$D$9*12*(1+Inflation)^(20+4-1)+$D$9*12*(1+Inflation)^(20+5-1))-((M31)*(1+B1Ret)-F32),0),(((N31)*(1+B2Ret))+(MIN(MAX(($D$9*12*(1+Inflation)^(20+1-1)+$D$9*12*(1+Inflation)^(20+2-1)+$D$9*12*(1+Inflation)^(20+3-1)+$D$9*12*(1+Inflation)^(20+4-1)+$D$9*12*(1+Inflation)^(20+5-1))-((M31)*(1+B1Ret)-F32),0),((O31)*(1+B3Ret))))))) -> 11215787 | N32: =(((N31)*(1+B2Ret))+(MIN(MAX(($D$9*12*(1+Inflation)^(20+1-1)+$D$9*12*(1+Inflation)^(20+2-1)+$D$9*12*(1+Inflation)^(20+3-1)+$D$9*12*(1+Inflation)^(20+4-1)+$D$9*12*(1+Inflation)^(20+5-1))-((M31)*(1+B1Ret)-F32),0),((O31)*(1+B3Ret)))))-(MIN(MAX(($D$9*12*(1+Inflation)^(20+1-1)+$D$9*12*(1+Inflation)^(20+2-1)+$D$9*12*(1+Inflation)^(20+3-1)+$D$9*12*(1+Inflation)^(20+4-1)+$D$9*12*(1+Inflation)^(20+5-1))-((M31)*(1+B1Ret)-F32),0),(((N31)*(1+B2Ret))+(MIN(MAX(($D$9*12*(1+Inflation)^(20+1-1)+$D$9*12*(1+Inflation)^(20+2-1)+$D$9*12*(1+Inflation)^(20+3-1)+$D$9*12*(1+Inflation)^(20+4-1)+$D$9*12*(1+Inflation)^(20+5-1))-((M31)*(1+B1Ret)-F32),0),((O31)*(1+B3Ret))))))) -> 0 | O32: =((O31)*(1+B3Ret))-(MIN(MAX(($D$9*12*(1+Inflation)^(20+1-1)+$D$9*12*(1+Inflation)^(20+2-1)+$D$9*12*(1+Inflation)^(20+3-1)+$D$9*12*(1+Inflation)^(20+4-1)+$D$9*12*(1+Inflation)^(20+5-1))-((M31)*(1+B1Ret)-F32),0),((O31)*(1+B3Ret)))) -> 9738074.2
A33: 21 | B33: =Age+A33-1 -> 82 | C33: =$D$8*12*(1+Inflation)^(A33-1) -> 2321810.7 | D33: =J33+K33+L33 -> 11044668 | E33: =IF(D33>0,"OK","OUT OF MONEY") -> OK | F33: =$D$9*12*(1+Inflation)^(A33-1) -> 1950321 | G33: =M33+N33+O33 -> 20859833 | H33: =IF(G33>0,"OK","OUT OF MONEY") -> OK | J33: =(J32)*(1+B1Ret)-C33 -> 11044668 | K33: =(K32)*(1+B2Ret) -> 0 | L33: =(L32)*(1+B3Ret) -> 0 | M33: =(M32)*(1+B1Ret)-F33 -> 10050571 | N33: =(N32)*(1+B2Ret) -> 0 | O33: =(O32)*(1+B3Ret) -> 10809262
A34: 22 | B34: =Age+A34-1 -> 83 | C34: =$D$8*12*(1+Inflation)^(A34-1) -> 2484337.4 | D34: =J34+K34+L34 -> 9333457.2 | E34: =IF(D34>0,"OK","OUT OF MONEY") -> OK | F34: =$D$9*12*(1+Inflation)^(A34-1) -> 2086843.4 | G34: =M34+N34+O34 -> 20665549 | H34: =IF(G34>0,"OK","OUT OF MONEY") -> OK | J34: =(J33)*(1+B1Ret)-C34 -> 9333457.2 | K34: =(K33)*(1+B2Ret) -> 0 | L34: =(L33)*(1+B3Ret) -> 0 | M34: =(M33)*(1+B1Ret)-F34 -> 8667267.5 | N34: =(N33)*(1+B2Ret) -> 0 | O34: =(O33)*(1+B3Ret) -> 11998281
A35: 23 | B35: =Age+A35-1 -> 84 | C35: =$D$8*12*(1+Inflation)^(A35-1) -> 2658241 | D35: =J35+K35+L35 -> 7328558.1 | E35: =IF(D35>0,"OK","OUT OF MONEY") -> OK | F35: =$D$9*12*(1+Inflation)^(A35-1) -> 2232922.5 | G35: =M35+N35+O35 -> 20359146 | H35: =IF(G35>0,"OK","OUT OF MONEY") -> OK | J35: =(J34)*(1+B1Ret)-C35 -> 7328558.1 | K35: =(K34)*(1+B2Ret) -> 0 | L35: =(L34)*(1+B3Ret) -> 0 | M35: =(M34)*(1+B1Ret)-F35 -> 7041053.8 | N35: =(N34)*(1+B2Ret) -> 0 | O35: =(O34)*(1+B3Ret) -> 13318092
A36: 24 | B36: =Age+A36-1 -> 85 | C36: =$D$8*12*(1+Inflation)^(A36-1) -> 2844317.9 | D36: =J36+K36+L36 -> 4997239.3 | E36: =IF(D36>0,"OK","OUT OF MONEY") -> OK | F36: =$D$9*12*(1+Inflation)^(A36-1) -> 2389227.1 | G36: =M36+N36+O36 -> 19927783 | H36: =IF(G36>0,"OK","OUT OF MONEY") -> OK | J36: =(J35)*(1+B1Ret)-C36 -> 4997239.3 | K36: =(K35)*(1+B2Ret) -> 0 | L36: =(L35)*(1+B3Ret) -> 0 | M36: =(M35)*(1+B1Ret)-F36 -> 5144700.5 | N36: =(N35)*(1+B2Ret) -> 0 | O36: =(O35)*(1+B3Ret) -> 14783082
A37: 25 | B37: =Age+A37-1 -> 86 | C37: =$D$8*12*(1+Inflation)^(A37-1) -> 3043420.2 | D37: =J37+K37+L37 -> 2303625.9 | E37: =IF(D37>0,"OK","OUT OF MONEY") -> OK | F37: =$D$9*12*(1+Inflation)^(A37-1) -> 2556472.9 | G37: =M37+N37+O37 -> 19357578 | H37: =IF(G37>0,"OK","OUT OF MONEY") -> OK | J37: =((J36)*(1+B1Ret)-C37)+(MIN(MAX(($D$8*12*(1+Inflation)^(25+1-1)+$D$8*12*(1+Inflation)^(25+2-1)+$D$8*12*(1+Inflation)^(25+3-1)+$D$8*12*(1+Inflation)^(25+4-1)+$D$8*12*(1+Inflation)^(25+5-1))-((J36)*(1+B1Ret)-C37),0),(((K36)*(1+B2Ret))+(MIN(MAX(($D$8*12*(1+Inflation)^(25+1-1)+$D$8*12*(1+Inflation)^(25+2-1)+$D$8*12*(1+Inflation)^(25+3-1)+$D$8*12*(1+Inflation)^(25+4-1)+$D$8*12*(1+Inflation)^(25+5-1))-((J36)*(1+B1Ret)-C37),0),((L36)*(1+B3Ret))))))) -> 2303625.9 | K37: =(((K36)*(1+B2Ret))+(MIN(MAX(($D$8*12*(1+Inflation)^(25+1-1)+$D$8*12*(1+Inflation)^(25+2-1)+$D$8*12*(1+Inflation)^(25+3-1)+$D$8*12*(1+Inflation)^(25+4-1)+$D$8*12*(1+Inflation)^(25+5-1))-((J36)*(1+B1Ret)-C37),0),((L36)*(1+B3Ret)))))-(MIN(MAX(($D$8*12*(1+Inflation)^(25+1-1)+$D$8*12*(1+Inflation)^(25+2-1)+$D$8*12*(1+Inflation)^(25+3-1)+$D$8*12*(1+Inflation)^(25+4-1)+$D$8*12*(1+Inflation)^(25+5-1))-((J36)*(1+B1Ret)-C37),0),(((K36)*(1+B2Ret))+(MIN(MAX(($D$8*12*(1+Inflation)^(25+1-1)+$D$8*12*(1+Inflation)^(25+2-1)+$D$8*12*(1+Inflation)^(25+3-1)+$D$8*12*(1+Inflation)^(25+4-1)+$D$8*12*(1+Inflation)^(25+5-1))-((J36)*(1+B1Ret)-C37),0),((L36)*(1+B3Ret))))))) -> 0 | L37: =((L36)*(1+B3Ret))-(MIN(MAX(($D$8*12*(1+Inflation)^(25+1-1)+$D$8*12*(1+Inflation)^(25+2-1)+$D$8*12*(1+Inflation)^(25+3-1)+$D$8*12*(1+Inflation)^(25+4-1)+$D$8*12*(1+Inflation)^(25+5-1))-((J36)*(1+B1Ret)-C37),0),((L36)*(1+B3Ret)))) -> 0 | M37: =((M36)*(1+B1Ret)-F37)+(MIN(MAX(($D$9*12*(1+Inflation)^(25+1-1)+$D$9*12*(1+Inflation)^(25+2-1)+$D$9*12*(1+Inflation)^(25+3-1)+$D$9*12*(1+Inflation)^(25+4-1)+$D$9*12*(1+Inflation)^(25+5-1))-((M36)*(1+B1Ret)-F37),0),(((N36)*(1+B2Ret))+(MIN(MAX(($D$9*12*(1+Inflation)^(25+1-1)+$D$9*12*(1+Inflation)^(25+2-1)+$D$9*12*(1+Inflation)^(25+3-1)+$D$9*12*(1+Inflation)^(25+4-1)+$D$9*12*(1+Inflation)^(25+5-1))-((M36)*(1+B1Ret)-F37),0),((O36)*(1+B3Ret))))))) -> 15730721 | N37: =(((N36)*(1+B2Ret))+(MIN(MAX(($D$9*12*(1+Inflation)^(25+1-1)+$D$9*12*(1+Inflation)^(25+2-1)+$D$9*12*(1+Inflation)^(25+3-1)+$D$9*12*(1+Inflation)^(25+4-1)+$D$9*12*(1+Inflation)^(25+5-1))-((M36)*(1+B1Ret)-F37),0),((O36)*(1+B3Ret)))))-(MIN(MAX(($D$9*12*(1+Inflation)^(25+1-1)+$D$9*12*(1+Inflation)^(25+2-1)+$D$9*12*(1+Inflation)^(25+3-1)+$D$9*12*(1+Inflation)^(25+4-1)+$D$9*12*(1+Inflation)^(25+5-1))-((M36)*(1+B1Ret)-F37),0),(((N36)*(1+B2Ret))+(MIN(MAX(($D$9*12*(1+Inflation)^(25+1-1)+$D$9*12*(1+Inflation)^(25+2-1)+$D$9*12*(1+Inflation)^(25+3-1)+$D$9*12*(1+Inflation)^(25+4-1)+$D$9*12*(1+Inflation)^(25+5-1))-((M36)*(1+B1Ret)-F37),0),((O36)*(1+B3Ret))))))) -> 0 | O37: =((O36)*(1+B3Ret))-(MIN(MAX(($D$9*12*(1+Inflation)^(25+1-1)+$D$9*12*(1+Inflation)^(25+2-1)+$D$9*12*(1+Inflation)^(25+3-1)+$D$9*12*(1+Inflation)^(25+4-1)+$D$9*12*(1+Inflation)^(25+5-1))-((M36)*(1+B1Ret)-F37),0),((O36)*(1+B3Ret)))) -> 3626856.6
A38: 26 | B38: =Age+A38-1 -> 87 | C38: =$D$8*12*(1+Inflation)^(A38-1) -> 3256459.6 | D38: =J38+K38+L38 -> -791579.92 | E38: =IF(D38>0,"OK","OUT OF MONEY") -> OUT OF MONEY | F38: =$D$9*12*(1+Inflation)^(A38-1) -> 2735426.1 | G38: =M38+N38+O38 -> 18122257 | H38: =IF(G38>0,"OK","OUT OF MONEY") -> OK | J38: =(J37)*(1+B1Ret)-C38 -> -791579.92 | K38: =(K37)*(1+B2Ret) -> 0 | L38: =(L37)*(1+B3Ret) -> 0 | M38: =(M37)*(1+B1Ret)-F38 -> 14096446 | N38: =(N37)*(1+B2Ret) -> 0 | O38: =(O37)*(1+B3Ret) -> 4025810.8
A39: 27 | B39: =Age+A39-1 -> 88 | C39: =$D$8*12*(1+Inflation)^(A39-1) -> 3484411.8 | D39: =J39+K39+L39 -> -4331402.3 | E39: =IF(D39>0,"OK","OUT OF MONEY") -> OUT OF MONEY | F39: =$D$9*12*(1+Inflation)^(A39-1) -> 2926905.9 | G39: =M39+N39+O39 -> 16624941 | H39: =IF(G39>0,"OK","OUT OF MONEY") -> OK | J39: =(J38)*(1+B1Ret)-C39 -> -4331402.3 | K39: =(K38)*(1+B2Ret) -> 0 | L39: =(L38)*(1+B3Ret) -> 0 | M39: =(M38)*(1+B1Ret)-F39 -> 12156291 | N39: =(N38)*(1+B2Ret) -> 0 | O39: =(O38)*(1+B3Ret) -> 4468650
A40: 28 | B40: =Age+A40-1 -> 89 | C40: =$D$8*12*(1+Inflation)^(A40-1) -> 3728320.6 | D40: =J40+K40+L40 -> -8362921 | E40: =IF(D40>0,"OK","OUT OF MONEY") -> OUT OF MONEY | F40: =$D$9*12*(1+Inflation)^(A40-1) -> 3131789.3 | G40: =M40+N40+O40 -> 14835644 | H40: =IF(G40>0,"OK","OUT OF MONEY") -> OK | J40: =(J39)*(1+B1Ret)-C40 -> -8362921 | K40: =(K39)*(1+B2Ret) -> 0 | L40: =(L39)*(1+B3Ret) -> 0 | M40: =(M39)*(1+B1Ret)-F40 -> 9875442.2 | N40: =(N39)*(1+B2Ret) -> 0 | O40: =(O39)*(1+B3Ret) -> 4960201.5
A41: 29 | B41: =Age+A41-1 -> 90 | C41: =$D$8*12*(1+Inflation)^(A41-1) -> 3989303 | D41: =J41+K41+L41 -> -12937628 | E41: =IF(D41>0,"OK","OUT OF MONEY") -> OUT OF MONEY | F41: =$D$9*12*(1+Inflation)^(A41-1) -> 3351014.5 | G41: =M41+N41+O41 -> 12721532 | H41: =IF(G41>0,"OK","OUT OF MONEY") -> OK | J41: =(J40)*(1+B1Ret)-C41 -> -12937628 | K41: =(K40)*(1+B2Ret) -> 0 | L41: =(L40)*(1+B3Ret) -> 0 | M41: =(M40)*(1+B1Ret)-F41 -> 7215708.6 | N41: =(N40)*(1+B2Ret) -> 0 | O41: =(O40)*(1+B3Ret) -> 5505823.6
A42: 30 | B42: =Age+A42-1 -> 91 | C42: =$D$8*12*(1+Inflation)^(A42-1) -> 4268554.2 | D42: =J42+K42+L42 -> -18111817 | E42: =IF(D42>0,"OK","OUT OF MONEY") -> OUT OF MONEY | F42: =$D$9*12*(1+Inflation)^(A42-1) -> 3585585.6 | G42: =M42+N42+O42 -> 10246687 | H42: =IF(G42>0,"OK","OUT OF MONEY") -> OK | J42: =(J41)*(1+B1Ret)-C42 -> -18111817 | K42: =(K41)*(1+B2Ret) -> 0 | L42: =(L41)*(1+B3Ret) -> 0 | M42: =(M41)*(1+B1Ret)-F42 -> 4135222.6 | N42: =(N41)*(1+B2Ret) -> 0 | O42: =(O41)*(1+B3Ret) -> 6111464.3
B44: Summary
B45: Ending Corpus after 30 Years (Desired Income) | D45: =D42 -> -18111817 | F45: Ending Corpus after 30 Years (Alternative Income) | G45: =G42 -> 10246687
B46: Ever ran out of money? (Desired Income) | D46: =IF(MIN(D13:D42)<=0,"YES - RISK","No, lasts 30 yrs") -> YES - RISK | F46: Ever ran out of money? (Alternative Income) | G46: =IF(MIN(G13:G42)<=0,"YES - RISK","No, lasts 30 yrs") -> No, lasts 30 yrs
B67: Key takeaway: with only the ₹1 Cr cash corpus (Gold held back as legacy), a ₹50,000/month withdrawal is too aggressive for a full 30-year runway at these assumptions (~6% starting withdrawal rate). Reduce the 'Alternative' cell above (try ₹40,000-₹43,000) until the status column turns fully green / says the plan lasts.

Sheet 5Cr Legacy Plan
A1: 5 CR LEGACY PLAN — ₹2.5L/month + Corpus that Grows for Future Generations
B3: Goal check over 60 years (~2 generations). Uses a growth-tilted 3-Bucket split (more in Bucket 3, since horizon is very long). Shows BOTH nominal ₹ and REAL (today's-rupee, inflation-adjusted) corpus — a plan can look 'growing' in nominal terms while actually shrinking in real purchasing power.
B6: Local Inputs for this Scenario (editable)
B7: Total Corpus (₹) | D7: 50000000
B8: Desired Monthly Income — today's value (₹) | D8: 250000
B9: Perpetual/Sustainable Monthly Income to test (₹) | D9: 140000 | F9: ← lower this until Real Corpus keeps rising, not falling, in later decades
B10: Bucket 1 / Bucket 2 / Bucket 3 split (growth-tilted, editable) | D10: 0.1 | E10: 0.25 | F10: 0.65
A13: Year | B13: Age | C13: Desired ₹2.5L-style Nominal Corpus | D13: Desired Real Corpus (today ₹) | E13: Status | F13: Sustainable ₹ Nominal Corpus | G13: Sustainable Real Corpus (today ₹) | H13: Status
A14: 1 | B14: =Age+A14-1 -> 62 | C14: =J14+K14+L14 -> 52050000 | D14: =C14/(1+Inflation)^A14 -> 48644860 | E14: =IF(C14>0,"OK","OUT OF MONEY") -> OK | F14: =M14+N14+O14 -> 53370000 | G14: =F14/(1+Inflation)^A14 -> 49878505 | H14: =IF(F14>0,"OK","OUT OF MONEY") -> OK | J14: =($D$7*$D$10)*(1+B1Ret)-($D$8*12*(1+Inflation)^(A14-1)) -> 2350000 | K14: =($D$7*$E$10)*(1+B2Ret) -> 13625000 | L14: =($D$7*$F$10)*(1+B3Ret) -> 36075000 | M14: =($D$7*$D$10)*(1+B1Ret)-($D$9*12*(1+Inflation)^(A14-1)) -> 3670000 | N14: =($D$7*$E$10)*(1+B2Ret) -> 13625000 | O14: =($D$7*$F$10)*(1+B3Ret) -> 36075000
A15: 2 | B15: =Age+A15-1 -> 63 | C15: =J15+K15+L15 -> 54199000 | D15: =C15/(1+Inflation)^A15 -> 47339506 | E15: =IF(C15>0,"OK","OUT OF MONEY") -> OK | F15: =M15+N15+O15 -> 57023800 | G15: =F15/(1+Inflation)^A15 -> 49806795 | H15: =IF(F15>0,"OK","OUT OF MONEY") -> OK | J15: =(J14)*(1+B1Ret)-($D$8*12*(1+Inflation)^(A15-1)) -> -695500 | K15: =(K14)*(1+B2Ret) -> 14851250 | L15: =(L14)*(1+B3Ret) -> 40043250 | M15: =(M14)*(1+B1Ret)-($D$9*12*(1+Inflation)^(A15-1)) -> 2129300 | N15: =(N14)*(1+B2Ret) -> 14851250 | O15: =(O14)*(1+B3Ret) -> 40043250
A16: 3 | B16: =Age+A16-1 -> 64 | C16: =J16+K16+L16 -> 56456985 | D16: =C16/(1+Inflation)^A16 -> 46085717 | E16: =IF(C16>0,"OK","OUT OF MONEY") -> OK | F16: =M16+N16+O16 -> 60990789 | G16: =F16/(1+Inflation)^A16 -> 49786652 | H16: =IF(F16>0,"OK","OUT OF MONEY") -> OK | J16: =(J15)*(1+B1Ret)-($D$8*12*(1+Inflation)^(A16-1)) -> -4178885 | K16: =(K15)*(1+B2Ret) -> 16187862 | L16: =(L15)*(1+B3Ret) -> 44448008 | M16: =(M15)*(1+B1Ret)-($D$9*12*(1+Inflation)^(A16-1)) -> 354919 | N16: =(N15)*(1+B2Ret) -> 16187862 | O16: =(O15)*(1+B3Ret) -> 44448008
A17: 4 | B17: =Age+A17-1 -> 65 | C17: =J17+K17+L17 -> 58835522 | D17: =C17/(1+Inflation)^A17 -> 44885338 | E17: =IF(C17>0,"OK","OUT OF MONEY") -> OK | F17: =M17+N17+O17 -> 65303750 | G17: =F17/(1+Inflation)^A17 -> 49819918 | H17: =IF(F17>0,"OK","OUT OF MONEY") -> OK | J17: =(J16)*(1+B1Ret)-($D$8*12*(1+Inflation)^(A17-1)) -> -8146536 | K17: =(K16)*(1+B2Ret) -> 17644770 | L17: =(L16)*(1+B3Ret) -> 49337288 | M17: =(M16)*(1+B1Ret)-($D$9*12*(1+Inflation)^(A17-1)) -> -1678308.9 | N17: =(N16)*(1+B2Ret) -> 17644770 | O17: =(O16)*(1+B3Ret) -> 49337288
A18: 5 | B18: =Age+A18-1 -> 66 | C18: =J18+K18+L18 -> 61348008 | D18: =C18/(1+Inflation)^A18 -> 43740282 | E18: =IF(C18>0,"OK","OUT OF MONEY") -> OK | F18: =M18+N18+O18 -> 69999262 | G18: =F18/(1+Inflation)^A18 -> 49908506 | H18: =IF(F18>0,"OK","OUT OF MONEY") -> OK | J18: =((J17)*(1+B1Ret)-($D$8*12*(1+Inflation)^(A18-1)))+(MIN(MAX(($D$8*12*(1+Inflation)^(5+1-1)+$D$8*12*(1+Inflation)^(5+2-1)+$D$8*12*(1+Inflation)^(5+3-1)+$D$8*12*(1+Inflation)^(5+4-1)+$D$8*12*(1+Inflation)^(5+5-1))-((J17)*(1+B1Ret)-($D$8*12*(1+Inflation)^(A18-1))),0),((K17)*(1+B2Ret)))) -> 6583617.9 | K18: =((K17)*(1+B2Ret))-(MIN(MAX(($D$8*12*(1+Inflation)^(5+1-1)+$D$8*12*(1+Inflation)^(5+2-1)+$D$8*12*(1+Inflation)^(5+3-1)+$D$8*12*(1+Inflation)^(5+4-1)+$D$8*12*(1+Inflation)^(5+5-1))-((J17)*(1+B1Ret)-($D$8*12*(1+Inflation)^(A18-1))),0),((K17)*(1+B2Ret)))) -> 0 | L18: =(L17)*(1+B3Ret) -> 54764390 | M18: =((M17)*(1+B1Ret)-($D$9*12*(1+Inflation)^(A18-1)))+(MIN(MAX(($D$9*12*(1+Inflation)^(5+1-1)+$D$9*12*(1+Inflation)^(5+2-1)+$D$9*12*(1+Inflation)^(5+3-1)+$D$9*12*(1+Inflation)^(5+4-1)+$D$9*12*(1+Inflation)^(5+5-1))-((M17)*(1+B1Ret)-($D$9*12*(1+Inflation)^(A18-1))),0),((N17)*(1+B2Ret)))) -> 13550391 | N18: =((N17)*(1+B2Ret))-(MIN(MAX(($D$9*12*(1+Inflation)^(5+1-1)+$D$9*12*(1+Inflation)^(5+2-1)+$D$9*12*(1+Inflation)^(5+3-1)+$D$9*12*(1+Inflation)^(5+4-1)+$D$9*12*(1+Inflation)^(5+5-1))-((M17)*(1+B1Ret)-($D$9*12*(1+Inflation)^(A18-1))),0),((N17)*(1+B2Ret)))) -> 1684480.6 | O18: =(O17)*(1+B3Ret) -> 54764390
A19: 6 | B19: =Age+A19-1 -> 67 | C19: =J19+K19+L19 -> 63625289 | D19: =C19/(1+Inflation)^A19 -> 42396217 | E19: =IF(C19>0,"OK","OUT OF MONEY") -> OK | F19: =M19+N19+O19 -> 74767188 | G19: =F19/(1+Inflation)^A19 -> 49820534 | H19: =IF(F19>0,"OK","OUT OF MONEY") -> OK | J19: =(J18)*(1+B1Ret)-($D$8*12*(1+Inflation)^(A19-1)) -> 2836816 | K19: =(K18)*(1+B2Ret) -> 0 | L19: =(L18)*(1+B3Ret) -> 60788473 | M19: =(M18)*(1+B1Ret)-($D$9*12*(1+Inflation)^(A19-1)) -> 12142632 | N19: =(N18)*(1+B2Ret) -> 1836083.8 | O19: =(O18)*(1+B3Ret) -> 60788473
A20: 7 | B20: =Age+A20-1 -> 68 | C20: =J20+K20+L20 -> 66008407 | D20: =C20/(1+Inflation)^A20 -> 41106718 | E20: =IF(C20>0,"OK","OUT OF MONEY") -> OK | F20: =M20+N20+O20 -> 79947925 | G20: =F20/(1+Inflation)^A20 -> 49787550 | H20: =IF(F20>0,"OK","OUT OF MONEY") -> OK | J20: =(J19)*(1+B1Ret)-($D$8*12*(1+Inflation)^(A20-1)) -> -1466797.9 | K20: =(K19)*(1+B2Ret) -> 0 | L20: =(L19)*(1+B3Ret) -> 67475205 | M20: =(M19)*(1+B1Ret)-($D$9*12*(1+Inflation)^(A20-1)) -> 10471389 | N20: =(N19)*(1+B2Ret) -> 2001331.4 | O20: =(O19)*(1+B3Ret) -> 67475205
A21: 8 | B21: =Age+A21-1 -> 69 | C21: =J21+K21+L21 -> 68510659 | D21: =C21/(1+Inflation)^A21 -> 39873827 | E21: =IF(C21>0,"OK","OUT OF MONEY") -> OK | F21: =M21+N21+O21 -> 85585602 | G21: =F21/(1+Inflation)^A21 -> 49811599 | H21: =IF(F21>0,"OK","OUT OF MONEY") -> OK | J21: =(J20)*(1+B1Ret)-($D$8*12*(1+Inflation)^(A21-1)) -> -6386818.2 | K21: =(K20)*(1+B2Ret) -> 0 | L21: =(L20)*(1+B3Ret) -> 74897478 | M21: =(M20)*(1+B1Ret)-($D$9*12*(1+Inflation)^(A21-1)) -> 8506673 | N21: =(N20)*(1+B2Ret) -> 2181451.2 | O21: =(O20)*(1+B3Ret) -> 74897478
A22: 9 | B22: =Age+A22-1 -> 70 | C22: =J22+K22+L22 -> 71147746 | D22: =C22/(1+Inflation)^A22 -> 38699660 | E22: =IF(C22>0,"OK","OUT OF MONEY") -> OK | F22: =M22+N22+O22 -> 91729569 | G22: =F22/(1+Inflation)^A22 -> 49894808 | H22: =IF(F22>0,"OK","OUT OF MONEY") -> OK | J22: =(J21)*(1+B1Ret)-($D$8*12*(1+Inflation)^(A22-1)) -> -11988454 | K22: =(K21)*(1+B2Ret) -> 0 | L22: =(L21)*(1+B3Ret) -> 83136200 | M22: =(M21)*(1+B1Ret)-($D$9*12*(1+Inflation)^(A22-1)) -> 6215587.4 | N22: =(N21)*(1+B2Ret) -> 2377781.8 | O22: =(O21)*(1+B3Ret) -> 83136200
A23: 10 | B23: =Age+A23-1 -> 71 | C23: =J23+K23+L23 -> 73938159 | D23: =C23/(1+Inflation)^A23 -> 37586411 | E23: =IF(C23>0,"OK","OUT OF MONEY") -> OK | F23: =M23+N23+O23 -> 98435031 | G23: =F23/(1+Inflation)^A23 -> 50039378 | H23: =IF(F23>0,"OK","OUT OF MONEY") -> OK | J23: =((J22)*(1+B1Ret)-($D$8*12*(1+Inflation)^(A23-1)))+(MIN(MAX(($D$8*12*(1+Inflation)^(10+1-1)+$D$8*12*(1+Inflation)^(10+2-1)+$D$8*12*(1+Inflation)^(10+3-1)+$D$8*12*(1+Inflation)^(10+4-1)+$D$8*12*(1+Inflation)^(10+5-1))-((J22)*(1+B1Ret)-($D$8*12*(1+Inflation)^(A23-1))),0),((K22)*(1+B2Ret)))) -> -18343023 | K23: =((K22)*(1+B2Ret))-(MIN(MAX(($D$8*12*(1+Inflation)^(10+1-1)+$D$8*12*(1+Inflation)^(10+2-1)+$D$8*12*(1+Inflation)^(10+3-1)+$D$8*12*(1+Inflation)^(10+4-1)+$D$8*12*(1+Inflation)^(10+5-1))-((J22)*(1+B1Ret)-($D$8*12*(1+Inflation)^(A23-1))),0),((K22)*(1+B2Ret)))) -> 0 | L23: =(L22)*(1+B3Ret) -> 92281182 | M23: =((M22)*(1+B1Ret)-($D$9*12*(1+Inflation)^(A23-1)))+(MIN(MAX(($D$9*12*(1+Inflation)^(10+1-1)+$D$9*12*(1+Inflation)^(10+2-1)+$D$9*12*(1+Inflation)^(10+3-1)+$D$9*12*(1+Inflation)^(10+4-1)+$D$9*12*(1+Inflation)^(10+5-1))-((M22)*(1+B1Ret)-($D$9*12*(1+Inflation)^(A23-1))),0),((N22)*(1+B2Ret)))) -> 6153849.2 | N23: =((N22)*(1+B2Ret))-(MIN(MAX(($D$9*12*(1+Inflation)^(10+1-1)+$D$9*12*(1+Inflation)^(10+2-1)+$D$9*12*(1+Inflation)^(10+3-1)+$D$9*12*(1+Inflation)^(10+4-1)+$D$9*12*(1+Inflation)^(10+5-1))-((M22)*(1+B1Ret)-($D$9*12*(1+Inflation)^(A23-1))),0),((N22)*(1+B2Ret)))) -> 0 | O23: =(O22)*(1+B3Ret) -> 92281182
A24: 11 | B24: =Age+A24-1 -> 72 | C24: =J24+K24+L24 -> 76903623 | D24: =C24/(1+Inflation)^A24 -> 36536357 | E24: =IF(C24>0,"OK","OUT OF MONEY") -> OK | F24: =M24+N24+O24 -> 1.0571192e+08 | G24: =F24/(1+Inflation)^A24 -> 50222970 | H24: =IF(F24>0,"OK","OUT OF MONEY") -> OK | J24: =(J23)*(1+B1Ret)-($D$8*12*(1+Inflation)^(A24-1)) -> -25528489 | K24: =(K23)*(1+B2Ret) -> 0 | L24: =(L23)*(1+B3Ret) -> 1.0243211e+08 | M24: =(M23)*(1+B1Ret)-($D$9*12*(1+Inflation)^(A24-1)) -> 3279804.3 | N24: =(N23)*(1+B2Ret) -> 0 | O24: =(O23)*(1+B3Ret) -> 1.0243211e+08
A25: 12 | B25: =Age+A25-1 -> 73 | C25: =J25+K25+L25 -> 80069605 | D25: =C25/(1+Inflation)^A25 -> 35551862 | E25: =IF(C25>0,"OK","OUT OF MONEY") -> OK | F25: =M25+N25+O25 -> 1.1367288e+08 | G25: =F25/(1+Inflation)^A25 -> 50472120 | H25: =IF(F25>0,"OK","OUT OF MONEY") -> OK | J25: =(J24)*(1+B1Ret)-($D$8*12*(1+Inflation)^(A25-1)) -> -33630039 | K25: =(K24)*(1+B2Ret) -> 0 | L25: =(L24)*(1+B3Ret) -> 1.1369964e+08 | M25: =(M24)*(1+B1Ret)-($D$9*12*(1+Inflation)^(A25-1)) -> -26760.644 | N25: =(N24)*(1+B2Ret) -> 0 | O25: =(O24)*(1+B3Ret) -> 1.1369964e+08
A26: 13 | B26: =Age+A26-1 -> 74 | C26: =J26+K26+L26 -> 83465889 | D26: =C26/(1+Inflation)^A26 -> 34635376 | E26: =IF(C26>0,"OK","OUT OF MONEY") -> OK | F26: =M26+N26+O26 -> 1.2239429e+08 | G26: =F26/(1+Inflation)^A26 -> 50789279 | H26: =IF(F26>0,"OK","OUT OF MONEY") -> OK | J26: =(J25)*(1+B1Ret)-($D$8*12*(1+Inflation)^(A26-1)) -> -42740717 | K26: =(K25)*(1+B2Ret) -> 0 | L26: =(L25)*(1+B3Ret) -> 1.2620661e+08 | M26: =(M25)*(1+B1Ret)-($D$9*12*(1+Inflation)^(A26-1)) -> -3812315.8 | N26: =(N25)*(1+B2Ret) -> 0 | O26: =(O25)*(1+B3Ret) -> 1.2620661e+08
A27: 14 | B27: =Age+A27-1 -> 75 | C27: =J27+K27+L27 -> 87127230 | D27: =C27/(1+Inflation)^A27 -> 33789442 | E27: =IF(C27>0,"OK","OUT OF MONEY") -> OK | F27: =M27+N27+O27 -> 1.3196161e+08 | G27: =F27/(1+Inflation)^A27 -> 51176989 | H27: =IF(F27>0,"OK","OUT OF MONEY") -> OK | J27: =(J26)*(1+B1Ret)-($D$8*12*(1+Inflation)^(A27-1)) -> -52962102 | K27: =(K26)*(1+B2Ret) -> 0 | L27: =(L26)*(1+B3Ret) -> 1.4008933e+08 | M27: =(M26)*(1+B1Ret)-($D$9*12*(1+Inflation)^(A27-1)) -> -8127717.5 | N27: =(N26)*(1+B2Ret) -> 0 | O27: =(O26)*(1+B3Ret) -> 1.4008933e+08
A28: 15 | B28: =Age+A28-1 -> 76 | C28: =J28+K28+L28 -> 91094107 | D28: =C28/(1+Inflation)^A28 -> 33016696 | E28: =IF(C28>0,"OK","OUT OF MONEY") -> OK | F28: =M28+N28+O28 -> 1.4247056e+08 | G28: =F28/(1+Inflation)^A28 -> 51637889 | H28: =IF(F28>0,"OK","OUT OF MONEY") -> OK | J28: =((J27)*(1+B1Ret)-($D$8*12*(1+Inflation)^(A28-1)))+(MIN(MAX(($D$8*12*(1+Inflation)^(15+1-1)+$D$8*12*(1+Inflation)^(15+2-1)+$D$8*12*(1+Inflation)^(15+3-1)+$D$8*12*(1+Inflation)^(15+4-1)+$D$8*12*(1+Inflation)^(15+5-1))-((J27)*(1+B1Ret)-($D$8*12*(1+Inflation)^(A28-1))),0),(((K27)*(1+B2Ret))+(MIN(MAX(($D$8*12*(1+Inflation)^(15+1-1)+$D$8*12*(1+Inflation)^(15+2-1)+$D$8*12*(1+Inflation)^(15+3-1)+$D$8*12*(1+Inflation)^(15+4-1)+$D$8*12*(1+Inflation)^(15+5-1))-((J27)*(1+B1Ret)-($D$8*12*(1+Inflation)^(A28-1))),0),((L27)*(1+B3Ret))))))) -> 47599411 | K28: =(((K27)*(1+B2Ret))+(MIN(MAX(($D$8*12*(1+Inflation)^(15+1-1)+$D$8*12*(1+Inflation)^(15+2-1)+$D$8*12*(1+Inflation)^(15+3-1)+$D$8*12*(1+Inflation)^(15+4-1)+$D$8*12*(1+Inflation)^(15+5-1))-((J27)*(1+B1Ret)-($D$8*12*(1+Inflation)^(A28-1))),0),((L27)*(1+B3Ret)))))-(MIN(MAX(($D$8*12*(1+Inflation)^(15+1-1)+$D$8*12*(1+Inflation)^(15+2-1)+$D$8*12*(1+Inflation)^(15+3-1)+$D$8*12*(1+Inflation)^(15+4-1)+$D$8*12*(1+Inflation)^(15+5-1))-((J27)*(1+B1Ret)-($D$8*12*(1+Inflation)^(A28-1))),0),(((K27)*(1+B2Ret))+(MIN(MAX(($D$8*12*(1+Inflation)^(15+1-1)+$D$8*12*(1+Inflation)^(15+2-1)+$D$8*12*(1+Inflation)^(15+3-1)+$D$8*12*(1+Inflation)^(15+4-1)+$D$8*12*(1+Inflation)^(15+5-1))-((J27)*(1+B1Ret)-($D$8*12*(1+Inflation)^(A28-1))),0),((L27)*(1+B3Ret))))))) -> 0 | L28: =((L27)*(1+B3Ret))-(MIN(MAX(($D$8*12*(1+Inflation)^(15+1-1)+$D$8*12*(1+Inflation)^(15+2-1)+$D$8*12*(1+Inflation)^(15+3-1)+$D$8*12*(1+Inflation)^(15+4-1)+$D$8*12*(1+Inflation)^(15+5-1))-((J27)*(1+B1Ret)-($D$8*12*(1+Inflation)^(A28-1))),0),((L27)*(1+B3Ret)))) -> 43494696 | M28: =((M27)*(1+B1Ret)-($D$9*12*(1+Inflation)^(A28-1)))+(MIN(MAX(($D$9*12*(1+Inflation)^(15+1-1)+$D$9*12*(1+Inflation)^(15+2-1)+$D$9*12*(1+Inflation)^(15+3-1)+$D$9*12*(1+Inflation)^(15+4-1)+$D$9*12*(1+Inflation)^(15+5-1))-((M27)*(1+B1Ret)-($D$9*12*(1+Inflation)^(A28-1))),0),(((N27)*(1+B2Ret))+(MIN(MAX(($D$9*12*(1+Inflation)^(15+1-1)+$D$9*12*(1+Inflation)^(15+2-1)+$D$9*12*(1+Inflation)^(15+3-1)+$D$9*12*(1+Inflation)^(15+4-1)+$D$9*12*(1+Inflation)^(15+5-1))-((M27)*(1+B1Ret)-($D$9*12*(1+Inflation)^(A28-1))),0),((O27)*(1+B3Ret))))))) -> 26655670 | N28: =(((N27)*(1+B2Ret))+(MIN(MAX(($D$9*12*(1+Inflation)^(15+1-1)+$D$9*12*(1+Inflation)^(15+2-1)+$D$9*12*(1+Inflation)^(15+3-1)+$D$9*12*(1+Inflation)^(15+4-1)+$D$9*12*(1+Inflation)^(15+5-1))-((M27)*(1+B1Ret)-($D$9*12*(1+Inflation)^(A28-1))),0),((O27)*(1+B3Ret)))))-(MIN(MAX(($D$9*12*(1+Inflation)^(15+1-1)+$D$9*12*(1+Inflation)^(15+2-1)+$D$9*12*(1+Inflation)^(15+3-1)+$D$9*12*(1+Inflation)^(15+4-1)+$D$9*12*(1+Inflation)^(15+5-1))-((M27)*(1+B1Ret)-($D$9*12*(1+Inflation)^(A28-1))),0),(((N27)*(1+B2Ret))+(MIN(MAX(($D$9*12*(1+Inflation)^(15+1-1)+$D$9*12*(1+Inflation)^(15+2-1)+$D$9*12*(1+Inflation)^(15+3-1)+$D$9*12*(1+Inflation)^(15+4-1)+$D$9*12*(1+Inflation)^(15+5-1))-((M27)*(1+B1Ret)-($D$9*12*(1+Inflation)^(A28-1))),0),((O27)*(1+B3Ret))))))) -> 0 | O28: =((O27)*(1+B3Ret))-(MIN(MAX(($D$9*12*(1+Inflation)^(15+1-1)+$D$9*12*(1+Inflation)^(15+2-1)+$D$9*12*(1+Inflation)^(15+3-1)+$D$9*12*(1+Inflation)^(15+4-1)+$D$9*12*(1+Inflation)^(15+5-1))-((M27)*(1+B1Ret)-($D$9*12*(1+Inflation)^(A28-1))),0),((O27)*(1+B3Ret)))) -> 1.1581489e+08
A29: 16 | B29: =Age+A29-1 -> 77 | C29: =J29+K29+L29 -> 90933388 | D29: =C29/(1+Inflation)^A29 -> 30802284 | E29: =IF(C29>0,"OK","OUT OF MONEY") -> OK | F29: =M29+N29+O29 -> 1.5244093e+08 | G29: =F29/(1+Inflation)^A29 -> 51637016 | H29: =IF(F29>0,"OK","OUT OF MONEY") -> OK | J29: =(J28)*(1+B1Ret)-($D$8*12*(1+Inflation)^(A29-1)) -> 42654275 | K29: =(K28)*(1+B2Ret) -> 0 | L29: =(L28)*(1+B3Ret) -> 48279112 | M29: =(M28)*(1+B1Ret)-($D$9*12*(1+Inflation)^(A29-1)) -> 23886394 | N29: =(N28)*(1+B2Ret) -> 0 | O29: =(O28)*(1+B3Ret) -> 1.2855453e+08
A30: 17 | B30: =Age+A30-1 -> 78 | C30: =J30+K30+L30 -> 90373398 | D30: =C30/(1+Inflation)^A30 -> 28609903 | E30: =IF(C30>0,"OK","OUT OF MONEY") -> OK | F30: =M30+N30+O30 -> 1.6329434e+08 | G30: =F30/(1+Inflation)^A30 -> 51694805 | H30: =IF(F30>0,"OK","OUT OF MONEY") -> OK | J30: =(J29)*(1+B1Ret)-($D$8*12*(1+Inflation)^(A30-1)) -> 36783583 | K30: =(K29)*(1+B2Ret) -> 0 | L30: =(L29)*(1+B3Ret) -> 53589815 | M30: =(M29)*(1+B1Ret)-($D$9*12*(1+Inflation)^(A30-1)) -> 20598807 | N30: =(N29)*(1+B2Ret) -> 0 | O30: =(O29)*(1+B3Ret) -> 1.4269553e+08
A31: 18 | B31: =Age+A31-1 -> 79 | C31: =J31+K31+L31 -> 89366683 | D31: =C31/(1+Inflation)^A31 -> 26440377 | E31: =IF(C31>0,"OK","OUT OF MONEY") -> OK | F31: =M31+N31+O31 -> 1.7512595e+08 | G31: =F31/(1+Inflation)^A31 -> 51813450 | H31: =IF(F31>0,"OK","OUT OF MONEY") -> OK | J31: =(J30)*(1+B1Ret)-($D$8*12*(1+Inflation)^(A31-1)) -> 29881988 | K31: =(K30)*(1+B2Ret) -> 0 | L31: =(L30)*(1+B3Ret) -> 59484694 | M31: =(M30)*(1+B1Ret)-($D$9*12*(1+Inflation)^(A31-1)) -> 16733913 | N31: =(N30)*(1+B2Ret) -> 0 | O31: =(O30)*(1+B3Ret) -> 1.5839204e+08
A32: 19 | B32: =Age+A32-1 -> 80 | C32: =J32+K32+L32 -> 87861941 | D32: =C32/(1+Inflation)^A32 -> 24294559 | E32: =IF(C32>0,"OK","OUT OF MONEY") -> OK | F32: =M32+N32+O32 -> 1.8804216e+08 | G32: =F32/(1+Inflation)^A32 -> 51995225 | H32: =IF(F32>0,"OK","OUT OF MONEY") -> OK | J32: =(J31)*(1+B1Ret)-($D$8*12*(1+Inflation)^(A32-1)) -> 21833931 | K32: =(K31)*(1+B2Ret) -> 0 | L32: =(L31)*(1+B3Ret) -> 66028011 | M32: =(M31)*(1+B1Ret)-($D$9*12*(1+Inflation)^(A32-1)) -> 12227001 | N32: =(N31)*(1+B2Ret) -> 0 | O32: =(O31)*(1+B3Ret) -> 1.7581516e+08
A33: 20 | B33: =Age+A33-1 -> 81 | C33: =J33+K33+L33 -> 85803815 | D33: =C33/(1+Inflation)^A33 -> 22173336 | E33: =IF(C33>0,"OK","OUT OF MONEY") -> OK | F33: =M33+N33+O33 -> 2.0216196e+08 | G33: =F33/(1+Inflation)^A33 -> 52242491 | H33: =IF(F33>0,"OK","OUT OF MONEY") -> OK | J33: =((J32)*(1+B1Ret)-($D$8*12*(1+Inflation)^(A33-1)))+(MIN(MAX(($D$8*12*(1+Inflation)^(20+1-1)+$D$8*12*(1+Inflation)^(20+2-1)+$D$8*12*(1+Inflation)^(20+3-1)+$D$8*12*(1+Inflation)^(20+4-1)+$D$8*12*(1+Inflation)^(20+5-1))-((J32)*(1+B1Ret)-($D$8*12*(1+Inflation)^(A33-1))),0),(((K32)*(1+B2Ret))+(MIN(MAX(($D$8*12*(1+Inflation)^(20+1-1)+$D$8*12*(1+Inflation)^(20+2-1)+$D$8*12*(1+Inflation)^(20+3-1)+$D$8*12*(1+Inflation)^(20+4-1)+$D$8*12*(1+Inflation)^(20+5-1))-((J32)*(1+B1Ret)-($D$8*12*(1+Inflation)^(A33-1))),0),((L32)*(1+B3Ret))))))) -> 66760636 | K33: =(((K32)*(1+B2Ret))+(MIN(MAX(($D$8*12*(1+Inflation)^(20+1-1)+$D$8*12*(1+Inflation)^(20+2-1)+$D$8*12*(1+Inflation)^(20+3-1)+$D$8*12*(1+Inflation)^(20+4-1)+$D$8*12*(1+Inflation)^(20+5-1))-((J32)*(1+B1Ret)-($D$8*12*(1+Inflation)^(A33-1))),0),((L32)*(1+B3Ret)))))-(MIN(MAX(($D$8*12*(1+Inflation)^(20+1-1)+$D$8*12*(1+Inflation)^(20+2-1)+$D$8*12*(1+Inflation)^(20+3-1)+$D$8*12*(1+Inflation)^(20+4-1)+$D$8*12*(1+Inflation)^(20+5-1))-((J32)*(1+B1Ret)-($D$8*12*(1+Inflation)^(A33-1))),0),(((K32)*(1+B2Ret))+(MIN(MAX(($D$8*12*(1+Inflation)^(20+1-1)+$D$8*12*(1+Inflation)^(20+2-1)+$D$8*12*(1+Inflation)^(20+3-1)+$D$8*12*(1+Inflation)^(20+4-1)+$D$8*12*(1+Inflation)^(20+5-1))-((J32)*(1+B1Ret)-($D$8*12*(1+Inflation)^(A33-1))),0),((L32)*(1+B3Ret))))))) -> 0 | L33: =((L32)*(1+B3Ret))-(MIN(MAX(($D$8*12*(1+Inflation)^(20+1-1)+$D$8*12*(1+Inflation)^(20+2-1)+$D$8*12*(1+Inflation)^(20+3-1)+$D$8*12*(1+Inflation)^(20+4-1)+$D$8*12*(1+Inflation)^(20+5-1))-((J32)*(1+B1Ret)-($D$8*12*(1+Inflation)^(A33-1))),0),((L32)*(1+B3Ret)))) -> 19043179 | M33: =((M32)*(1+B1Ret)-($D$9*12*(1+Inflation)^(A33-1)))+(MIN(MAX(($D$9*12*(1+Inflation)^(20+1-1)+$D$9*12*(1+Inflation)^(20+2-1)+$D$9*12*(1+Inflation)^(20+3-1)+$D$9*12*(1+Inflation)^(20+4-1)+$D$9*12*(1+Inflation)^(20+5-1))-((M32)*(1+B1Ret)-($D$9*12*(1+Inflation)^(A33-1))),0),(((N32)*(1+B2Ret))+(MIN(MAX(($D$9*12*(1+Inflation)^(20+1-1)+$D$9*12*(1+Inflation)^(20+2-1)+$D$9*12*(1+Inflation)^(20+3-1)+$D$9*12*(1+Inflation)^(20+4-1)+$D$9*12*(1+Inflation)^(20+5-1))-((M32)*(1+B1Ret)-($D$9*12*(1+Inflation)^(A33-1))),0),((O32)*(1+B3Ret))))))) -> 37385956 | N33: =(((N32)*(1+B2Ret))+(MIN(MAX(($D$9*12*(1+Inflation)^(20+1-1)+$D$9*12*(1+Inflation)^(20+2-1)+$D$9*12*(1+Inflation)^(20+3-1)+$D$9*12*(1+Inflation)^(20+4-1)+$D$9*12*(1+Inflation)^(20+5-1))-((M32)*(1+B1Ret)-($D$9*12*(1+Inflation)^(A33-1))),0),((O32)*(1+B3Ret)))))-(MIN(MAX(($D$9*12*(1+Inflation)^(20+1-1)+$D$9*12*(1+Inflation)^(20+2-1)+$D$9*12*(1+Inflation)^(20+3-1)+$D$9*12*(1+Inflation)^(20+4-1)+$D$9*12*(1+Inflation)^(20+5-1))-((M32)*(1+B1Ret)-($D$9*12*(1+Inflation)^(A33-1))),0),(((N32)*(1+B2Ret))+(MIN(MAX(($D$9*12*(1+Inflation)^(20+1-1)+$D$9*12*(1+Inflation)^(20+2-1)+$D$9*12*(1+Inflation)^(20+3-1)+$D$9*12*(1+Inflation)^(20+4-1)+$D$9*12*(1+Inflation)^(20+5-1))-((M32)*(1+B1Ret)-($D$9*12*(1+Inflation)^(A33-1))),0),((O32)*(1+B3Ret))))))) -> 0 | O33: =((O32)*(1+B3Ret))-(MIN(MAX(($D$9*12*(1+Inflation)^(20+1-1)+$D$9*12*(1+Inflation)^(20+2-1)+$D$9*12*(1+Inflation)^(20+3-1)+$D$9*12*(1+Inflation)^(20+4-1)+$D$9*12*(1+Inflation)^(20+5-1))-((M32)*(1+B1Ret)-($D$9*12*(1+Inflation)^(A33-1))),0),((O32)*(1+B3Ret)))) -> 1.64776e+08
A34: 21 | B34: =Age+A34-1 -> 82 | C34: =J34+K34+L34 -> 80962756 | D34: =C34/(1+Inflation)^A34 -> 19553565 | E34: =IF(C34>0,"OK","OUT OF MONEY") -> OK | F34: =M34+N34+O34 -> 2.1640326e+08 | G34: =F34/(1+Inflation)^A34 -> 52264220 | H34: =IF(F34>0,"OK","OUT OF MONEY") -> OK | J34: =(J33)*(1+B1Ret)-($D$8*12*(1+Inflation)^(A34-1)) -> 59824827 | K34: =(K33)*(1+B2Ret) -> 0 | L34: =(L33)*(1+B3Ret) -> 21137929 | M34: =(M33)*(1+B1Ret)-($D$9*12*(1+Inflation)^(A34-1)) -> 33501903 | N34: =(N33)*(1+B2Ret) -> 0 | O34: =(O33)*(1+B3Ret) -> 1.8290136e+08
A35: 22 | B35: =Age+A35-1 -> 83 | C35: =J35+K35+L35 -> 75053979 | D35: =C35/(1+Inflation)^A35 -> 16940671 | E35: =IF(C35>0,"OK","OUT OF MONEY") -> OK | F35: =M35+N35+O35 -> 2.319114e+08 | G35: =F35/(1+Inflation)^A35 -> 52345456 | H35: =IF(F35>0,"OK","OUT OF MONEY") -> OK | J35: =(J34)*(1+B1Ret)-($D$8*12*(1+Inflation)^(A35-1)) -> 51590878 | K35: =(K34)*(1+B2Ret) -> 0 | L35: =(L34)*(1+B3Ret) -> 23463101 | M35: =(M34)*(1+B1Ret)-($D$9*12*(1+Inflation)^(A35-1)) -> 28890892 | N35: =(N34)*(1+B2Ret) -> 0 | O35: =(O34)*(1+B3Ret) -> 2.0302051e+08
A36: 23 | B36: =Age+A36-1 -> 84 | C36: =J36+K36+L36 -> 67955076 | D36: =C36/(1+Inflation)^A36 -> 14334912 | E36: =IF(C36>0,"OK","OUT OF MONEY") -> OK | F36: =M36+N36+O36 -> 2.4882294e+08 | G36: =F36/(1+Inflation)^A36 -> 52488424 | H36: =IF(F36>0,"OK","OUT OF MONEY") -> OK | J36: =(J35)*(1+B1Ret)-($D$8*12*(1+Inflation)^(A36-1)) -> 41911034 | K36: =(K35)*(1+B2Ret) -> 0 | L36: =(L35)*(1+B3Ret) -> 26044042 | M36: =(M35)*(1+B1Ret)-($D$9*12*(1+Inflation)^(A36-1)) -> 23470179 | N36: =(N35)*(1+B2Ret) -> 0 | O36: =(O35)*(1+B3Ret) -> 2.2535276e+08
A37: 24 | B37: =Age+A37-1 -> 85 | C37: =J37+K37+L37 -> 59532104 | D37: =C37/(1+Inflation)^A37 -> 11736553 | E37: =IF(C37>0,"OK","OUT OF MONEY") -> OK | F37: =M37+N37+O37 -> 2.6729057e+08 | G37: =F37/(1+Inflation)^A37 -> 52695432 | H37: =IF(F37>0,"OK","OUT OF MONEY") -> OK | J37: =(J36)*(1+B1Ret)-($D$8*12*(1+Inflation)^(A37-1)) -> 30623217 | K37: =(K36)*(1+B2Ret) -> 0 | L37: =(L36)*(1+B3Ret) -> 28908887 | M37: =(M36)*(1+B1Ret)-($D$9*12*(1+Inflation)^(A37-1)) -> 17149002 | N37: =(N36)*(1+B2Ret) -> 0 | O37: =(O36)*(1+B3Ret) -> 2.5014157e+08
A38: 25 | B38: =Age+A38-1 -> 86 | C38: =J38+K38+L38 -> 49638606 | D38: =C38/(1+Inflation)^A38 -> 9145872.3 | E38: =IF(C38>0,"OK","OUT OF MONEY") -> OK | F38: =M38+N38+O38 -> 2.87485e+08 | G38: =F38/(1+Inflation)^A38 -> 52968874 | H38: =IF(F38>0,"OK","OUT OF MONEY") -> OK | J38: =((J37)*(1+B1Ret)-($D$8*12*(1+Inflation)^(A38-1)))+(MIN(MAX(($D$8*12*(1+Inflation)^(25+1-1)+$D$8*12*(1+Inflation)^(25+2-1)+$D$8*12*(1+Inflation)^(25+3-1)+$D$8*12*(1+Inflation)^(25+4-1)+$D$8*12*(1+Inflation)^(25+5-1))-((J37)*(1+B1Ret)-($D$8*12*(1+Inflation)^(A38-1))),0),(((K37)*(1+B2Ret))+(MIN(MAX(($D$8*12*(1+Inflation)^(25+1-1)+$D$8*12*(1+Inflation)^(25+2-1)+$D$8*12*(1+Inflation)^(25+3-1)+$D$8*12*(1+Inflation)^(25+4-1)+$D$8*12*(1+Inflation)^(25+5-1))-((J37)*(1+B1Ret)-($D$8*12*(1+Inflation)^(A38-1))),0),((L37)*(1+B3Ret))))))) -> 49638606 | K38: =(((K37)*(1+B2Ret))+(MIN(MAX(($D$8*12*(1+Inflation)^(25+1-1)+$D$8*12*(1+Inflation)^(25+2-1)+$D$8*12*(1+Inflation)^(25+3-1)+$D$8*12*(1+Inflation)^(25+4-1)+$D$8*12*(1+Inflation)^(25+5-1))-((J37)*(1+B1Ret)-($D$8*12*(1+Inflation)^(A38-1))),0),((L37)*(1+B3Ret)))))-(MIN(MAX(($D$8*12*(1+Inflation)^(25+1-1)+$D$8*12*(1+Inflation)^(25+2-1)+$D$8*12*(1+Inflation)^(25+3-1)+$D$8*12*(1+Inflation)^(25+4-1)+$D$8*12*(1+Inflation)^(25+5-1))-((J37)*(1+B1Ret)-($D$8*12*(1+Inflation)^(A38-1))),0),(((K37)*(1+B2Ret))+(MIN(MAX(($D$8*12*(1+Inflation)^(25+1-1)+$D$8*12*(1+Inflation)^(25+2-1)+$D$8*12*(1+Inflation)^(25+3-1)+$D$8*12*(1+Inflation)^(25+4-1)+$D$8*12*(1+Inflation)^(25+5-1))-((J37)*(1+B1Ret)-($D$8*12*(1+Inflation)^(A38-1))),0),((L37)*(1+B3Ret))))))) -> 0 | L38: =((L37)*(1+B3Ret))-(MIN(MAX(($D$8*12*(1+Inflation)^(25+1-1)+$D$8*12*(1+Inflation)^(25+2-1)+$D$8*12*(1+Inflation)^(25+3-1)+$D$8*12*(1+Inflation)^(25+4-1)+$D$8*12*(1+Inflation)^(25+5-1))-((J37)*(1+B1Ret)-($D$8*12*(1+Inflation)^(A38-1))),0),((L37)*(1+B3Ret)))) -> 0 | M38: =((M37)*(1+B1Ret)-($D$9*12*(1+Inflation)^(A38-1)))+(MIN(MAX(($D$9*12*(1+Inflation)^(25+1-1)+$D$9*12*(1+Inflation)^(25+2-1)+$D$9*12*(1+Inflation)^(25+3-1)+$D$9*12*(1+Inflation)^(25+4-1)+$D$9*12*(1+Inflation)^(25+5-1))-((M37)*(1+B1Ret)-($D$9*12*(1+Inflation)^(A38-1))),0),(((N37)*(1+B2Ret))+(MIN(MAX(($D$9*12*(1+Inflation)^(25+1-1)+$D$9*12*(1+Inflation)^(25+2-1)+$D$9*12*(1+Inflation)^(25+3-1)+$D$9*12*(1+Inflation)^(25+4-1)+$D$9*12*(1+Inflation)^(25+5-1))-((M37)*(1+B1Ret)-($D$9*12*(1+Inflation)^(A38-1))),0),((O37)*(1+B3Ret))))))) -> 52435738 | N38: =(((N37)*(1+B2Ret))+(MIN(MAX(($D$9*12*(1+Inflation)^(25+1-1)+$D$9*12*(1+Inflation)^(25+2-1)+$D$9*12*(1+Inflation)^(25+3-1)+$D$9*12*(1+Inflation)^(25+4-1)+$D$9*12*(1+Inflation)^(25+5-1))-((M37)*(1+B1Ret)-($D$9*12*(1+Inflation)^(A38-1))),0),((O37)*(1+B3Ret)))))-(MIN(MAX(($D$9*12*(1+Inflation)^(25+1-1)+$D$9*12*(1+Inflation)^(25+2-1)+$D$9*12*(1+Inflation)^(25+3-1)+$D$9*12*(1+Inflation)^(25+4-1)+$D$9*12*(1+Inflation)^(25+5-1))-((M37)*(1+B1Ret)-($D$9*12*(1+Inflation)^(A38-1))),0),(((N37)*(1+B2Ret))+(MIN(MAX(($D$9*12*(1+Inflation)^(25+1-1)+$D$9*12*(1+Inflation)^(25+2-1)+$D$9*12*(1+Inflation)^(25+3-1)+$D$9*12*(1+Inflation)^(25+4-1)+$D$9*12*(1+Inflation)^(25+5-1))-((M37)*(1+B1Ret)-($D$9*12*(1+Inflation)^(A38-1))),0),((O37)*(1+B3Ret))))))) -> 0 | O38: =((O37)*(1+B3Ret))-(MIN(MAX(($D$9*12*(1+Inflation)^(25+1-1)+$D$9*12*(1+Inflation)^(25+2-1)+$D$9*12*(1+Inflation)^(25+3-1)+$D$9*12*(1+Inflation)^(25+4-1)+$D$9*12*(1+Inflation)^(25+5-1))-((M37)*(1+B1Ret)-($D$9*12*(1+Inflation)^(A38-1))),0),((O37)*(1+B3Ret)))) -> 2.3504926e+08
A39: 26 | B39: =Age+A39-1 -> 87 | C39: =J39+K39+L39 -> 36831010 | D39: =C39/(1+Inflation)^A39 -> 6342133.9 | E39: =IF(C39>0,"OK","OUT OF MONEY") -> OK | F39: =M39+N39+O39 -> 3.0789283e+08 | G39: =F39/(1+Inflation)^A39 -> 53017758 | H39: =IF(F39>0,"OK","OUT OF MONEY") -> OK | J39: =(J38)*(1+B1Ret)-($D$8*12*(1+Inflation)^(A39-1)) -> 36831010 | K39: =(K38)*(1+B2Ret) -> 0 | L39: =(L38)*(1+B3Ret) -> 0 | M39: =(M38)*(1+B1Ret)-($D$9*12*(1+Inflation)^(A39-1)) -> 46988152 | N39: =(N38)*(1+B2Ret) -> 0 | O39: =(O38)*(1+B3Ret) -> 2.6090468e+08
A40: 27 | B40: =Age+A40-1 -> 88 | C40: =J40+K40+L40 -> 21987122 | D40: =C40/(1+Inflation)^A40 -> 3538395.6 | E40: =IF(C40>0,"OK","OUT OF MONEY") -> OK | F40: =M40+N40+O40 -> 3.3012516e+08 | G40: =F40/(1+Inflation)^A40 -> 53127163 | H40: =IF(F40>0,"OK","OUT OF MONEY") -> OK | J40: =(J39)*(1+B1Ret)-($D$8*12*(1+Inflation)^(A40-1)) -> 21987122 | K40: =(K39)*(1+B2Ret) -> 0 | L40: =(L39)*(1+B3Ret) -> 0 | M40: =(M39)*(1+B1Ret)-($D$9*12*(1+Inflation)^(A40-1)) -> 40520970 | N40: =(N39)*(1+B2Ret) -> 0 | O40: =(O39)*(1+B3Ret) -> 2.8960419e+08
A41: 28 | B41: =Age+A41-1 -> 89 | C41: =J41+K41+L41 -> 4884617.6 | D41: =C41/(1+Inflation)^A41 -> 734657.3 | E41: =IF(C41>0,"OK","OUT OF MONEY") -> OK | F41: =M41+N41+O41 -> 3.5437879e+08 | G41: =F41/(1+Inflation)^A41 -> 53299354 | H41: =IF(F41>0,"OK","OUT OF MONEY") -> OK | J41: =(J40)*(1+B1Ret)-($D$8*12*(1+Inflation)^(A41-1)) -> 4884617.6 | K41: =(K40)*(1+B2Ret) -> 0 | L41: =(L40)*(1+B3Ret) -> 0 | M41: =(M40)*(1+B1Ret)-($D$9*12*(1+Inflation)^(A41-1)) -> 32918141 | N41: =(N40)*(1+B2Ret) -> 0 | O41: =(O40)*(1+B3Ret) -> 3.2146065e+08
A42: 29 | B42: =Age+A42-1 -> 90 | C42: =J42+K42+L42 -> -14719974 | D42: =C42/(1+Inflation)^A42 -> -2069081 | E42: =IF(C42>0,"OK","OUT OF MONEY") -> OUT OF MONEY | F42: =M42+N42+O42 -> 3.8087369e+08 | G42: =F42/(1+Inflation)^A42 -> 53536678 | H42: =IF(F42>0,"OK","OUT OF MONEY") -> OK | J42: =(J41)*(1+B1Ret)-($D$8*12*(1+Inflation)^(A42-1)) -> -14719974 | K42: =(K41)*(1+B2Ret) -> 0 | L42: =(L41)*(1+B3Ret) -> 0 | M42: =(M41)*(1+B1Ret)-($D$9*12*(1+Inflation)^(A42-1)) -> 24052362 | N42: =(N41)*(1+B2Ret) -> 0 | O42: =(O41)*(1+B3Ret) -> 3.5682132e+08
A43: 30 | B43: =Age+A43-1 -> 91 | C43: =J43+K43+L43 -> -37093144 | D43: =C43/(1+Inflation)^A43 -> -4872819.3 | E43: =IF(C43>0,"OK","OUT OF MONEY") -> OUT OF MONEY | F43: =M43+N43+O43 -> 4.0985575e+08 | G43: =F43/(1+Inflation)^A43 -> 53841568 | H43: =IF(F43>0,"OK","OUT OF MONEY") -> OK | J43: =((J42)*(1+B1Ret)-($D$8*12*(1+Inflation)^(A43-1)))+(MIN(MAX(($D$8*12*(1+Inflation)^(30+1-1)+$D$8*12*(1+Inflation)^(30+2-1)+$D$8*12*(1+Inflation)^(30+3-1)+$D$8*12*(1+Inflation)^(30+4-1)+$D$8*12*(1+Inflation)^(30+5-1))-((J42)*(1+B1Ret)-($D$8*12*(1+Inflation)^(A43-1))),0),(((K42)*(1+B2Ret))+(MIN(MAX(($D$8*12*(1+Inflation)^(30+1-1)+$D$8*12*(1+Inflation)^(30+2-1)+$D$8*12*(1+Inflation)^(30+3-1)+$D$8*12*(1+Inflation)^(30+4-1)+$D$8*12*(1+Inflation)^(30+5-1))-((J42)*(1+B1Ret)-($D$8*12*(1+Inflation)^(A43-1))),0),((L42)*(1+B3Ret))))))) -> -37093144 | K43: =(((K42)*(1+B2Ret))+(MIN(MAX(($D$8*12*(1+Inflation)^(30+1-1)+$D$8*12*(1+Inflation)^(30+2-1)+$D$8*12*(1+Inflation)^(30+3-1)+$D$8*12*(1+Inflation)^(30+4-1)+$D$8*12*(1+Inflation)^(30+5-1))-((J42)*(1+B1Ret)-($D$8*12*(1+Inflation)^(A43-1))),0),((L42)*(1+B3Ret)))))-(MIN(MAX(($D$8*12*(1+Inflation)^(30+1-1)+$D$8*12*(1+Inflation)^(30+2-1)+$D$8*12*(1+Inflation)^(30+3-1)+$D$8*12*(1+Inflation)^(30+4-1)+$D$8*12*(1+Inflation)^(30+5-1))-((J42)*(1+B1Ret)-($D$8*12*(1+Inflation)^(A43-1))),0),(((K42)*(1+B2Ret))+(MIN(MAX(($D$8*12*(1+Inflation)^(30+1-1)+$D$8*12*(1+Inflation)^(30+2-1)+$D$8*12*(1+Inflation)^(30+3-1)+$D$8*12*(1+Inflation)^(30+4-1)+$D$8*12*(1+Inflation)^(30+5-1))-((J42)*(1+B1Ret)-($D$8*12*(1+Inflation)^(A43-1))),0),((L42)*(1+B3Ret))))))) -> 0 | L43: =((L42)*(1+B3Ret))-(MIN(MAX(($D$8*12*(1+Inflation)^(30+1-1)+$D$8*12*(1+Inflation)^(30+2-1)+$D$8*12*(1+Inflation)^(30+3-1)+$D$8*12*(1+Inflation)^(30+4-1)+$D$8*12*(1+Inflation)^(30+5-1))-((J42)*(1+B1Ret)-($D$8*12*(1+Inflation)^(A43-1))),0),((L42)*(1+B3Ret)))) -> 0 | M43: =((M42)*(1+B1Ret)-($D$9*12*(1+Inflation)^(A43-1)))+(MIN(MAX(($D$9*12*(1+Inflation)^(30+1-1)+$D$9*12*(1+Inflation)^(30+2-1)+$D$9*12*(1+Inflation)^(30+3-1)+$D$9*12*(1+Inflation)^(30+4-1)+$D$9*12*(1+Inflation)^(30+5-1))-((M42)*(1+B1Ret)-($D$9*12*(1+Inflation)^(A43-1))),0),(((N42)*(1+B2Ret))+(MIN(MAX(($D$9*12*(1+Inflation)^(30+1-1)+$D$9*12*(1+Inflation)^(30+2-1)+$D$9*12*(1+Inflation)^(30+3-1)+$D$9*12*(1+Inflation)^(30+4-1)+$D$9*12*(1+Inflation)^(30+5-1))-((M42)*(1+B1Ret)-($D$9*12*(1+Inflation)^(A43-1))),0),((O42)*(1+B3Ret))))))) -> 73543835 | N43: =(((N42)*(1+B2Ret))+(MIN(MAX(($D$9*12*(1+Inflation)^(30+1-1)+$D$9*12*(1+Inflation)^(30+2-1)+$D$9*12*(1+Inflation)^(30+3-1)+$D$9*12*(1+Inflation)^(30+4-1)+$D$9*12*(1+Inflation)^(30+5-1))-((M42)*(1+B1Ret)-($D$9*12*(1+Inflation)^(A43-1))),0),((O42)*(1+B3Ret)))))-(MIN(MAX(($D$9*12*(1+Inflation)^(30+1-1)+$D$9*12*(1+Inflation)^(30+2-1)+$D$9*12*(1+Inflation)^(30+3-1)+$D$9*12*(1+Inflation)^(30+4-1)+$D$9*12*(1+Inflation)^(30+5-1))-((M42)*(1+B1Ret)-($D$9*12*(1+Inflation)^(A43-1))),0),(((N42)*(1+B2Ret))+(MIN(MAX(($D$9*12*(1+Inflation)^(30+1-1)+$D$9*12*(1+Inflation)^(30+2-1)+$D$9*12*(1+Inflation)^(30+3-1)+$D$9*12*(1+Inflation)^(30+4-1)+$D$9*12*(1+Inflation)^(30+5-1))-((M42)*(1+B1Ret)-($D$9*12*(1+Inflation)^(A43-1))),0),((O42)*(1+B3Ret))))))) -> 0 | O43: =((O42)*(1+B3Ret))-(MIN(MAX(($D$9*12*(1+Inflation)^(30+1-1)+$D$9*12*(1+Inflation)^(30+2-1)+$D$9*12*(1+Inflation)^(30+3-1)+$D$9*12*(1+Inflation)^(30+4-1)+$D$9*12*(1+Inflation)^(30+5-1))-((M42)*(1+B1Ret)-($D$9*12*(1+Inflation)^(A43-1))),0),((O42)*(1+B3Ret)))) -> 3.3631191e+08
A44: 31 | B44: =Age+A44-1 -> 92 | C44: =J44+K44+L44 -> -62526429 | D44: =C44/(1+Inflation)^A44 -> -7676557.7 | E44: =IF(C44>0,"OK","OUT OF MONEY") -> OUT OF MONEY | F44: =M44+N44+O44 -> 4.3920954e+08 | G44: =F44/(1+Inflation)^A44 -> 53923075 | H44: =IF(F44>0,"OK","OUT OF MONEY") -> OK | J44: =(J43)*(1+B1Ret)-($D$8*12*(1+Inflation)^(A44-1)) -> -62526429 | K44: =(K43)*(1+B2Ret) -> 0 | L44: =(L43)*(1+B3Ret) -> 0 | M44: =(M43)*(1+B1Ret)-($D$9*12*(1+Inflation)^(A44-1)) -> 65903315 | N44: =(N43)*(1+B2Ret) -> 0 | O44: =(O43)*(1+B3Ret) -> 3.7330622e+08
A45: 32 | B45: =Age+A45-1 -> 93 | C45: =J45+K45+L45 -> -91338617 | D45: =C45/(1+Inflation)^A45 -> -10480296 | E45: =IF(C45>0,"OK","OUT OF MONEY") -> OUT OF MONEY | F45: =M45+N45+O45 -> 4.7120266e+08 | G45: =F45/(1+Inflation)^A45 -> 54066325 | H45: =IF(F45>0,"OK","OUT OF MONEY") -> OK | J45: =(J44)*(1+B1Ret)-($D$8*12*(1+Inflation)^(A45-1)) -> -91338617 | K45: =(K44)*(1+B2Ret) -> 0 | L45: =(L44)*(1+B3Ret) -> 0 | M45: =(M44)*(1+B1Ret)-($D$9*12*(1+Inflation)^(A45-1)) -> 56832757 | N45: =(N44)*(1+B2Ret) -> 0 | O45: =(O44)*(1+B3Ret) -> 4.143699e+08
A46: 33 | B46: =Age+A46-1 -> 94 | C46: =J46+K46+L46 -> -1.2387813e+08 | D46: =C46/(1+Inflation)^A46 -> -13284034 | E46: =IF(C46>0,"OK","OUT OF MONEY") -> OUT OF MONEY | F46: =M46+N46+O46 -> 5.0611999e+08 | G46: =F46/(1+Inflation)^A46 -> 54273625 | H46: =IF(F46>0,"OK","OUT OF MONEY") -> OK | J46: =(J45)*(1+B1Ret)-($D$8*12*(1+Inflation)^(A46-1)) -> -1.2387813e+08 | K46: =(K45)*(1+B2Ret) -> 0 | L46: =(L45)*(1+B3Ret) -> 0 | M46: =(M45)*(1+B1Ret)-($D$9*12*(1+Inflation)^(A46-1)) -> 46169395 | N46: =(N45)*(1+B2Ret) -> 0 | O46: =(O45)*(1+B3Ret) -> 4.5995059e+08
A47: 34 | B47: =Age+A47-1 -> 95 | C47: =J47+K47+L47 -> -1.6052562e+08 | D47: =C47/(1+Inflation)^A47 -> -16087773 | E47: =IF(C47>0,"OK","OUT OF MONEY") -> OUT OF MONEY | F47: =M47+N47+O47 -> 5.4427984e+08 | G47: =F47/(1+Inflation)^A47 -> 54547369 | H47: =IF(F47>0,"OK","OUT OF MONEY") -> OK | J47: =(J46)*(1+B1Ret)-($D$8*12*(1+Inflation)^(A47-1)) -> -1.6052562e+08 | K47: =(K46)*(1+B2Ret) -> 0 | L47: =(L46)*(1+B3Ret) -> 0 | M47: =(M46)*(1+B1Ret)-($D$9*12*(1+Inflation)^(A47-1)) -> 33734682 | N47: =(N46)*(1+B2Ret) -> 0 | O47: =(O46)*(1+B3Ret) -> 5.1054516e+08
A48: 35 | B48: =Age+A48-1 -> 96 | C48: =J48+K48+L48 -> -2.0169676e+08 | D48: =C48/(1+Inflation)^A48 -> -18891511 | E48: =IF(C48>0,"OK","OUT OF MONEY") -> OUT OF MONEY | F48: =M48+N48+O48 -> 5.8603801e+08 | G48: =F48/(1+Inflation)^A48 -> 54890042 | H48: =IF(F48>0,"OK","OUT OF MONEY") -> OK | J48: =((J47)*(1+B1Ret)-($D$8*12*(1+Inflation)^(A48-1)))+(MIN(MAX(($D$8*12*(1+Inflation)^(35+1-1)+$D$8*12*(1+Inflation)^(35+2-1)+$D$8*12*(1+Inflation)^(35+3-1)+$D$8*12*(1+Inflation)^(35+4-1)+$D$8*12*(1+Inflation)^(35+5-1))-((J47)*(1+B1Ret)-($D$8*12*(1+Inflation)^(A48-1))),0),(((K47)*(1+B2Ret))+(MIN(MAX(($D$8*12*(1+Inflation)^(35+1-1)+$D$8*12*(1+Inflation)^(35+2-1)+$D$8*12*(1+Inflation)^(35+3-1)+$D$8*12*(1+Inflation)^(35+4-1)+$D$8*12*(1+Inflation)^(35+5-1))-((J47)*(1+B1Ret)-($D$8*12*(1+Inflation)^(A48-1))),0),((L47)*(1+B3Ret))))))) -> -2.0169676e+08 | K48: =(((K47)*(1+B2Ret))+(MIN(MAX(($D$8*12*(1+Inflation)^(35+1-1)+$D$8*12*(1+Inflation)^(35+2-1)+$D$8*12*(1+Inflation)^(35+3-1)+$D$8*12*(1+Inflation)^(35+4-1)+$D$8*12*(1+Inflation)^(35+5-1))-((J47)*(1+B1Ret)-($D$8*12*(1+Inflation)^(A48-1))),0),((L47)*(1+B3Ret)))))-(MIN(MAX(($D$8*12*(1+Inflation)^(35+1-1)+$D$8*12*(1+Inflation)^(35+2-1)+$D$8*12*(1+Inflation)^(35+3-1)+$D$8*12*(1+Inflation)^(35+4-1)+$D$8*12*(1+Inflation)^(35+5-1))-((J47)*(1+B1Ret)-($D$8*12*(1+Inflation)^(A48-1))),0),(((K47)*(1+B2Ret))+(MIN(MAX(($D$8*12*(1+Inflation)^(35+1-1)+$D$8*12*(1+Inflation)^(35+2-1)+$D$8*12*(1+Inflation)^(35+3-1)+$D$8*12*(1+Inflation)^(35+4-1)+$D$8*12*(1+Inflation)^(35+5-1))-((J47)*(1+B1Ret)-($D$8*12*(1+Inflation)^(A48-1))),0),((L47)*(1+B3Ret))))))) -> 0 | L48: =((L47)*(1+B3Ret))-(MIN(MAX(($D$8*12*(1+Inflation)^(35+1-1)+$D$8*12*(1+Inflation)^(35+2-1)+$D$8*12*(1+Inflation)^(35+3-1)+$D$8*12*(1+Inflation)^(35+4-1)+$D$8*12*(1+Inflation)^(35+5-1))-((J47)*(1+B1Ret)-($D$8*12*(1+Inflation)^(A48-1))),0),((L47)*(1+B3Ret)))) -> 0 | M48: =((M47)*(1+B1Ret)-($D$9*12*(1+Inflation)^(A48-1)))+(MIN(MAX(($D$9*12*(1+Inflation)^(35+1-1)+$D$9*12*(1+Inflation)^(35+2-1)+$D$9*12*(1+Inflation)^(35+3-1)+$D$9*12*(1+Inflation)^(35+4-1)+$D$9*12*(1+Inflation)^(35+5-1))-((M47)*(1+B1Ret)-($D$9*12*(1+Inflation)^(A48-1))),0),(((N47)*(1+B2Ret))+(MIN(MAX(($D$9*12*(1+Inflation)^(35+1-1)+$D$9*12*(1+Inflation)^(35+2-1)+$D$9*12*(1+Inflation)^(35+3-1)+$D$9*12*(1+Inflation)^(35+4-1)+$D$9*12*(1+Inflation)^(35+5-1))-((M47)*(1+B1Ret)-($D$9*12*(1+Inflation)^(A48-1))),0),((O47)*(1+B3Ret))))))) -> 1.0314903e+08 | N48: =(((N47)*(1+B2Ret))+(MIN(MAX(($D$9*12*(1+Inflation)^(35+1-1)+$D$9*12*(1+Inflation)^(35+2-1)+$D$9*12*(1+Inflation)^(35+3-1)+$D$9*12*(1+Inflation)^(35+4-1)+$D$9*12*(1+Inflation)^(35+5-1))-((M47)*(1+B1Ret)-($D$9*12*(1+Inflation)^(A48-1))),0),((O47)*(1+B3Ret)))))-(MIN(MAX(($D$9*12*(1+Inflation)^(35+1-1)+$D$9*12*(1+Inflation)^(35+2-1)+$D$9*12*(1+Inflation)^(35+3-1)+$D$9*12*(1+Inflation)^(35+4-1)+$D$9*12*(1+Inflation)^(35+5-1))-((M47)*(1+B1Ret)-($D$9*12*(1+Inflation)^(A48-1))),0),(((N47)*(1+B2Ret))+(MIN(MAX(($D$9*12*(1+Inflation)^(35+1-1)+$D$9*12*(1+Inflation)^(35+2-1)+$D$9*12*(1+Inflation)^(35+3-1)+$D$9*12*(1+Inflation)^(35+4-1)+$D$9*12*(1+Inflation)^(35+5-1))-((M47)*(1+B1Ret)-($D$9*12*(1+Inflation)^(A48-1))),0),((O47)*(1+B3Ret))))))) -> 0 | O48: =((O47)*(1+B3Ret))-(MIN(MAX(($D$9*12*(1+Inflation)^(35+1-1)+$D$9*12*(1+Inflation)^(35+2-1)+$D$9*12*(1+Inflation)^(35+3-1)+$D$9*12*(1+Inflation)^(35+4-1)+$D$9*12*(1+Inflation)^(35+5-1))-((M47)*(1+B1Ret)-($D$9*12*(1+Inflation)^(A48-1))),0),((O47)*(1+B3Ret)))) -> 4.8288897e+08
A49: 36 | B49: =Age+A49-1 -> 97 | C49: =J49+K49+L49 -> -2.4784527e+08 | D49: =C49/(1+Inflation)^A49 -> -21695249 | E49: =IF(C49>0,"OK","OUT OF MONEY") -> OUT OF MONEY | F49: =M49+N49+O49 -> 6.2843957e+08 | G49: =F49/(1+Inflation)^A49 -> 55010745 | H49: =IF(F49>0,"OK","OUT OF MONEY") -> OK | J49: =(J48)*(1+B1Ret)-($D$8*12*(1+Inflation)^(A49-1)) -> -2.4784527e+08 | K49: =(K48)*(1+B2Ret) -> 0 | L49: =(L48)*(1+B3Ret) -> 0 | M49: =(M48)*(1+B1Ret)-($D$9*12*(1+Inflation)^(A49-1)) -> 92432808 | N49: =(N48)*(1+B2Ret) -> 0 | O49: =(O48)*(1+B3Ret) -> 5.3600676e+08
A50: 37 | B50: =Age+A50-1 -> 98 | C50: =J50+K50+L50 -> -2.9946627e+08 | D50: =C50/(1+Inflation)^A50 -> -24498988 | E50: =IF(C50>0,"OK","OUT OF MONEY") -> OUT OF MONEY | F50: =M50+N50+O50 -> 6.7467839e+08 | G50: =F50/(1+Inflation)^A50 -> 55194655 | H50: =IF(F50>0,"OK","OUT OF MONEY") -> OK | J50: =(J49)*(1+B1Ret)-($D$8*12*(1+Inflation)^(A50-1)) -> -2.9946627e+08 | K50: =(K49)*(1+B2Ret) -> 0 | L50: =(L49)*(1+B3Ret) -> 0 | M50: =(M49)*(1+B1Ret)-($D$9*12*(1+Inflation)^(A50-1)) -> 79710882 | N50: =(N49)*(1+B2Ret) -> 0 | O50: =(O49)*(1+B3Ret) -> 5.949675e+08
A51: 38 | B51: =Age+A51-1 -> 99 | C51: =J51+K51+L51 -> -3.5709976e+08 | D51: =C51/(1+Inflation)^A51 -> -27302726 | E51: =IF(C51>0,"OK","OUT OF MONEY") -> OUT OF MONEY | F51: =M51+N51+O51 -> 7.2516889e+08 | G51: =F51/(1+Inflation)^A51 -> 55444135 | H51: =IF(F51>0,"OK","OUT OF MONEY") -> OK | J51: =(J50)*(1+B1Ret)-($D$8*12*(1+Inflation)^(A51-1)) -> -3.5709976e+08 | K51: =(K50)*(1+B2Ret) -> 0 | L51: =(L50)*(1+B3Ret) -> 0 | M51: =(M50)*(1+B1Ret)-($D$9*12*(1+Inflation)^(A51-1)) -> 64754965 | N51: =(N50)*(1+B2Ret) -> 0 | O51: =(O50)*(1+B3Ret) -> 6.6041393e+08
A52: 39 | B52: =Age+A52-1 -> 100 | C52: =J52+K52+L52 -> -4.2133456e+08 | D52: =C52/(1+Inflation)^A52 -> -30106464 | E52: =IF(C52>0,"OK","OUT OF MONEY") -> OUT OF MONEY | F52: =M52+N52+O52 -> 7.803741e+08 | G52: =F52/(1+Inflation)^A52 -> 55761637 | H52: =IF(F52>0,"OK","OUT OF MONEY") -> OK | J52: =(J51)*(1+B1Ret)-($D$8*12*(1+Inflation)^(A52-1)) -> -4.2133456e+08 | K52: =(K51)*(1+B2Ret) -> 0 | L52: =(L51)*(1+B3Ret) -> 0 | M52: =(M51)*(1+B1Ret)-($D$9*12*(1+Inflation)^(A52-1)) -> 47314636 | N52: =(N51)*(1+B2Ret) -> 0 | O52: =(O51)*(1+B3Ret) -> 7.3305946e+08
A53: 40 | B53: =Age+A53-1 -> 101 | C53: =J53+K53+L53 -> -4.9281244e+08 | D53: =C53/(1+Inflation)^A53 -> -32910203 | E53: =IF(C53>0,"OK","OUT OF MONEY") -> OUT OF MONEY | F53: =M53+N53+O53 -> 8.4081137e+08 | G53: =F53/(1+Inflation)^A53 -> 56149703 | H53: =IF(F53>0,"OK","OUT OF MONEY") -> OK | J53: =((J52)*(1+B1Ret)-($D$8*12*(1+Inflation)^(A53-1)))+(MIN(MAX(($D$8*12*(1+Inflation)^(40+1-1)+$D$8*12*(1+Inflation)^(40+2-1)+$D$8*12*(1+Inflation)^(40+3-1)+$D$8*12*(1+Inflation)^(40+4-1)+$D$8*12*(1+Inflation)^(40+5-1))-((J52)*(1+B1Ret)-($D$8*12*(1+Inflation)^(A53-1))),0),(((K52)*(1+B2Ret))+(MIN(MAX(($D$8*12*(1+Inflation)^(40+1-1)+$D$8*12*(1+Inflation)^(40+2-1)+$D$8*12*(1+Inflation)^(40+3-1)+$D$8*12*(1+Inflation)^(40+4-1)+$D$8*12*(1+Inflation)^(40+5-1))-((J52)*(1+B1Ret)-($D$8*12*(1+Inflation)^(A53-1))),0),((L52)*(1+B3Ret))))))) -> -4.9281244e+08 | K53: =(((K52)*(1+B2Ret))+(MIN(MAX(($D$8*12*(1+Inflation)^(40+1-1)+$D$8*12*(1+Inflation)^(40+2-1)+$D$8*12*(1+Inflation)^(40+3-1)+$D$8*12*(1+Inflation)^(40+4-1)+$D$8*12*(1+Inflation)^(40+5-1))-((J52)*(1+B1Ret)-($D$8*12*(1+Inflation)^(A53-1))),0),((L52)*(1+B3Ret)))))-(MIN(MAX(($D$8*12*(1+Inflation)^(40+1-1)+$D$8*12*(1+Inflation)^(40+2-1)+$D$8*12*(1+Inflation)^(40+3-1)+$D$8*12*(1+Inflation)^(40+4-1)+$D$8*12*(1+Inflation)^(40+5-1))-((J52)*(1+B1Ret)-($D$8*12*(1+Inflation)^(A53-1))),0),(((K52)*(1+B2Ret))+(MIN(MAX(($D$8*12*(1+Inflation)^(40+1-1)+$D$8*12*(1+Inflation)^(40+2-1)+$D$8*12*(1+Inflation)^(40+3-1)+$D$8*12*(1+Inflation)^(40+4-1)+$D$8*12*(1+Inflation)^(40+5-1))-((J52)*(1+B1Ret)-($D$8*12*(1+Inflation)^(A53-1))),0),((L52)*(1+B3Ret))))))) -> 0 | L53: =((L52)*(1+B3Ret))-(MIN(MAX(($D$8*12*(1+Inflation)^(40+1-1)+$D$8*12*(1+Inflation)^(40+2-1)+$D$8*12*(1+Inflation)^(40+3-1)+$D$8*12*(1+Inflation)^(40+4-1)+$D$8*12*(1+Inflation)^(40+5-1))-((J52)*(1+B1Ret)-($D$8*12*(1+Inflation)^(A53-1))),0),((L52)*(1+B3Ret)))) -> 0 | M53: =((M52)*(1+B1Ret)-($D$9*12*(1+Inflation)^(A53-1)))+(MIN(MAX(($D$9*12*(1+Inflation)^(40+1-1)+$D$9*12*(1+Inflation)^(40+2-1)+$D$9*12*(1+Inflation)^(40+3-1)+$D$9*12*(1+Inflation)^(40+4-1)+$D$9*12*(1+Inflation)^(40+5-1))-((M52)*(1+B1Ret)-($D$9*12*(1+Inflation)^(A53-1))),0),(((N52)*(1+B2Ret))+(MIN(MAX(($D$9*12*(1+Inflation)^(40+1-1)+$D$9*12*(1+Inflation)^(40+2-1)+$D$9*12*(1+Inflation)^(40+3-1)+$D$9*12*(1+Inflation)^(40+4-1)+$D$9*12*(1+Inflation)^(40+5-1))-((M52)*(1+B1Ret)-($D$9*12*(1+Inflation)^(A53-1))),0),((O52)*(1+B3Ret))))))) -> 1.4467185e+08 | N53: =(((N52)*(1+B2Ret))+(MIN(MAX(($D$9*12*(1+Inflation)^(40+1-1)+$D$9*12*(1+Inflation)^(40+2-1)+$D$9*12*(1+Inflation)^(40+3-1)+$D$9*12*(1+Inflation)^(40+4-1)+$D$9*12*(1+Inflation)^(40+5-1))-((M52)*(1+B1Ret)-($D$9*12*(1+Inflation)^(A53-1))),0),((O52)*(1+B3Ret)))))-(MIN(MAX(($D$9*12*(1+Inflation)^(40+1-1)+$D$9*12*(1+Inflation)^(40+2-1)+$D$9*12*(1+Inflation)^(40+3-1)+$D$9*12*(1+Inflation)^(40+4-1)+$D$9*12*(1+Inflation)^(40+5-1))-((M52)*(1+B1Ret)-($D$9*12*(1+Inflation)^(A53-1))),0),(((N52)*(1+B2Ret))+(MIN(MAX(($D$9*12*(1+Inflation)^(40+1-1)+$D$9*12*(1+Inflation)^(40+2-1)+$D$9*12*(1+Inflation)^(40+3-1)+$D$9*12*(1+Inflation)^(40+4-1)+$D$9*12*(1+Inflation)^(40+5-1))-((M52)*(1+B1Ret)-($D$9*12*(1+Inflation)^(A53-1))),0),((O52)*(1+B3Ret))))))) -> 0 | O53: =((O52)*(1+B3Ret))-(MIN(MAX(($D$9*12*(1+Inflation)^(40+1-1)+$D$9*12*(1+Inflation)^(40+2-1)+$D$9*12*(1+Inflation)^(40+3-1)+$D$9*12*(1+Inflation)^(40+4-1)+$D$9*12*(1+Inflation)^(40+5-1))-((M52)*(1+B1Ret)-($D$9*12*(1+Inflation)^(A53-1))),0),((O52)*(1+B3Ret)))) -> 6.9613951e+08
A54: 41 | B54: =Age+A54-1 -> 102 | C54: =J54+K54+L54 -> -5.7223268e+08 | D54: =C54/(1+Inflation)^A54 -> -35713941 | E54: =IF(C54>0,"OK","OUT OF MONEY") -> OUT OF MONEY | F54: =M54+N54+O54 -> 9.0235665e+08 | G54: =F54/(1+Inflation)^A54 -> 56317496 | H54: =IF(F54>0,"OK","OUT OF MONEY") -> OK | J54: =(J53)*(1+B1Ret)-($D$8*12*(1+Inflation)^(A54-1)) -> -5.7223268e+08 | K54: =(K53)*(1+B2Ret) -> 0 | L54: =(L53)*(1+B3Ret) -> 0 | M54: =(M53)*(1+B1Ret)-($D$9*12*(1+Inflation)^(A54-1)) -> 1.2964179e+08 | N54: =(N53)*(1+B2Ret) -> 0 | O54: =(O53)*(1+B3Ret) -> 7.7271486e+08
A55: 42 | B55: =Age+A55-1 -> 103 | C55: =J55+K55+L55 -> -6.6035698e+08 | D55: =C55/(1+Inflation)^A55 -> -38517679 | E55: =IF(C55>0,"OK","OUT OF MONEY") -> OUT OF MONEY | F55: =M55+N55+O55 -> 9.6951213e+08 | G55: =F55/(1+Inflation)^A55 -> 56550257 | H55: =IF(F55>0,"OK","OUT OF MONEY") -> OK | J55: =(J54)*(1+B1Ret)-($D$8*12*(1+Inflation)^(A55-1)) -> -6.6035698e+08 | K55: =(K54)*(1+B2Ret) -> 0 | L55: =(L54)*(1+B3Ret) -> 0 | M55: =(M54)*(1+B1Ret)-($D$9*12*(1+Inflation)^(A55-1)) -> 1.1179863e+08 | N55: =(N54)*(1+B2Ret) -> 0 | O55: =(O54)*(1+B3Ret) -> 8.5771349e+08
A56: 43 | B56: =Age+A56-1 -> 104 | C56: =J56+K56+L56 -> -7.5801474e+08 | D56: =C56/(1+Inflation)^A56 -> -41321417 | E56: =IF(C56>0,"OK","OUT OF MONEY") -> OUT OF MONEY | F56: =M56+N56+O56 -> 1.0428842e+09 | G56: =F56/(1+Inflation)^A56 -> 56850414 | H56: =IF(F56>0,"OK","OUT OF MONEY") -> OK | J56: =(J55)*(1+B1Ret)-($D$8*12*(1+Inflation)^(A56-1)) -> -7.5801474e+08 | K56: =(K55)*(1+B2Ret) -> 0 | L56: =(L55)*(1+B3Ret) -> 0 | M56: =(M55)*(1+B1Ret)-($D$9*12*(1+Inflation)^(A56-1)) -> 90822188 | N56: =(N55)*(1+B2Ret) -> 0 | O56: =(O55)*(1+B3Ret) -> 9.5206198e+08
A57: 44 | B57: =Age+A57-1 -> 105 | C57: =J57+K57+L57 -> -8.6610884e+08 | D57: =C57/(1+Inflation)^A57 -> -44125156 | E57: =IF(C57>0,"OK","OUT OF MONEY") -> OUT OF MONEY | F57: =M57+N57+O57 -> 1.12315e+09 | G57: =F57/(1+Inflation)^A57 -> 57220487 | H57: =IF(F57>0,"OK","OUT OF MONEY") -> OK | J57: =(J56)*(1+B1Ret)-($D$8*12*(1+Inflation)^(A57-1)) -> -8.6610884e+08 | K57: =(K56)*(1+B2Ret) -> 0 | L57: =(L56)*(1+B3Ret) -> 0 | M57: =(M56)*(1+B1Ret)-($D$9*12*(1+Inflation)^(A57-1)) -> 66361225 | N57: =(N56)*(1+B2Ret) -> 0 | O57: =(O56)*(1+B3Ret) -> 1.0567888e+09
A58: 45 | B58: =Age+A58-1 -> 106 | C58: =J58+K58+L58 -> -9.8562183e+08 | D58: =C58/(1+Inflation)^A58 -> -46928894 | E58: =IF(C58>0,"OK","OUT OF MONEY") -> OUT OF MONEY | F58: =M58+N58+O58 -> 1.2110663e+09 | G58: =F58/(1+Inflation)^A58 -> 57663090 | H58: =IF(F58>0,"OK","OUT OF MONEY") -> OK | J58: =((J57)*(1+B1Ret)-($D$8*12*(1+Inflation)^(A58-1)))+(MIN(MAX(($D$8*12*(1+Inflation)^(45+1-1)+$D$8*12*(1+Inflation)^(45+2-1)+$D$8*12*(1+Inflation)^(45+3-1)+$D$8*12*(1+Inflation)^(45+4-1)+$D$8*12*(1+Inflation)^(45+5-1))-((J57)*(1+B1Ret)-($D$8*12*(1+Inflation)^(A58-1))),0),(((K57)*(1+B2Ret))+(MIN(MAX(($D$8*12*(1+Inflation)^(45+1-1)+$D$8*12*(1+Inflation)^(45+2-1)+$D$8*12*(1+Inflation)^(45+3-1)+$D$8*12*(1+Inflation)^(45+4-1)+$D$8*12*(1+Inflation)^(45+5-1))-((J57)*(1+B1Ret)-($D$8*12*(1+Inflation)^(A58-1))),0),((L57)*(1+B3Ret))))))) -> -9.8562183e+08 | K58: =(((K57)*(1+B2Ret))+(MIN(MAX(($D$8*12*(1+Inflation)^(45+1-1)+$D$8*12*(1+Inflation)^(45+2-1)+$D$8*12*(1+Inflation)^(45+3-1)+$D$8*12*(1+Inflation)^(45+4-1)+$D$8*12*(1+Inflation)^(45+5-1))-((J57)*(1+B1Ret)-($D$8*12*(1+Inflation)^(A58-1))),0),((L57)*(1+B3Ret)))))-(MIN(MAX(($D$8*12*(1+Inflation)^(45+1-1)+$D$8*12*(1+Inflation)^(45+2-1)+$D$8*12*(1+Inflation)^(45+3-1)+$D$8*12*(1+Inflation)^(45+4-1)+$D$8*12*(1+Inflation)^(45+5-1))-((J57)*(1+B1Ret)-($D$8*12*(1+Inflation)^(A58-1))),0),(((K57)*(1+B2Ret))+(MIN(MAX(($D$8*12*(1+Inflation)^(45+1-1)+$D$8*12*(1+Inflation)^(45+2-1)+$D$8*12*(1+Inflation)^(45+3-1)+$D$8*12*(1+Inflation)^(45+4-1)+$D$8*12*(1+Inflation)^(45+5-1))-((J57)*(1+B1Ret)-($D$8*12*(1+Inflation)^(A58-1))),0),((L57)*(1+B3Ret))))))) -> 0 | L58: =((L57)*(1+B3Ret))-(MIN(MAX(($D$8*12*(1+Inflation)^(45+1-1)+$D$8*12*(1+Inflation)^(45+2-1)+$D$8*12*(1+Inflation)^(45+3-1)+$D$8*12*(1+Inflation)^(45+4-1)+$D$8*12*(1+Inflation)^(45+5-1))-((J57)*(1+B1Ret)-($D$8*12*(1+Inflation)^(A58-1))),0),((L57)*(1+B3Ret)))) -> 0 | M58: =((M57)*(1+B1Ret)-($D$9*12*(1+Inflation)^(A58-1)))+(MIN(MAX(($D$9*12*(1+Inflation)^(45+1-1)+$D$9*12*(1+Inflation)^(45+2-1)+$D$9*12*(1+Inflation)^(45+3-1)+$D$9*12*(1+Inflation)^(45+4-1)+$D$9*12*(1+Inflation)^(45+5-1))-((M57)*(1+B1Ret)-($D$9*12*(1+Inflation)^(A58-1))),0),(((N57)*(1+B2Ret))+(MIN(MAX(($D$9*12*(1+Inflation)^(45+1-1)+$D$9*12*(1+Inflation)^(45+2-1)+$D$9*12*(1+Inflation)^(45+3-1)+$D$9*12*(1+Inflation)^(45+4-1)+$D$9*12*(1+Inflation)^(45+5-1))-((M57)*(1+B1Ret)-($D$9*12*(1+Inflation)^(A58-1))),0),((O57)*(1+B3Ret))))))) -> 2.0290976e+08 | N58: =(((N57)*(1+B2Ret))+(MIN(MAX(($D$9*12*(1+Inflation)^(45+1-1)+$D$9*12*(1+Inflation)^(45+2-1)+$D$9*12*(1+Inflation)^(45+3-1)+$D$9*12*(1+Inflation)^(45+4-1)+$D$9*12*(1+Inflation)^(45+5-1))-((M57)*(1+B1Ret)-($D$9*12*(1+Inflation)^(A58-1))),0),((O57)*(1+B3Ret)))))-(MIN(MAX(($D$9*12*(1+Inflation)^(45+1-1)+$D$9*12*(1+Inflation)^(45+2-1)+$D$9*12*(1+Inflation)^(45+3-1)+$D$9*12*(1+Inflation)^(45+4-1)+$D$9*12*(1+Inflation)^(45+5-1))-((M57)*(1+B1Ret)-($D$9*12*(1+Inflation)^(A58-1))),0),(((N57)*(1+B2Ret))+(MIN(MAX(($D$9*12*(1+Inflation)^(45+1-1)+$D$9*12*(1+Inflation)^(45+2-1)+$D$9*12*(1+Inflation)^(45+3-1)+$D$9*12*(1+Inflation)^(45+4-1)+$D$9*12*(1+Inflation)^(45+5-1))-((M57)*(1+B1Ret)-($D$9*12*(1+Inflation)^(A58-1))),0),((O57)*(1+B3Ret))))))) -> 0 | O58: =((O57)*(1+B3Ret))-(MIN(MAX(($D$9*12*(1+Inflation)^(45+1-1)+$D$9*12*(1+Inflation)^(45+2-1)+$D$9*12*(1+Inflation)^(45+3-1)+$D$9*12*(1+Inflation)^(45+4-1)+$D$9*12*(1+Inflation)^(45+5-1))-((M57)*(1+B1Ret)-($D$9*12*(1+Inflation)^(A58-1))),0),((O57)*(1+B3Ret)))) -> 1.0081565e+09
A59: 46 | B59: =Age+A59-1 -> 107 | C59: =J59+K59+L59 -> -1.1176227e+09 | D59: =C59/(1+Inflation)^A59 -> -49732632 | E59: =IF(C59>0,"OK","OUT OF MONEY") -> OUT OF MONEY | F59: =M59+N59+O59 -> 1.300883e+09 | G59: =F59/(1+Inflation)^A59 -> 57887458 | H59: =IF(F59>0,"OK","OUT OF MONEY") -> OK | J59: =(J58)*(1+B1Ret)-($D$8*12*(1+Inflation)^(A59-1)) -> -1.1176227e+09 | K59: =(K58)*(1+B2Ret) -> 0 | L59: =(L58)*(1+B3Ret) -> 0 | M59: =(M58)*(1+B1Ret)-($D$9*12*(1+Inflation)^(A59-1)) -> 1.8182932e+08 | N59: =(N58)*(1+B2Ret) -> 0 | O59: =(O58)*(1+B3Ret) -> 1.1190537e+09
A60: 47 | B60: =Age+A60-1 -> 108 | C60: =J60+K60+L60 -> -1.2632742e+09 | D60: =C60/(1+Inflation)^A60 -> -52536371 | E60: =IF(C60>0,"OK","OUT OF MONEY") -> OUT OF MONEY | F60: =M60+N60+O60 -> 1.398953e+09 | G60: =F60/(1+Inflation)^A60 -> 58178909 | H60: =IF(F60>0,"OK","OUT OF MONEY") -> OK | J60: =(J59)*(1+B1Ret)-($D$8*12*(1+Inflation)^(A60-1)) -> -1.2632742e+09 | K60: =(K59)*(1+B2Ret) -> 0 | L60: =(L59)*(1+B3Ret) -> 0 | M60: =(M59)*(1+B1Ret)-($D$9*12*(1+Inflation)^(A60-1)) -> 1.5680337e+08 | N60: =(N59)*(1+B2Ret) -> 0 | O60: =(O59)*(1+B3Ret) -> 1.2421496e+09
