Workbook
Name d: OFFSET([1]DATA!$M$3,,,COUNTIF([1]DATA!$M$1:$M$65536,"?*"))
Name DRIVER: 'DATA '!$AH$1:$AH$2
Name PLANT: 'DATA '!$AG$1:$AG$3

Sheet OTHER PLANT ATTN.
A1: ='RJ ATTENDENCE SHEET'!A1 -> 46204 | D1: 1 | E1: 2 | F1: 3 | G1: 4 | H1: 5 | I1: 6 | J1: 7 | K1: 8 | L1: 9 | M1: 10 | N1: 11 | O1: 12 | P1: 13 | Q1: 14 | R1: 15 | S1: 16 | T1: 17 | U1: 18 | V1: 19 | W1: 20 | X1: 21 | Y1: 22 | Z1: 23 | AA1: 24 | AB1: 25 | AC1: 26 | AD1: 27 | AE1: 28 | AF1: 29 | AG1: 30 | AH1: 31
A2: PLANT | B2: CATEGORY | C2: RAJARHAT / JALAN TRIP | D2: 1 | E2: 2 | F2: 3 | G2: 4 | H2: 5 | I2: 6 | J2: 7 | K2: 8 | L2: 9 | M2: 10 | N2: 11 | O2: 12 | P2: 13 | Q2: 14 | R2: 15 | S2: 16 | T2: 17 | U2: 18 | V2: 19 | W2: 20 | X2: 21 | Y2: 22 | Z2: 23 | AA2: 24 | AB2: 25 | AC2: 26 | AD2: 27 | AE2: 28 | AF2: 29 | AG2: 30 | AH2: 31
A3: TARATALA | B3: DRIVER | C3: MANOJ | E3: 1
A4: TARATALA | B4: DRIVER
A5: TARATALA | B5: DRIVER | C5: TAPAS | F5: 2 | G5: 2 | J5: 1
A6: TARATALA | B6: HELPER | C6: KRISH | E6: 1
A7: TARATALA | B7: HELPER | C7: KHAIRUL | G7: 1 | H7: 2 | I7: 3 | J7: 1
A8: TARATALA | B8: HELPER | C8: SAJAN
A9: TARATALA | B9: DRIVER | C9: GIASUDDIN | F9: 1 | H9: 2 | I9: 3
A10: JALAN | B10: DRIVER | C10: RAKESH | I10: 2
A11: TARATALA | B11: DRIVER | C11: ANSAR | I11: 2
A12: TARATALA | B12: DRIVER | C12: RANJIT
A13: TARATALA | B13: HELPER | C13: KAPIL | I13: 2
A14: TARATALA | B14: HELPER | C14: RINTU
A15: TARATALA | B15: HELPER | C15: RABIN
A16: JALAN | B16: HELPER | C16: MITHUN | I16: 2
A17: JALAN | B17: HELPER | C17: RAMU | I17: 1
A18: JALAN | B18: DRIVER | C18: TAPAS | I18: 1
A19: TARATALA | B19: DRIVER | C19: SANJOY
A20: TARATALA | B20: DRIVER | C20: ASIT
A21: TARATALA | B21: HELPER | C21: BIJOY
A22: TARATALA | B22: HELPER | C22: LOUL
A23: TARATALA | B23: HELPER | C23: SAMIR BARMAN
A24: TARATALA | B24: DRIVER | C24: ROBIUL
A25: TARATALA | B25: HELPER | C25: SALEK
A26: TARATALA | B26: DRIVER | C26: HASAN
A27: TARATALA | B27: HELPER | C27: ASISH
A28: TARATALA | B28: DRIVER | C28: LALJI
A29: TARATALA | B29: DRIVER | C29: TAPAS
A30: JALAN | B30: DRIVER | C30: CHORUA
... A58: TARATALA | B58: DRIVER | C58: SABIR

Sheet DATA 
C1: ='RJ ATTENDENCE SHEET'!B:B -> 0 | D1: ='RJ ATTENDENCE SHEET'!C:C -> 0 | E1: =C1 -> 0 | X1: ='OTHER PLANT ATTN.'!C:C -> 0 | AC1: SALARY | AD1: WAGES | AE1: CONTRACT | AG1: RAJARHAT | AH1: DRIVER
C2: ='RJ ATTENDENCE SHEET'!B:B -> SUB-CATEGORY | D2: ='RJ ATTENDENCE SHEET'!C:C -> NAME | E2: =C2 -> SUB-CATEGORY | F2: SALARY | I2: WAGES | M2: CONTRACT | Q2: SALARY | T2: SALARY | X2: ='OTHER PLANT ATTN.'!C:C -> RAJARHAT / JALAN TRIP | Y2: =Table1[[#This Row],[CATEGORY ]] -> #VALUE! | Z2: =Table1[[#This Row],[PLANT]] -> #VALUE! | AB2: SALARY | AC2: OFFICE | AD2: LAB | AE2: LAB | AG2: JALAN | AH2: HELPER
A3: =CONCATENATE(B3,C3,D3) -> SALARYOFFICEABED ALI | B3: =Table4[[#This Row],[CATEGORY]] -> SALARY | C3: =Table4[[#This Row],[SUB-CATEGORY]] -> OFFICE | D3: ='RJ ATTENDENCE SHEET'!C:C -> ABED ALI | E3: =C3 -> OFFICE | F3: =IFERROR(SEARCH("SALARYOFFICE",$A:$A),"") -> 1 | G3: =IFERROR(IF(F3=0,"",COUNTIF($F$3:F3,">0")),"") -> 1 | H3: =IFERROR(VLOOKUP(INDEX($A:$A,MATCH(ROW(F1),G:G,0)),$A:$D,4,0),"") -> ABED ALI | I3: =IFERROR(SEARCH("WAGES",$A:$A),"") | J3: =IFERROR(IF(I3=0,"",COUNTIF($I$3:I3,">0")),"") -> 0 | K3: =IFERROR(VLOOKUP(INDEX($A:$A,MATCH(ROW(I1),J:J,0)),$A:$D,4,0),"") -> ANISUR | L3: =IFERROR(VLOOKUP(K3,$D:$E,2,0),"") -> DRIVER | M3: =IFERROR(SEARCH("CONTRACT",$A:$A),"") | N3: =IFERROR(IF(M3=0,"",COUNTIF($M$3:M3,">0")),"") -> 0 | O3: =IFERROR(VLOOKUP(INDEX($A:$A,MATCH(ROW(M1),N:N,0)),$A:$D,4,0),"") -> AMIT BISWAS | P3: =IFERROR(VLOOKUP(O3,$D:$E,2,0),"") -> HELPER | Q3: =IFERROR(SEARCH("SALARY",$A:$A),"") -> 1 | R3: =IFERROR(IF(Q3=0,"",COUNTIF($Q$3:Q3,">0")),"") -> 1 | S3: =IFERROR(VLOOKUP(INDEX($A:$A,MATCH(ROW(Q1),R:R,0)),$A:$D,4,0),"") -> ABED ALI | T3: =IFERROR(SEARCH("OTHERS0",$A:$A),"") | U3: =IFERROR(IF(T3=0,"",COUNTIF($T$3:T3,">0")),"") -> 0 | V3: =IFERROR(VLOOKUP(INDEX($A:$A,MATCH(ROW(T1),U:U,0)),$A:$D,4,0),"") | W3: =CONCATENATE(Z3,Y3,X3) -> TARATALADRIVERMANOJ | X3: ='OTHER PLANT ATTN.'!C:C -> MANOJ | Y3: =Table1[[#This Row],[CATEGORY ]] -> DRIVER | Z3: =Table1[[#This Row],[PLANT]] -> TARATALA | AA3: =DAY(WHATSAPP!$K$4) -> 21 | AB3: WAGES | AC3: OTHERS | AD3: DRIVER | AE3: DRIVER | AG3: TARATALA
A4: =CONCATENATE(B4,C4,D4) -> SALARYOFFICEABHI MUKHERJEE | B4: =Table4[[#This Row],[CATEGORY]] -> SALARY | C4: =Table4[[#This Row],[SUB-CATEGORY]] -> OFFICE | D4: ='RJ ATTENDENCE SHEET'!C:C -> ABHI MUKHERJEE | E4: =C4 -> OFFICE | F4: =IFERROR(SEARCH("SALARYOFFICE",$A:$A),"") -> 1 | G4: =IFERROR(IF(F4=0,"",COUNTIF($F$3:F4,">0")),"") -> 2 | H4: =IFERROR(VLOOKUP(INDEX($A:$A,MATCH(ROW(F2),G:G,0)),$A:$D,4,0),"") -> ABHI MUKHERJEE | I4: =IFERROR(SEARCH("WAGES",$A:$A),"") | J4: =IFERROR(IF(I4=0,"",COUNTIF($I$3:I4,">0")),"") -> 0 | K4: =IFERROR(VLOOKUP(INDEX($A:$A,MATCH(ROW(I2),J:J,0)),$A:$D,4,0),"") -> ARMAN ALI MONDAL | L4: =IFERROR(VLOOKUP(K4,$D:$E,2,0),"") -> DRIVER | M4: =IFERROR(SEARCH("CONTRACT",$A:$A),"") | N4: =IFERROR(IF(M4=0,"",COUNTIF($M$3:M4,">0")),"") -> 0 | O4: =IFERROR(VLOOKUP(INDEX($A:$A,MATCH(ROW(M2),N:N,0)),$A:$D,4,0),"") -> JHANTU MONDAL | P4: =IFERROR(VLOOKUP(O4,$D:$E,2,0),"") -> HELPER | Q4: =IFERROR(SEARCH("SALARY",$A:$A),"") -> 1 | R4: =IFERROR(IF(Q4=0,"",COUNTIF($Q$3:Q4,">0")),"") -> 2 | S4: =IFERROR(VLOOKUP(INDEX($A:$A,MATCH(ROW(Q2),R:R,0)),$A:$D,4,0),"") -> ABHI MUKHERJEE | T4: =IFERROR(SEARCH("OTHERS0",$A:$A),"") | U4: =IFERROR(IF(T4=0,"",COUNTIF($T$3:T4,">0")),"") -> 0 | V4: =IFERROR(VLOOKUP(INDEX($A:$A,MATCH(ROW(T2),U:U,0)),$A:$D,4,0),"") | W4: =CONCATENATE(Z4,Y4,X4) -> TARATALADRIVER0 | X4: ='OTHER PLANT ATTN.'!C:C -> 0 | Y4: =Table1[[#This Row],[CATEGORY ]] -> DRIVER | Z4: =Table1[[#This Row],[PLANT]] -> TARATALA | AB4: CONTRACT | AD4: HELPER | AE4: HELPER
A5: =CONCATENATE(B5,C5,D5) -> SALARYOFFICEACHIN GUPTA | B5: =Table4[[#This Row],[CATEGORY]] -> SALARY | C5: =Table4[[#This Row],[SUB-CATEGORY]] -> OFFICE | D5: ='RJ ATTENDENCE SHEET'!C:C -> ACHIN GUPTA | E5: =C5 -> OFFICE | F5: =IFERROR(SEARCH("SALARYOFFICE",$A:$A),"") -> 1 | G5: =IFERROR(IF(F5=0,"",COUNTIF($F$3:F5,">0")),"") -> 3 | H5: =IFERROR(VLOOKUP(INDEX($A:$A,MATCH(ROW(F3),G:G,0)),$A:$D,4,0),"") -> ACHIN GUPTA | I5: =IFERROR(SEARCH("WAGES",$A:$A),"") | J5: =IFERROR(IF(I5=0,"",COUNTIF($I$3:I5,">0")),"") -> 0 | K5: =IFERROR(VLOOKUP(INDEX($A:$A,MATCH(ROW(I3),J:J,0)),$A:$D,4,0),"") -> ASUTOSH SARDAR | L5: =IFERROR(VLOOKUP(K5,$D:$E,2,0),"") -> HELPER | M5: =IFERROR(SEARCH("CONTRACT",$A:$A),"") | N5: =IFERROR(IF(M5=0,"",COUNTIF($M$3:M5,">0")),"") -> 0 | O5: =IFERROR(VLOOKUP(INDEX($A:$A,MATCH(ROW(M3),N:N,0)),$A:$D,4,0),"") -> ASHIT BISWAS | P5: =IFERROR(VLOOKUP(O5,$D:$E,2,0),"") -> DRIVER | Q5: =IFERROR(SEARCH("SALARY",$A:$A),"") -> 1 | R5: =IFERROR(IF(Q5=0,"",COUNTIF($Q$3:Q5,">0")),"") -> 3 | S5: =IFERROR(VLOOKUP(INDEX($A:$A,MATCH(ROW(Q3),R:R,0)),$A:$D,4,0),"") -> ACHIN GUPTA | T5: =IFERROR(SEARCH("OTHERS0",$A:$A),"") | U5: =IFERROR(IF(T5=0,"",COUNTIF($T$3:T5,">0")),"") -> 0 | V5: =IFERROR(VLOOKUP(INDEX($A:$A,MATCH(ROW(T3),U:U,0)),$A:$D,4,0),"") | W5: =CONCATENATE(Z5,Y5,X5) -> TARATALADRIVERTAPAS | X5: ='OTHER PLANT ATTN.'!C:C -> TAPAS | Y5: =Table1[[#This Row],[CATEGORY ]] -> DRIVER | Z5: =Table1[[#This Row],[PLANT]] -> TARATALA | AD5: HOPPER | AE5: HOPPER
A6: =CONCATENATE(B6,C6,D6) -> SALARYOFFICEAMIN YADAV | B6: =Table4[[#This Row],[CATEGORY]] -> SALARY | C6: =Table4[[#This Row],[SUB-CATEGORY]] -> OFFICE | D6: ='RJ ATTENDENCE SHEET'!C:C -> AMIN YADAV | E6: =C6 -> OFFICE | F6: =IFERROR(SEARCH("SALARYOFFICE",$A:$A),"") -> 1 | G6: =IFERROR(IF(F6=0,"",COUNTIF($F$3:F6,">0")),"") -> 4 | H6: =IFERROR(VLOOKUP(INDEX($A:$A,MATCH(ROW(F4),G:G,0)),$A:$D,4,0),"") -> AMIN YADAV | I6: =IFERROR(SEARCH("WAGES",$A:$A),"") | J6: =IFERROR(IF(I6=0,"",COUNTIF($I$3:I6,">0")),"") -> 0 | K6: =IFERROR(VLOOKUP(INDEX($A:$A,MATCH(ROW(I4),J:J,0)),$A:$D,4,0),"") -> BUDDHADEV SEAL | L6: =IFERROR(VLOOKUP(K6,$D:$E,2,0),"") -> LAB | M6: =IFERROR(SEARCH("CONTRACT",$A:$A),"") | N6: =IFERROR(IF(M6=0,"",COUNTIF($M$3:M6,">0")),"") -> 0 | O6: =IFERROR(VLOOKUP(INDEX($A:$A,MATCH(ROW(M4),N:N,0)),$A:$D,4,0),"") -> NASIB KARIKAR | P6: =IFERROR(VLOOKUP(O6,$D:$E,2,0),"") -> HELPER | Q6: =IFERROR(SEARCH("SALARY",$A:$A),"") -> 1 | R6: =IFERROR(IF(Q6=0,"",COUNTIF($Q$3:Q6,">0")),"") -> 4 | S6: =IFERROR(VLOOKUP(INDEX($A:$A,MATCH(ROW(Q4),R:R,0)),$A:$D,4,0),"") -> AMIN YADAV | T6: =IFERROR(SEARCH("OTHERS0",$A:$A),"") | U6: =IFERROR(IF(T6=0,"",COUNTIF($T$3:T6,">0")),"") -> 0 | V6: =IFERROR(VLOOKUP(INDEX($A:$A,MATCH(ROW(T4),U:U,0)),$A:$D,4,0),"") | W6: =CONCATENATE(Z6,Y6,X6) -> TARATALAHELPERKRISH | X6: ='OTHER PLANT ATTN.'!C:C -> KRISH | Y6: =Table1[[#This Row],[CATEGORY ]] -> HELPER | Z6: =Table1[[#This Row],[PLANT]] -> TARATALA | AD6: OTHERS | AE6: OTHERS
A7: =CONCATENATE(B7,C7,D7) -> CONTRACTHELPERAMIT BISWAS | B7: =Table4[[#This Row],[CATEGORY]] -> CONTRACT | C7: =Table4[[#This Row],[SUB-CATEGORY]] -> HELPER | D7: ='RJ ATTENDENCE SHEET'!C:C -> AMIT BISWAS | E7: =C7 -> HELPER | F7: =IFERROR(SEARCH("SALARYOFFICE",$A:$A),"") | G7: =IFERROR(IF(F7=0,"",COUNTIF($F$3:F7,">0")),"") -> 4 | H7: =IFERROR(VLOOKUP(INDEX($A:$A,MATCH(ROW(F5),G:G,0)),$A:$D,4,0),"") -> ANOWAR MOLLA | I7: =IFERROR(SEARCH("WAGES",$A:$A),"") | J7: =IFERROR(IF(I7=0,"",COUNTIF($I$3:I7,">0")),"") -> 0 | K7: =IFERROR(VLOOKUP(INDEX($A:$A,MATCH(ROW(I5),J:J,0)),$A:$D,4,0),"") -> FARUK ALI | L7: =IFERROR(VLOOKUP(K7,$D:$E,2,0),"") -> DRIVER | M7: =IFERROR(SEARCH("CONTRACT",$A:$A),"") -> 1 | N7: =IFERROR(IF(M7=0,"",COUNTIF($M$3:M7,">0")),"") -> 1 | O7: =IFERROR(VLOOKUP(INDEX($A:$A,MATCH(ROW(M5),N:N,0)),$A:$D,4,0),"") -> BASIRUDDIN KHAN | P7: =IFERROR(VLOOKUP(O7,$D:$E,2,0),"") -> OTHERS | Q7: =IFERROR(SEARCH("SALARY",$A:$A),"") | R7: =IFERROR(IF(Q7=0,"",COUNTIF($Q$3:Q7,">0")),"") -> 4 | S7: =IFERROR(VLOOKUP(INDEX($A:$A,MATCH(ROW(Q5),R:R,0)),$A:$D,4,0),"") -> ANOWAR MOLLA | T7: =IFERROR(SEARCH("OTHERS0",$A:$A),"") | U7: =IFERROR(IF(T7=0,"",COUNTIF($T$3:T7,">0")),"") -> 0 | V7: =IFERROR(VLOOKUP(INDEX($A:$A,MATCH(ROW(T5),U:U,0)),$A:$D,4,0),"") | W7: =CONCATENATE(Z7,Y7,X7) -> TARATALAHELPERKHAIRUL | X7: ='OTHER PLANT ATTN.'!C:C -> KHAIRUL | Y7: =Table1[[#This Row],[CATEGORY ]] -> HELPER | Z7: =Table1[[#This Row],[PLANT]] -> TARATALA
A8: =CONCATENATE(B8,C8,D8) -> WAGESDRIVERANISUR | B8: =Table4[[#This Row],[CATEGORY]] -> WAGES | C8: =Table4[[#This Row],[SUB-CATEGORY]] -> DRIVER | D8: ='RJ ATTENDENCE SHEET'!C:C -> ANISUR | E8: =C8 -> DRIVER | F8: =IFERROR(SEARCH("SALARYOFFICE",$A:$A),"") | G8: =IFERROR(IF(F8=0,"",COUNTIF($F$3:F8,">0")),"") -> 4 | H8: =IFERROR(VLOOKUP(INDEX($A:$A,MATCH(ROW(F6),G:G,0)),$A:$D,4,0),"") -> DIBAKAR MONDAL | I8: =IFERROR(SEARCH("WAGES",$A:$A),"") -> 1 | J8: =IFERROR(IF(I8=0,"",COUNTIF($I$3:I8,">0")),"") -> 1 | K8: =IFERROR(VLOOKUP(INDEX($A:$A,MATCH(ROW(I6),J:J,0)),$A:$D,4,0),"") -> KUTUBUDDIN MOLLA | L8: =IFERROR(VLOOKUP(K8,$D:$E,2,0),"") -> HOPPER | M8: =IFERROR(SEARCH("CONTRACT",$A:$A),"") | N8: =IFERROR(IF(M8=0,"",COUNTIF($M$3:M8,">0")),"") -> 1 | O8: =IFERROR(VLOOKUP(INDEX($A:$A,MATCH(ROW(M6),N:N,0)),$A:$D,4,0),"") -> DIN MOHAMMOD ALI | P8: =IFERROR(VLOOKUP(O8,$D:$E,2,0),"") -> DRIVER | Q8: =IFERROR(SEARCH("SALARY",$A:$A),"") | R8: =IFERROR(IF(Q8=0,"",COUNTIF($Q$3:Q8,">0")),"") -> 4 | S8: =IFERROR(VLOOKUP(INDEX($A:$A,MATCH(ROW(Q6),R:R,0)),$A:$D,4,0),"") -> DIBAKAR MONDAL | T8: =IFERROR(SEARCH("OTHERS0",$A:$A),"") | U8: =IFERROR(IF(T8=0,"",COUNTIF($T$3:T8,">0")),"") -> 0 | V8: =IFERROR(VLOOKUP(INDEX($A:$A,MATCH(ROW(T6),U:U,0)),$A:$D,4,0),"") | W8: =CONCATENATE(Z8,Y8,X8) -> TARATALAHELPERSAJAN | X8: ='OTHER PLANT ATTN.'!C:C -> SAJAN | Y8: =Table1[[#This Row],[CATEGORY ]] -> HELPER | Z8: =Table1[[#This Row],[PLANT]] -> TARATALA
A9: =CONCATENATE(B9,C9,D9) -> SALARYOFFICEANOWAR MOLLA | B9: =Table4[[#This Row],[CATEGORY]] -> SALARY | C9: =Table4[[#This Row],[SUB-CATEGORY]] -> OFFICE | D9: ='RJ ATTENDENCE SHEET'!C:C -> ANOWAR MOLLA | E9: =C9 -> OFFICE | F9: =IFERROR(SEARCH("SALARYOFFICE",$A:$A),"") -> 1 | G9: =IFERROR(IF(F9=0,"",COUNTIF($F$3:F9,">0")),"") -> 5 | H9: =IFERROR(VLOOKUP(INDEX($A:$A,MATCH(ROW(F7),G:G,0)),$A:$D,4,0),"") -> GOLAM SARWAR | I9: =IFERROR(SEARCH("WAGES",$A:$A),"") | J9: =IFERROR(IF(I9=0,"",COUNTIF($I$3:I9,">0")),"") -> 1 | K9: =IFERROR(VLOOKUP(INDEX($A:$A,MATCH(ROW(I7),J:J,0)),$A:$D,4,0),"") -> MD. SAMIM AKRAM | L9: =IFERROR(VLOOKUP(K9,$D:$E,2,0),"") -> OTHERS | M9: =IFERROR(SEARCH("CONTRACT",$A:$A),"") | N9: =IFERROR(IF(M9=0,"",COUNTIF($M$3:M9,">0")),"") -> 1 | O9: =IFERROR(VLOOKUP(INDEX($A:$A,MATCH(ROW(M7),N:N,0)),$A:$D,4,0),"") -> RAFIQUE MOLLA | P9: =IFERROR(VLOOKUP(O9,$D:$E,2,0),"") -> DRIVER | Q9: =IFERROR(SEARCH("SALARY",$A:$A),"") -> 1 | R9: =IFERROR(IF(Q9=0,"",COUNTIF($Q$3:Q9,">0")),"") -> 5 | S9: =IFERROR(VLOOKUP(INDEX($A:$A,MATCH(ROW(Q7),R:R,0)),$A:$D,4,0),"") -> GOLAM SARWAR | T9: =IFERROR(SEARCH("OTHERS0",$A:$A),"") | U9: =IFERROR(IF(T9=0,"",COUNTIF($T$3:T9,">0")),"") -> 0 | V9: =IFERROR(VLOOKUP(INDEX($A:$A,MATCH(ROW(T7),U:U,0)),$A:$D,4,0),"") | W9: =CONCATENATE(Z9,Y9,X9) -> TARATALADRIVERGIASUDDIN | X9: ='OTHER PLANT ATTN.'!C:C -> GIASUDDIN | Y9: =Table1[[#This Row],[CATEGORY ]] -> DRIVER | Z9: =Table1[[#This Row],[PLANT]] -> TARATALA
A10: =CONCATENATE(B10,C10,D10) -> WAGESDRIVERARMAN ALI MONDAL | B10: =Table4[[#This Row],[CATEGORY]] -> WAGES | C10: =Table4[[#This Row],[SUB-CATEGORY]] -> DRIVER | D10: ='RJ ATTENDENCE SHEET'!C:C -> ARMAN ALI MONDAL | E10: =C10 -> DRIVER | F10: =IFERROR(SEARCH("SALARYOFFICE",$A:$A),"") | G10: =IFERROR(IF(F10=0,"",COUNTIF($F$3:F10,">0")),"") -> 5 | H10: =IFERROR(VLOOKUP(INDEX($A:$A,MATCH(ROW(F8),G:G,0)),$A:$D,4,0),"") -> IMAN ALI MOLLA | I10: =IFERROR(SEARCH("WAGES",$A:$A),"") -> 1 | J10: =IFERROR(IF(I10=0,"",COUNTIF($I$3:I10,">0")),"") -> 2 | K10: =IFERROR(VLOOKUP(INDEX($A:$A,MATCH(ROW(I8),J:J,0)),$A:$D,4,0),"") -> MOTIAR RAHAMAN | L10: =IFERROR(VLOOKUP(K10,$D:$E,2,0),"") -> DRIVER | M10: =IFERROR(SEARCH("CONTRACT",$A:$A),"") | N10: =IFERROR(IF(M10=0,"",COUNTIF($M$3:M10,">0")),"") -> 1 | O10: =IFERROR(VLOOKUP(INDEX($A:$A,MATCH(ROW(M8),N:N,0)),$A:$D,4,0),"") -> RAFIKUL MOLLA | P10: =IFERROR(VLOOKUP(O10,$D:$E,2,0),"") -> HELPER | Q10: =IFERROR(SEARCH("SALARY",$A:$A),"") | R10: =IFERROR(IF(Q10=0,"",COUNTIF($Q$3:Q10,">0")),"") -> 5 | S10: =IFERROR(VLOOKUP(INDEX($A:$A,MATCH(ROW(Q8),R:R,0)),$A:$D,4,0),"") -> IMAN ALI MOLLA | T10: =IFERROR(SEARCH("OTHERS0",$A:$A),"") | U10: =IFERROR(IF(T10=0,"",COUNTIF($T$3:T10,">0")),"") -> 0 | V10: =IFERROR(VLOOKUP(INDEX($A:$A,MATCH(ROW(T8),U:U,0)),$A:$D,4,0),"") | W10: =CONCATENATE(Z10,Y10,X10) -> JALANDRIVERRAKESH | X10: ='OTHER PLANT ATTN.'!C:C -> RAKESH | Y10: =Table1[[#This Row],[CATEGORY ]] -> DRIVER | Z10: =Table1[[#This Row],[PLANT]] -> JALAN
A11: =CONCATENATE(B11,C11,D11) -> CONTRACTHELPERJHANTU MONDAL | B11: =Table4[[#This Row],[CATEGORY]] -> CONTRACT | C11: =Table4[[#This Row],[SUB-CATEGORY]] -> HELPER | D11: ='RJ ATTENDENCE SHEET'!C:C -> JHANTU MONDAL | E11: =C11 -> HELPER | F11: =IFERROR(SEARCH("SALARYOFFICE",$A:$A),"") | G11: =IFERROR(IF(F11=0,"",COUNTIF($F$3:F11,">0")),"") -> 5 | H11: =IFERROR(VLOOKUP(INDEX($A:$A,MATCH(ROW(F9),G:G,0)),$A:$D,4,0),"") -> PULIN MONDAL | I11: =IFERROR(SEARCH("WAGES",$A:$A),"") | J11: =IFERROR(IF(I11=0,"",COUNTIF($I$3:I11,">0")),"") -> 2 | K11: =IFERROR(VLOOKUP(INDEX($A:$A,MATCH(ROW(I9),J:J,0)),$A:$D,4,0),"") -> MOKSHED ALI | L11: =IFERROR(VLOOKUP(K11,$D:$E,2,0),"") -> DRIVER | M11: =IFERROR(SEARCH("CONTRACT",$A:$A),"") -> 1 | N11: =IFERROR(IF(M11=0,"",COUNTIF($M$3:M11,">0")),"") -> 2 | O11: =IFERROR(VLOOKUP(INDEX($A:$A,MATCH(ROW(M9),N:N,0)),$A:$D,4,0),"") -> AYAN PAUL | P11: =IFERROR(VLOOKUP(O11,$D:$E,2,0),"") -> OTHERS | Q11: =IFERROR(SEARCH("SALARY",$A:$A),"") | R11: =IFERROR(IF(Q11=0,"",COUNTIF($Q$3:Q11,">0")),"") -> 5 | S11: =IFERROR(VLOOKUP(INDEX($A:$A,MATCH(ROW(Q9),R:R,0)),$A:$D,4,0),"") -> PULIN MONDAL | T11: =IFERROR(SEARCH("OTHERS0",$A:$A),"") | U11: =IFERROR(IF(T11=0,"",COUNTIF($T$3:T11,">0")),"") -> 0 | V11: =IFERROR(VLOOKUP(INDEX($A:$A,MATCH(ROW(T9),U:U,0)),$A:$D,4,0),"") | W11: =CONCATENATE(Z11,Y11,X11) -> TARATALADRIVERANSAR | X11: ='OTHER PLANT ATTN.'!C:C -> ANSAR | Y11: =Table1[[#This Row],[CATEGORY ]] -> DRIVER | Z11: =Table1[[#This Row],[PLANT]] -> TARATALA
A12: =CONCATENATE(B12,C12,D12) -> CONTRACTDRIVERASHIT BISWAS | B12: =Table4[[#This Row],[CATEGORY]] -> CONTRACT | C12: =Table4[[#This Row],[SUB-CATEGORY]] -> DRIVER | D12: ='RJ ATTENDENCE SHEET'!C:C -> ASHIT BISWAS | E12: =C12 -> DRIVER | F12: =IFERROR(SEARCH("SALARYOFFICE",$A:$A),"") | G12: =IFERROR(IF(F12=0,"",COUNTIF($F$3:F12,">0")),"") -> 5 | H12: =IFERROR(VLOOKUP(INDEX($A:$A,MATCH(ROW(F10),G:G,0)),$A:$D,4,0),"") -> RAJU PAL | I12: =IFERROR(SEARCH("WAGES",$A:$A),"") | J12: =IFERROR(IF(I12=0,"",COUNTIF($I$3:I12,">0")),"") -> 2 | K12: =IFERROR(VLOOKUP(INDEX($A:$A,MATCH(ROW(I10),J:J,0)),$A:$D,4,0),"") -> SAMSER ALI | L12: =IFERROR(VLOOKUP(K12,$D:$E,2,0),"") -> DRIVER | M12: =IFERROR(SEARCH("CONTRACT",$A:$A),"") -> 1 | N12: =IFERROR(IF(M12=0,"",COUNTIF($M$3:M12,">0")),"") -> 3 | O12: =IFERROR(VLOOKUP(INDEX($A:$A,MATCH(ROW(M10),N:N,0)),$A:$D,4,0),"") -> NAYAN MONDAL | P12: =IFERROR(VLOOKUP(O12,$D:$E,2,0),"") -> HELPER | Q12: =IFERROR(SEARCH("SALARY",$A:$A),"") | R12: =IFERROR(IF(Q12=0,"",COUNTIF($Q$3:Q12,">0")),"") -> 5 | S12: =IFERROR(VLOOKUP(INDEX($A:$A,MATCH(ROW(Q10),R:R,0)),$A:$D,4,0),"") -> RAJU PAL | T12: =IFERROR(SEARCH("OTHERS0",$A:$A),"") | U12: =IFERROR(IF(T12=0,"",COUNTIF($T$3:T12,">0")),"") -> 0 | V12: =IFERROR(VLOOKUP(INDEX($A:$A,MATCH(ROW(T10),U:U,0)),$A:$D,4,0),"") | W12: =CONCATENATE(Z12,Y12,X12) -> TARATALADRIVERRANJIT | X12: ='OTHER PLANT ATTN.'!C:C -> RANJIT | Y12: =Table1[[#This Row],[CATEGORY ]] -> DRIVER | Z12: =Table1[[#This Row],[PLANT]] -> TARATALA
A13: =CONCATENATE(B13,C13,D13) -> WAGESHELPERASUTOSH SARDAR | B13: =Table4[[#This Row],[CATEGORY]] -> WAGES | C13: =Table4[[#This Row],[SUB-CATEGORY]] -> HELPER | D13: ='RJ ATTENDENCE SHEET'!C:C -> ASUTOSH SARDAR | E13: =C13 -> HELPER | F13: =IFERROR(SEARCH("SALARYOFFICE",$A:$A),"") | G13: =IFERROR(IF(F13=0,"",COUNTIF($F$3:F13,">0")),"") -> 5 | H13: =IFERROR(VLOOKUP(INDEX($A:$A,MATCH(ROW(F11),G:G,0)),$A:$D,4,0),"") -> UJJAL MUKHERJEE | I13: =IFERROR(SEARCH("WAGES",$A:$A),"") -> 1 | J13: =IFERROR(IF(I13=0,"",COUNTIF($I$3:I13,">0")),"") -> 3 | K13: =IFERROR(VLOOKUP(INDEX($A:$A,MATCH(ROW(I11),J:J,0)),$A:$D,4,0),"") -> SHANTI MONDAL | L13: =IFERROR(VLOOKUP(K13,$D:$E,2,0),"") -> DRIVER | M13: =IFERROR(SEARCH("CONTRACT",$A:$A),"") | N13: =IFERROR(IF(M13=0,"",COUNTIF($M$3:M13,">0")),"") -> 3 | O13: =IFERROR(VLOOKUP(INDEX($A:$A,MATCH(ROW(M11),N:N,0)),$A:$D,4,0),"") -> SHIB SANKAR MAJHI | P13: =IFERROR(VLOOKUP(O13,$D:$E,2,0),"") -> OTHERS | Q13: =IFERROR(SEARCH("SALARY",$A:$A),"") | R13: =IFERROR(IF(Q13=0,"",COUNTIF($Q$3:Q13,">0")),"") -> 5 | S13: =IFERROR(VLOOKUP(INDEX($A:$A,MATCH(ROW(Q11),R:R,0)),$A:$D,4,0),"") -> UJJAL MUKHERJEE | T13: =IFERROR(SEARCH("OTHERS0",$A:$A),"") | U13: =IFERROR(IF(T13=0,"",COUNTIF($T$3:T13,">0")),"") -> 0 | V13: =IFERROR(VLOOKUP(INDEX($A:$A,MATCH(ROW(T11),U:U,0)),$A:$D,4,0),"") | W13: =CONCATENATE(Z13,Y13,X13) -> TARATALAHELPERKAPIL | X13: ='OTHER PLANT ATTN.'!C:C -> KAPIL | Y13: =Table1[[#This Row],[CATEGORY ]] -> HELPER | Z13: =Table1[[#This Row],[PLANT]] -> TARATALA
A14: =CONCATENATE(B14,C14,D14) -> CONTRACTHELPERNASIB KARIKAR | B14: =Table4[[#This Row],[CATEGORY]] -> CONTRACT | C14: =Table4[[#This Row],[SUB-CATEGORY]] -> HELPER | D14: ='RJ ATTENDENCE SHEET'!C:C -> NASIB KARIKAR | E14: =C14 -> HELPER | F14: =IFERROR(SEARCH("SALARYOFFICE",$A:$A),"") | G14: =IFERROR(IF(F14=0,"",COUNTIF($F$3:F14,">0")),"") -> 5 | H14: =IFERROR(VLOOKUP(INDEX($A:$A,MATCH(ROW(F12),G:G,0)),$A:$D,4,0),"") -> PROBIR GHOSH | I14: =IFERROR(SEARCH("WAGES",$A:$A),"") | J14: =IFERROR(IF(I14=0,"",COUNTIF($I$3:I14,">0")),"") -> 3 | K14: =IFERROR(VLOOKUP(INDEX($A:$A,MATCH(ROW(I12),J:J,0)),$A:$D,4,0),"") -> SIRAJUL MOLLA | L14: =IFERROR(VLOOKUP(K14,$D:$E,2,0),"") -> DRIVER | M14: =IFERROR(SEARCH("CONTRACT",$A:$A),"") -> 1 | N14: =IFERROR(IF(M14=0,"",COUNTIF($M$3:M14,">0")),"") -> 4 | O14: =IFERROR(VLOOKUP(INDEX($A:$A,MATCH(ROW(M12),N:N,0)),$A:$D,4,0),"") -> ABUL KALAM AZAD | P14: =IFERROR(VLOOKUP(O14,$D:$E,2,0),"") -> OTHERS | Q14: =IFERROR(SEARCH("SALARY",$A:$A),"") | R14: =IFERROR(IF(Q14=0,"",COUNTIF($Q$3:Q14,">0")),"") -> 5 | S14: =IFERROR(VLOOKUP(INDEX($A:$A,MATCH(ROW(Q12),R:R,0)),$A:$D,4,0),"") -> PROBIR GHOSH | T14: =IFERROR(SEARCH("OTHERS0",$A:$A),"") | U14: =IFERROR(IF(T14=0,"",COUNTIF($T$3:T14,">0")),"") -> 0 | V14: =IFERROR(VLOOKUP(INDEX($A:$A,MATCH(ROW(T12),U:U,0)),$A:$D,4,0),"") | W14: =CONCATENATE(Z14,Y14,X14) -> TARATALAHELPERRINTU | X14: ='OTHER PLANT ATTN.'!C:C -> RINTU | Y14: =Table1[[#This Row],[CATEGORY ]] -> HELPER | Z14: =Table1[[#This Row],[PLANT]] -> TARATALA
A15: =CONCATENATE(B15,C15,D15) -> CONTRACTOTHERSBASIRUDDIN KHAN | B15: =Table4[[#This Row],[CATEGORY]] -> CONTRACT | C15: =Table4[[#This Row],[SUB-CATEGORY]] -> OTHERS | D15: ='RJ ATTENDENCE SHEET'!C:C -> BASIRUDDIN KHAN | E15: =C15 -> OTHERS | F15: =IFERROR(SEARCH("SALARYOFFICE",$A:$A),"") | G15: =IFERROR(IF(F15=0,"",COUNTIF($F$3:F15,">0")),"") -> 5 | H15: =IFERROR(VLOOKUP(INDEX($A:$A,MATCH(ROW(F13),G:G,0)),$A:$D,4,0),"") -> NABA KUMAR BISWAS | I15: =IFERROR(SEARCH("WAGES",$A:$A),"") | J15: =IFERROR(IF(I15=0,"",COUNTIF($I$3:I15,">0")),"") -> 3 | K15: =IFERROR(VLOOKUP(INDEX($A:$A,MATCH(ROW(I13),J:J,0)),$A:$D,4,0),"") -> SK. ANARUL ISLAM | L15: =IFERROR(VLOOKUP(K15,$D:$E,2,0),"") -> HELPER | M15: =IFERROR(SEARCH("CONTRACT",$A:$A),"") -> 1 | N15: =IFERROR(IF(M15=0,"",COUNTIF($M$3:M15,">0")),"") -> 5 | O15: =IFERROR(VLOOKUP(INDEX($A:$A,MATCH(ROW(M13),N:N,0)),$A:$D,4,0),"") -> SATYA NASKAR | P15: =IFERROR(VLOOKUP(O15,$D:$E,2,0),"") -> DRIVER | Q15: =IFERROR(SEARCH("SALARY",$A:$A),"") | R15: =IFERROR(IF(Q15=0,"",COUNTIF($Q$3:Q15,">0")),"") -> 5 | S15: =IFERROR(VLOOKUP(INDEX($A:$A,MATCH(ROW(Q13),R:R,0)),$A:$D,4,0),"") -> NABA KUMAR BISWAS | T15: =IFERROR(SEARCH("OTHERS0",$A:$A),"") | U15: =IFERROR(IF(T15=0,"",COUNTIF($T$3:T15,">0")),"") -> 0 | V15: =IFERROR(VLOOKUP(INDEX($A:$A,MATCH(ROW(T13),U:U,0)),$A:$D,4,0),"") | W15: =CONCATENATE(Z15,Y15,X15) -> TARATALAHELPERRABIN | X15: ='OTHER PLANT ATTN.'!C:C -> RABIN | Y15: =Table1[[#This Row],[CATEGORY ]] -> HELPER | Z15: =Table1[[#This Row],[PLANT]] -> TARATALA
A16: =CONCATENATE(B16,C16,D16) -> WAGESLABBUDDHADEV SEAL | B16: =Table4[[#This Row],[CATEGORY]] -> WAGES | C16: =Table4[[#This Row],[SUB-CATEGORY]] -> LAB | D16: ='RJ ATTENDENCE SHEET'!C:C -> BUDDHADEV SEAL | E16: =C16 -> LAB | F16: =IFERROR(SEARCH("SALARYOFFICE",$A:$A),"") | G16: =IFERROR(IF(F16=0,"",COUNTIF($F$3:F16,">0")),"") -> 5 | H16: =IFERROR(VLOOKUP(INDEX($A:$A,MATCH(ROW(F14),G:G,0)),$A:$D,4,0),"") -> ASIM KHUNTIA | I16: =IFERROR(SEARCH("WAGES",$A:$A),"") -> 1 | J16: =IFERROR(IF(I16=0,"",COUNTIF($I$3:I16,">0")),"") -> 4 | K16: =IFERROR(VLOOKUP(INDEX($A:$A,MATCH(ROW(I14),J:J,0)),$A:$D,4,0),"") -> SRISTI DHAR MONDAL | L16: =IFERROR(VLOOKUP(K16,$D:$E,2,0),"") -> HOPPER | M16: =IFERROR(SEARCH("CONTRACT",$A:$A),"") | N16: =IFERROR(IF(M16=0,"",COUNTIF($M$3:M16,">0")),"") -> 5 | O16: =IFERROR(VLOOKUP(INDEX($A:$A,MATCH(ROW(M14),N:N,0)),$A:$D,4,0),"") -> JAMSHED ALI | P16: =IFERROR(VLOOKUP(O16,$D:$E,2,0),"") -> HELPER | Q16: =IFERROR(SEARCH("SALARY",$A:$A),"") | R16: =IFERROR(IF(Q16=0,"",COUNTIF($Q$3:Q16,">0")),"") -> 5 | S16: =IFERROR(VLOOKUP(INDEX($A:$A,MATCH(ROW(Q14),R:R,0)),$A:$D,4,0),"") -> ASIM KHUNTIA | T16: =IFERROR(SEARCH("OTHERS0",$A:$A),"") | U16: =IFERROR(IF(T16=0,"",COUNTIF($T$3:T16,">0")),"") -> 0 | V16: =IFERROR(VLOOKUP(INDEX($A:$A,MATCH(ROW(T14),U:U,0)),$A:$D,4,0),"") | W16: =CONCATENATE(Z16,Y16,X16) -> JALANHELPERMITHUN | X16: ='OTHER PLANT ATTN.'!C:C -> MITHUN | Y16: =Table1[[#This Row],[CATEGORY ]] -> HELPER | Z16: =Table1[[#This Row],[PLANT]] -> JALAN
A17: =CONCATENATE(B17,C17,D17) -> SALARYOFFICEDIBAKAR MONDAL | B17: =Table4[[#This Row],[CATEGORY]] -> SALARY | C17: =Table4[[#This Row],[SUB-CATEGORY]] -> OFFICE | D17: ='RJ ATTENDENCE SHEET'!C:C -> DIBAKAR MONDAL | E17: =C17 -> OFFICE | F17: =IFERROR(SEARCH("SALARYOFFICE",$A:$A),"") -> 1 | G17: =IFERROR(IF(F17=0,"",COUNTIF($F$3:F17,">0")),"") -> 6 | H17: =IFERROR(VLOOKUP(INDEX($A:$A,MATCH(ROW(F15),G:G,0)),$A:$D,4,0),"") -> MANABINDU BISWAS | I17: =IFERROR(SEARCH("WAGES",$A:$A),"") | J17: =IFERROR(IF(I17=0,"",COUNTIF($I$3:I17,">0")),"") -> 4 | K17: =IFERROR(VLOOKUP(INDEX($A:$A,MATCH(ROW(I15),J:J,0)),$A:$D,4,0),"") -> SUDHAN MONDAL | L17: =IFERROR(VLOOKUP(K17,$D:$E,2,0),"") -> HOPPER | M17: =IFERROR(SEARCH("CONTRACT",$A:$A),"") | N17: =IFERROR(IF(M17=0,"",COUNTIF($M$3:M17,">0")),"") -> 5 | O17: =IFERROR(VLOOKUP(INDEX($A:$A,MATCH(ROW(M15),N:N,0)),$A:$D,4,0),"") -> ABHIJIT MONDAL | P17: =IFERROR(VLOOKUP(O17,$D:$E,2,0),"") -> HELPER | Q17: =IFERROR(SEARCH("SALARY",$A:$A),"") -> 1 | R17: =IFERROR(IF(Q17=0,"",COUNTIF($Q$3:Q17,">0")),"") -> 6 | S17: =IFERROR(VLOOKUP(INDEX($A:$A,MATCH(ROW(Q15),R:R,0)),$A:$D,4,0),"") -> MANABINDU BISWAS | T17: =IFERROR(SEARCH("OTHERS0",$A:$A),"") | U17: =IFERROR(IF(T17=0,"",COUNTIF($T$3:T17,">0")),"") -> 0 | V17: =IFERROR(VLOOKUP(INDEX($A:$A,MATCH(ROW(T15),U:U,0)),$A:$D,4,0),"") | W17: =CONCATENATE(Z17,Y17,X17) -> JALANHELPERRAMU | X17: ='OTHER PLANT ATTN.'!C:C -> RAMU | Y17: =Table1[[#This Row],[CATEGORY ]] -> HELPER | Z17: =Table1[[#This Row],[PLANT]] -> JALAN
A18: =CONCATENATE(B18,C18,D18) -> CONTRACTDRIVERDIN MOHAMMOD ALI | B18: =Table4[[#This Row],[CATEGORY]] -> CONTRACT | C18: =Table4[[#This Row],[SUB-CATEGORY]] -> DRIVER | D18: ='RJ ATTENDENCE SHEET'!C:C -> DIN MOHAMMOD ALI | E18: =C18 -> DRIVER | F18: =IFERROR(SEARCH("SALARYOFFICE",$A:$A),"") | G18: =IFERROR(IF(F18=0,"",COUNTIF($F$3:F18,">0")),"") -> 6 | H18: =IFERROR(VLOOKUP(INDEX($A:$A,MATCH(ROW(F16),G:G,0)),$A:$D,4,0),"") -> SUVANKAR SAMADDAR | I18: =IFERROR(SEARCH("WAGES",$A:$A),"") | J18: =IFERROR(IF(I18=0,"",COUNTIF($I$3:I18,">0")),"") -> 4 | K18: =IFERROR(VLOOKUP(INDEX($A:$A,MATCH(ROW(I16),J:J,0)),$A:$D,4,0),"") -> SWAPAN MONDAL | L18: =IFERROR(VLOOKUP(K18,$D:$E,2,0),"") -> LAB | M18: =IFERROR(SEARCH("CONTRACT",$A:$A),"") -> 1 | N18: =IFERROR(IF(M18=0,"",COUNTIF($M$3:M18,">0")),"") -> 6 | O18: =IFERROR(VLOOKUP(INDEX($A:$A,MATCH(ROW(M16),N:N,0)),$A:$D,4,0),"") -> KHALEK DHALI | P18: =IFERROR(VLOOKUP(O18,$D:$E,2,0),"") -> HELPER | Q18: =IFERROR(SEARCH("SALARY",$A:$A),"") | R18: =IFERROR(IF(Q18=0,"",COUNTIF($Q$3:Q18,">0")),"") -> 6 | S18: =IFERROR(VLOOKUP(INDEX($A:$A,MATCH(ROW(Q16),R:R,0)),$A:$D,4,0),"") -> SUVANKAR SAMADDAR | T18: =IFERROR(SEARCH("OTHERS0",$A:$A),"") | U18: =IFERROR(IF(T18=0,"",COUNTIF($T$3:T18,">0")),"") -> 0 | V18: =IFERROR(VLOOKUP(INDEX($A:$A,MATCH(ROW(T16),U:U,0)),$A:$D,4,0),"") | W18: =CONCATENATE(Z18,Y18,X18) -> JALANDRIVERTAPAS | X18: ='OTHER PLANT ATTN.'!C:C -> TAPAS | Y18: =Table1[[#This Row],[CATEGORY ]] -> DRIVER | Z18: =Table1[[#This Row],[PLANT]] -> JALAN
... A438: =CONCATENATE(B438,C438,D438) -> #VALUE! | B438: =Table4[[#This Row],[CATEGORY]] -> #VALUE! | C438: =Table4[[#This Row],[SUB-CATEGORY]] -> #VALUE! | D438: ='RJ ATTENDENCE SHEET'!C:C -> 0 | E438: =C438 -> #VALUE! | F438: =IFERROR(SEARCH("SALARYOFFICE",$A:$A),"") | G438: =IFERROR(IF(F438=0,"",COUNTIF($F$3:F438,">0")),"") -> 16 | H438: =IFERROR(VLOOKUP(INDEX($A:$A,MATCH(ROW(F436),G:G,0)),$A:$D,4,0),"") | I438: =IFERROR(SEARCH("WAGES",$A:$A),"") | J438: =IFERROR(IF(I438=0,"",COUNTIF($I$3:I438,">0")),"") -> 34 | K438: =IFERROR(VLOOKUP(INDEX($A:$A,MATCH(ROW(I436),J:J,0)),$A:$D,4,0),"") | L438: =IFERROR(VLOOKUP(K438,$D:$E,2,0),"") | M438: =IFERROR(SEARCH("CONTRACT",$A:$A),"") | N438: =IFERROR(IF(M438=0,"",COUNTIF($M$3:M438,">0")),"") -> 33 | O438: =IFERROR(VLOOKUP(INDEX($A:$A,MATCH(ROW(M436),N:N,0)),$A:$D,4,0),"") | P438: =IFERROR(VLOOKUP(O438,$D:$E,2,0),"") | Q438: =IFERROR(SEARCH("SALARY",$A:$A),"") | R438: =IFERROR(IF(Q438=0,"",COUNTIF($Q$3:Q438,">0")),"") -> 16 | S438: =IFERROR(VLOOKUP(INDEX($A:$A,MATCH(ROW(Q436),R:R,0)),$A:$D,4,0),"") | T438: =IFERROR(SEARCH("OTHERS0",$A:$A),"") | U438: =IFERROR(IF(T438=0,"",COUNTIF($T$3:T438,">0")),"") -> 0 | V438: =IFERROR(VLOOKUP(INDEX($A:$A,MATCH(ROW(T436),U:U,0)),$A:$D,4,0),"") | W438: =CONCATENATE(Z438,Y438,X438) -> #VALUE! | X438: ='OTHER PLANT ATTN.'!C:C -> 0 | Y438: =Table1[[#This Row],[CATEGORY ]] -> #VALUE! | Z438: =Table1[[#This Row],[PLANT]] -> #VALUE!
A439: =CONCATENATE(B439,C439,D439) -> #VALUE! | B439: =Table4[[#This Row],[CATEGORY]] -> #VALUE! | C439: =Table4[[#This Row],[SUB-CATEGORY]] -> #VALUE! | D439: ='RJ ATTENDENCE SHEET'!C:C -> 0 | E439: =C439 -> #VALUE! | F439: =IFERROR(SEARCH("SALARYOFFICE",$A:$A),"") | G439: =IFERROR(IF(F439=0,"",COUNTIF($F$3:F439,">0")),"") -> 16 | H439: =IFERROR(VLOOKUP(INDEX($A:$A,MATCH(ROW(F437),G:G,0)),$A:$D,4,0),"") | I439: =IFERROR(SEARCH("WAGES",$A:$A),"") | J439: =IFERROR(IF(I439=0,"",COUNTIF($I$3:I439,">0")),"") -> 34 | K439: =IFERROR(VLOOKUP(INDEX($A:$A,MATCH(ROW(I437),J:J,0)),$A:$D,4,0),"") | L439: =IFERROR(VLOOKUP(K439,$D:$E,2,0),"") | M439: =IFERROR(SEARCH("CONTRACT",$A:$A),"") | N439: =IFERROR(IF(M439=0,"",COUNTIF($M$3:M439,">0")),"") -> 33 | O439: =IFERROR(VLOOKUP(INDEX($A:$A,MATCH(ROW(M437),N:N,0)),$A:$D,4,0),"") | P439: =IFERROR(VLOOKUP(O439,$D:$E,2,0),"") | Q439: =IFERROR(SEARCH("SALARY",$A:$A),"") | R439: =IFERROR(IF(Q439=0,"",COUNTIF($Q$3:Q439,">0")),"") -> 16 | S439: =IFERROR(VLOOKUP(INDEX($A:$A,MATCH(ROW(Q437),R:R,0)),$A:$D,4,0),"") | T439: =IFERROR(SEARCH("OTHERS0",$A:$A),"") | U439: =IFERROR(IF(T439=0,"",COUNTIF($T$3:T439,">0")),"") -> 0 | V439: =IFERROR(VLOOKUP(INDEX($A:$A,MATCH(ROW(T437),U:U,0)),$A:$D,4,0),"")
A440: =CONCATENATE(B440,C440,D440) -> #VALUE! | B440: =Table4[[#This Row],[CATEGORY]] -> #VALUE! | C440: =Table4[[#This Row],[SUB-CATEGORY]] -> #VALUE! | D440: ='RJ ATTENDENCE SHEET'!C:C -> 0 | E440: =C440 -> #VALUE! | F440: =IFERROR(SEARCH("SALARYOFFICE",$A:$A),"") | G440: =IFERROR(IF(F440=0,"",COUNTIF($F$3:F440,">0")),"") -> 16 | H440: =IFERROR(VLOOKUP(INDEX($A:$A,MATCH(ROW(F438),G:G,0)),$A:$D,4,0),"") | I440: =IFERROR(SEARCH("WAGES",$A:$A),"") | J440: =IFERROR(IF(I440=0,"",COUNTIF($I$3:I440,">0")),"") -> 34 | K440: =IFERROR(VLOOKUP(INDEX($A:$A,MATCH(ROW(I438),J:J,0)),$A:$D,4,0),"") | L440: =IFERROR(VLOOKUP(K440,$D:$E,2,0),"") | M440: =IFERROR(SEARCH("CONTRACT",$A:$A),"") | N440: =IFERROR(IF(M440=0,"",COUNTIF($M$3:M440,">0")),"") -> 33 | O440: =IFERROR(VLOOKUP(INDEX($A:$A,MATCH(ROW(M438),N:N,0)),$A:$D,4,0),"") | P440: =IFERROR(VLOOKUP(O440,$D:$E,2,0),"") | Q440: =IFERROR(SEARCH("SALARY",$A:$A),"") | R440: =IFERROR(IF(Q440=0,"",COUNTIF($Q$3:Q440,">0")),"") -> 16 | S440: =IFERROR(VLOOKUP(INDEX($A:$A,MATCH(ROW(Q438),R:R,0)),$A:$D,4,0),"") | T440: =IFERROR(SEARCH("OTHERS0",$A:$A),"") | U440: =IFERROR(IF(T440=0,"",COUNTIF($T$3:T440,">0")),"") -> 0 | V440: =IFERROR(VLOOKUP(INDEX($A:$A,MATCH(ROW(T438),U:U,0)),$A:$D,4,0),"")
A441: =CONCATENATE(B441,C441,D441) -> #VALUE! | B441: =Table4[[#This Row],[CATEGORY]] -> #VALUE! | C441: =Table4[[#This Row],[SUB-CATEGORY]] -> #VALUE! | D441: ='RJ ATTENDENCE SHEET'!C:C -> 0 | E441: =C441 -> #VALUE! | F441: =IFERROR(SEARCH("SALARYOFFICE",$A:$A),"") | G441: =IFERROR(IF(F441=0,"",COUNTIF($F$3:F441,">0")),"") -> 16 | H441: =IFERROR(VLOOKUP(INDEX($A:$A,MATCH(ROW(F439),G:G,0)),$A:$D,4,0),"") | I441: =IFERROR(SEARCH("WAGES",$A:$A),"") | J441: =IFERROR(IF(I441=0,"",COUNTIF($I$3:I441,">0")),"") -> 34 | K441: =IFERROR(VLOOKUP(INDEX($A:$A,MATCH(ROW(I439),J:J,0)),$A:$D,4,0),"") | L441: =IFERROR(VLOOKUP(K441,$D:$E,2,0),"") | M441: =IFERROR(SEARCH("CONTRACT",$A:$A),"") | N441: =IFERROR(IF(M441=0,"",COUNTIF($M$3:M441,">0")),"") -> 33 | O441: =IFERROR(VLOOKUP(INDEX($A:$A,MATCH(ROW(M439),N:N,0)),$A:$D,4,0),"") | P441: =IFERROR(VLOOKUP(O441,$D:$E,2,0),"") | Q441: =IFERROR(SEARCH("SALARY",$A:$A),"") | R441: =IFERROR(IF(Q441=0,"",COUNTIF($Q$3:Q441,">0")),"") -> 16 | S441: =IFERROR(VLOOKUP(INDEX($A:$A,MATCH(ROW(Q439),R:R,0)),$A:$D,4,0),"") | T441: =IFERROR(SEARCH("OTHERS0",$A:$A),"") | U441: =IFERROR(IF(T441=0,"",COUNTIF($T$3:T441,">0")),"") -> 0 | V441: =IFERROR(VLOOKUP(INDEX($A:$A,MATCH(ROW(T439),U:U,0)),$A:$D,4,0),"")
A442: =CONCATENATE(B442,C442,D442) -> #VALUE! | B442: =Table4[[#This Row],[CATEGORY]] -> #VALUE! | C442: =Table4[[#This Row],[SUB-CATEGORY]] -> #VALUE! | D442: ='RJ ATTENDENCE SHEET'!C:C -> 0 | E442: =C442 -> #VALUE! | F442: =IFERROR(SEARCH("SALARYOFFICE",$A:$A),"") | G442: =IFERROR(IF(F442=0,"",COUNTIF($F$3:F442,">0")),"") -> 16 | H442: =IFERROR(VLOOKUP(INDEX($A:$A,MATCH(ROW(F440),G:G,0)),$A:$D,4,0),"") | I442: =IFERROR(SEARCH("WAGES",$A:$A),"") | J442: =IFERROR(IF(I442=0,"",COUNTIF($I$3:I442,">0")),"") -> 34 | K442: =IFERROR(VLOOKUP(INDEX($A:$A,MATCH(ROW(I440),J:J,0)),$A:$D,4,0),"") | L442: =IFERROR(VLOOKUP(K442,$D:$E,2,0),"") | M442: =IFERROR(SEARCH("CONTRACT",$A:$A),"") | N442: =IFERROR(IF(M442=0,"",COUNTIF($M$3:M442,">0")),"") -> 33 | O442: =IFERROR(VLOOKUP(INDEX($A:$A,MATCH(ROW(M440),N:N,0)),$A:$D,4,0),"") | P442: =IFERROR(VLOOKUP(O442,$D:$E,2,0),"") | Q442: =IFERROR(SEARCH("SALARY",$A:$A),"") | R442: =IFERROR(IF(Q442=0,"",COUNTIF($Q$3:Q442,">0")),"") -> 16 | S442: =IFERROR(VLOOKUP(INDEX($A:$A,MATCH(ROW(Q440),R:R,0)),$A:$D,4,0),"") | T442: =IFERROR(SEARCH("OTHERS0",$A:$A),"") | U442: =IFERROR(IF(T442=0,"",COUNTIF($T$3:T442,">0")),"") -> 0 | V442: =IFERROR(VLOOKUP(INDEX($A:$A,MATCH(ROW(T440),U:U,0)),$A:$D,4,0),"")
A443: =CONCATENATE(B443,C443,D443) -> #VALUE! | B443: =Table4[[#This Row],[CATEGORY]] -> #VALUE! | C443: =Table4[[#This Row],[SUB-CATEGORY]] -> #VALUE! | D443: ='RJ ATTENDENCE SHEET'!C:C -> 0 | E443: =C443 -> #VALUE! | F443: =IFERROR(SEARCH("SALARYOFFICE",$A:$A),"") | G443: =IFERROR(IF(F443=0,"",COUNTIF($F$3:F443,">0")),"") -> 16 | H443: =IFERROR(VLOOKUP(INDEX($A:$A,MATCH(ROW(F441),G:G,0)),$A:$D,4,0),"") | I443: =IFERROR(SEARCH("WAGES",$A:$A),"") | J443: =IFERROR(IF(I443=0,"",COUNTIF($I$3:I443,">0")),"") -> 34 | K443: =IFERROR(VLOOKUP(INDEX($A:$A,MATCH(ROW(I441),J:J,0)),$A:$D,4,0),"") | L443: =IFERROR(VLOOKUP(K443,$D:$E,2,0),"") | M443: =IFERROR(SEARCH("CONTRACT",$A:$A),"") | N443: =IFERROR(IF(M443=0,"",COUNTIF($M$3:M443,">0")),"") -> 33 | O443: =IFERROR(VLOOKUP(INDEX($A:$A,MATCH(ROW(M441),N:N,0)),$A:$D,4,0),"") | P443: =IFERROR(VLOOKUP(O443,$D:$E,2,0),"") | Q443: =IFERROR(SEARCH("SALARY",$A:$A),"") | R443: =IFERROR(IF(Q443=0,"",COUNTIF($Q$3:Q443,">0")),"") -> 16 | S443: =IFERROR(VLOOKUP(INDEX($A:$A,MATCH(ROW(Q441),R:R,0)),$A:$D,4,0),"") | T443: =IFERROR(SEARCH("OTHERS0",$A:$A),"") | U443: =IFERROR(IF(T443=0,"",COUNTIF($T$3:T443,">0")),"") -> 0 | V443: =IFERROR(VLOOKUP(INDEX($A:$A,MATCH(ROW(T441),U:U,0)),$A:$D,4,0),"")
A444: =CONCATENATE(B444,C444,D444) -> #VALUE! | B444: =Table4[[#This Row],[CATEGORY]] -> #VALUE! | C444: =Table4[[#This Row],[SUB-CATEGORY]] -> #VALUE! | D444: ='RJ ATTENDENCE SHEET'!C:C -> 0 | E444: =C444 -> #VALUE! | F444: =IFERROR(SEARCH("SALARYOFFICE",$A:$A),"") | G444: =IFERROR(IF(F444=0,"",COUNTIF($F$3:F444,">0")),"") -> 16 | H444: =IFERROR(VLOOKUP(INDEX($A:$A,MATCH(ROW(F442),G:G,0)),$A:$D,4,0),"") | I444: =IFERROR(SEARCH("WAGES",$A:$A),"") | J444: =IFERROR(IF(I444=0,"",COUNTIF($I$3:I444,">0")),"") -> 34 | K444: =IFERROR(VLOOKUP(INDEX($A:$A,MATCH(ROW(I442),J:J,0)),$A:$D,4,0),"") | L444: =IFERROR(VLOOKUP(K444,$D:$E,2,0),"") | M444: =IFERROR(SEARCH("CONTRACT",$A:$A),"") | N444: =IFERROR(IF(M444=0,"",COUNTIF($M$3:M444,">0")),"") -> 33 | O444: =IFERROR(VLOOKUP(INDEX($A:$A,MATCH(ROW(M442),N:N,0)),$A:$D,4,0),"") | P444: =IFERROR(VLOOKUP(O444,$D:$E,2,0),"") | Q444: =IFERROR(SEARCH("SALARY",$A:$A),"") | R444: =IFERROR(IF(Q444=0,"",COUNTIF($Q$3:Q444,">0")),"") -> 16 | S444: =IFERROR(VLOOKUP(INDEX($A:$A,MATCH(ROW(Q442),R:R,0)),$A:$D,4,0),"") | T444: =IFERROR(SEARCH("OTHERS0",$A:$A),"") | U444: =IFERROR(IF(T444=0,"",COUNTIF($T$3:T444,">0")),"") -> 0 | V444: =IFERROR(VLOOKUP(INDEX($A:$A,MATCH(ROW(T442),U:U,0)),$A:$D,4,0),"")
A445: =CONCATENATE(B445,C445,D445) -> #VALUE! | B445: =Table4[[#This Row],[CATEGORY]] -> #VALUE! | C445: =Table4[[#This Row],[SUB-CATEGORY]] -> #VALUE! | D445: ='RJ ATTENDENCE SHEET'!C:C -> 0 | E445: =C445 -> #VALUE! | F445: =IFERROR(SEARCH("SALARYOFFICE",$A:$A),"") | G445: =IFERROR(IF(F445=0,"",COUNTIF($F$3:F445,">0")),"") -> 16 | H445: =IFERROR(VLOOKUP(INDEX($A:$A,MATCH(ROW(F443),G:G,0)),$A:$D,4,0),"") | I445: =IFERROR(SEARCH("WAGES",$A:$A),"") | J445: =IFERROR(IF(I445=0,"",COUNTIF($I$3:I445,">0")),"") -> 34 | K445: =IFERROR(VLOOKUP(INDEX($A:$A,MATCH(ROW(I443),J:J,0)),$A:$D,4,0),"") | L445: =IFERROR(VLOOKUP(K445,$D:$E,2,0),"") | M445: =IFERROR(SEARCH("CONTRACT",$A:$A),"") | N445: =IFERROR(IF(M445=0,"",COUNTIF($M$3:M445,">0")),"") -> 33 | O445: =IFERROR(VLOOKUP(INDEX($A:$A,MATCH(ROW(M443),N:N,0)),$A:$D,4,0),"") | P445: =IFERROR(VLOOKUP(O445,$D:$E,2,0),"") | Q445: =IFERROR(SEARCH("SALARY",$A:$A),"") | R445: =IFERROR(IF(Q445=0,"",COUNTIF($Q$3:Q445,">0")),"") -> 16 | S445: =IFERROR(VLOOKUP(INDEX($A:$A,MATCH(ROW(Q443),R:R,0)),$A:$D,4,0),"") | T445: =IFERROR(SEARCH("OTHERS0",$A:$A),"") | U445: =IFERROR(IF(T445=0,"",COUNTIF($T$3:T445,">0")),"") -> 0 | V445: =IFERROR(VLOOKUP(INDEX($A:$A,MATCH(ROW(T443),U:U,0)),$A:$D,4,0),"")
A446: =CONCATENATE(B446,C446,D446) -> #VALUE! | B446: =Table4[[#This Row],[CATEGORY]] -> #VALUE! | C446: =Table4[[#This Row],[SUB-CATEGORY]] -> #VALUE! | D446: ='RJ ATTENDENCE SHEET'!C:C -> 0 | E446: =C446 -> #VALUE! | F446: =IFERROR(SEARCH("SALARYOFFICE",$A:$A),"") | G446: =IFERROR(IF(F446=0,"",COUNTIF($F$3:F446,">0")),"") -> 16 | H446: =IFERROR(VLOOKUP(INDEX($A:$A,MATCH(ROW(F444),G:G,0)),$A:$D,4,0),"") | I446: =IFERROR(SEARCH("WAGES",$A:$A),"") | J446: =IFERROR(IF(I446=0,"",COUNTIF($I$3:I446,">0")),"") -> 34 | K446: =IFERROR(VLOOKUP(INDEX($A:$A,MATCH(ROW(I444),J:J,0)),$A:$D,4,0),"") | L446: =IFERROR(VLOOKUP(K446,$D:$E,2,0),"") | M446: =IFERROR(SEARCH("CONTRACT",$A:$A),"") | N446: =IFERROR(IF(M446=0,"",COUNTIF($M$3:M446,">0")),"") -> 33 | O446: =IFERROR(VLOOKUP(INDEX($A:$A,MATCH(ROW(M444),N:N,0)),$A:$D,4,0),"") | P446: =IFERROR(VLOOKUP(O446,$D:$E,2,0),"") | Q446: =IFERROR(SEARCH("SALARY",$A:$A),"") | R446: =IFERROR(IF(Q446=0,"",COUNTIF($Q$3:Q446,">0")),"") -> 16 | S446: =IFERROR(VLOOKUP(INDEX($A:$A,MATCH(ROW(Q444),R:R,0)),$A:$D,4,0),"") | T446: =IFERROR(SEARCH("OTHERS0",$A:$A),"") | U446: =IFERROR(IF(T446=0,"",COUNTIF($T$3:T446,">0")),"") -> 0 | V446: =IFERROR(VLOOKUP(INDEX($A:$A,MATCH(ROW(T444),U:U,0)),$A:$D,4,0),"")
A447: =CONCATENATE(B447,C447,D447) -> #VALUE! | B447: =Table4[[#This Row],[CATEGORY]] -> #VALUE! | C447: =Table4[[#This Row],[SUB-CATEGORY]] -> #VALUE! | D447: ='RJ ATTENDENCE SHEET'!C:C -> 0 | E447: =C447 -> #VALUE! | F447: =IFERROR(SEARCH("SALARYOFFICE",$A:$A),"") | G447: =IFERROR(IF(F447=0,"",COUNTIF($F$3:F447,">0")),"") -> 16 | H447: =IFERROR(VLOOKUP(INDEX($A:$A,MATCH(ROW(F445),G:G,0)),$A:$D,4,0),"") | I447: =IFERROR(SEARCH("WAGES",$A:$A),"") | J447: =IFERROR(IF(I447=0,"",COUNTIF($I$3:I447,">0")),"") -> 34 | K447: =IFERROR(VLOOKUP(INDEX($A:$A,MATCH(ROW(I445),J:J,0)),$A:$D,4,0),"") | L447: =IFERROR(VLOOKUP(K447,$D:$E,2,0),"") | M447: =IFERROR(SEARCH("CONTRACT",$A:$A),"") | N447: =IFERROR(IF(M447=0,"",COUNTIF($M$3:M447,">0")),"") -> 33 | O447: =IFERROR(VLOOKUP(INDEX($A:$A,MATCH(ROW(M445),N:N,0)),$A:$D,4,0),"") | P447: =IFERROR(VLOOKUP(O447,$D:$E,2,0),"") | Q447: =IFERROR(SEARCH("SALARY",$A:$A),"") | R447: =IFERROR(IF(Q447=0,"",COUNTIF($Q$3:Q447,">0")),"") -> 16 | S447: =IFERROR(VLOOKUP(INDEX($A:$A,MATCH(ROW(Q445),R:R,0)),$A:$D,4,0),"") | T447: =IFERROR(SEARCH("OTHERS0",$A:$A),"") | U447: =IFERROR(IF(T447=0,"",COUNTIF($T$3:T447,">0")),"") -> 0 | V447: =IFERROR(VLOOKUP(INDEX($A:$A,MATCH(ROW(T445),U:U,0)),$A:$D,4,0),"")
A448: =CONCATENATE(B448,C448,D448) -> #VALUE! | B448: =Table4[[#This Row],[CATEGORY]] -> #VALUE! | C448: =Table4[[#This Row],[SUB-CATEGORY]] -> #VALUE! | D448: ='RJ ATTENDENCE SHEET'!C:C -> 0 | E448: =C448 -> #VALUE! | F448: =IFERROR(SEARCH("SALARYOFFICE",$A:$A),"") | G448: =IFERROR(IF(F448=0,"",COUNTIF($F$3:F448,">0")),"") -> 16 | H448: =IFERROR(VLOOKUP(INDEX($A:$A,MATCH(ROW(F446),G:G,0)),$A:$D,4,0),"") | I448: =IFERROR(SEARCH("WAGES",$A:$A),"") | J448: =IFERROR(IF(I448=0,"",COUNTIF($I$3:I448,">0")),"") -> 34 | K448: =IFERROR(VLOOKUP(INDEX($A:$A,MATCH(ROW(I446),J:J,0)),$A:$D,4,0),"") | L448: =IFERROR(VLOOKUP(K448,$D:$E,2,0),"") | M448: =IFERROR(SEARCH("CONTRACT",$A:$A),"") | N448: =IFERROR(IF(M448=0,"",COUNTIF($M$3:M448,">0")),"") -> 33 | O448: =IFERROR(VLOOKUP(INDEX($A:$A,MATCH(ROW(M446),N:N,0)),$A:$D,4,0),"") | P448: =IFERROR(VLOOKUP(O448,$D:$E,2,0),"") | Q448: =IFERROR(SEARCH("SALARY",$A:$A),"") | R448: =IFERROR(IF(Q448=0,"",COUNTIF($Q$3:Q448,">0")),"") -> 16 | S448: =IFERROR(VLOOKUP(INDEX($A:$A,MATCH(ROW(Q446),R:R,0)),$A:$D,4,0),"") | T448: =IFERROR(SEARCH("OTHERS0",$A:$A),"") | U448: =IFERROR(IF(T448=0,"",COUNTIF($T$3:T448,">0")),"") -> 0 | V448: =IFERROR(VLOOKUP(INDEX($A:$A,MATCH(ROW(T446),U:U,0)),$A:$D,4,0),"")
A449: =CONCATENATE(B449,C449,D449) -> #VALUE! | B449: =Table4[[#This Row],[CATEGORY]] -> #VALUE! | C449: =Table4[[#This Row],[SUB-CATEGORY]] -> #VALUE! | D449: ='RJ ATTENDENCE SHEET'!C:C -> 0 | E449: =C449 -> #VALUE! | F449: =IFERROR(SEARCH("SALARYOFFICE",$A:$A),"") | G449: =IFERROR(IF(F449=0,"",COUNTIF($F$3:F449,">0")),"") -> 16 | H449: =IFERROR(VLOOKUP(INDEX($A:$A,MATCH(ROW(F447),G:G,0)),$A:$D,4,0),"") | I449: =IFERROR(SEARCH("WAGES",$A:$A),"") | J449: =IFERROR(IF(I449=0,"",COUNTIF($I$3:I449,">0")),"") -> 34 | K449: =IFERROR(VLOOKUP(INDEX($A:$A,MATCH(ROW(I447),J:J,0)),$A:$D,4,0),"") | L449: =IFERROR(VLOOKUP(K449,$D:$E,2,0),"") | M449: =IFERROR(SEARCH("CONTRACT",$A:$A),"") | N449: =IFERROR(IF(M449=0,"",COUNTIF($M$3:M449,">0")),"") -> 33 | O449: =IFERROR(VLOOKUP(INDEX($A:$A,MATCH(ROW(M447),N:N,0)),$A:$D,4,0),"") | P449: =IFERROR(VLOOKUP(O449,$D:$E,2,0),"") | Q449: =IFERROR(SEARCH("SALARY",$A:$A),"") | R449: =IFERROR(IF(Q449=0,"",COUNTIF($Q$3:Q449,">0")),"") -> 16 | S449: =IFERROR(VLOOKUP(INDEX($A:$A,MATCH(ROW(Q447),R:R,0)),$A:$D,4,0),"") | T449: =IFERROR(SEARCH("OTHERS0",$A:$A),"") | U449: =IFERROR(IF(T449=0,"",COUNTIF($T$3:T449,">0")),"") -> 0 | V449: =IFERROR(VLOOKUP(INDEX($A:$A,MATCH(ROW(T447),U:U,0)),$A:$D,4,0),"")
A450: =CONCATENATE(B450,C450,D450) -> #VALUE! | B450: =Table4[[#This Row],[CATEGORY]] -> #VALUE! | C450: =Table4[[#This Row],[SUB-CATEGORY]] -> #VALUE! | D450: ='RJ ATTENDENCE SHEET'!C:C -> 0 | E450: =C450 -> #VALUE! | F450: =IFERROR(SEARCH("SALARYOFFICE",$A:$A),"") | G450: =IFERROR(IF(F450=0,"",COUNTIF($F$3:F450,">0")),"") -> 16 | H450: =IFERROR(VLOOKUP(INDEX($A:$A,MATCH(ROW(F448),G:G,0)),$A:$D,4,0),"") | I450: =IFERROR(SEARCH("WAGES",$A:$A),"") | J450: =IFERROR(IF(I450=0,"",COUNTIF($I$3:I450,">0")),"") -> 34 | K450: =IFERROR(VLOOKUP(INDEX($A:$A,MATCH(ROW(I448),J:J,0)),$A:$D,4,0),"") | L450: =IFERROR(VLOOKUP(K450,$D:$E,2,0),"") | M450: =IFERROR(SEARCH("CONTRACT",$A:$A),"") | N450: =IFERROR(IF(M450=0,"",COUNTIF($M$3:M450,">0")),"") -> 33 | O450: =IFERROR(VLOOKUP(INDEX($A:$A,MATCH(ROW(M448),N:N,0)),$A:$D,4,0),"") | P450: =IFERROR(VLOOKUP(O450,$D:$E,2,0),"") | Q450: =IFERROR(SEARCH("SALARY",$A:$A),"") | R450: =IFERROR(IF(Q450=0,"",COUNTIF($Q$3:Q450,">0")),"") -> 16 | S450: =IFERROR(VLOOKUP(INDEX($A:$A,MATCH(ROW(Q448),R:R,0)),$A:$D,4,0),"") | T450: =IFERROR(SEARCH("OTHERS0",$A:$A),"") | U450: =IFERROR(IF(T450=0,"",COUNTIF($T$3:T450,">0")),"") -> 0 | V450: =IFERROR(VLOOKUP(INDEX($A:$A,MATCH(ROW(T448),U:U,0)),$A:$D,4,0),"")
... A1000: =CONCATENATE(B1000,C1000,D1000) -> #VALUE! | B1000: =Table4[[#This Row],[CATEGORY]] -> #VALUE! | C1000: =Table4[[#This Row],[SUB-CATEGORY]] -> #VALUE! | D1000: ='RJ ATTENDENCE SHEET'!C:C -> 0 | E1000: =C1000 -> #VALUE! | F1000: =IFERROR(SEARCH("SALARYOFFICE",$A:$A),"") | G1000: =IFERROR(IF(F1000=0,"",COUNTIF($F$3:F1000,">0")),"") -> 16 | H1000: =IFERROR(VLOOKUP(INDEX($A:$A,MATCH(ROW(F998),G:G,0)),$A:$D,4,0),"") | I1000: =IFERROR(SEARCH("WAGES",$A:$A),"") | J1000: =IFERROR(IF(I1000=0,"",COUNTIF($I$3:I1000,">0")),"") -> 34 | K1000: =IFERROR(VLOOKUP(INDEX($A:$A,MATCH(ROW(I998),J:J,0)),$A:$D,4,0),"") | L1000: =IFERROR(VLOOKUP(K1000,$D:$E,2,0),"") | M1000: =IFERROR(SEARCH("CONTRACT",$A:$A),"") | N1000: =IFERROR(IF(M1000=0,"",COUNTIF($M$3:M1000,">0")),"") -> 33 | O1000: =IFERROR(VLOOKUP(INDEX($A:$A,MATCH(ROW(M998),N:N,0)),$A:$D,4,0),"") | P1000: =IFERROR(VLOOKUP(O1000,$D:$E,2,0),"") | Q1000: =IFERROR(SEARCH("SALARY",$A:$A),"") | R1000: =IFERROR(IF(Q1000=0,"",COUNTIF($Q$3:Q1000,">0")),"") -> 16 | S1000: =IFERROR(VLOOKUP(INDEX($A:$A,MATCH(ROW(Q998),R:R,0)),$A:$D,4,0),"") | T1000: =IFERROR(SEARCH("OTHERS0",$A:$A),"") | U1000: =IFERROR(IF(T1000=0,"",COUNTIF($T$3:T1000,">0")),"") -> 0 | V1000: =IFERROR(VLOOKUP(INDEX($A:$A,MATCH(ROW(T998),U:U,0)),$A:$D,4,0),"")
A1200: password : admin
A1201: password : taratala

Sheet WHATSAPP
A3: DAILY STAFF ATTENDANCE REPORT OF RAJARHAT PLANT
J4: DATE: | K4: 43911
A5: SL.NO | B5: NAME | D5: DUTY | H5: SL.NO | J5: NAME | K5: DUTY | M5: TRIP
D6: DAY | E6: NIGHT | K6: DAY | L6: NIGHT
A7: SALARY | H7: CONTRACT
A8: 1 | B8: ='DATA '!S3 -> ABED ALI | D8: =IFERROR(VLOOKUP(B8,'RJ ATTENDENCE SHEET'!$C:$CG,('DATA '!$AA$3+21+('DATA '!$AA$3-1)),0),"") -> P | E8: =IFERROR(VLOOKUP(B8,'RJ ATTENDENCE SHEET'!$C:$CG,('DATA '!$AA$3+22+('DATA '!$AA$3-1)),0),"") -> A | H8: 1 | I8: =VLOOKUP(J8,'DATA '!$O:$P,2,0) -> HELPER | J8: ='DATA '!O3 -> AMIT BISWAS | K8: =IFERROR(VLOOKUP(J8,'RJ ATTENDENCE SHEET'!$C:$CG,('DATA '!$AA$3+21+('DATA '!$AA$3-1)),0),"") -> A | L8: =IFERROR(VLOOKUP(J8,'RJ ATTENDENCE SHEET'!$C:$CG,('DATA '!$AA$3+22+('DATA '!$AA$3-1)),0),"") -> P | M8: =IFERROR(VLOOKUP(J8,'RJ ATTENDENCE SHEET'!$C:$DM,('DATA '!$AA$3+84),0),"") -> 0
A9: 2 | B9: ='DATA '!S4 -> ABHI MUKHERJEE | D9: =IFERROR(VLOOKUP(B9,'RJ ATTENDENCE SHEET'!$C:$CG,('DATA '!$AA$3+21+('DATA '!$AA$3-1)),0),"") -> P | E9: =IFERROR(VLOOKUP(B9,'RJ ATTENDENCE SHEET'!$C:$CG,('DATA '!$AA$3+22+('DATA '!$AA$3-1)),0),"") -> A | H9: 2 | I9: =VLOOKUP(J9,'DATA '!$O:$P,2,0) -> HELPER | J9: ='DATA '!O4 -> JHANTU MONDAL | K9: =IFERROR(VLOOKUP(J9,'RJ ATTENDENCE SHEET'!$C:$CG,('DATA '!$AA$3+21+('DATA '!$AA$3-1)),0),"") -> P | L9: =IFERROR(VLOOKUP(J9,'RJ ATTENDENCE SHEET'!$C:$CG,('DATA '!$AA$3+22+('DATA '!$AA$3-1)),0),"") -> A | M9: =IFERROR(VLOOKUP(J9,'RJ ATTENDENCE SHEET'!$C:$DM,('DATA '!$AA$3+84),0),"") -> 0
A10: 3 | B10: ='DATA '!S5 -> ACHIN GUPTA | D10: =IFERROR(VLOOKUP(B10,'RJ ATTENDENCE SHEET'!$C:$CG,('DATA '!$AA$3+21+('DATA '!$AA$3-1)),0),"") -> P | E10: =IFERROR(VLOOKUP(B10,'RJ ATTENDENCE SHEET'!$C:$CG,('DATA '!$AA$3+22+('DATA '!$AA$3-1)),0),"") -> A | H10: 3 | I10: =VLOOKUP(J10,'DATA '!$O:$P,2,0) -> DRIVER | J10: ='DATA '!O5 -> ASHIT BISWAS | K10: =IFERROR(VLOOKUP(J10,'RJ ATTENDENCE SHEET'!$C:$CG,('DATA '!$AA$3+21+('DATA '!$AA$3-1)),0),"") -> A | L10: =IFERROR(VLOOKUP(J10,'RJ ATTENDENCE SHEET'!$C:$CG,('DATA '!$AA$3+22+('DATA '!$AA$3-1)),0),"") -> P | M10: =IFERROR(VLOOKUP(J10,'RJ ATTENDENCE SHEET'!$C:$DM,('DATA '!$AA$3+84),0),"") -> 0
A11: 4 | B11: ='DATA '!S6 -> AMIN YADAV | D11: =IFERROR(VLOOKUP(B11,'RJ ATTENDENCE SHEET'!$C:$CG,('DATA '!$AA$3+21+('DATA '!$AA$3-1)),0),"") -> P | E11: =IFERROR(VLOOKUP(B11,'RJ ATTENDENCE SHEET'!$C:$CG,('DATA '!$AA$3+22+('DATA '!$AA$3-1)),0),"") -> A | H11: 4 | I11: =VLOOKUP(J11,'DATA '!$O:$P,2,0) -> HELPER | J11: ='DATA '!O6 -> NASIB KARIKAR | K11: =IFERROR(VLOOKUP(J11,'RJ ATTENDENCE SHEET'!$C:$CG,('DATA '!$AA$3+21+('DATA '!$AA$3-1)),0),"") -> P | L11: =IFERROR(VLOOKUP(J11,'RJ ATTENDENCE SHEET'!$C:$CG,('DATA '!$AA$3+22+('DATA '!$AA$3-1)),0),"") -> P | M11: =IFERROR(VLOOKUP(J11,'RJ ATTENDENCE SHEET'!$C:$DM,('DATA '!$AA$3+84),0),"") -> 0
A12: 5 | B12: ='DATA '!S7 -> ANOWAR MOLLA | D12: =IFERROR(VLOOKUP(B12,'RJ ATTENDENCE SHEET'!$C:$CG,('DATA '!$AA$3+21+('DATA '!$AA$3-1)),0),"") -> P | E12: =IFERROR(VLOOKUP(B12,'RJ ATTENDENCE SHEET'!$C:$CG,('DATA '!$AA$3+22+('DATA '!$AA$3-1)),0),"") -> A | H12: 5 | I12: =VLOOKUP(J12,'DATA '!$O:$P,2,0) -> OTHERS | J12: ='DATA '!O7 -> BASIRUDDIN KHAN | K12: =IFERROR(VLOOKUP(J12,'RJ ATTENDENCE SHEET'!$C:$CG,('DATA '!$AA$3+21+('DATA '!$AA$3-1)),0),"") -> P | L12: =IFERROR(VLOOKUP(J12,'RJ ATTENDENCE SHEET'!$C:$CG,('DATA '!$AA$3+22+('DATA '!$AA$3-1)),0),"") -> A | M12: =IFERROR(VLOOKUP(J12,'RJ ATTENDENCE SHEET'!$C:$DM,('DATA '!$AA$3+84),0),"") -> 0
A13: 6 | B13: ='DATA '!S8 -> DIBAKAR MONDAL | D13: =IFERROR(VLOOKUP(B13,'RJ ATTENDENCE SHEET'!$C:$CG,('DATA '!$AA$3+21+('DATA '!$AA$3-1)),0),"") -> P | E13: =IFERROR(VLOOKUP(B13,'RJ ATTENDENCE SHEET'!$C:$CG,('DATA '!$AA$3+22+('DATA '!$AA$3-1)),0),"") -> A | H13: 6 | I13: =VLOOKUP(J13,'DATA '!$O:$P,2,0) -> DRIVER | J13: ='DATA '!O8 -> DIN MOHAMMOD ALI | K13: =IFERROR(VLOOKUP(J13,'RJ ATTENDENCE SHEET'!$C:$CG,('DATA '!$AA$3+21+('DATA '!$AA$3-1)),0),"") -> P | L13: =IFERROR(VLOOKUP(J13,'RJ ATTENDENCE SHEET'!$C:$CG,('DATA '!$AA$3+22+('DATA '!$AA$3-1)),0),"") -> A | M13: =IFERROR(VLOOKUP(J13,'RJ ATTENDENCE SHEET'!$C:$DM,('DATA '!$AA$3+84),0),"") -> 0
A14: 7 | B14: ='DATA '!S9 -> GOLAM SARWAR | D14: =IFERROR(VLOOKUP(B14,'RJ ATTENDENCE SHEET'!$C:$CG,('DATA '!$AA$3+21+('DATA '!$AA$3-1)),0),"") -> P | E14: =IFERROR(VLOOKUP(B14,'RJ ATTENDENCE SHEET'!$C:$CG,('DATA '!$AA$3+22+('DATA '!$AA$3-1)),0),"") -> A | H14: 7 | I14: =VLOOKUP(J14,'DATA '!$O:$P,2,0) -> DRIVER | J14: ='DATA '!O9 -> RAFIQUE MOLLA | K14: =IFERROR(VLOOKUP(J14,'RJ ATTENDENCE SHEET'!$C:$CG,('DATA '!$AA$3+21+('DATA '!$AA$3-1)),0),"") -> A | L14: =IFERROR(VLOOKUP(J14,'RJ ATTENDENCE SHEET'!$C:$CG,('DATA '!$AA$3+22+('DATA '!$AA$3-1)),0),"") -> P | M14: =IFERROR(VLOOKUP(J14,'RJ ATTENDENCE SHEET'!$C:$DM,('DATA '!$AA$3+84),0),"") -> 0
A15: 8 | B15: ='DATA '!S10 -> IMAN ALI MOLLA | D15: =IFERROR(VLOOKUP(B15,'RJ ATTENDENCE SHEET'!$C:$CG,('DATA '!$AA$3+21+('DATA '!$AA$3-1)),0),"") -> P | E15: =IFERROR(VLOOKUP(B15,'RJ ATTENDENCE SHEET'!$C:$CG,('DATA '!$AA$3+22+('DATA '!$AA$3-1)),0),"") -> A | H15: 8 | I15: =VLOOKUP(J15,'DATA '!$O:$P,2,0) -> HELPER | J15: ='DATA '!O10 -> RAFIKUL MOLLA | K15: =IFERROR(VLOOKUP(J15,'RJ ATTENDENCE SHEET'!$C:$CG,('DATA '!$AA$3+21+('DATA '!$AA$3-1)),0),"") -> A | L15: =IFERROR(VLOOKUP(J15,'RJ ATTENDENCE SHEET'!$C:$CG,('DATA '!$AA$3+22+('DATA '!$AA$3-1)),0),"") -> A | M15: =IFERROR(VLOOKUP(J15,'RJ ATTENDENCE SHEET'!$C:$DM,('DATA '!$AA$3+84),0),"") -> 0
A16: 9 | B16: ='DATA '!S11 -> PULIN MONDAL | D16: =IFERROR(VLOOKUP(B16,'RJ ATTENDENCE SHEET'!$C:$CG,('DATA '!$AA$3+21+('DATA '!$AA$3-1)),0),"") -> P | E16: =IFERROR(VLOOKUP(B16,'RJ ATTENDENCE SHEET'!$C:$CG,('DATA '!$AA$3+22+('DATA '!$AA$3-1)),0),"") -> A | H16: 9 | I16: =VLOOKUP(J16,'DATA '!$O:$P,2,0) -> OTHERS | J16: ='DATA '!O11 -> AYAN PAUL | K16: =IFERROR(VLOOKUP(J16,'RJ ATTENDENCE SHEET'!$C:$CG,('DATA '!$AA$3+21+('DATA '!$AA$3-1)),0),"") -> P | L16: =IFERROR(VLOOKUP(J16,'RJ ATTENDENCE SHEET'!$C:$CG,('DATA '!$AA$3+22+('DATA '!$AA$3-1)),0),"") -> A | M16: =IFERROR(VLOOKUP(J16,'RJ ATTENDENCE SHEET'!$C:$DM,('DATA '!$AA$3+84),0),"") -> 0
A17: 10 | B17: ='DATA '!S12 -> RAJU PAL | D17: =IFERROR(VLOOKUP(B17,'RJ ATTENDENCE SHEET'!$C:$CG,('DATA '!$AA$3+21+('DATA '!$AA$3-1)),0),"") -> P | E17: =IFERROR(VLOOKUP(B17,'RJ ATTENDENCE SHEET'!$C:$CG,('DATA '!$AA$3+22+('DATA '!$AA$3-1)),0),"") -> A | H17: 10 | I17: =VLOOKUP(J17,'DATA '!$O:$P,2,0) -> HELPER | J17: ='DATA '!O12 -> NAYAN MONDAL | K17: =IFERROR(VLOOKUP(J17,'RJ ATTENDENCE SHEET'!$C:$CG,('DATA '!$AA$3+21+('DATA '!$AA$3-1)),0),"") -> P | L17: =IFERROR(VLOOKUP(J17,'RJ ATTENDENCE SHEET'!$C:$CG,('DATA '!$AA$3+22+('DATA '!$AA$3-1)),0),"") -> A | M17: =IFERROR(VLOOKUP(J17,'RJ ATTENDENCE SHEET'!$C:$DM,('DATA '!$AA$3+84),0),"") -> 0
A18: 11 | B18: ='DATA '!S13 -> UJJAL MUKHERJEE | D18: =IFERROR(VLOOKUP(B18,'RJ ATTENDENCE SHEET'!$C:$CG,('DATA '!$AA$3+21+('DATA '!$AA$3-1)),0),"") -> P | E18: =IFERROR(VLOOKUP(B18,'RJ ATTENDENCE SHEET'!$C:$CG,('DATA '!$AA$3+22+('DATA '!$AA$3-1)),0),"") -> A | H18: 11 | I18: =VLOOKUP(J18,'DATA '!$O:$P,2,0) -> OTHERS | J18: ='DATA '!O13 -> SHIB SANKAR MAJHI | K18: =IFERROR(VLOOKUP(J18,'RJ ATTENDENCE SHEET'!$C:$CG,('DATA '!$AA$3+21+('DATA '!$AA$3-1)),0),"") -> P | L18: =IFERROR(VLOOKUP(J18,'RJ ATTENDENCE SHEET'!$C:$CG,('DATA '!$AA$3+22+('DATA '!$AA$3-1)),0),"") -> A | M18: =IFERROR(VLOOKUP(J18,'RJ ATTENDENCE SHEET'!$C:$DM,('DATA '!$AA$3+84),0),"") -> 0
A19: 12 | B19: ='DATA '!S14 -> PROBIR GHOSH | D19: =IFERROR(VLOOKUP(B19,'RJ ATTENDENCE SHEET'!$C:$CG,('DATA '!$AA$3+21+('DATA '!$AA$3-1)),0),"") -> P | E19: =IFERROR(VLOOKUP(B19,'RJ ATTENDENCE SHEET'!$C:$CG,('DATA '!$AA$3+22+('DATA '!$AA$3-1)),0),"") -> A | H19: 12 | I19: =VLOOKUP(J19,'DATA '!$O:$P,2,0) -> OTHERS | J19: ='DATA '!O14 -> ABUL KALAM AZAD | K19: =IFERROR(VLOOKUP(J19,'RJ ATTENDENCE SHEET'!$C:$CG,('DATA '!$AA$3+21+('DATA '!$AA$3-1)),0),"") -> P | L19: =IFERROR(VLOOKUP(J19,'RJ ATTENDENCE SHEET'!$C:$CG,('DATA '!$AA$3+22+('DATA '!$AA$3-1)),0),"") -> A | M19: =IFERROR(VLOOKUP(J19,'RJ ATTENDENCE SHEET'!$C:$DM,('DATA '!$AA$3+84),0),"") -> 0
... A27: 20 | B27: ='DATA '!S22 | D27: =IFERROR(VLOOKUP(B27,'RJ ATTENDENCE SHEET'!$C:$CG,('DATA '!$AA$3+21+('DATA '!$AA$3-1)),0),"") | E27: =IFERROR(VLOOKUP(B27,'RJ ATTENDENCE SHEET'!$C:$CG,('DATA '!$AA$3+22+('DATA '!$AA$3-1)),0),"") | H27: 20 | I27: =VLOOKUP(J27,'DATA '!$O:$P,2,0) -> DRIVER | J27: ='DATA '!O22 -> MOFIJUL ALI | K27: =IFERROR(VLOOKUP(J27,'RJ ATTENDENCE SHEET'!$C:$CG,('DATA '!$AA$3+21+('DATA '!$AA$3-1)),0),"") -> P | L27: =IFERROR(VLOOKUP(J27,'RJ ATTENDENCE SHEET'!$C:$CG,('DATA '!$AA$3+22+('DATA '!$AA$3-1)),0),"") -> A | M27: =IFERROR(VLOOKUP(J27,'RJ ATTENDENCE SHEET'!$C:$DM,('DATA '!$AA$3+84),0),"") -> 0
B28: ='DATA '!S23 | D28: =IFERROR(VLOOKUP(B28,'RJ ATTENDENCE SHEET'!$C:$CG,('DATA '!$AA$3+21+('DATA '!$AA$3-1)),0),"") | E28: =IFERROR(VLOOKUP(B28,'RJ ATTENDENCE SHEET'!$C:$CG,('DATA '!$AA$3+22+('DATA '!$AA$3-1)),0),"") | H28: 21 | I28: =VLOOKUP(J28,'DATA '!$O:$P,2,0) -> LAB | J28: ='DATA '!O23 -> ASHIK AHMED | K28: =IFERROR(VLOOKUP(J28,'RJ ATTENDENCE SHEET'!$C:$CG,('DATA '!$AA$3+21+('DATA '!$AA$3-1)),0),"") -> A | L28: =IFERROR(VLOOKUP(J28,'RJ ATTENDENCE SHEET'!$C:$CG,('DATA '!$AA$3+22+('DATA '!$AA$3-1)),0),"") -> P | M28: =IFERROR(VLOOKUP(J28,'RJ ATTENDENCE SHEET'!$C:$DM,('DATA '!$AA$3+84),0),"") -> 0
B29: ='DATA '!S24 | D29: =IFERROR(VLOOKUP(B29,'RJ ATTENDENCE SHEET'!$C:$CG,('DATA '!$AA$3+21+('DATA '!$AA$3-1)),0),"") | E29: =IFERROR(VLOOKUP(B29,'RJ ATTENDENCE SHEET'!$C:$CG,('DATA '!$AA$3+22+('DATA '!$AA$3-1)),0),"") | H29: 22 | I29: =VLOOKUP(J29,'DATA '!$O:$P,2,0) -> LAB | J29: ='DATA '!O24 -> SAMIT MONDAL | K29: =IFERROR(VLOOKUP(J29,'RJ ATTENDENCE SHEET'!$C:$CG,('DATA '!$AA$3+21+('DATA '!$AA$3-1)),0),"") -> P | L29: =IFERROR(VLOOKUP(J29,'RJ ATTENDENCE SHEET'!$C:$CG,('DATA '!$AA$3+22+('DATA '!$AA$3-1)),0),"") -> A | M29: =IFERROR(VLOOKUP(J29,'RJ ATTENDENCE SHEET'!$C:$DM,('DATA '!$AA$3+84),0),"") -> 0
B30: ='DATA '!S25 | D30: =IFERROR(VLOOKUP(B30,'RJ ATTENDENCE SHEET'!$C:$CG,('DATA '!$AA$3+21+('DATA '!$AA$3-1)),0),"") | E30: =IFERROR(VLOOKUP(B30,'RJ ATTENDENCE SHEET'!$C:$CG,('DATA '!$AA$3+22+('DATA '!$AA$3-1)),0),"") | H30: 23 | I30: =VLOOKUP(J30,'DATA '!$O:$P,2,0) -> LAB | J30: ='DATA '!O25 -> SIDHARTHA MONDAL | K30: =IFERROR(VLOOKUP(J30,'RJ ATTENDENCE SHEET'!$C:$CG,('DATA '!$AA$3+21+('DATA '!$AA$3-1)),0),"") -> P | L30: =IFERROR(VLOOKUP(J30,'RJ ATTENDENCE SHEET'!$C:$CG,('DATA '!$AA$3+22+('DATA '!$AA$3-1)),0),"") -> A | M30: =IFERROR(VLOOKUP(J30,'RJ ATTENDENCE SHEET'!$C:$DM,('DATA '!$AA$3+84),0),"") -> 0
B31: ='DATA '!S26 | D31: =IFERROR(VLOOKUP(B31,'RJ ATTENDENCE SHEET'!$C:$CG,('DATA '!$AA$3+21+('DATA '!$AA$3-1)),0),"") | E31: =IFERROR(VLOOKUP(B31,'RJ ATTENDENCE SHEET'!$C:$CG,('DATA '!$AA$3+22+('DATA '!$AA$3-1)),0),"") | H31: 24 | I31: =VLOOKUP(J31,'DATA '!$O:$P,2,0) -> HOPPER | J31: ='DATA '!O26 -> SUBRATA MONDAL | K31: =IFERROR(VLOOKUP(J31,'RJ ATTENDENCE SHEET'!$C:$CG,('DATA '!$AA$3+21+('DATA '!$AA$3-1)),0),"") -> P | L31: =IFERROR(VLOOKUP(J31,'RJ ATTENDENCE SHEET'!$C:$CG,('DATA '!$AA$3+22+('DATA '!$AA$3-1)),0),"") -> A | M31: =IFERROR(VLOOKUP(J31,'RJ ATTENDENCE SHEET'!$C:$DM,('DATA '!$AA$3+84),0),"") -> 0
B32: ='DATA '!S27 | D32: =IFERROR(VLOOKUP(B32,'RJ ATTENDENCE SHEET'!$C:$CG,('DATA '!$AA$3+21+('DATA '!$AA$3-1)),0),"") | E32: =IFERROR(VLOOKUP(B32,'RJ ATTENDENCE SHEET'!$C:$CG,('DATA '!$AA$3+22+('DATA '!$AA$3-1)),0),"") | H32: 25 | I32: =VLOOKUP(J32,'DATA '!$O:$P,2,0) -> HELPER | J32: ='DATA '!O27 -> REJJAK MONDAL | K32: =IFERROR(VLOOKUP(J32,'RJ ATTENDENCE SHEET'!$C:$CG,('DATA '!$AA$3+21+('DATA '!$AA$3-1)),0),"") -> P | L32: =IFERROR(VLOOKUP(J32,'RJ ATTENDENCE SHEET'!$C:$CG,('DATA '!$AA$3+22+('DATA '!$AA$3-1)),0),"") -> A | M32: =IFERROR(VLOOKUP(J32,'RJ ATTENDENCE SHEET'!$C:$DM,('DATA '!$AA$3+84),0),"") -> 0
B33: ='DATA '!S28 | D33: =IFERROR(VLOOKUP(B33,'RJ ATTENDENCE SHEET'!$C:$CG,('DATA '!$AA$3+21+('DATA '!$AA$3-1)),0),"") | E33: =IFERROR(VLOOKUP(B33,'RJ ATTENDENCE SHEET'!$C:$CG,('DATA '!$AA$3+22+('DATA '!$AA$3-1)),0),"") | H33: 26 | I33: =VLOOKUP(J33,'DATA '!$O:$P,2,0) -> DRIVER | J33: ='DATA '!O28 -> BISWANTH MONDAL | K33: =IFERROR(VLOOKUP(J33,'RJ ATTENDENCE SHEET'!$C:$CG,('DATA '!$AA$3+21+('DATA '!$AA$3-1)),0),"") -> A | L33: =IFERROR(VLOOKUP(J33,'RJ ATTENDENCE SHEET'!$C:$CG,('DATA '!$AA$3+22+('DATA '!$AA$3-1)),0),"") -> P | M33: =IFERROR(VLOOKUP(J33,'RJ ATTENDENCE SHEET'!$C:$DM,('DATA '!$AA$3+84),0),"") -> 0
B34: ='DATA '!S29 | D34: =IFERROR(VLOOKUP(B34,'RJ ATTENDENCE SHEET'!$C:$CG,('DATA '!$AA$3+21+('DATA '!$AA$3-1)),0),"") | E34: =IFERROR(VLOOKUP(B34,'RJ ATTENDENCE SHEET'!$C:$CG,('DATA '!$AA$3+22+('DATA '!$AA$3-1)),0),"") | H34: 27 | I34: =VLOOKUP(J34,'DATA '!$O:$P,2,0) -> HELPER | J34: ='DATA '!O29 -> TAPAS MONDAL | K34: =IFERROR(VLOOKUP(J34,'RJ ATTENDENCE SHEET'!$C:$CG,('DATA '!$AA$3+21+('DATA '!$AA$3-1)),0),"") -> P | L34: =IFERROR(VLOOKUP(J34,'RJ ATTENDENCE SHEET'!$C:$CG,('DATA '!$AA$3+22+('DATA '!$AA$3-1)),0),"") -> P | M34: =IFERROR(VLOOKUP(J34,'RJ ATTENDENCE SHEET'!$C:$DM,('DATA '!$AA$3+84),0),"") -> 1
B35: ='DATA '!S30 | D35: =IFERROR(VLOOKUP(B35,'RJ ATTENDENCE SHEET'!$C:$CG,('DATA '!$AA$3+21+('DATA '!$AA$3-1)),0),"") | E35: =IFERROR(VLOOKUP(B35,'RJ ATTENDENCE SHEET'!$C:$CG,('DATA '!$AA$3+22+('DATA '!$AA$3-1)),0),"") | H35: 28 | I35: =VLOOKUP(J35,'DATA '!$O:$P,2,0) -> HELPER | J35: ='DATA '!O30 -> RASHID MONDAL | K35: =IFERROR(VLOOKUP(J35,'RJ ATTENDENCE SHEET'!$C:$CG,('DATA '!$AA$3+21+('DATA '!$AA$3-1)),0),"") -> P | L35: =IFERROR(VLOOKUP(J35,'RJ ATTENDENCE SHEET'!$C:$CG,('DATA '!$AA$3+22+('DATA '!$AA$3-1)),0),"") -> A | M35: =IFERROR(VLOOKUP(J35,'RJ ATTENDENCE SHEET'!$C:$DM,('DATA '!$AA$3+84),0),"") -> 0
B36: ='DATA '!S31 | D36: =IFERROR(VLOOKUP(B36,'RJ ATTENDENCE SHEET'!$C:$CG,('DATA '!$AA$3+21+('DATA '!$AA$3-1)),0),"") | E36: =IFERROR(VLOOKUP(B36,'RJ ATTENDENCE SHEET'!$C:$CG,('DATA '!$AA$3+22+('DATA '!$AA$3-1)),0),"") | H36: 29 | I36: =VLOOKUP(J36,'DATA '!$O:$P,2,0) -> HELPER | J36: ='DATA '!O31 -> RAJU MONDAL | K36: =IFERROR(VLOOKUP(J36,'RJ ATTENDENCE SHEET'!$C:$CG,('DATA '!$AA$3+21+('DATA '!$AA$3-1)),0),"") -> A | L36: =IFERROR(VLOOKUP(J36,'RJ ATTENDENCE SHEET'!$C:$CG,('DATA '!$AA$3+22+('DATA '!$AA$3-1)),0),"") -> P | M36: =IFERROR(VLOOKUP(J36,'RJ ATTENDENCE SHEET'!$C:$DM,('DATA '!$AA$3+84),0),"") -> 0
B37: ='DATA '!S32 | D37: =IFERROR(VLOOKUP(B37,'RJ ATTENDENCE SHEET'!$C:$CG,('DATA '!$AA$3+21+('DATA '!$AA$3-1)),0),"") | E37: =IFERROR(VLOOKUP(B37,'RJ ATTENDENCE SHEET'!$C:$CG,('DATA '!$AA$3+22+('DATA '!$AA$3-1)),0),"") | H37: 30 | I37: =VLOOKUP(J37,'DATA '!$O:$P,2,0) -> HELPER | J37: ='DATA '!O32 -> SUDIP MONDAL | K37: =IFERROR(VLOOKUP(J37,'RJ ATTENDENCE SHEET'!$C:$CG,('DATA '!$AA$3+21+('DATA '!$AA$3-1)),0),"") -> A | L37: =IFERROR(VLOOKUP(J37,'RJ ATTENDENCE SHEET'!$C:$CG,('DATA '!$AA$3+22+('DATA '!$AA$3-1)),0),"") -> P | M37: =IFERROR(VLOOKUP(J37,'RJ ATTENDENCE SHEET'!$C:$DM,('DATA '!$AA$3+84),0),"") -> 0
B38: ='DATA '!S33 | D38: =IFERROR(VLOOKUP(B38,'RJ ATTENDENCE SHEET'!$C:$CG,('DATA '!$AA$3+21+('DATA '!$AA$3-1)),0),"") | E38: =IFERROR(VLOOKUP(B38,'RJ ATTENDENCE SHEET'!$C:$CG,('DATA '!$AA$3+22+('DATA '!$AA$3-1)),0),"") | H38: 31 | I38: =VLOOKUP(J38,'DATA '!$O:$P,2,0) -> OTHERS | J38: ='DATA '!O33 -> ALMIRAJ JHAN | K38: =IFERROR(VLOOKUP(J38,'RJ ATTENDENCE SHEET'!$C:$CG,('DATA '!$AA$3+21+('DATA '!$AA$3-1)),0),"") -> 0 | L38: =IFERROR(VLOOKUP(J38,'RJ ATTENDENCE SHEET'!$C:$CG,('DATA '!$AA$3+22+('DATA '!$AA$3-1)),0),"") -> 0 | M38: =IFERROR(VLOOKUP(J38,'RJ ATTENDENCE SHEET'!$C:$DM,('DATA '!$AA$3+84),0),"") -> 0
B39: ='DATA '!S34 | D39: =IFERROR(VLOOKUP(B39,'RJ ATTENDENCE SHEET'!$C:$CG,('DATA '!$AA$3+21+('DATA '!$AA$3-1)),0),"") | E39: =IFERROR(VLOOKUP(B39,'RJ ATTENDENCE SHEET'!$C:$CG,('DATA '!$AA$3+22+('DATA '!$AA$3-1)),0),"") | H39: 32 | I39: =VLOOKUP(J39,'DATA '!$O:$P,2,0) -> HELPER | J39: ='DATA '!O34 -> SAMSUR | K39: =IFERROR(VLOOKUP(J39,'RJ ATTENDENCE SHEET'!$C:$CG,('DATA '!$AA$3+21+('DATA '!$AA$3-1)),0),"") -> P | L39: =IFERROR(VLOOKUP(J39,'RJ ATTENDENCE SHEET'!$C:$CG,('DATA '!$AA$3+22+('DATA '!$AA$3-1)),0),"") -> P | M39: =IFERROR(VLOOKUP(J39,'RJ ATTENDENCE SHEET'!$C:$DM,('DATA '!$AA$3+84),0),"") -> 0
... B42: ='DATA '!S37 | D42: =IFERROR(VLOOKUP(B42,'RJ ATTENDENCE SHEET'!$C:$CG,('DATA '!$AA$3+21+('DATA '!$AA$3-1)),0),"") | E42: =IFERROR(VLOOKUP(B42,'RJ ATTENDENCE SHEET'!$C:$CG,('DATA '!$AA$3+22+('DATA '!$AA$3-1)),0),"") | H42: 35 | I42: =VLOOKUP(J42,'DATA '!$O:$P,2,0) | J42: ='DATA '!O37 | K42: =IFERROR(VLOOKUP(J42,'RJ ATTENDENCE SHEET'!$C:$CG,('DATA '!$AA$3+21+('DATA '!$AA$3-1)),0),"") | L42: =IFERROR(VLOOKUP(J42,'RJ ATTENDENCE SHEET'!$C:$CG,('DATA '!$AA$3+22+('DATA '!$AA$3-1)),0),"") | M42: =IFERROR(VLOOKUP(J42,'RJ ATTENDENCE SHEET'!$C:$DM,('DATA '!$AA$3+84),0),"")
H43: 36 | I43: =VLOOKUP(J43,'DATA '!$O:$P,2,0) | J43: ='DATA '!O38 | K43: =IFERROR(VLOOKUP(J43,'RJ ATTENDENCE SHEET'!$C:$CG,('DATA '!$AA$3+21+('DATA '!$AA$3-1)),0),"") | L43: =IFERROR(VLOOKUP(J43,'RJ ATTENDENCE SHEET'!$C:$CG,('DATA '!$AA$3+22+('DATA '!$AA$3-1)),0),"") | M43: =IFERROR(VLOOKUP(J43,'RJ ATTENDENCE SHEET'!$C:$DM,('DATA '!$AA$3+84),0),"")
H44: 37 | I44: =VLOOKUP(J44,'DATA '!$O:$P,2,0) | J44: ='DATA '!O39 | K44: =IFERROR(VLOOKUP(J44,'RJ ATTENDENCE SHEET'!$C:$CG,('DATA '!$AA$3+21+('DATA '!$AA$3-1)),0),"") | L44: =IFERROR(VLOOKUP(J44,'RJ ATTENDENCE SHEET'!$C:$CG,('DATA '!$AA$3+22+('DATA '!$AA$3-1)),0),"") | M44: =IFERROR(VLOOKUP(J44,'RJ ATTENDENCE SHEET'!$C:$DM,('DATA '!$AA$3+84),0),"")
H45: 38 | I45: =VLOOKUP(J45,'DATA '!$O:$P,2,0) | J45: ='DATA '!O40 | K45: =IFERROR(VLOOKUP(J45,'RJ ATTENDENCE SHEET'!$C:$CG,('DATA '!$AA$3+21+('DATA '!$AA$3-1)),0),"") | L45: =IFERROR(VLOOKUP(J45,'RJ ATTENDENCE SHEET'!$C:$CG,('DATA '!$AA$3+22+('DATA '!$AA$3-1)),0),"") | M45: =IFERROR(VLOOKUP(J45,'RJ ATTENDENCE SHEET'!$C:$DM,('DATA '!$AA$3+84),0),"")
H46: 39 | I46: =VLOOKUP(J46,'DATA '!$O:$P,2,0) | J46: ='DATA '!O41 | K46: =IFERROR(VLOOKUP(J46,'RJ ATTENDENCE SHEET'!$C:$CG,('DATA '!$AA$3+21+('DATA '!$AA$3-1)),0),"") | L46: =IFERROR(VLOOKUP(J46,'RJ ATTENDENCE SHEET'!$C:$CG,('DATA '!$AA$3+22+('DATA '!$AA$3-1)),0),"") | M46: =IFERROR(VLOOKUP(J46,'RJ ATTENDENCE SHEET'!$C:$DM,('DATA '!$AA$3+84),0),"")
H47: 40 | I47: =VLOOKUP(J47,'DATA '!$O:$P,2,0) | J47: ='DATA '!O42 | K47: =IFERROR(VLOOKUP(J47,'RJ ATTENDENCE SHEET'!$C:$CG,('DATA '!$AA$3+21+('DATA '!$AA$3-1)),0),"") | L47: =IFERROR(VLOOKUP(J47,'RJ ATTENDENCE SHEET'!$C:$CG,('DATA '!$AA$3+22+('DATA '!$AA$3-1)),0),"") | M47: =IFERROR(VLOOKUP(J47,'RJ ATTENDENCE SHEET'!$C:$DM,('DATA '!$AA$3+84),0),"")
H48: 41 | I48: =VLOOKUP(J48,'DATA '!$O:$P,2,0) | J48: ='DATA '!O43 | K48: =IFERROR(VLOOKUP(J48,'RJ ATTENDENCE SHEET'!$C:$CG,('DATA '!$AA$3+21+('DATA '!$AA$3-1)),0),"") | L48: =IFERROR(VLOOKUP(J48,'RJ ATTENDENCE SHEET'!$C:$CG,('DATA '!$AA$3+22+('DATA '!$AA$3-1)),0),"") | M48: =IFERROR(VLOOKUP(J48,'RJ ATTENDENCE SHEET'!$C:$DM,('DATA '!$AA$3+84),0),"")
A49: SL.NO | C49: NAME | D49: DUTY | F49: TRIP | H49: 42 | I49: =VLOOKUP(J49,'DATA '!$O:$P,2,0) | J49: ='DATA '!O44 | K49: =IFERROR(VLOOKUP(J49,'RJ ATTENDENCE SHEET'!$C:$CG,('DATA '!$AA$3+21+('DATA '!$AA$3-1)),0),"") | L49: =IFERROR(VLOOKUP(J49,'RJ ATTENDENCE SHEET'!$C:$CG,('DATA '!$AA$3+22+('DATA '!$AA$3-1)),0),"") | M49: =IFERROR(VLOOKUP(J49,'RJ ATTENDENCE SHEET'!$C:$DM,('DATA '!$AA$3+84),0),"")
D50: DAY | E50: NIGHT | H50: 43 | I50: =VLOOKUP(J50,'DATA '!$O:$P,2,0) | J50: ='DATA '!O45 | K50: =IFERROR(VLOOKUP(J50,'RJ ATTENDENCE SHEET'!$C:$CG,('DATA '!$AA$3+21+('DATA '!$AA$3-1)),0),"") | L50: =IFERROR(VLOOKUP(J50,'RJ ATTENDENCE SHEET'!$C:$CG,('DATA '!$AA$3+22+('DATA '!$AA$3-1)),0),"") | M50: =IFERROR(VLOOKUP(J50,'RJ ATTENDENCE SHEET'!$C:$DM,('DATA '!$AA$3+84),0),"")
A51: WAGES | H51: 44 | I51: =VLOOKUP(J51,'DATA '!$O:$P,2,0) | J51: ='DATA '!O46 | K51: =IFERROR(VLOOKUP(J51,'RJ ATTENDENCE SHEET'!$C:$CG,('DATA '!$AA$3+21+('DATA '!$AA$3-1)),0),"") | L51: =IFERROR(VLOOKUP(J51,'RJ ATTENDENCE SHEET'!$C:$CG,('DATA '!$AA$3+22+('DATA '!$AA$3-1)),0),"") | M51: =IFERROR(VLOOKUP(J51,'RJ ATTENDENCE SHEET'!$C:$DM,('DATA '!$AA$3+84),0),"")
A52: 1 | B52: =VLOOKUP(C52,'DATA '!$K:$L,2,0) -> DRIVER | C52: ='DATA '!K3 -> ANISUR | D52: =IFERROR(VLOOKUP(C52,'RJ ATTENDENCE SHEET'!$C:$CG,('DATA '!$AA$3+21+('DATA '!$AA$3-1)),0),"") -> A | E52: =IFERROR(VLOOKUP(C52,'RJ ATTENDENCE SHEET'!$C:$CG,('DATA '!$AA$3+22+('DATA '!$AA$3-1)),0),"") -> P | F52: =VLOOKUP(C52,'RJ ATTENDENCE SHEET'!$C:$DM,('DATA '!$AA$3+84),0) -> 0 | H52: 45 | I52: =VLOOKUP(J52,'DATA '!$O:$P,2,0) | J52: ='DATA '!O47 | K52: =IFERROR(VLOOKUP(J52,'RJ ATTENDENCE SHEET'!$C:$CG,('DATA '!$AA$3+21+('DATA '!$AA$3-1)),0),"") | L52: =IFERROR(VLOOKUP(J52,'RJ ATTENDENCE SHEET'!$C:$CG,('DATA '!$AA$3+22+('DATA '!$AA$3-1)),0),"") | M52: =IFERROR(VLOOKUP(J52,'RJ ATTENDENCE SHEET'!$C:$DM,('DATA '!$AA$3+84),0),"")
A53: 2 | B53: =VLOOKUP(C53,'DATA '!$K:$L,2,0) -> DRIVER | C53: ='DATA '!K4 -> ARMAN ALI MONDAL | D53: =IFERROR(VLOOKUP(C53,'RJ ATTENDENCE SHEET'!$C:$CG,('DATA '!$AA$3+21+('DATA '!$AA$3-1)),0),"") -> P | E53: =IFERROR(VLOOKUP(C53,'RJ ATTENDENCE SHEET'!$C:$CG,('DATA '!$AA$3+22+('DATA '!$AA$3-1)),0),"") -> P | F53: =VLOOKUP(C53,'RJ ATTENDENCE SHEET'!$C:$DM,('DATA '!$AA$3+84),0) -> 1 | H53: 46 | I53: =VLOOKUP(J53,'DATA '!$O:$P,2,0) | J53: ='DATA '!O48 | K53: =IFERROR(VLOOKUP(J53,'RJ ATTENDENCE SHEET'!$C:$CG,('DATA '!$AA$3+21+('DATA '!$AA$3-1)),0),"") | L53: =IFERROR(VLOOKUP(J53,'RJ ATTENDENCE SHEET'!$C:$CG,('DATA '!$AA$3+22+('DATA '!$AA$3-1)),0),"") | M53: =IFERROR(VLOOKUP(J53,'RJ ATTENDENCE SHEET'!$C:$DM,('DATA '!$AA$3+84),0),"")
A54: 3 | B54: =VLOOKUP(C54,'DATA '!$K:$L,2,0) -> HELPER | C54: ='DATA '!K5 -> ASUTOSH SARDAR | D54: =IFERROR(VLOOKUP(C54,'RJ ATTENDENCE SHEET'!$C:$CG,('DATA '!$AA$3+21+('DATA '!$AA$3-1)),0),"") -> P | E54: =IFERROR(VLOOKUP(C54,'RJ ATTENDENCE SHEET'!$C:$CG,('DATA '!$AA$3+22+('DATA '!$AA$3-1)),0),"") -> P | F54: =VLOOKUP(C54,'RJ ATTENDENCE SHEET'!$C:$DM,('DATA '!$AA$3+84),0) -> 1 | H54: 47 | I54: =VLOOKUP(J54,'DATA '!$O:$P,2,0) | J54: ='DATA '!O49 | K54: =IFERROR(VLOOKUP(J54,'RJ ATTENDENCE SHEET'!$C:$CG,('DATA '!$AA$3+21+('DATA '!$AA$3-1)),0),"") | L54: =IFERROR(VLOOKUP(J54,'RJ ATTENDENCE SHEET'!$C:$CG,('DATA '!$AA$3+22+('DATA '!$AA$3-1)),0),"") | M54: =IFERROR(VLOOKUP(J54,'RJ ATTENDENCE SHEET'!$C:$DM,('DATA '!$AA$3+84),0),"")
A55: 4 | B55: =VLOOKUP(C55,'DATA '!$K:$L,2,0) -> LAB | C55: ='DATA '!K6 -> BUDDHADEV SEAL | D55: =IFERROR(VLOOKUP(C55,'RJ ATTENDENCE SHEET'!$C:$CG,('DATA '!$AA$3+21+('DATA '!$AA$3-1)),0),"") -> A | E55: =IFERROR(VLOOKUP(C55,'RJ ATTENDENCE SHEET'!$C:$CG,('DATA '!$AA$3+22+('DATA '!$AA$3-1)),0),"") -> P | F55: =VLOOKUP(C55,'RJ ATTENDENCE SHEET'!$C:$DM,('DATA '!$AA$3+84),0) -> 0 | H55: 48 | I55: =VLOOKUP(J55,'DATA '!$O:$P,2,0) | J55: ='DATA '!O50 | K55: =IFERROR(VLOOKUP(J55,'RJ ATTENDENCE SHEET'!$C:$CG,('DATA '!$AA$3+21+('DATA '!$AA$3-1)),0),"") | L55: =IFERROR(VLOOKUP(J55,'RJ ATTENDENCE SHEET'!$C:$CG,('DATA '!$AA$3+22+('DATA '!$AA$3-1)),0),"") | M55: =IFERROR(VLOOKUP(J55,'RJ ATTENDENCE SHEET'!$C:$DM,('DATA '!$AA$3+84),0),"")
A56: 5 | B56: =VLOOKUP(C56,'DATA '!$K:$L,2,0) -> DRIVER | C56: ='DATA '!K7 -> FARUK ALI | D56: =IFERROR(VLOOKUP(C56,'RJ ATTENDENCE SHEET'!$C:$CG,('DATA '!$AA$3+21+('DATA '!$AA$3-1)),0),"") -> P | E56: =IFERROR(VLOOKUP(C56,'RJ ATTENDENCE SHEET'!$C:$CG,('DATA '!$AA$3+22+('DATA '!$AA$3-1)),0),"") -> P | F56: =VLOOKUP(C56,'RJ ATTENDENCE SHEET'!$C:$DM,('DATA '!$AA$3+84),0) -> 1 | H56: 49 | I56: =VLOOKUP(J56,'DATA '!$O:$P,2,0) | J56: ='DATA '!O51 | K56: =IFERROR(VLOOKUP(J56,'RJ ATTENDENCE SHEET'!$C:$CG,('DATA '!$AA$3+21+('DATA '!$AA$3-1)),0),"") | L56: =IFERROR(VLOOKUP(J56,'RJ ATTENDENCE SHEET'!$C:$CG,('DATA '!$AA$3+22+('DATA '!$AA$3-1)),0),"") | M56: =IFERROR(VLOOKUP(J56,'RJ ATTENDENCE SHEET'!$C:$DM,('DATA '!$AA$3+84),0),"")
A57: 6 | B57: =VLOOKUP(C57,'DATA '!$K:$L,2,0) -> HOPPER | C57: ='DATA '!K8 -> KUTUBUDDIN MOLLA | D57: =IFERROR(VLOOKUP(C57,'RJ ATTENDENCE SHEET'!$C:$CG,('DATA '!$AA$3+21+('DATA '!$AA$3-1)),0),"") -> P | E57: =IFERROR(VLOOKUP(C57,'RJ ATTENDENCE SHEET'!$C:$CG,('DATA '!$AA$3+22+('DATA '!$AA$3-1)),0),"") -> A | F57: =VLOOKUP(C57,'RJ ATTENDENCE SHEET'!$C:$DM,('DATA '!$AA$3+84),0) -> 0 | H57: 50 | I57: =VLOOKUP(J57,'DATA '!$O:$P,2,0) | J57: ='DATA '!O52 | K57: =IFERROR(VLOOKUP(J57,'RJ ATTENDENCE SHEET'!$C:$CG,('DATA '!$AA$3+21+('DATA '!$AA$3-1)),0),"") | L57: =IFERROR(VLOOKUP(J57,'RJ ATTENDENCE SHEET'!$C:$CG,('DATA '!$AA$3+22+('DATA '!$AA$3-1)),0),"") | M57: =IFERROR(VLOOKUP(J57,'RJ ATTENDENCE SHEET'!$C:$DM,('DATA '!$AA$3+84),0),"")
A58: 7 | B58: =VLOOKUP(C58,'DATA '!$K:$L,2,0) -> OTHERS | C58: ='DATA '!K9 -> MD. SAMIM AKRAM | D58: =IFERROR(VLOOKUP(C58,'RJ ATTENDENCE SHEET'!$C:$CG,('DATA '!$AA$3+21+('DATA '!$AA$3-1)),0),"") -> P | E58: =IFERROR(VLOOKUP(C58,'RJ ATTENDENCE SHEET'!$C:$CG,('DATA '!$AA$3+22+('DATA '!$AA$3-1)),0),"") -> A | F58: =VLOOKUP(C58,'RJ ATTENDENCE SHEET'!$C:$DM,('DATA '!$AA$3+84),0) -> 0 | H58: 51 | I58: =VLOOKUP(J58,'DATA '!$O:$P,2,0) | J58: ='DATA '!O53 | K58: =IFERROR(VLOOKUP(J58,'RJ ATTENDENCE SHEET'!$C:$CG,('DATA '!$AA$3+21+('DATA '!$AA$3-1)),0),"") | L58: =IFERROR(VLOOKUP(J58,'RJ ATTENDENCE SHEET'!$C:$CG,('DATA '!$AA$3+22+('DATA '!$AA$3-1)),0),"") | M58: =IFERROR(VLOOKUP(J58,'RJ ATTENDENCE SHEET'!$C:$DM,('DATA '!$AA$3+84),0),"")
A59: 8 | B59: =VLOOKUP(C59,'DATA '!$K:$L,2,0) -> DRIVER | C59: ='DATA '!K10 -> MOTIAR RAHAMAN | D59: =IFERROR(VLOOKUP(C59,'RJ ATTENDENCE SHEET'!$C:$CG,('DATA '!$AA$3+21+('DATA '!$AA$3-1)),0),"") -> P | E59: =IFERROR(VLOOKUP(C59,'RJ ATTENDENCE SHEET'!$C:$CG,('DATA '!$AA$3+22+('DATA '!$AA$3-1)),0),"") -> P | F59: =VLOOKUP(C59,'RJ ATTENDENCE SHEET'!$C:$DM,('DATA '!$AA$3+84),0) -> 0 | H59: 52 | I59: =VLOOKUP(J59,'DATA '!$O:$P,2,0) | J59: ='DATA '!O54 | K59: =IFERROR(VLOOKUP(J59,'RJ ATTENDENCE SHEET'!$C:$CG,('DATA '!$AA$3+21+('DATA '!$AA$3-1)),0),"") | L59: =IFERROR(VLOOKUP(J59,'RJ ATTENDENCE SHEET'!$C:$CG,('DATA '!$AA$3+22+('DATA '!$AA$3-1)),0),"") | M59: =IFERROR(VLOOKUP(J59,'RJ ATTENDENCE SHEET'!$C:$DM,('DATA '!$AA$3+84),0),"")
A60: 9 | B60: =VLOOKUP(C60,'DATA '!$K:$L,2,0) -> DRIVER | C60: ='DATA '!K11 -> MOKSHED ALI | D60: =IFERROR(VLOOKUP(C60,'RJ ATTENDENCE SHEET'!$C:$CG,('DATA '!$AA$3+21+('DATA '!$AA$3-1)),0),"") -> P | E60: =IFERROR(VLOOKUP(C60,'RJ ATTENDENCE SHEET'!$C:$CG,('DATA '!$AA$3+22+('DATA '!$AA$3-1)),0),"") -> P | F60: =VLOOKUP(C60,'RJ ATTENDENCE SHEET'!$C:$DM,('DATA '!$AA$3+84),0) -> 0 | H60: 53 | I60: =VLOOKUP(J60,'DATA '!$O:$P,2,0) | J60: ='DATA '!O55 | K60: =IFERROR(VLOOKUP(J60,'RJ ATTENDENCE SHEET'!$C:$CG,('DATA '!$AA$3+21+('DATA '!$AA$3-1)),0),"") | L60: =IFERROR(VLOOKUP(J60,'RJ ATTENDENCE SHEET'!$C:$CG,('DATA '!$AA$3+22+('DATA '!$AA$3-1)),0),"") | M60: =IFERROR(VLOOKUP(J60,'RJ ATTENDENCE SHEET'!$C:$DM,('DATA '!$AA$3+84),0),"")
A61: 10 | B61: =VLOOKUP(C61,'DATA '!$K:$L,2,0) -> DRIVER | C61: ='DATA '!K12 -> SAMSER ALI | D61: =IFERROR(VLOOKUP(C61,'RJ ATTENDENCE SHEET'!$C:$CG,('DATA '!$AA$3+21+('DATA '!$AA$3-1)),0),"") -> P | E61: =IFERROR(VLOOKUP(C61,'RJ ATTENDENCE SHEET'!$C:$CG,('DATA '!$AA$3+22+('DATA '!$AA$3-1)),0),"") -> A | F61: =VLOOKUP(C61,'RJ ATTENDENCE SHEET'!$C:$DM,('DATA '!$AA$3+84),0) -> 0 | H61: 54 | I61: =VLOOKUP(J61,'DATA '!$O:$P,2,0) | J61: ='DATA '!O56 | K61: =IFERROR(VLOOKUP(J61,'RJ ATTENDENCE SHEET'!$C:$CG,('DATA '!$AA$3+21+('DATA '!$AA$3-1)),0),"") | L61: =IFERROR(VLOOKUP(J61,'RJ ATTENDENCE SHEET'!$C:$CG,('DATA '!$AA$3+22+('DATA '!$AA$3-1)),0),"") | M61: =IFERROR(VLOOKUP(J61,'RJ ATTENDENCE SHEET'!$C:$DM,('DATA '!$AA$3+84),0),"")
A62: 11 | B62: =VLOOKUP(C62,'DATA '!$K:$L,2,0) -> DRIVER | C62: ='DATA '!K13 -> SHANTI MONDAL | D62: =IFERROR(VLOOKUP(C62,'RJ ATTENDENCE SHEET'!$C:$CG,('DATA '!$AA$3+21+('DATA '!$AA$3-1)),0),"") -> P | E62: =IFERROR(VLOOKUP(C62,'RJ ATTENDENCE SHEET'!$C:$CG,('DATA '!$AA$3+22+('DATA '!$AA$3-1)),0),"") -> P | F62: =VLOOKUP(C62,'RJ ATTENDENCE SHEET'!$C:$DM,('DATA '!$AA$3+84),0) -> 0 | H62: 55 | I62: =VLOOKUP(J62,'DATA '!$O:$P,2,0) | J62: ='DATA '!O57 | K62: =IFERROR(VLOOKUP(J62,'RJ ATTENDENCE SHEET'!$C:$CG,('DATA '!$AA$3+21+('DATA '!$AA$3-1)),0),"") | L62: =IFERROR(VLOOKUP(J62,'RJ ATTENDENCE SHEET'!$C:$CG,('DATA '!$AA$3+22+('DATA '!$AA$3-1)),0),"") | M62: =IFERROR(VLOOKUP(J62,'RJ ATTENDENCE SHEET'!$C:$DM,('DATA '!$AA$3+84),0),"")
A63: 12 | B63: =VLOOKUP(C63,'DATA '!$K:$L,2,0) -> DRIVER | C63: ='DATA '!K14 -> SIRAJUL MOLLA | D63: =IFERROR(VLOOKUP(C63,'RJ ATTENDENCE SHEET'!$C:$CG,('DATA '!$AA$3+21+('DATA '!$AA$3-1)),0),"") -> A | E63: =IFERROR(VLOOKUP(C63,'RJ ATTENDENCE SHEET'!$C:$CG,('DATA '!$AA$3+22+('DATA '!$AA$3-1)),0),"") -> P | F63: =VLOOKUP(C63,'RJ ATTENDENCE SHEET'!$C:$DM,('DATA '!$AA$3+84),0) -> 0 | H63: 56 | I63: =VLOOKUP(J63,'DATA '!$O:$P,2,0) | J63: ='DATA '!O58 | K63: =IFERROR(VLOOKUP(J63,'RJ ATTENDENCE SHEET'!$C:$CG,('DATA '!$AA$3+21+('DATA '!$AA$3-1)),0),"") | L63: =IFERROR(VLOOKUP(J63,'RJ ATTENDENCE SHEET'!$C:$CG,('DATA '!$AA$3+22+('DATA '!$AA$3-1)),0),"") | M63: =IFERROR(VLOOKUP(J63,'RJ ATTENDENCE SHEET'!$C:$DM,('DATA '!$AA$3+84),0),"")
... A75: 24 | B75: =VLOOKUP(C75,'DATA '!$K:$L,2,0) -> LAB | C75: ='DATA '!K26 -> MOMINUL HAQUE | D75: =IFERROR(VLOOKUP(C75,'RJ ATTENDENCE SHEET'!$C:$CG,('DATA '!$AA$3+21+('DATA '!$AA$3-1)),0),"") -> P | E75: =IFERROR(VLOOKUP(C75,'RJ ATTENDENCE SHEET'!$C:$CG,('DATA '!$AA$3+22+('DATA '!$AA$3-1)),0),"") -> A | F75: =VLOOKUP(C75,'RJ ATTENDENCE SHEET'!$C:$DM,('DATA '!$AA$3+84),0) -> 0 | H75: 68 | I75: =VLOOKUP(J75,'DATA '!$O:$P,2,0) | J75: ='DATA '!O70 | K75: =IFERROR(VLOOKUP(J75,'RJ ATTENDENCE SHEET'!$C:$CG,('DATA '!$AA$3+21+('DATA '!$AA$3-1)),0),"") | L75: =IFERROR(VLOOKUP(J75,'RJ ATTENDENCE SHEET'!$C:$CG,('DATA '!$AA$3+22+('DATA '!$AA$3-1)),0),"") | M75: =IFERROR(VLOOKUP(J75,'RJ ATTENDENCE SHEET'!$C:$DM,('DATA '!$AA$3+84),0),"")
A76: 25 | B76: =VLOOKUP(C76,'DATA '!$K:$L,2,0) -> HELPER | C76: ='DATA '!K27 -> EKRAMUL ALI | D76: =IFERROR(VLOOKUP(C76,'RJ ATTENDENCE SHEET'!$C:$CG,('DATA '!$AA$3+18+('DATA '!$AA$3-1)),0),"") -> P | E76: =IFERROR(VLOOKUP(C76,'RJ ATTENDENCE SHEET'!$C:$CG,('DATA '!$AA$3+19+('DATA '!$AA$3-1)),0),"") -> P | F76: =VLOOKUP(C76,'RJ ATTENDENCE SHEET'!$C:$DM,('DATA '!$AA$3+84),0) -> 0 | H76: 69 | I76: =VLOOKUP(J76,'DATA '!$O:$P,2,0) | J76: ='DATA '!O71 | K76: =IFERROR(VLOOKUP(J76,'RJ ATTENDENCE SHEET'!$C:$CG,('DATA '!$AA$3+21+('DATA '!$AA$3-1)),0),"") | L76: =IFERROR(VLOOKUP(J76,'RJ ATTENDENCE SHEET'!$C:$CG,('DATA '!$AA$3+22+('DATA '!$AA$3-1)),0),"") | M76: =IFERROR(VLOOKUP(J76,'RJ ATTENDENCE SHEET'!$C:$DM,('DATA '!$AA$3+84),0),"")
A77: 26 | B77: =VLOOKUP(C77,'DATA '!$K:$L,2,0) -> DRIVER | C77: ='DATA '!K28 -> JULFIKAR DHALI | D77: =IFERROR(VLOOKUP(C77,'RJ ATTENDENCE SHEET'!$C:$CG,('DATA '!$AA$3+18+('DATA '!$AA$3-1)),0),"") -> P | E77: =IFERROR(VLOOKUP(C77,'RJ ATTENDENCE SHEET'!$C:$CG,('DATA '!$AA$3+19+('DATA '!$AA$3-1)),0),"") -> P | H77: 70 | I77: =VLOOKUP(J77,'DATA '!$O:$P,2,0) | J77: ='DATA '!O72 | K77: =IFERROR(VLOOKUP(J77,'RJ ATTENDENCE SHEET'!$C:$CG,('DATA '!$AA$3+21+('DATA '!$AA$3-1)),0),"") | L77: =IFERROR(VLOOKUP(J77,'RJ ATTENDENCE SHEET'!$C:$CG,('DATA '!$AA$3+22+('DATA '!$AA$3-1)),0),"") | M77: =IFERROR(VLOOKUP(J77,'RJ ATTENDENCE SHEET'!$C:$DM,('DATA '!$AA$3+84),0),"")
A78: 27 | B78: =VLOOKUP(C78,'DATA '!$K:$L,2,0) -> LAB | C78: ='DATA '!K29 -> SUPRAKASH SAMANTO | D78: =IFERROR(VLOOKUP(C78,'RJ ATTENDENCE SHEET'!$C:$CG,('DATA '!$AA$3+18+('DATA '!$AA$3-1)),0),"") -> A | E78: =IFERROR(VLOOKUP(C78,'RJ ATTENDENCE SHEET'!$C:$CG,('DATA '!$AA$3+19+('DATA '!$AA$3-1)),0),"") -> A | H78: 71 | I78: =VLOOKUP(J78,'DATA '!$O:$P,2,0) | J78: ='DATA '!O73 | K78: =IFERROR(VLOOKUP(J78,'RJ ATTENDENCE SHEET'!$C:$CG,('DATA '!$AA$3+21+('DATA '!$AA$3-1)),0),"") | L78: =IFERROR(VLOOKUP(J78,'RJ ATTENDENCE SHEET'!$C:$CG,('DATA '!$AA$3+22+('DATA '!$AA$3-1)),0),"") | M78: =IFERROR(VLOOKUP(J78,'RJ ATTENDENCE SHEET'!$C:$DM,('DATA '!$AA$3+84),0),"")
D79: =IFERROR(VLOOKUP(C79,'RJ ATTENDENCE SHEET'!$C:$CG,('DATA '!$AA$3+5+('DATA '!$AA$3-1)),0),"") | E79: =IFERROR(VLOOKUP(C79,'RJ ATTENDENCE SHEET'!$C:$CG,('DATA '!$AA$3+6+('DATA '!$AA$3-1)),0),"") | H79: 72 | I79: =VLOOKUP(J79,'DATA '!$O:$P,2,0) | J79: ='DATA '!O74 | K79: =IFERROR(VLOOKUP(J79,'RJ ATTENDENCE SHEET'!$C:$CG,('DATA '!$AA$3+21+('DATA '!$AA$3-1)),0),"") | L79: =IFERROR(VLOOKUP(J79,'RJ ATTENDENCE SHEET'!$C:$CG,('DATA '!$AA$3+22+('DATA '!$AA$3-1)),0),"") | M79: =IFERROR(VLOOKUP(J79,'RJ ATTENDENCE SHEET'!$C:$DM,('DATA '!$AA$3+84),0),"")
D80: =IFERROR(VLOOKUP(C80,'RJ ATTENDENCE SHEET'!$C:$CG,('DATA '!$AA$3+5+('DATA '!$AA$3-1)),0),"") | E80: =IFERROR(VLOOKUP(C80,'RJ ATTENDENCE SHEET'!$C:$CG,('DATA '!$AA$3+6+('DATA '!$AA$3-1)),0),"") | H80: 73 | I80: =VLOOKUP(J80,'DATA '!$O:$P,2,0) | J80: ='DATA '!O75 | K80: =IFERROR(VLOOKUP(J80,'RJ ATTENDENCE SHEET'!$C:$CG,('DATA '!$AA$3+21+('DATA '!$AA$3-1)),0),"") | L80: =IFERROR(VLOOKUP(J80,'RJ ATTENDENCE SHEET'!$C:$CG,('DATA '!$AA$3+22+('DATA '!$AA$3-1)),0),"") | M80: =IFERROR(VLOOKUP(J80,'RJ ATTENDENCE SHEET'!$C:$DM,('DATA '!$AA$3+84),0),"")
D81: =IFERROR(VLOOKUP(C81,'RJ ATTENDENCE SHEET'!$C:$CG,('DATA '!$AA$3+5+('DATA '!$AA$3-1)),0),"") | E81: =IFERROR(VLOOKUP(C81,'RJ ATTENDENCE SHEET'!$C:$CG,('DATA '!$AA$3+6+('DATA '!$AA$3-1)),0),"") | H81: 74 | I81: =VLOOKUP(J81,'DATA '!$O:$P,2,0) | J81: ='DATA '!O76 | K81: =IFERROR(VLOOKUP(J81,'RJ ATTENDENCE SHEET'!$C:$CG,('DATA '!$AA$3+21+('DATA '!$AA$3-1)),0),"") | L81: =IFERROR(VLOOKUP(J81,'RJ ATTENDENCE SHEET'!$C:$CG,('DATA '!$AA$3+22+('DATA '!$AA$3-1)),0),"") | M81: =IFERROR(VLOOKUP(J81,'RJ ATTENDENCE SHEET'!$C:$DM,('DATA '!$AA$3+84),0),"")
D82: =IFERROR(VLOOKUP(C82,'RJ ATTENDENCE SHEET'!$C:$CG,('DATA '!$AA$3+5+('DATA '!$AA$3-1)),0),"") | E82: =IFERROR(VLOOKUP(C82,'RJ ATTENDENCE SHEET'!$C:$CG,('DATA '!$AA$3+6+('DATA '!$AA$3-1)),0),"") | H82: 75 | I82: =VLOOKUP(J82,'DATA '!$O:$P,2,0) | J82: ='DATA '!O77 | K82: =IFERROR(VLOOKUP(J82,'RJ ATTENDENCE SHEET'!$C:$CG,('DATA '!$AA$3+21+('DATA '!$AA$3-1)),0),"") | L82: =IFERROR(VLOOKUP(J82,'RJ ATTENDENCE SHEET'!$C:$CG,('DATA '!$AA$3+22+('DATA '!$AA$3-1)),0),"") | M82: =IFERROR(VLOOKUP(J82,'RJ ATTENDENCE SHEET'!$C:$DM,('DATA '!$AA$3+84),0),"")
D83: =IFERROR(VLOOKUP(C83,'RJ ATTENDENCE SHEET'!$C:$CG,('DATA '!$AA$3+5+('DATA '!$AA$3-1)),0),"") | E83: =IFERROR(VLOOKUP(C83,'RJ ATTENDENCE SHEET'!$C:$CG,('DATA '!$AA$3+6+('DATA '!$AA$3-1)),0),"") | H83: 76 | I83: =VLOOKUP(J83,'DATA '!$O:$P,2,0) | J83: ='DATA '!O78 | K83: =IFERROR(VLOOKUP(J83,'RJ ATTENDENCE SHEET'!$C:$CG,('DATA '!$AA$3+21+('DATA '!$AA$3-1)),0),"") | L83: =IFERROR(VLOOKUP(J83,'RJ ATTENDENCE SHEET'!$C:$CG,('DATA '!$AA$3+22+('DATA '!$AA$3-1)),0),"") | M83: =IFERROR(VLOOKUP(J83,'RJ ATTENDENCE SHEET'!$C:$DM,('DATA '!$AA$3+84),0),"")
D84: =IFERROR(VLOOKUP(C84,'RJ ATTENDENCE SHEET'!$C:$CG,('DATA '!$AA$3+5+('DATA '!$AA$3-1)),0),"") | E84: =IFERROR(VLOOKUP(C84,'RJ ATTENDENCE SHEET'!$C:$CG,('DATA '!$AA$3+6+('DATA '!$AA$3-1)),0),"") | H84: 77 | I84: =VLOOKUP(J84,'DATA '!$O:$P,2,0) | J84: ='DATA '!O79 | K84: =IFERROR(VLOOKUP(J84,'RJ ATTENDENCE SHEET'!$C:$CG,('DATA '!$AA$3+21+('DATA '!$AA$3-1)),0),"") | L84: =IFERROR(VLOOKUP(J84,'RJ ATTENDENCE SHEET'!$C:$CG,('DATA '!$AA$3+22+('DATA '!$AA$3-1)),0),"") | M84: =IFERROR(VLOOKUP(J84,'RJ ATTENDENCE SHEET'!$C:$DM,('DATA '!$AA$3+84),0),"")
D85: =IFERROR(VLOOKUP(C85,'RJ ATTENDENCE SHEET'!$C:$CG,('DATA '!$AA$3+5+('DATA '!$AA$3-1)),0),"") | E85: =IFERROR(VLOOKUP(C85,'RJ ATTENDENCE SHEET'!$C:$CG,('DATA '!$AA$3+6+('DATA '!$AA$3-1)),0),"") | H85: 78 | I85: =VLOOKUP(J85,'DATA '!$O:$P,2,0) | J85: ='DATA '!O80 | K85: =IFERROR(VLOOKUP(J85,'RJ ATTENDENCE SHEET'!$C:$CG,('DATA '!$AA$3+21+('DATA '!$AA$3-1)),0),"") | L85: =IFERROR(VLOOKUP(J85,'RJ ATTENDENCE SHEET'!$C:$CG,('DATA '!$AA$3+22+('DATA '!$AA$3-1)),0),"") | M85: =IFERROR(VLOOKUP(J85,'RJ ATTENDENCE SHEET'!$C:$DM,('DATA '!$AA$3+84),0),"")
D86: =IFERROR(VLOOKUP(C86,'RJ ATTENDENCE SHEET'!$C:$CG,('DATA '!$AA$3+5+('DATA '!$AA$3-1)),0),"") | E86: =IFERROR(VLOOKUP(C86,'RJ ATTENDENCE SHEET'!$C:$CG,('DATA '!$AA$3+6+('DATA '!$AA$3-1)),0),"") | H86: 79 | I86: =VLOOKUP(J86,'DATA '!$O:$P,2,0) | J86: ='DATA '!O81 | K86: =IFERROR(VLOOKUP(J86,'RJ ATTENDENCE SHEET'!$C:$CG,('DATA '!$AA$3+21+('DATA '!$AA$3-1)),0),"") | L86: =IFERROR(VLOOKUP(J86,'RJ ATTENDENCE SHEET'!$C:$CG,('DATA '!$AA$3+22+('DATA '!$AA$3-1)),0),"") | M86: =IFERROR(VLOOKUP(J86,'RJ ATTENDENCE SHEET'!$C:$DM,('DATA '!$AA$3+84),0),"")
A87: TOTAL | F87: =SUM(F52:F86) -> 3 | H87: 80 | I87: =VLOOKUP(J87,'DATA '!$O:$P,2,0) | J87: ='DATA '!O82 | K87: =IFERROR(VLOOKUP(J87,'RJ ATTENDENCE SHEET'!$C:$CG,('DATA '!$AA$3+21+('DATA '!$AA$3-1)),0),"") | L87: =IFERROR(VLOOKUP(J87,'RJ ATTENDENCE SHEET'!$C:$CG,('DATA '!$AA$3+22+('DATA '!$AA$3-1)),0),"") | M87: =IFERROR(VLOOKUP(J87,'RJ ATTENDENCE SHEET'!$C:$DM,('DATA '!$AA$3+84),0),"")
H88: 81 | I88: =VLOOKUP(J88,'DATA '!$O:$P,2,0) | J88: ='DATA '!O83 | K88: =IFERROR(VLOOKUP(J88,'RJ ATTENDENCE SHEET'!$C:$CG,('DATA '!$AA$3+21+('DATA '!$AA$3-1)),0),"") | L88: =IFERROR(VLOOKUP(J88,'RJ ATTENDENCE SHEET'!$C:$CG,('DATA '!$AA$3+22+('DATA '!$AA$3-1)),0),"") | M88: =IFERROR(VLOOKUP(J88,'RJ ATTENDENCE SHEET'!$C:$DM,('DATA '!$AA$3+84),0),"")
H89: 82 | I89: =VLOOKUP(J89,'DATA '!$O:$P,2,0) | J89: ='DATA '!O84 | K89: =IFERROR(VLOOKUP(J89,'RJ ATTENDENCE SHEET'!$C:$CG,('DATA '!$AA$3+21+('DATA '!$AA$3-1)),0),"") | L89: =IFERROR(VLOOKUP(J89,'RJ ATTENDENCE SHEET'!$C:$CG,('DATA '!$AA$3+22+('DATA '!$AA$3-1)),0),"") | M89: =IFERROR(VLOOKUP(J89,'RJ ATTENDENCE SHEET'!$C:$DM,('DATA '!$AA$3+84),0),"")
H90: 83 | I90: =VLOOKUP(J90,'DATA '!$O:$P,2,0) | J90: ='DATA '!O85 | K90: =IFERROR(VLOOKUP(J90,'RJ ATTENDENCE SHEET'!$C:$CG,('DATA '!$AA$3+21+('DATA '!$AA$3-1)),0),"") | L90: =IFERROR(VLOOKUP(J90,'RJ ATTENDENCE SHEET'!$C:$CG,('DATA '!$AA$3+22+('DATA '!$AA$3-1)),0),"") | M90: =IFERROR(VLOOKUP(J90,'RJ ATTENDENCE SHEET'!$C:$DM,('DATA '!$AA$3+84),0),"")
H91: 84 | I91: =VLOOKUP(J91,'DATA '!$O:$P,2,0) | J91: ='DATA '!O86 | K91: =IFERROR(VLOOKUP(J91,'RJ ATTENDENCE SHEET'!$C:$CG,('DATA '!$AA$3+21+('DATA '!$AA$3-1)),0),"") | L91: =IFERROR(VLOOKUP(J91,'RJ ATTENDENCE SHEET'!$C:$CG,('DATA '!$AA$3+22+('DATA '!$AA$3-1)),0),"") | M91: =IFERROR(VLOOKUP(J91,'RJ ATTENDENCE SHEET'!$C:$DM,('DATA '!$AA$3+84),0),"")
H92: 85 | I92: =VLOOKUP(J92,'DATA '!$O:$P,2,0) | J92: ='DATA '!O87 | K92: =IFERROR(VLOOKUP(J92,'RJ ATTENDENCE SHEET'!$C:$CG,('DATA '!$AA$3+21+('DATA '!$AA$3-1)),0),"") | L92: =IFERROR(VLOOKUP(J92,'RJ ATTENDENCE SHEET'!$C:$CG,('DATA '!$AA$3+22+('DATA '!$AA$3-1)),0),"") | M92: =IFERROR(VLOOKUP(J92,'RJ ATTENDENCE SHEET'!$C:$DM,('DATA '!$AA$3+84),0),"")
H93: 86 | I93: =VLOOKUP(J93,'DATA '!$O:$P,2,0) | J93: ='DATA '!O88 | K93: =IFERROR(VLOOKUP(J93,'RJ ATTENDENCE SHEET'!$C:$CG,('DATA '!$AA$3+21+('DATA '!$AA$3-1)),0),"") | L93: =IFERROR(VLOOKUP(J93,'RJ ATTENDENCE SHEET'!$C:$CG,('DATA '!$AA$3+22+('DATA '!$AA$3-1)),0),"") | M93: =IFERROR(VLOOKUP(J93,'RJ ATTENDENCE SHEET'!$C:$DM,('DATA '!$AA$3+84),0),"")
H94: 87 | I94: =VLOOKUP(J94,'DATA '!$O:$P,2,0) | J94: ='DATA '!O89 | K94: =IFERROR(VLOOKUP(J94,'RJ ATTENDENCE SHEET'!$C:$CG,('DATA '!$AA$3+21+('DATA '!$AA$3-1)),0),"") | L94: =IFERROR(VLOOKUP(J94,'RJ ATTENDENCE SHEET'!$C:$CG,('DATA '!$AA$3+22+('DATA '!$AA$3-1)),0),"") | M94: =IFERROR(VLOOKUP(J94,'RJ ATTENDENCE SHEET'!$C:$DM,('DATA '!$AA$3+84),0),"")
H95: 88 | I95: =VLOOKUP(J95,'DATA '!$O:$P,2,0) | J95: ='DATA '!O90 | K95: =IFERROR(VLOOKUP(J95,'RJ ATTENDENCE SHEET'!$C:$CG,('DATA '!$AA$3+5+('DATA '!$AA$3-1)),0),"") | L95: =IFERROR(VLOOKUP(J95,'RJ ATTENDENCE SHEET'!$C:$CG,('DATA '!$AA$3+6+('DATA '!$AA$3-1)),0),"")
H96: 89 | I96: =VLOOKUP(J96,'DATA '!$O:$P,2,0) | J96: ='DATA '!O91 | K96: =IFERROR(VLOOKUP(J96,'RJ ATTENDENCE SHEET'!$C:$CG,('DATA '!$AA$3+5+('DATA '!$AA$3-1)),0),"") | L96: =IFERROR(VLOOKUP(J96,'RJ ATTENDENCE SHEET'!$C:$CG,('DATA '!$AA$3+6+('DATA '!$AA$3-1)),0),"")
A97: SL. NO | C97: PLANT | D97: NAME | F97: TRIP | H97: TOTAL | M97: =SUM(M8:M96) -> 1
A98: OTHERS PLANT TRIP
A99: 1 | B99: =VLOOKUP(D99,'DATA '!$X:$Y,2,0) -> DRIVER | C99: =VLOOKUP(D99,'DATA '!$X:$Z,3,0) -> TARATALA | D99: ='DATA '!X3 -> MANOJ | F99: =VLOOKUP(D99,'OTHER PLANT ATTN.'!$C:$AH,('DATA '!$AA$3+1),0) -> 0 | J99: TOTAL NO OF TRIP | K99: =M97+F87+F128 -> #N/A
A100: 2 | B100: =VLOOKUP(D100,'DATA '!$X:$Y,2,0) -> 0 | C100: =VLOOKUP(D100,'DATA '!$X:$Z,3,0) -> 0 | D100: ='DATA '!X4 -> 0 | F100: =VLOOKUP(D100,'OTHER PLANT ATTN.'!$C:$AH,('DATA '!$AA$3+1),0) -> #N/A | J100: TOTAL INVOICE DESPATCH | K100: =K99/2 -> #N/A
A101: 3 | B101: =VLOOKUP(D101,'DATA '!$X:$Y,2,0) -> DRIVER | C101: =VLOOKUP(D101,'DATA '!$X:$Z,3,0) -> TARATALA | D101: ='DATA '!X5 -> TAPAS | F101: =VLOOKUP(D101,'OTHER PLANT ATTN.'!$C:$AH,('DATA '!$AA$3+1),0) -> 0 | J101: DRIVER TRIP | K101: =K100 -> #N/A
A102: 4 | B102: =VLOOKUP(D102,'DATA '!$X:$Y,2,0) -> HELPER | C102: =VLOOKUP(D102,'DATA '!$X:$Z,3,0) -> TARATALA | D102: ='DATA '!X6 -> KRISH | F102: =VLOOKUP(D102,'OTHER PLANT ATTN.'!$C:$AH,('DATA '!$AA$3+1),0) -> 0 | J102: HELPER TRIP | K102: =K100 -> #N/A
A103: 5 | B103: =VLOOKUP(D103,'DATA '!$X:$Y,2,0) -> HELPER | C103: =VLOOKUP(D103,'DATA '!$X:$Z,3,0) -> TARATALA | D103: ='DATA '!X7 -> KHAIRUL | F103: =VLOOKUP(D103,'OTHER PLANT ATTN.'!$C:$AH,('DATA '!$AA$3+1),0) -> 0
A104: 6 | B104: =VLOOKUP(D104,'DATA '!$X:$Y,2,0) -> HELPER | C104: =VLOOKUP(D104,'DATA '!$X:$Z,3,0) -> TARATALA | D104: ='DATA '!X8 -> SAJAN | F104: =VLOOKUP(D104,'OTHER PLANT ATTN.'!$C:$AH,('DATA '!$AA$3+1),0) -> 0
A105: 7 | B105: =VLOOKUP(D105,'DATA '!$X:$Y,2,0) -> DRIVER | C105: =VLOOKUP(D105,'DATA '!$X:$Z,3,0) -> TARATALA | D105: ='DATA '!X9 -> GIASUDDIN | F105: =VLOOKUP(D105,'OTHER PLANT ATTN.'!$C:$AH,('DATA '!$AA$3+1),0) -> 0
A106: 8 | B106: =VLOOKUP(D106,'DATA '!$X:$Y,2,0) -> DRIVER | C106: =VLOOKUP(D106,'DATA '!$X:$Z,3,0) -> JALAN | D106: ='DATA '!X10 -> RAKESH | F106: =VLOOKUP(D106,'OTHER PLANT ATTN.'!$C:$AH,('DATA '!$AA$3+1),0) -> 0
A107: 9 | B107: =VLOOKUP(D107,'DATA '!$X:$Y,2,0) -> DRIVER | C107: =VLOOKUP(D107,'DATA '!$X:$Z,3,0) -> TARATALA | D107: ='DATA '!X11 -> ANSAR | F107: =VLOOKUP(D107,'OTHER PLANT ATTN.'!$C:$AH,('DATA '!$AA$3+1),0) -> 0
A108: 10 | B108: =VLOOKUP(D108,'DATA '!$X:$Y,2,0) -> DRIVER | C108: =VLOOKUP(D108,'DATA '!$X:$Z,3,0) -> TARATALA | D108: ='DATA '!X12 -> RANJIT | F108: =VLOOKUP(D108,'OTHER PLANT ATTN.'!$C:$AH,('DATA '!$AA$3+1),0) -> 0
A109: 11 | B109: =VLOOKUP(D109,'DATA '!$X:$Y,2,0) -> HELPER | C109: =VLOOKUP(D109,'DATA '!$X:$Z,3,0) -> TARATALA | D109: ='DATA '!X13 -> KAPIL | F109: =VLOOKUP(D109,'OTHER PLANT ATTN.'!$C:$AH,('DATA '!$AA$3+1),0) -> 0
A110: 12 | B110: =VLOOKUP(D110,'DATA '!$X:$Y,2,0) -> HELPER | C110: =VLOOKUP(D110,'DATA '!$X:$Z,3,0) -> TARATALA | D110: ='DATA '!X14 -> RINTU | F110: =VLOOKUP(D110,'OTHER PLANT ATTN.'!$C:$AH,('DATA '!$AA$3+1),0) -> 0
A111: 13 | B111: =VLOOKUP(D111,'DATA '!$X:$Y,2,0) -> HELPER | C111: =VLOOKUP(D111,'DATA '!$X:$Z,3,0) -> TARATALA | D111: ='DATA '!X15 -> RABIN | F111: =VLOOKUP(D111,'OTHER PLANT ATTN.'!$C:$AH,('DATA '!$AA$3+1),0) -> 0
A112: 14 | B112: =VLOOKUP(D112,'DATA '!$X:$Y,2,0) -> HELPER | C112: =VLOOKUP(D112,'DATA '!$X:$Z,3,0) -> JALAN | D112: ='DATA '!X16 -> MITHUN | F112: =VLOOKUP(D112,'OTHER PLANT ATTN.'!$C:$AH,('DATA '!$AA$3+1),0) -> 0
A113: 15 | B113: =VLOOKUP(D113,'DATA '!$X:$Y,2,0) -> HELPER | C113: =VLOOKUP(D113,'DATA '!$X:$Z,3,0) -> JALAN | D113: ='DATA '!X17 -> RAMU | F113: =VLOOKUP(D113,'OTHER PLANT ATTN.'!$C:$AH,('DATA '!$AA$3+1),0) -> 0
A114: 16 | B114: =VLOOKUP(D114,'DATA '!$X:$Y,2,0) -> DRIVER | C114: =VLOOKUP(D114,'DATA '!$X:$Z,3,0) -> TARATALA | D114: ='DATA '!X18 -> TAPAS | F114: =VLOOKUP(D114,'OTHER PLANT ATTN.'!$C:$AH,('DATA '!$AA$3+1),0) -> 0
... A119: 21 | B119: =VLOOKUP(D119,'DATA '!$X:$Y,2,0) -> HELPER | C119: =VLOOKUP(D119,'DATA '!$X:$Z,3,0) -> TARATALA | D119: ='DATA '!X23 -> SAMIR BARMAN | F119: =VLOOKUP(D119,'OTHER PLANT ATTN.'!$C:$AH,('DATA '!$AA$3+1),0) -> 0
A128: TOTAL | F128: =SUM(F99:F127) -> #N/A

Sheet RJ ATTENDENCE SHEET
A1: 46204 | P1: BRANCH | Q1: IFSC | R1: ACCOUNT NO. | S1: ADVANCE | T1: TOTAL ATTN. | U1: WH | V1: TOTAL ATTN. | W1: TOTAL TRIP | X1: 1 | Z1: 2 | AB1: 3 | AD1: 4 | AF1: 5 | AH1: 6 | AJ1: 7 | AL1: 8 | AN1: 9 | AP1: 10 | AR1: 11 | AT1: 12 | AV1: 13 | AX1: 14 | AZ1: 15 | BB1: 16 | BD1: 17 | BF1: 18 | BH1: 19 | BJ1: 20 | BL1: 21 | BN1: 22 | BP1: 23 | BR1: 24 | BT1: 25 | BV1: 26 | BX1: 27 | BZ1: 28 | CB1: 29 | CD1: 30 | CF1: 31 | CI1: 1 | CJ1: 2 | CK1: 3 | CL1: 4 | CM1: 5 | CN1: 6 | CO1: 7 | CP1: 8 | CQ1: 9 | CR1: 10 | CS1: 11 | CT1: 12 | CU1: 13 | CV1: 14 | CW1: 15 | CX1: 16 | CY1: 17 | CZ1: 18 | DA1: 19 | DB1: 20 | DC1: 21 | DD1: 22 | DE1: 23 | DF1: 24 | DG1: 25 | DH1: 26 | DI1: 27 | DJ1: 28 | DK1: 29 | DL1: 30 | DM1: 31
A2: CATEGORY | B2: SUB-CATEGORY | C2: NAME | D2: EMP CODE | E2: BASIC | F2: HRA | G2: FOOD | H2: TOTAL | I2: MONTHLY RATE | J2: DUTY RATE | K2: TRIP RATE | L2: ESI BASIC | M2: ESI HRA | N2: ESI FOOD | O2: ESI TOTAL | P2: BRANCH | Q2: IFSC | R2: ACCOUNT NO. | S2: ADVANCE | T2: Column1 | U2: Column2 | V2: Column3 | W2: Column4 | X2: DAY | Y2: NIGHT | Z2: DAY2 | AA2: NIGHT3 | AB2: DAY4 | AC2: NIGHT5 | AD2: DAY6 | AE2: NIGHT7 | AF2: DAY8 | AG2: NIGHT9 | AH2: DAY10 | AI2: NIGHT11 | AJ2: DAY12 | AK2: NIGHT13 | AL2: DAY14 | AM2: NIGHT15 | AN2: DAY16 | AO2: NIGHT17 | AP2: DAY18 | AQ2: NIGHT19 | AR2: DAY20 | AS2: NIGHT21 | AT2: DAY22 | AU2: NIGHT23 | AV2: DAY24 | AW2: NIGHT25 | AX2: P | AY2: NIGHT27 | AZ2: DAY28 | BA2: NIGHT29 | BB2: DAY30 | BC2: NIGHT31 | BD2: DAY32 | BE2: NIGHT33 | BF2: DAY34 | BG2: NIGHT35 | BH2: DAY36 | BI2: NIGHT37 | BJ2: DAY38 | BK2: NIGHT39 | BL2: DAY40 | BM2: NIGHT41 | BN2: DAY42 | BO2: NIGHT43 | BP2: DAY44 | BQ2: NIGHT45 | BR2: DAY46 | BS2: NIGHT47 | BT2: DAY48 | BU2: NIGHT49 | BV2: DAY50 | BW2: NIGHT51 | BX2: DAY52 | BY2: NIGHT53 | BZ2: DAY54 | CA2: NIGHT55 | CB2: DAY56 | CC2: NIGHT57 | CD2: DAY58 | CE2: NIGHT59 | CF2: DAY60 | CG2: NIGHT61 | CH2: NIGHT62 | CI2: Column5 | CJ2: 2 | CK2: 3 | CL2: 4 | CM2: 5 | CN2: 6 | CO2: 7 | CP2: 8 | CQ2: 9 | CR2: 10 | CS2: 11 | CT2: 12 | CU2: 13 | CV2: 14 | CW2: 15 | CX2: 16 | CY2: 17 | CZ2: 18 | DA2: 19 | DB2: 20 | DC2: 21 | DD2: 22 | DE2: 23 | DF2: 24 | DG2: 25 | DH2: 26 | DI2: 27 | DJ2: 28 | DK2: 29 | DL2: 30 | DM2: 31 | DN2: 32
A3: SALARY | B3: OFFICE | C3: ABED ALI | D3: TC 0005 | E3: 10560 | F3: 5000 | G3: 4440 | H3: =SUBTOTAL(9,Table4[[#This Row],[BASIC]:[FOOD]]) -> 20000 | P3: IOB | Q3: IOBA0000013 | R3: 1301000024464 | T3: =COUNTIF(X3:CG3,"P") -> 29 | U3: 2 | V3: =T3+U3 -> 31 | W3: =SUM(CI3:DM3) -> 0 | X3: P | Y3: A | Z3: P | AA3: A | AB3: P | AC3: A | AD3: P | AE3: A | AF3: P | AG3: A | AH3: P | AI3: A | AJ3: P | AK3: A | AL3: A | AM3: A | AN3: P | AO3: A | AP3: P | AQ3: A | AR3: P | AS3: A | AT3: P | AU3: A | AV3: P | AW3: A | AX3: P | AY3: A | AZ3: P | BA3: A | BB3: P | BC3: A | BD3: P | BE3: A | BF3: P | BG3: A | BH3: P | BI3: A | BJ3: P | BK3: A | BL3: P | BM3: A | BN3: P | BO3: A | BP3: P | BQ3: A | BR3: P | BS3: A | BT3: P | BU3: A | BV3: A | BW3: A | BX3: P | BY3: A | BZ3: P | CA3: A | CB3: P | CC3: A | CD3: P | CE3: A | CF3: P | CG3: A
A4: SALARY | B4: OFFICE | C4: ABHI MUKHERJEE | D4: TC 0003 | E4: 14300 | F4: 7000 | G4: 7200 | H4: =SUBTOTAL(9,Table4[[#This Row],[BASIC]:[FOOD]]) -> 28500 | P4: SBI | Q4: SBIN0016917 | R4: 37720693683 | T4: =COUNTIF(X4:CG4,"P") -> 29 | U4: 2 | V4: =T4+U4 -> 31 | W4: =SUM(CI4:DM4) -> 0 | X4: P | Y4: A | Z4: P | AA4: A | AB4: P | AC4: A | AD4: P | AE4: A | AF4: P | AG4: A | AH4: P | AI4: A | AJ4: P | AK4: A | AL4: P | AM4: A | AN4: P | AO4: A | AP4: A | AQ4: A | AR4: P | AS4: A | AT4: P | AU4: A | AV4: P | AW4: A | AX4: P | AY4: A | AZ4: P | BA4: A | BB4: P | BC4: A | BD4: P | BE4: A | BF4: P | BG4: A | BH4: P | BI4: A | BJ4: P | BK4: A | BL4: P | BM4: A | BN4: P | BO4: A | BP4: P | BQ4: A | BR4: P | BS4: A | BT4: P | BU4: A | BV4: P | BW4: A | BX4: P | BY4: A | BZ4: A | CA4: A | CB4: P | CC4: A | CD4: P | CE4: A | CF4: P | CG4: A
A5: SALARY | B5: OFFICE | C5: ACHIN GUPTA | D5: TC 0001 | E5: 12000 | F5: 6000 | G5: 4500 | H5: =SUBTOTAL(9,Table4[[#This Row],[BASIC]:[FOOD]]) -> 22500 | P5: Bank of Baroda | Q5: BARB0DBRAJR | R5: 80850100001569 | T5: =COUNTIF(X5:CG5,"P") -> 30 | U5: 1 | V5: =T5+U5 -> 31 | W5: =SUM(CI5:DM5) -> 0 | X5: P | Y5: A | Z5: P | AA5: A | AB5: P | AC5: A | AD5: P | AE5: A | AF5: P | AG5: A | AH5: P | AI5: A | AJ5: P | AK5: A | AL5: A | AM5: A | AN5: P | AO5: A | AP5: P | AQ5: A | AR5: P | AS5: A | AT5: P | AU5: A | AV5: P | AW5: A | AX5: P | AY5: A | AZ5: P | BA5: A | BB5: P | BC5: A | BD5: P | BE5: A | BF5: P | BG5: A | BH5: P | BI5: A | BJ5: P | BK5: A | BL5: P | BM5: A | BN5: P | BO5: A | BP5: P | BQ5: A | BR5: P | BS5: A | BT5: P | BU5: A | BV5: P | BW5: A | BX5: P | BY5: A | BZ5: P | CA5: A | CB5: P | CC5: A | CD5: P | CE5: A | CF5: P | CG5: A
A6: SALARY | B6: OFFICE | C6: AMIN YADAV | D6: TC 0006 | E6: 12780 | F6: 6000 | G6: 5720 | H6: =SUBTOTAL(9,Table4[[#This Row],[BASIC]:[FOOD]]) -> 24500 | P6: IOB | Q6: IOBA0000013 | R6: 1301000024469 | T6: =COUNTIF(X6:CG6,"P") -> 26 | U6: 5 | V6: =T6+U6 -> 31 | W6: =SUM(CI6:DM6) -> 0 | X6: P | Y6: A | Z6: P | AA6: A | AB6: P | AC6: A | AD6: P | AE6: A | AF6: P | AG6: A | AH6: P | AI6: A | AJ6: P | AK6: A | AL6: P | AM6: A | AN6: P | AO6: A | AP6: A | AQ6: A | AR6: A | AS6: A | AT6: A | AU6: A | AV6: A | AW6: A | AX6: A | AY6: A | AZ6: P | BA6: A | BB6: P | BC6: A | BD6: P | BE6: A | BF6: P | BG6: A | BH6: P | BI6: A | BJ6: P | BK6: A | BL6: P | BM6: A | BN6: P | BO6: A | BP6: P | BQ6: A | BR6: P | BS6: A | BT6: P | BU6: A | BV6: P | BW6: A | BX6: P | BY6: A | BZ6: P | CA6: A | CB6: P | CC6: A | CD6: P | CE6: A | CF6: P | CG6: A
A7: CONTRACT | B7: HELPER | C7: AMIT BISWAS | H7: 0 | J7: 285 | K7: 80 | O7: =SUBTOTAL(9,Table4[[#This Row],[ESI BASIC]:[ESI FOOD]]) -> 0 | T7: =COUNTIF(X7:CG7,"P") -> 38 | V7: =T7+U7 -> 38 | W7: =SUM(CI7:DM7) -> 10 | X7: P | Y7: A | Z7: P | AA7: P | AB7: A | AC7: P | AD7: P | AE7: A | AF7: P | AG7: P | AH7: A | AI7: P | AJ7: P | AK7: A | AL7: P | AM7: P | AN7: A | AO7: P | AP7: P | AQ7: A | AR7: P | AS7: P | AT7: A | AU7: P | AV7: P | AW7: A | AX7: P | AY7: P | AZ7: A | BA7: P | BB7: P | BC7: A | BD7: P | BE7: P | BF7: A | BG7: P | BH7: P | BI7: A | BJ7: P | BK7: P | BL7: A | BM7: P | BN7: P | BO7: A | BP7: P | BQ7: P | BR7: A | BS7: A | BT7: A | BU7: A | BV7: P | BW7: P | BX7: A | BY7: P | BZ7: P | CA7: A | CB7: P | CC7: P | CD7: A | CE7: P | CF7: A | CG7: A | CI7: 0 | CJ7: 0 | CK7: 0 | CL7: 0 | CM7: 0 | CN7: 0 | CO7: 0 | CP7: 1 | CQ7: 0 | CR7: 0 | CS7: 1 | CT7: 0 | CU7: 0 | CV7: 4 | CW7: 0 | CX7: 1 | CY7: 0 | CZ7: 1 | DA7: 0 | DB7: 1 | DC7: 0 | DD7: 0 | DE7: 0 | DF7: 0 | DG7: 0 | DH7: 0 | DI7: 0 | DJ7: 1 | DK7: 0 | DL7: 0 | DM7: 0
A8: WAGES | B8: DRIVER | C8: ANISUR | D8: TC 0179 | H8: 0 | J8: 325 | K8: 185 | L8: 20200 | O8: =SUBTOTAL(9,Table4[[#This Row],[ESI BASIC]:[ESI FOOD]]) -> 0 | P8: Bank of Baroda | Q8: BARB0DBRAJR | R8: 119710024815 | T8: =COUNTIF(X8:CG8,"P") -> 40 | V8: =T8+U8 -> 40 | W8: =SUM(CI8:DM8) -> 13 | X8: P | Y8: A | Z8: P | AA8: P | AB8: A | AC8: P | AD8: P | AE8: A | AF8: P | AG8: P | AH8: A | AI8: P | AJ8: P | AK8: A | AL8: P | AM8: P | AN8: A | AO8: P | AP8: P | AQ8: A | AR8: P | AS8: P | AT8: A | AU8: P | AV8: P | AW8: A | AX8: P | AY8: P | AZ8: A | BA8: P | BB8: P | BC8: A | BD8: A | BE8: P | BF8: A | BG8: P | BH8: P | BI8: A | BJ8: P | BK8: P | BL8: A | BM8: P | BN8: P | BO8: A | BP8: P | BQ8: P | BR8: A | BS8: P | BT8: P | BU8: A | BV8: P | BW8: P | BX8: A | BY8: P | BZ8: P | CA8: A | CB8: P | CC8: P | CD8: A | CE8: P | CF8: P | CG8: A | CI8: 0 | CJ8: 0 | CK8: 0 | CL8: 0 | CM8: 0 | CN8: 0 | CO8: 0 | CP8: 0 | CQ8: 1 | CR8: 0 | CS8: 1 | CT8: 0 | CU8: 0 | CV8: 3 | CW8: 2 | CX8: 0 | CY8: 0 | CZ8: 1 | DA8: 1 | DB8: 0 | DC8: 0 | DD8: 1 | DE8: 0 | DF8: 1 | DG8: 0 | DH8: 0 | DI8: 1 | DJ8: 0 | DK8: 1 | DL8: 0
A9: SALARY | B9: OFFICE | C9: ANOWAR MOLLA | D9: TC 0185 | E9: 10560 | F9: 2000 | G9: 1440 | H9: =SUBTOTAL(9,Table4[[#This Row],[BASIC]:[FOOD]]) -> 14000 | P9: SBI | Q9: SBIN0012380 | R9: 20357794848 | T9: =COUNTIF(X9:CG9,"P") -> 27 | U9: 4 | V9: =T9+U9 -> 31 | W9: =SUM(CI9:DM9) -> 0 | X9: P | Y9: A | Z9: P | AA9: A | AB9: P | AC9: A | AD9: P | AE9: A | AF9: A | AG9: A | AH9: P | AI9: A | AJ9: P | AK9: A | AL9: P | AM9: A | AN9: P | AO9: A | AP9: A | AQ9: A | AR9: P | AS9: A | AT9: P | AU9: A | AV9: P | AW9: A | AX9: P | AY9: A | AZ9: P | BA9: A | BB9: P | BC9: A | BD9: P | BE9: A | BF9: P | BG9: A | BH9: A | BI9: A | BJ9: P | BK9: A | BL9: P | BM9: A | BN9: P | BO9: A | BP9: P | BQ9: A | BR9: P | BS9: A | BT9: P | BU9: A | BV9: A | BW9: A | BX9: P | BY9: A | BZ9: P | CA9: A | CB9: P | CC9: A | CD9: P | CE9: A | CF9: P | CG9: A
A10: WAGES | B10: DRIVER | C10: ARMAN ALI MONDAL | D10: TC 0074 | H10: 0 | J10: 320 | K10: 185 | L10: 11620 | M10: 2240 | N10: 2040 | O10: =SUBTOTAL(9,Table4[[#This Row],[ESI BASIC]:[ESI FOOD]]) -> 0 | P10: CANARA BANK | Q10: CNRB0019776 | R10: 97762010009114 | T10: =COUNTIF(X10:CG10,"P") -> 41 | V10: =T10+U10 -> 41 | W10: =SUM(CI10:DM10) -> 8 | X10: A | Y10: P | Z10: P | AA10: A | AB10: P | AC10: P | AD10: A | AE10: P | AF10: P | AG10: A | AH10: P | AI10: P | AJ10: A | AK10: P | AL10: P | AM10: A | AN10: P | AO10: P | AP10: A | AQ10: P | AR10: P | AS10: A | AT10: P | AU10: P | AV10: A | AW10: P | AX10: P | AY10: A | AZ10: P | BA10: P | BB10: A | BC10: P | BD10: P | BE10: A | BF10: P | BG10: P | BH10: A | BI10: P | BJ10: P | BK10: A | BL10: P | BM10: P | BN10: A | BO10: P | BP10: P | BQ10: A | BR10: P | BS10: P | BT10: A | BU10: P | BV10: P | BW10: A | BX10: P | BY10: P | BZ10: A | CA10: P | CB10: P | CC10: A | CD10: P | CE10: P | CF10: A | CG10: P | CI10: 0 | CJ10: 1 | CK10: 0 | CL10: 0 | CM10: 0 | CN10: 0 | CO10: 1 | CP10: 0 | CQ10: 0 | CR10: 0 | CS10: 0 | CT10: 0 | CU10: 0 | CV10: 2 | CW10: 0 | CX10: 0 | CY10: 0 | CZ10: 0 | DA10: 0 | DB10: 1 | DC10: 1 | DD10: 0 | DE10: 0 | DF10: 0 | DG10: 0 | DH10: 0 | DI10: 1 | DJ10: 0 | DK10: 1 | DL10: 0 | DM10: 0
A11: CONTRACT | B11: HELPER | C11: JHANTU MONDAL | H11: 0 | J11: 260 | K11: 80 | O11: =SUBTOTAL(9,Table4[[#This Row],[ESI BASIC]:[ESI FOOD]]) -> 0 | T11: =COUNTIF(X11:CG11,"P") -> 41 | V11: =T11+U11 -> 41 | W11: =SUM(CI11:DM11) -> 10 | X11: P | Y11: P | Z11: A | AA11: P | AB11: P | AC11: A | AD11: P | AE11: P | AF11: A | AG11: P | AH11: P | AI11: A | AJ11: P | AK11: P | AL11: A | AM11: P | AN11: P | AO11: A | AP11: A | AQ11: P | AR11: A | AS11: P | AT11: P | AU11: A | AV11: P | AW11: P | AX11: A | AY11: P | AZ11: P | BA11: A | BB11: P | BC11: P | BD11: A | BE11: P | BF11: P | BG11: A | BH11: P | BI11: P | BJ11: A | BK11: P | BL11: P | BM11: A | BN11: P | BO11: P | BP11: A | BQ11: P | BR11: P | BS11: A | BT11: P | BU11: P | BV11: A | BW11: P | BX11: P | BY11: A | BZ11: P | CA11: P | CB11: A | CC11: P | CD11: P | CE11: A | CF11: P | CG11: P | CI11: 0 | CJ11: 0 | CK11: 0 | CL11: 0 | CM11: 0 | CN11: 0 | CO11: 0 | CP11: 0 | CQ11: 1 | CR11: 0 | CS11: 0 | CT11: 1 | CU11: 0 | CV11: 1 | CW11: 1 | CX11: 1 | CY11: 0 | CZ11: 0 | DA11: 0 | DB11: 0 | DC11: 0 | DD11: 2 | DE11: 0 | DF11: 0 | DG11: 0 | DH11: 0 | DI11: 2 | DJ11: 0 | DK11: 1 | DL11: 0 | DM11: 0
A12: CONTRACT | B12: DRIVER | C12: ASHIT BISWAS | H12: 0 | J12: 320 | K12: 185 | O12: =SUBTOTAL(9,Table4[[#This Row],[ESI BASIC]:[ESI FOOD]]) -> 0 | T12: =COUNTIF(X12:CG12,"P") -> 40 | V12: =T12+U12 -> 40 | W12: =SUM(CI12:DM12) -> 9 | X12: P | Y12: A | Z12: P | AA12: P | AB12: A | AC12: P | AD12: P | AE12: A | AF12: P | AG12: P | AH12: A | AI12: P | AJ12: P | AK12: A | AL12: P | AM12: P | AN12: A | AO12: P | AP12: P | AQ12: A | AR12: P | AS12: P | AT12: A | AU12: P | AV12: P | AW12: A | AX12: P | AY12: P | AZ12: A | BA12: P | BB12: P | BC12: A | BD12: P | BE12: P | BF12: A | BG12: P | BH12: P | BI12: A | BJ12: P | BK12: P | BL12: A | BM12: P | BN12: P | BO12: A | BP12: P | BQ12: P | BR12: A | BS12: P | BT12: A | BU12: A | BV12: P | BW12: P | BX12: A | BY12: P | BZ12: P | CA12: A | CB12: P | CC12: P | CD12: A | CE12: P | CF12: P | CG12: A | CI12: 0 | CJ12: 0 | CK12: 0 | CL12: 0 | CM12: 0 | CN12: 0 | CO12: 0 | CP12: 0 | CQ12: 0 | CR12: 0 | CS12: 1 | CT12: 0 | CU12: 0 | CV12: 4 | CW12: 0 | CX12: 0 | CY12: 0 | CZ12: 0 | DA12: 1 | DB12: 0 | DC12: 0 | DD12: 1 | DE12: 1 | DF12: 0 | DG12: 0 | DH12: 0 | DI12: 0 | DJ12: 1 | DK12: 0 | DL12: 0 | DM12: 0
A13: WAGES | B13: HELPER | C13: ASUTOSH SARDAR | D13: TC 0187 | H13: 0 | J13: 285 | K13: 80 | L13: 10560 | M13: 920 | N13: 720 | O13: =SUBTOTAL(9,Table4[[#This Row],[ESI BASIC]:[ESI FOOD]]) -> 0 | P13: UNION BANK | Q13: UBIN0912344 | R13: 123400101005434 | T13: =COUNTIF(X13:CG13,"P") -> 40 | V13: =T13+U13 -> 40 | W13: =SUM(CI13:DM13) -> 8 | X13: A | Y13: P | Z13: P | AA13: A | AB13: P | AC13: P | AD13: A | AE13: P | AF13: P | AG13: A | AH13: P | AI13: P | AJ13: A | AK13: P | AL13: P | AM13: A | AN13: P | AO13: P | AP13: A | AQ13: P | AR13: P | AS13: A | AT13: P | AU13: P | AV13: A | AW13: P | AX13: P | AY13: A | AZ13: P | BA13: P | BB13: A | BC13: P | BD13: P | BE13: A | BF13: P | BG13: A | BH13: A | BI13: P | BJ13: P | BK13: A | BL13: P | BM13: P | BN13: A | BO13: P | BP13: P | BQ13: A | BR13: P | BS13: P | BT13: A | BU13: P | BV13: P | BW13: A | BX13: P | BY13: P | BZ13: A | CA13: P | CB13: P | CC13: A | CD13: P | CE13: P | CF13: A | CG13: P | CI13: 0 | CJ13: 1 | CK13: 0 | CL13: 0 | CM13: 0 | CN13: 0 | CO13: 1 | CP13: 0 | CQ13: 0 | CR13: 0 | CS13: 0 | CT13: 0 | CU13: 0 | CV13: 2 | CW13: 0 | CX13: 0 | CY13: 0 | CZ13: 0 | DA13: 0 | DB13: 1 | DC13: 1 | DD13: 0 | DE13: 0 | DF13: 0 | DG13: 0 | DH13: 0 | DI13: 1 | DJ13: 0 | DK13: 1 | DL13: 0 | DM13: 0
A14: CONTRACT | B14: HELPER | C14: NASIB KARIKAR | H14: 0 | J14: 250 | K14: 70 | O14: =Table4[[#This Row],[ESI FOOD]]+Table4[[#This Row],[ESI HRA]]+Table4[[#This Row],[ESI BASIC]] -> 0 | T14: =COUNTIF(X14:CG14,"P") -> 40 | V14: =T14+U14 -> 40 | W14: =SUM(CI14:DM14) -> 7 | X14: A | Y14: P | Z14: P | AA14: A | AB14: P | AC14: P | AD14: A | AE14: P | AF14: P | AG14: A | AH14: P | AI14: P | AJ14: A | AK14: P | AL14: P | AM14: A | AN14: P | AO14: P | AP14: A | AQ14: P | AR14: P | AS14: A | AT14: A | AU14: P | AV14: A | AW14: P | AX14: P | AY14: A | AZ14: P | BA14: P | BB14: A | BC14: P | BD14: P | BE14: A | BF14: P | BG14: P | BH14: A | BI14: P | BJ14: P | BK14: A | BL14: P | BM14: P | BN14: A | BO14: P | BP14: P | BQ14: A | BR14: P | BS14: P | BT14: A | BU14: P | BV14: P | BW14: A | BX14: P | BY14: P | BZ14: A | CA14: P | CB14: P | CC14: A | CD14: P | CE14: P | CF14: A | CG14: P | CI14: 0 | CJ14: 0 | CK14: 0 | CL14: 0 | CM14: 0 | CN14: 0 | CO14: 0 | CP14: 0 | CQ14: 0 | CR14: 0 | CS14: 0 | CT14: 0 | CU14: 0 | CV14: 1 | CW14: 0 | CX14: 0 | CY14: 0 | CZ14: 1 | DA14: 0 | DB14: 0 | DC14: 0 | DD14: 1 | DE14: 1 | DF14: 0 | DG14: 0 | DH14: 0 | DI14: 1 | DJ14: 2 | DK14: 0 | DL14: 0 | DM14: 0
A15: CONTRACT | B15: OTHERS | C15: BASIRUDDIN KHAN | H15: 0 | I15: 15500 | T15: =COUNTIF(X15:CG15,"P") -> 31 | U15: 4 | V15: =T15+U15 -> 35 | W15: =SUM(CI15:DM15) -> 0 | X15: P | Y15: A | Z15: P | AA15: A | AB15: P | AC15: A | AD15: P | AE15: A | AF15: P | AG15: A | AH15: P | AI15: A | AJ15: P | AK15: A | AL15: P | AM15: A | AN15: P | AO15: A | AP15: P | AQ15: A | AR15: P | AS15: A | AT15: P | AU15: A | AV15: P | AW15: A | AX15: P | AY15: A | AZ15: P | BA15: A | BB15: P | BC15: A | BD15: P | BE15: A | BF15: P | BG15: A | BH15: P | BI15: A | BJ15: P | BK15: A | BL15: P | BM15: A | BN15: P | BO15: A | BP15: P | BQ15: A | BR15: P | BS15: A | BT15: P | BU15: A | BV15: P | BW15: A | BX15: P | BY15: A | BZ15: P | CA15: A | CB15: P | CC15: A | CD15: P | CE15: A | CF15: P | CG15: A
A16: WAGES | B16: LAB | C16: BUDDHADEV SEAL | D16: TC 0222 | H16: 0 | I16: 15225 | L16: 10560 | M16: 2665 | N16: 2000 | O16: =SUBTOTAL(9,Table4[[#This Row],[ESI BASIC]:[ESI FOOD]]) -> 0 | P16: SBI | Q16: SBIN0006208 | R16: 36573214016 | T16: =COUNTIF(X16:CG16,"P") -> 30 | U16: 4 | V16: =T16+U16 -> 34 | W16: =SUM(CI16:DM16) -> 0 | X16: P | Y16: A | Z16: P | AA16: A | AB16: P | AC16: A | AD16: P | AE16: A | AF16: P | AG16: A | AH16: P | AI16: P | AJ16: P | AK16: A | AL16: P | AM16: A | AN16: P | AO16: A | AP16: P | AQ16: A | AR16: P | AS16: A | AT16: P | AU16: A | AV16: P | AW16: A | AX16: P | AY16: A | AZ16: P | BA16: A | BB16: A | BC16: A | BD16: P | BE16: A | BF16: P | BG16: A | BH16: P | BI16: A | BJ16: A | BK16: P | BL16: A | BM16: P | BN16: A | BO16: P | BP16: A | BQ16: P | BR16: A | BS16: A | BT16: A | BU16: P | BV16: A | BW16: P | BX16: P | BY16: A | BZ16: P | CA16: A | CB16: P | CC16: A | CD16: P | CE16: A | CF16: P | CG16: A
A17: SALARY | B17: OFFICE | C17: DIBAKAR MONDAL | D17: TC 0260 | E17: 10560 | F17: 4000 | G17: 3440 | H17: =SUBTOTAL(9,Table4[[#This Row],[BASIC]:[FOOD]]) -> 18000 | P17: CANARA BANK | Q17: CNRB0019776 | R17: 97762010010800 | T17: =COUNTIF(X17:CG17,"P") -> 31 | V17: =T17+U17 -> 31 | W17: =SUM(CI17:DM17) -> 0 | X17: P | Y17: A | Z17: P | AA17: A | AB17: P | AC17: A | AD17: P | AE17: A | AF17: P | AG17: A | AH17: P | AI17: A | AJ17: P | AK17: A | AL17: P | AM17: A | AN17: P | AO17: A | AP17: P | AQ17: A | AR17: P | AS17: A | AT17: P | AU17: A | AV17: P | AW17: A | AX17: P | AY17: P | AZ17: P | BA17: A | BB17: P | BC17: A | BD17: A | BE17: A | BF17: P | BG17: A | BH17: P | BI17: A | BJ17: P | BK17: A | BL17: P | BM17: A | BN17: P | BO17: A | BP17: P | BQ17: A | BR17: P | BS17: A | BT17: P | BU17: A | BV17: P | BW17: A | BX17: P | BY17: A | BZ17: P | CA17: A | CB17: P | CC17: A | CD17: P | CE17: A | CF17: P | CG17: A
A18: CONTRACT | B18: DRIVER | C18: DIN MOHAMMOD ALI | H18: 0 | J18: 320 | K18: 185 | O18: =SUBTOTAL(9,Table4[[#This Row],[ESI BASIC]:[ESI FOOD]]) -> 0 | T18: =COUNTIF(X18:CG18,"P") -> 41 | V18: =T18+U18 -> 41 | W18: =SUM(CI18:DM18) -> 10 | X18: P | Y18: P | Z18: A | AA18: P | AB18: P | AC18: A | AD18: P | AE18: P | AF18: A | AG18: P | AH18: P | AI18: A | AJ18: P | AK18: P | AL18: A | AM18: P | AN18: P | AO18: A | AP18: P | AQ18: P | AR18: A | AS18: P | AT18: P | AU18: A | AV18: P | AW18: P | AX18: A | AY18: P | AZ18: P | BA18: A | BB18: P | BC18: A | BD18: A | BE18: P | BF18: P | BG18: A | BH18: P | BI18: P | BJ18: A | BK18: P | BL18: P | BM18: A | BN18: P | BO18: P | BP18: A | BQ18: P | BR18: P | BS18: A | BT18: P | BU18: P | BV18: A | BW18: P | BX18: P | BY18: A | BZ18: P | CA18: P | CB18: A | CC18: P | CD18: P | CE18: A | CF18: P | CG18: P | CI18: 0 | CJ18: 0 | CK18: 0 | CL18: 0 | CM18: 0 | CN18: 0 | CO18: 0 | CP18: 0 | CQ18: 1 | CR18: 0 | CS18: 0 | CT18: 1 | CU18: 0 | CV18: 2 | CW18: 1 | CX18: 0 | CY18: 1 | CZ18: 0 | DA18: 1 | DB18: 0 | DC18: 0 | DD18: 1 | DE18: 1 | DF18: 0 | DG18: 0 | DH18: 0 | DI18: 1 | DJ18: 0 | DK18: 0 | DL18: 0 | DM18: 0
A19: WAGES | B19: DRIVER | C19: FARUK ALI | D19: TC0361 | H19: 0 | J19: 300 | K19: 185 | L19: 11620 | M19: 2170 | N19: 2010 | O19: =SUBTOTAL(9,Table4[[#This Row],[ESI BASIC]:[ESI FOOD]]) -> 0 | P19: SBI | Q19: SBIN0016917 | R19: 40361475410 | T19: =COUNTIF(X19:CG19,"P") -> 41 | V19: =T19+U19 -> 41 | W19: =SUM(CI19:DM19) -> 12 | X19: A | Y19: P | Z19: P | AA19: A | AB19: P | AC19: P | AD19: A | AE19: P | AF19: P | AG19: A | AH19: P | AI19: P | AJ19: A | AK19: P | AL19: P | AM19: A | AN19: P | AO19: P | AP19: A | AQ19: P | AR19: P | AS19: A | AT19: P | AU19: P | AV19: A | AW19: P | AX19: P | AY19: A | AZ19: P | BA19: P | BB19: A | BC19: P | BD19: P | BE19: A | BF19: P | BG19: P | BH19: A | BI19: P | BJ19: P | BK19: A | BL19: P | BM19: P | BN19: A | BO19: P | BP19: P | BQ19: A | BR19: P | BS19: P | BT19: A | BU19: P | BV19: P | BW19: A | BX19: P | BY19: P | BZ19: A | CA19: P | CB19: P | CC19: A | CD19: P | CE19: P | CF19: A | CG19: P | CI19: 0 | CJ19: 0 | CK19: 0 | CL19: 0 | CM19: 1 | CN19: 0 | CO19: 0 | CP19: 1 | CQ19: 1 | CR19: 0 | CS19: 1 | CT19: 0 | CU19: 0 | CV19: 2 | CW19: 1 | CX19: 0 | CY19: 0 | CZ19: 0 | DA19: 0 | DB19: 0 | DC19: 1 | DD19: 1 | DE19: 1 | DF19: 0 | DG19: 0 | DH19: 0 | DI19: 2 | DJ19: 0 | DK19: 0 | DL19: 0 | DM19: 0
A20: SALARY | B20: OFFICE | C20: GOLAM SARWAR | D20: TC 0122 | E20: 26000 | F20: 0 | G20: 0 | H20: =SUBTOTAL(9,Table4[[#This Row],[BASIC]:[FOOD]]) -> 26000 | P20: PNB | Q20: PUNB0058400 | R20: 163000100058792 | T20: =COUNTIF(X20:CG20,"P") -> 30 | U20: 1 | V20: =T20+U20 -> 31 | W20: =SUM(CI20:DM20) -> 0 | X20: P | Y20: A | Z20: P | AA20: A | AB20: A | AC20: A | AD20: P | AE20: A | AF20: P | AG20: A | AH20: P | AI20: A | AJ20: P | AK20: A | AL20: P | AM20: A | AN20: P | AO20: A | AP20: P | AQ20: A | AR20: P | AS20: A | AT20: P | AU20: A | AV20: P | AW20: A | AX20: P | AY20: A | AZ20: P | BA20: A | BB20: P | BC20: A | BD20: P | BE20: A | BF20: P | BG20: A | BH20: P | BI20: A | BJ20: P | BK20: A | BL20: P | BM20: A | BN20: P | BO20: A | BP20: P | BQ20: A | BR20: P | BS20: A | BT20: P | BU20: A | BV20: P | BW20: A | BX20: P | BY20: A | BZ20: P | CA20: A | CB20: P | CC20: A | CD20: P | CE20: A | CF20: P | CG20: A
A21: SALARY | B21: OFFICE | C21: IMAN ALI MOLLA | D21: TC 0205 | E21: 10560 | F21: 4000 | G21: 2440 | H21: =SUBTOTAL(9,Table4[[#This Row],[BASIC]:[FOOD]]) -> 17000 | P21: UCO BANK | Q21: UCBA0002951 | R21: 29510110048184 | T21: =COUNTIF(X21:CG21,"P") -> 27 | U21: 4 | V21: =T21+U21 -> 31 | W21: =SUM(CI21:DM21) -> 0 | X21: P | Y21: A | Z21: P | AA21: A | AB21: P | AC21: A | AD21: P | AE21: A | AF21: P | AG21: A | AH21: P | AI21: A | AJ21: A | AK21: A | AL21: P | AM21: A | AN21: P | AO21: A | AP21: P | AQ21: A | AR21: P | AS21: A | AT21: P | AU21: A | AV21: P | AW21: A | AX21: P | AY21: A | AZ21: P | BA21: A | BB21: A | BC21: A | BD21: P | BE21: A | BF21: P | BG21: A | BH21: P | BI21: A | BJ21: P | BK21: A | BL21: P | BM21: A | BN21: P | BO21: A | BP21: A | BQ21: A | BR21: P | BS21: A | BT21: P | BU21: A | BV21: P | BW21: A | BX21: P | BY21: A | BZ21: P | CA21: A | CB21: P | CC21: A | CD21: A | CE21: A | CF21: P | CG21: A
A22: CONTRACT | B22: DRIVER | C22: RAFIQUE MOLLA | H22: 0 | J22: 300 | K22: 185 | O22: =SUBTOTAL(9,Table4[[#This Row],[ESI BASIC]:[ESI FOOD]]) -> 0 | T22: =COUNTIF(X22:CG22,"P") -> 41 | V22: =T22+U22 -> 41 | W22: =SUM(CI22:DM22) -> 10 | X22: P | Y22: A | Z22: P | AA22: P | AB22: A | AC22: P | AD22: P | AE22: A | AF22: P | AG22: P | AH22: A | AI22: P | AJ22: P | AK22: A | AL22: P | AM22: P | AN22: A | AO22: P | AP22: P | AQ22: A | AR22: P | AS22: P | AT22: A | AU22: P | AV22: P | AW22: A | AX22: P | AY22: P | AZ22: A | BA22: P | BB22: P | BC22: A | BD22: P | BE22: P | BF22: A | BG22: P | BH22: P | BI22: A | BJ22: P | BK22: P | BL22: A | BM22: P | BN22: P | BO22: A | BP22: P | BQ22: P | BR22: A | BS22: P | BT22: P | BU22: A | BV22: P | BW22: P | BX22: A | BY22: P | BZ22: P | CA22: A | CB22: P | CC22: P | CD22: A | CE22: P | CF22: P | CG22: A | CI22: 0 | CJ22: 0 | CK22: 0 | CL22: 0 | CM22: 0 | CN22: 0 | CO22: 0 | CP22: 1 | CQ22: 0 | CR22: 0 | CS22: 1 | CT22: 0 | CU22: 0 | CV22: 4 | CW22: 0 | CX22: 0 | CY22: 0 | CZ22: 1 | DA22: 0 | DB22: 1 | DC22: 0 | DD22: 1 | DE22: 0 | DF22: 0 | DG22: 0 | DH22: 0 | DI22: 0 | DJ22: 0 | DK22: 1 | DL22: 0 | DM22: 0
A23: WAGES | B23: HOPPER | C23: KUTUBUDDIN MOLLA | D23: TC 0219 | H23: 0 | I23: 15000 | L23: 11615 | M23: 1765 | N23: 1620 | O23: =SUBTOTAL(9,Table4[[#This Row],[ESI BASIC]:[ESI FOOD]]) -> 0 | P23: UCO BANK | Q23: UCBA0002550 | R23: 25500110064306 | T23: =COUNTIF(X23:CG23,"P") -> 30 | U23: 4 | V23: =T23+U23 -> 34 | W23: =SUM(CI23:DM23) -> 0 | X23: P | Y23: A | Z23: P | AA23: A | AB23: P | AC23: A | AD23: P | AE23: A | AF23: P | AG23: A | AH23: P | AI23: A | AJ23: P | AK23: A | AL23: P | AM23: A | AN23: P | AO23: A | AP23: P | AQ23: A | AR23: P | AS23: A | AT23: P | AU23: A | AV23: P | AW23: A | AX23: P | AY23: A | AZ23: P | BA23: A | BB23: P | BC23: A | BD23: P | BE23: A | BF23: P | BG23: A | BH23: P | BI23: A | BJ23: P | BK23: A | BL23: P | BM23: A | BN23: P | BO23: A | BP23: P | BQ23: A | BR23: P | BS23: A | BT23: P | BU23: A | BV23: A | BW23: A | BX23: P | BY23: A | BZ23: P | CA23: A | CB23: P | CC23: A | CD23: P | CE23: A | CF23: P | CG23: A
A24: CONTRACT | B24: HELPER | C24: RAFIKUL MOLLA | H24: 0 | J24: 260 | K24: 80 | O24: =SUBTOTAL(9,Table4[[#This Row],[ESI BASIC]:[ESI FOOD]]) -> 0 | T24: =COUNTIF(X24:CG24,"P") -> 36 | V24: =T24+U24 -> 36 | W24: =SUM(CI24:DM24) -> 8 | X24: A | Y24: P | Z24: P | AA24: A | AB24: P | AC24: P | AD24: A | AE24: P | AF24: P | AG24: A | AH24: P | AI24: P | AJ24: A | AK24: P | AL24: P | AM24: A | AN24: A | AO24: P | AP24: A | AQ24: P | AR24: P | AS24: A | AT24: P | AU24: P | AV24: A | AW24: P | AX24: P | AY24: A | AZ24: P | BA24: P | BB24: A | BC24: P | BD24: P | BE24: A | BF24: A | BG24: P | BH24: A | BI24: P | BJ24: A | BK24: A | BL24: A | BM24: A | BN24: A | BO24: P | BP24: P | BQ24: A | BR24: P | BS24: P | BT24: A | BU24: P | BV24: P | BW24: A | BX24: P | BY24: P | BZ24: A | CA24: P | CB24: P | CC24: A | CD24: P | CE24: P | CF24: A | CG24: P | CI24: 0 | CJ24: 0 | CK24: 0 | CL24: 0 | CM24: 0 | CN24: 1 | CO24: 1 | CP24: 0 | CQ24: 0 | CR24: 0 | CS24: 0 | CT24: 0 | CU24: 0 | CV24: 1 | CW24: 0 | CX24: 0 | CY24: 0 | CZ24: 0 | DA24: 0 | DB24: 0 | DC24: 0 | DD24: 1 | DE24: 0 | DF24: 0 | DG24: 1 | DH24: 0 | DI24: 1 | DJ24: 1 | DK24: 1 | DL24: 0 | DM24: 0
A25: WAGES | B25: OTHERS | C25: MD. SAMIM AKRAM | D25: TC0391 | H25: 0 | I25: 15500 | L25: 12777 | M25: 1556 | N25: 1167 | O25: =SUBTOTAL(9,Table4[[#This Row],[ESI BASIC]:[ESI FOOD]]) -> 0 | P25: UCO BANK | Q25: UCBA0001119 | R25: 11193210017690 | T25: =COUNTIF(X25:CG25,"P") -> 31 | U25: 4 | V25: =T25+U25 -> 35 | W25: =SUM(CI25:DM25) -> 0 | X25: P | Y25: A | Z25: P | AA25: A | AB25: P | AC25: A | AD25: P | AE25: A | AF25: P | AG25: A | AH25: P | AI25: A | AJ25: P | AK25: A | AL25: P | AM25: A | AN25: P | AO25: A | AP25: P | AQ25: A | AR25: P | AS25: A | AT25: P | AU25: A | AV25: P | AW25: A | AX25: P | AY25: A | AZ25: P | BA25: A | BB25: P | BC25: A | BD25: P | BE25: A | BF25: P | BG25: A | BH25: P | BI25: A | BJ25: P | BK25: A | BL25: P | BM25: A | BN25: P | BO25: A | BP25: P | BQ25: A | BR25: P | BS25: A | BT25: P | BU25: A | BV25: P | BW25: A | BX25: P | BY25: A | BZ25: P | CA25: A | CB25: P | CC25: A | CD25: P | CE25: A | CF25: P | CG25: A
A26: WAGES | B26: DRIVER | C26: MOTIAR RAHAMAN | D26: TC0051 | H26: 0 | J26: 360 | K26: 185 | L26: 11620 | M26: 3130 | N26: 2550 | O26: =SUBTOTAL(9,Table4[[#This Row],[ESI BASIC]:[ESI FOOD]]) -> 0 | P26: UCO BANK | Q26: UCBA0002550 | R26: 25500110099254 | T26: =COUNTIF(X26:CG26,"P") -> 33 | V26: =T26+U26 -> 33 | W26: =SUM(CI26:DM26) -> 6 | X26: A | Y26: P | Z26: P | AA26: A | AB26: P | AC26: P | AD26: A | AE26: P | AF26: P | AG26: A | AH26: P | AI26: P | AJ26: A | AK26: P | AL26: P | AM26: A | AN26: A | AO26: A | AP26: A | AQ26: P | AR26: P | AS26: A | AT26: A | AU26: A | AV26: A | AW26: A | AX26: A | AY26: A | AZ26: A | BA26: A | BB26: A | BC26: P | BD26: P | BE26: A | BF26: P | BG26: P | BH26: A | BI26: P | BJ26: P | BK26: A | BL26: P | BM26: P | BN26: A | BO26: P | BP26: P | BQ26: A | BR26: P | BS26: P | BT26: A | BU26: P | BV26: P | BW26: A | BX26: P | BY26: P | BZ26: A | CA26: P | CB26: P | CC26: A | CD26: P | CE26: P | CF26: A | CG26: P | CI26: 0 | CJ26: 0 | CK26: 0 | CL26: 0 | CM26: 0 | CN26: 1 | CO26: 1 | CP26: 0 | CQ26: 0 | CR26: 0 | CS26: 0 | CT26: 0 | CU26: 0 | CV26: 0 | CW26: 0 | CX26: 0 | CY26: 0 | CZ26: 0 | DA26: 0 | DB26: 0 | DC26: 0 | DD26: 1 | DE26: 0 | DF26: 0 | DG26: 1 | DH26: 0 | DI26: 1 | DJ26: 0 | DK26: 1 | DL26: 0 | DM26: 0
A27: CONTRACT | B27: OTHERS | C27: AYAN PAUL | H27: 0 | I27: 12000 | O27: =SUBTOTAL(9,Table4[[#This Row],[ESI BASIC]:[ESI FOOD]]) -> 0 | T27: =COUNTIF(X27:CG27,"P") -> 31 | U27: 4 | V27: =T27+U27 -> 35 | W27: =SUM(CI27:DM27) -> 0 | X27: P | Y27: A | Z27: P | AA27: A | AB27: P | AC27: A | AD27: P | AE27: A | AF27: P | AG27: A | AH27: P | AI27: A | AJ27: P | AK27: A | AL27: P | AM27: A | AN27: P | AO27: A | AP27: P | AQ27: A | AR27: P | AS27: A | AT27: P | AU27: A | AV27: P | AW27: A | AX27: P | AY27: A | AZ27: P | BA27: A | BB27: P | BC27: A | BD27: P | BE27: A | BF27: P | BG27: A | BH27: P | BI27: A | BJ27: P | BK27: A | BL27: P | BM27: A | BN27: P | BO27: A | BP27: P | BQ27: A | BR27: P | BS27: A | BT27: P | BU27: A | BV27: P | BW27: A | BX27: P | BY27: A | BZ27: P | CA27: A | CB27: P | CC27: A | CD27: P | CE27: A | CF27: P | CG27: A
A28: SALARY | B28: OFFICE | C28: PULIN MONDAL | D28: TC 0024 | E28: 10560 | F28: 500 | G28: 440 | H28: =SUBTOTAL(9,Table4[[#This Row],[BASIC]:[FOOD]]) -> 11500 | P28: SBI | Q28: SBIN0016917 | R28: 34576474280 | T28: =COUNTIF(X28:CG28,"P") -> 27 | U28: 4 | V28: =T28+U28 -> 31 | W28: =SUM(CI28:DM28) -> 0 | X28: P | Y28: A | Z28: P | AA28: A | AB28: P | AC28: A | AD28: P | AE28: A | AF28: A | AG28: A | AH28: P | AI28: A | AJ28: P | AK28: A | AL28: P | AM28: A | AN28: P | AO28: A | AP28: P | AQ28: A | AR28: P | AS28: A | AT28: A | AU28: A | AV28: P | AW28: A | AX28: P | AY28: A | AZ28: P | BA28: A | BB28: P | BC28: A | BD28: P | BE28: A | BF28: P | BG28: A | BH28: A | BI28: A | BJ28: P | BK28: A | BL28: P | BM28: A | BN28: P | BO28: A | BP28: P | BQ28: A | BR28: P | BS28: A | BT28: P | BU28: A | BV28: A | BW28: A | BX28: P | BY28: A | BZ28: P | CA28: A | CB28: P | CC28: A | CD28: P | CE28: A | CF28: P | CG28: A | CH28: A
A29: SALARY | B29: OFFICE | C29: RAJU PAL | D29: TC 0040 | E29: 11620 | F29: 5000 | G29: 3380 | H29: =SUBTOTAL(9,Table4[[#This Row],[BASIC]:[FOOD]]) -> 20000 | P29: UCO BANK | Q29: UCBA0002567 | R29: 25670110051610 | T29: =COUNTIF(X29:CG29,"P") -> 29 | U29: 2 | V29: =T29+U29 -> 31 | W29: =SUM(CI29:DM29) -> 0 | X29: P | Y29: A | Z29: P | AA29: A | AB29: P | AC29: A | AD29: P | AE29: A | AF29: P | AG29: A | AH29: P | AI29: A | AJ29: P | AK29: A | AL29: P | AM29: A | AN29: P | AO29: A | AP29: P | AQ29: A | AR29: P | AS29: A | AT29: P | AU29: A | AV29: P | AW29: A | AX29: P | AY29: A | AZ29: P | BA29: A | BB29: A | BC29: A | BD29: P | BE29: A | BF29: P | BG29: A | BH29: P | BI29: A | BJ29: P | BK29: A | BL29: P | BM29: A | BN29: P | BO29: A | BP29: P | BQ29: A | BR29: P | BS29: A | BT29: P | BU29: A | BV29: P | BW29: A | BX29: P | BY29: A | BZ29: P | CA29: A | CB29: P | CC29: A | CD29: A | CE29: A | CF29: P | CG29: A
A30: WAGES | B30: DRIVER | C30: MOKSHED ALI | H30: 0 | J30: 300 | K30: 185 | L30: 19000 | O30: =SUBTOTAL(9,Table4[[#This Row],[ESI BASIC]:[ESI FOOD]]) -> 0 | P30: UNION BANK | Q30: UBIN0912344 | R30: 520441033294786 | T30: =COUNTIF(X30:CG30,"P") -> 41 | V30: =T30+U30 -> 41 | W30: =SUM(CI30:DM30) -> 12 | X30: A | Y30: P | Z30: P | AA30: A | AB30: P | AC30: P | AD30: A | AE30: P | AF30: P | AG30: A | AH30: P | AI30: P | AJ30: A | AK30: P | AL30: P | AM30: A | AN30: P | AO30: P | AP30: A | AQ30: P | AR30: P | AS30: A | AT30: P | AU30: P | AV30: A | AW30: P | AX30: P | AY30: A | AZ30: P | BA30: P | BB30: A | BC30: P | BD30: P | BE30: A | BF30: P | BG30: P | BH30: A | BI30: P | BJ30: P | BK30: A | BL30: P | BM30: P | BN30: A | BO30: P | BP30: P | BQ30: A | BR30: P | BS30: P | BT30: A | BU30: P | BV30: P | BW30: A | BX30: P | BY30: P | BZ30: A | CA30: P | CB30: P | CC30: A | CD30: P | CE30: P | CF30: A | CG30: P | CI30: 0 | CJ30: 0 | CK30: 0 | CL30: 1 | CM30: 0 | CN30: 0 | CO30: 2 | CP30: 0 | CQ30: 1 | CR30: 0 | CS30: 0 | CT30: 0 | CU30: 0 | CV30: 1 | CW30: 1 | CX30: 0 | CY30: 0 | CZ30: 0 | DA30: 0 | DB30: 1 | DC30: 0 | DD30: 0 | DE30: 1 | DF30: 0 | DG30: 0 | DH30: 0 | DI30: 1 | DJ30: 1 | DK30: 1 | DL30: 1 | DM30: 0
A31: CONTRACT | B31: HELPER | C31: NAYAN MONDAL | H31: 0 | J31: 250 | K31: 70 | O31: =SUBTOTAL(9,Table4[[#This Row],[ESI BASIC]:[ESI FOOD]]) -> 0 | T31: =COUNTIF(X31:CG31,"P") -> 42 | V31: =T31+U31 -> 42 | W31: =SUM(CI31:DM31) -> 9 | X31: P | Y31: P | Z31: A | AA31: P | AB31: P | AC31: A | AD31: P | AE31: P | AF31: A | AG31: P | AH31: P | AI31: A | AJ31: P | AK31: P | AL31: A | AM31: P | AN31: P | AO31: A | AP31: P | AQ31: P | AR31: A | AS31: P | AT31: P | AU31: A | AV31: P | AW31: P | AX31: A | AY31: P | AZ31: P | BA31: A | BB31: P | BC31: P | BD31: A | BE31: P | BF31: P | BG31: A | BH31: P | BI31: P | BJ31: A | BK31: P | BL31: P | BM31: A | BN31: P | BO31: P | BP31: A | BQ31: P | BR31: P | BS31: A | BT31: P | BU31: P | BV31: A | BW31: P | BX31: P | BY31: A | BZ31: P | CA31: P | CB31: A | CC31: P | CD31: P | CE31: A | CF31: P | CG31: P | CI31: 0 | CJ31: 0 | CK31: 0 | CL31: 0 | CM31: 0 | CN31: 0 | CO31: 0 | CP31: 0 | CQ31: 1 | CR31: 0 | CS31: 0 | CT31: 1 | CU31: 0 | CV31: 0 | CW31: 0 | CX31: 1 | CY31: 0 | CZ31: 1 | DA31: 0 | DB31: 0 | DC31: 0 | DD31: 1 | DE31: 0 | DF31: 0 | DG31: 1 | DH31: 0 | DI31: 2 | DJ31: 1 | DK31: 0 | DL31: 0 | DM31: 0
A32: CONTRACT | B32: OTHERS | C32: SHIB SANKAR MAJHI | H32: 0 | I32: 17900 | O32: =SUBTOTAL(9,Table4[[#This Row],[ESI BASIC]:[ESI FOOD]]) -> 0 | T32: =COUNTIF(X32:CG32,"P") -> 31 | U32: 4 | V32: =T32+U32 -> 35 | W32: =SUM(CI32:DM32) -> 0 | X32: P | Y32: A | Z32: P | AA32: A | AB32: P | AC32: A | AD32: P | AE32: A | AF32: A | AG32: A | AH32: P | AI32: A | AJ32: P | AK32: A | AL32: P | AM32: A | AN32: P | AO32: A | AP32: P | AQ32: A | AR32: P | AS32: A | AT32: P | AU32: P | AV32: P | AW32: A | AX32: P | AY32: A | AZ32: P | BA32: A | BB32: P | BC32: A | BD32: P | BE32: A | BF32: P | BG32: A | BH32: A | BI32: A | BJ32: P | BK32: A | BL32: P | BM32: A | BN32: P | BO32: A | BP32: P | BQ32: A | BR32: P | BS32: A | BT32: P | BU32: A | BV32: P | BW32: P | BX32: P | BY32: A | BZ32: P | CA32: A | CB32: P | CC32: A | CD32: P | CE32: A | CF32: P | CG32: A
A33: WAGES | B33: DRIVER | C33: SAMSER ALI | D33: TC 0143 | H33: 0 | J33: 325 | K33: 185 | L33: 20600 | O33: =SUBTOTAL(9,Table4[[#This Row],[ESI BASIC]:[ESI FOOD]]) -> 0 | P33: UNION BANK | Q33: UBIN0912344 | R33: 690302010003128 | T33: =COUNTIF(X33:CG33,"P") -> 37 | V33: =T33+U33 -> 37 | W33: =SUM(CI33:DM33) -> 7 | X33: P | Y33: P | Z33: A | AA33: P | AB33: A | AC33: A | AD33: P | AE33: P | AF33: A | AG33: P | AH33: P | AI33: A | AJ33: P | AK33: P | AL33: A | AM33: P | AN33: P | AO33: A | AP33: A | AQ33: P | AR33: A | AS33: P | AT33: P | AU33: A | AV33: P | AW33: P | AX33: A | AY33: P | AZ33: P | BA33: A | BB33: P | BC33: P | BD33: A | BE33: P | BF33: P | BG33: A | BH33: P | BI33: P | BJ33: A | BK33: P | BL33: P | BM33: A | BN33: P | BO33: P | BP33: A | BQ33: P | BR33: A | BS33: A | BT33: P | BU33: P | BV33: A | BW33: P | BX33: A | BY33: A | BZ33: A | CA33: P | CB33: A | CC33: P | CD33: P | CE33: A | CF33: P | CG33: P | CH33: A | CI33: 1 | CJ33: 0 | CK33: 0 | CL33: 0 | CM33: 0 | CN33: 0 | CO33: 0 | CP33: 0 | CQ33: 0 | CR33: 0 | CS33: 0 | CT33: 1 | CU33: 0 | CV33: 2 | CW33: 0 | CX33: 0 | CY33: 0 | CZ33: 1 | DA33: 0 | DB33: 0 | DC33: 0 | DD33: 1 | DE33: 0 | DF33: 0 | DG33: 1 | DH33: 0 | DI33: 0 | DJ33: 0 | DK33: 0 | DL33: 0 | DM33: 0
A34: CONTRACT | B34: OTHERS | C34: ABUL KALAM AZAD | H34: 0 | I34: 17900 | O34: =SUBTOTAL(9,Table4[[#This Row],[ESI BASIC]:[ESI FOOD]]) -> 0 | T34: =COUNTIF(X34:CG34,"P") -> 31 | U34: 4 | V34: =T34+U34 -> 35 | W34: =SUM(CI34:DM34) -> 0 | X34: P | Y34: A | Z34: P | AA34: A | AB34: P | AC34: A | AD34: P | AE34: A | AF34: P | AG34: P | AH34: P | AI34: A | AJ34: P | AK34: A | AL34: P | AM34: A | AN34: P | AO34: A | AP34: P | AQ34: A | AR34: P | AS34: A | AT34: A | AU34: A | AV34: P | AW34: A | AX34: P | AY34: A | AZ34: P | BA34: A | BB34: P | BC34: A | BD34: P | BE34: A | BF34: P | BG34: A | BH34: P | BI34: P | BJ34: P | BK34: A | BL34: P | BM34: A | BN34: P | BO34: A | BP34: P | BQ34: A | BR34: P | BS34: A | BT34: P | BU34: A | BV34: A | BW34: A | BX34: P | BY34: A | BZ34: P | CA34: A | CB34: P | CC34: A | CD34: P | CE34: A | CF34: P | CG34: A
A35: CONTRACT | B35: DRIVER | C35: SATYA NASKAR | H35: 0 | J35: 300 | K35: 185 | T35: =COUNTIF(X35:CG35,"P") -> 41 | V35: =T35+U35 -> 41 | W35: =SUM(CI35:DM35) -> 9 | X35: P | Y35: A | Z35: P | AA35: P | AB35: A | AC35: P | AD35: P | AE35: A | AF35: P | AG35: P | AH35: A | AI35: P | AJ35: P | AK35: A | AL35: P | AM35: P | AN35: A | AO35: P | AP35: P | AQ35: A | AR35: P | AS35: P | AT35: A | AU35: P | AV35: P | AW35: A | AX35: P | AY35: P | AZ35: A | BA35: P | BB35: P | BC35: A | BD35: P | BE35: P | BF35: A | BG35: P | BH35: P | BI35: A | BJ35: P | BK35: P | BL35: A | BM35: P | BN35: P | BO35: A | BP35: P | BQ35: P | BR35: A | BS35: P | BT35: P | BU35: A | BV35: P | BW35: P | BX35: A | BY35: P | BZ35: P | CA35: A | CB35: P | CC35: P | CD35: A | CE35: P | CF35: P | CG35: A | CI35: 1 | CJ35: 0 | CK35: 0 | CL35: 0 | CM35: 0 | CN35: 0 | CO35: 1 | CP35: 0 | CQ35: 1 | CR35: 0 | CS35: 0 | CT35: 1 | CU35: 0 | CV35: 2 | CW35: 0 | CX35: 0 | CY35: 0 | CZ35: 0 | DA35: 1 | DB35: 0 | DC35: 0 | DD35: 1 | DE35: 1 | DF35: 0 | DG35: 0 | DH35: 0 | DI35: 0 | DJ35: 0 | DK35: 0 | DL35: 0 | DM35: 0
A36: WAGES | B36: DRIVER | C36: SHANTI MONDAL | D36: TC 0412 | H36: 0 | J36: 310 | K36: 185 | L36: 20000 | O36: =SUBTOTAL(9,Table4[[#This Row],[ESI BASIC]:[ESI FOOD]]) -> 0 | P36: UCO BANK | Q36: UCBA0002550 | R36: 25503211002376 | T36: =COUNTIF(X36:CG36,"P") -> 41 | V36: =T36+U36 -> 41 | W36: =SUM(CI36:DM36) -> 7 | X36: A | Y36: P | Z36: P | AA36: A | AB36: P | AC36: P | AD36: A | AE36: P | AF36: P | AG36: A | AH36: P | AI36: P | AJ36: A | AK36: P | AL36: P | AM36: A | AN36: P | AO36: P | AP36: A | AQ36: P | AR36: P | AS36: A | AT36: P | AU36: P | AV36: A | AW36: P | AX36: P | AY36: A | AZ36: P | BA36: P | BB36: A | BC36: P | BD36: P | BE36: A | BF36: P | BG36: P | BH36: A | BI36: P | BJ36: P | BK36: A | BL36: P | BM36: P | BN36: A | BO36: P | BP36: P | BQ36: A | BR36: P | BS36: P | BT36: A | BU36: P | BV36: P | BW36: A | BX36: P | BY36: P | BZ36: A | CA36: P | CB36: P | CC36: A | CD36: P | CE36: P | CF36: A | CG36: P | CI36: 0 | CJ36: 0 | CK36: 0 | CL36: 0 | CM36: 0 | CN36: 0 | CO36: 0 | CP36: 0 | CQ36: 0 | CR36: 0 | CS36: 0 | CT36: 0 | CU36: 0 | CV36: 1 | CW36: 0 | CX36: 0 | CY36: 0 | CZ36: 1 | DA36: 0 | DB36: 0 | DC36: 0 | DD36: 1 | DE36: 1 | DF36: 0 | DG36: 0 | DH36: 0 | DI36: 1 | DJ36: 2 | DK36: 0 | DL36: 0 | DM36: 0
A37: WAGES | B37: DRIVER | C37: SIRAJUL MOLLA | D37: TC 0072 | H37: 0 | J37: 320 | K37: 185 | L37: 11620 | M37: 2160 | N37: 1920 | O37: =SUBTOTAL(9,Table4[[#This Row],[ESI BASIC]:[ESI FOOD]]) -> 0 | P37: SBI | Q37: SBIN0016917 | R37: 34256315188 | T37: =COUNTIF(X37:CG37,"P") -> 41 | V37: =T37+U37 -> 41 | W37: =SUM(CI37:DM37) -> 13 | X37: P | Y37: A | Z37: P | AA37: P | AB37: A | AC37: P | AD37: P | AE37: A | AF37: P | AG37: P | AH37: A | AI37: P | AJ37: P | AK37: A | AL37: P | AM37: P | AN37: A | AO37: P | AP37: P | AQ37: A | AR37: P | AS37: P | AT37: A | AU37: P | AV37: P | AW37: A | AX37: P | AY37: P | AZ37: A | BA37: P | BB37: P | BC37: A | BD37: P | BE37: P | BF37: A | BG37: P | BH37: P | BI37: A | BJ37: P | BK37: P | BL37: A | BM37: P | BN37: P | BO37: A | BP37: P | BQ37: P | BR37: A | BS37: P | BT37: P | BU37: A | BV37: P | BW37: P | BX37: A | BY37: P | BZ37: P | CA37: A | CB37: P | CC37: P | CD37: A | CE37: P | CF37: P | CG37: A | CI37: 0 | CJ37: 0 | CK37: 0 | CL37: 0 | CM37: 0 | CN37: 0 | CO37: 0 | CP37: 0 | CQ37: 2 | CR37: 0 | CS37: 0 | CT37: 1 | CU37: 0 | CV37: 3 | CW37: 0 | CX37: 1 | CY37: 0 | CZ37: 1 | DA37: 0 | DB37: 1 | DC37: 0 | DD37: 1 | DE37: 1 | DF37: 0 | DG37: 1 | DH37: 0 | DI37: 0 | DJ37: 1 | DK37: 0 | DL37: 0 | DM37: 0
A38: WAGES | B38: HELPER | C38: SK. ANARUL ISLAM | D38: TC 0076 | H38: 0 | J38: 420 | K38: 0 | L38: 10560 | M38: 1140 | N38: 900 | O38: =SUBTOTAL(9,Table4[[#This Row],[ESI BASIC]:[ESI FOOD]]) -> 0 | P38: IOB | Q38: IOBA0000013 | R38: 1301000024478 | T38: =COUNTIF(X38:CG38,"P") -> 31 | V38: =T38+U38 -> 31 | W38: =SUM(CI38:DM38) -> 0 | X38: P | Y38: A | Z38: P | AA38: A | AB38: P | AC38: A | AD38: P | AE38: A | AF38: P | AG38: A | AH38: P | AI38: A | AJ38: P | AK38: A | AL38: P | AM38: A | AN38: P | AO38: A | AP38: P | AQ38: A | AR38: P | AS38: A | AT38: P | AU38: A | AV38: P | AW38: A | AX38: P | AY38: A | AZ38: P | BA38: A | BB38: P | BC38: A | BD38: P | BE38: A | BF38: P | BG38: A | BH38: P | BI38: A | BJ38: P | BK38: A | BL38: P | BM38: A | BN38: P | BO38: A | BP38: P | BQ38: A | BR38: P | BS38: A | BT38: P | BU38: A | BV38: P | BW38: A | BX38: P | BY38: A | BZ38: P | CA38: A | CB38: P | CC38: A | CD38: P | CE38: A | CF38: P | CG38: A
A39: WAGES | B39: HOPPER | C39: SRISTI DHAR MONDAL | D39: TC 0014 | H39: 0 | I39: 14000 | L39: 11615 | M39: 1378 | N39: 1007 | O39: =SUBTOTAL(9,Table4[[#This Row],[ESI BASIC]:[ESI FOOD]]) -> 0 | P39: CANARA BANK | Q39: CNRB0019776 | R39: 97762210013678 | T39: =COUNTIF(X39:CG39,"P") -> 33 | U39: 4 | V39: =T39+U39 -> 37 | W39: =SUM(CI39:DM39) -> 0 | X39: P | Y39: P | Z39: P | AA39: A | AB39: P | AC39: A | AD39: P | AE39: A | AF39: P | AG39: A | AH39: P | AI39: A | AJ39: P | AK39: A | AL39: P | AM39: A | AN39: P | AO39: A | AP39: P | AQ39: A | AR39: P | AS39: A | AT39: P | AU39: A | AV39: P | AW39: A | AX39: P | AY39: A | AZ39: P | BA39: A | BB39: P | BC39: A | BD39: P | BE39: A | BF39: P | BG39: A | BH39: P | BI39: A | BJ39: P | BK39: A | BL39: P | BM39: A | BN39: P | BO39: A | BP39: P | BQ39: A | BR39: P | BS39: A | BT39: P | BU39: A | BV39: P | BW39: P | BX39: P | BY39: A | BZ39: P | CA39: A | CB39: P | CC39: A | CD39: P | CE39: A | CF39: P | CG39: A
A40: WAGES | B40: HOPPER | C40: SUDHAN MONDAL | D40: TC 0109 | H40: 0 | I40: 15200 | L40: 11615 | M40: 1894 | N40: 1691 | O40: =SUBTOTAL(9,Table4[[#This Row],[ESI BASIC]:[ESI FOOD]]) -> 0 | P40: SBI | Q40: SBIN0016917 | R40: 36454318522 | T40: =COUNTIF(X40:CG40,"P") -> 29 | U40: 4 | V40: =T40+U40 -> 33 | W40: =SUM(CI40:DM40) -> 0 | X40: A | Y40: A | Z40: P | AA40: A | AB40: P | AC40: A | AD40: P | AE40: A | AF40: P | AG40: A | AH40: P | AI40: A | AJ40: P | AK40: A | AL40: P | AM40: A | AN40: P | AO40: A | AP40: P | AQ40: A | AR40: P | AS40: A | AT40: P | AU40: A | AV40: P | AW40: A | AX40: P | AY40: A | AZ40: P | BA40: A | BB40: A | BC40: A | BD40: P | BE40: A | BF40: P | BG40: A | BH40: P | BI40: A | BJ40: P | BK40: A | BL40: P | BM40: A | BN40: P | BO40: A | BP40: P | BQ40: A | BR40: P | BS40: A | BT40: P | BU40: A | BV40: P | BW40: A | BX40: P | BY40: A | BZ40: P | CA40: A | CB40: P | CC40: A | CD40: P | CE40: A | CF40: P | CG40: A
A41: WAGES | B41: LAB | C41: SWAPAN MONDAL | D41: TC 0023 | H41: 0 | I41: 16800 | L41: 11620 | M41: 2600 | N41: 2580 | O41: =SUBTOTAL(9,Table4[[#This Row],[ESI BASIC]:[ESI FOOD]]) -> 0 | P41: CENTRAL BANK OF INDIA | Q41: CBIN0281927 | R41: 1937031426 | T41: =COUNTIF(X41:CG41,"P") -> 30 | U41: 4 | V41: =T41+U41 -> 34 | W41: =SUM(CI41:DM41) -> 0 | X41: P | Y41: A | Z41: P | AA41: A | AB41: P | AC41: A | AD41: P | AE41: A | AF41: P | AG41: A | AH41: P | AI41: A | AJ41: P | AK41: A | AL41: P | AM41: A | AN41: P | AO41: A | AP41: A | AQ41: A | AR41: P | AS41: A | AT41: P | AU41: A | AV41: A | AW41: A | AX41: P | AY41: P | AZ41: P | BA41: A | BB41: P | BC41: A | BD41: P | BE41: A | BF41: P | BG41: A | BH41: P | BI41: A | BJ41: A | BK41: A | BL41: P | BM41: A | BN41: P | BO41: A | BP41: P | BQ41: A | BR41: P | BS41: A | BT41: P | BU41: A | BV41: P | BW41: P | BX41: P | BY41: A | BZ41: P | CA41: A | CB41: P | CC41: A | CD41: P | CE41: A | CF41: P | CG41: A
A42: SALARY | B42: OFFICE | C42: UJJAL MUKHERJEE | D42: TC 0032 | E42: 10560 | F42: 5000 | G42: 4440 | H42: =SUBTOTAL(9,Table4[[#This Row],[BASIC]:[FOOD]]) -> 20000 | P42: CANARA BANK | Q42: CNRB0019776 | R42: 110062333588 | T42: =COUNTIF(X42:CG42,"P") -> 31 | V42: =T42+U42 -> 31 | W42: =SUM(CI42:DM42) -> 0 | X42: P | Y42: A | Z42: P | AA42: A | AB42: P | AC42: A | AD42: P | AE42: A | AF42: P | AG42: A | AH42: P | AI42: A | AJ42: P | AK42: A | AL42: P | AM42: A | AN42: P | AO42: A | AP42: P | AQ42: A | AR42: P | AS42: A | AT42: P | AU42: A | AV42: P | AW42: A | AX42: P | AY42: A | AZ42: P | BA42: A | BB42: P | BC42: A | BD42: P | BE42: A | BF42: P | BG42: A | BH42: P | BI42: A | BJ42: P | BK42: A | BL42: P | BM42: A | BN42: P | BO42: A | BP42: P | BQ42: A | BR42: P | BS42: A | BT42: P | BU42: A | BV42: P | BW42: A | BX42: P | BY42: A | BZ42: P | CA42: A | CB42: P | CC42: A | CD42: P | CE42: A | CF42: P | CG42: A
A43: WAGES | B43: DRIVER | C43: MOSIAR MOLLA | H43: 0 | J43: 300 | K43: 185 | L43: 19000 | O43: =SUBTOTAL(9,Table4[[#This Row],[ESI BASIC]:[ESI FOOD]]) -> 0 | P43: BANK OF BARODA | Q43: BARB0DBRAJR | R43: 80850100011310 | T43: =COUNTIF(X43:CG43,"P") -> 34 | V43: =T43+U43 -> 34 | W43: =SUM(CI43:DM43) -> 8 | X43: P | Y43: P | Z43: A | AA43: P | AB43: P | AC43: A | AD43: P | AE43: P | AF43: A | AG43: P | AH43: P | AI43: A | AJ43: P | AK43: P | AL43: A | AM43: P | AN43: P | AO43: A | AP43: P | AQ43: P | AR43: A | AS43: P | AT43: P | AU43: A | AV43: P | AW43: P | AX43: A | AY43: P | AZ43: P | BA43: A | BB43: P | BC43: A | BD43: A | BE43: A | BF43: A | BG43: A | BH43: A | BI43: A | BJ43: A | BK43: A | BL43: A | BM43: A | BN43: A | BO43: P | BP43: A | BQ43: P | BR43: P | BS43: A | BT43: P | BU43: P | BV43: A | BW43: P | BX43: P | BY43: A | BZ43: P | CA43: P | CB43: A | CC43: P | CD43: P | CE43: A | CF43: P | CG43: P | CI43: 0 | CJ43: 0 | CK43: 0 | CL43: 0 | CM43: 1 | CN43: 0 | CO43: 0 | CP43: 0 | CQ43: 1 | CR43: 0 | CS43: 0 | CT43: 0 | CU43: 0 | CV43: 0 | CW43: 1 | CX43: 0 | CY43: 0 | CZ43: 0 | DA43: 0 | DB43: 0 | DC43: 0 | DD43: 0 | DE43: 1 | DF43: 0 | DG43: 1 | DH43: 0 | DI43: 2 | DJ43: 0 | DK43: 0 | DL43: 1 | DM43: 0
A44: WAGES | B44: DRIVER | C44: ISRAFIL DHALI | D44: TC 0427 | H44: 0 | J44: 300 | K44: 185 | L44: 21000 | O44: =Table4[[#This Row],[ESI FOOD]]+Table4[[#This Row],[ESI HRA]]+Table4[[#This Row],[ESI BASIC]] -> 21000 | P44: UJJIVAN SMALL FINANCE BANK | Q44: UJVN0003572 | R44: 3572110010050084 | T44: =COUNTIF(X44:CG44,"P") -> 41 | V44: =T44+U44 -> 41 | W44: =SUM(CI44:DM44) -> 10 | X44: A | Y44: P | Z44: P | AA44: A | AB44: P | AC44: P | AD44: A | AE44: P | AF44: P | AG44: A | AH44: P | AI44: P | AJ44: A | AK44: P | AL44: P | AM44: A | AN44: P | AO44: P | AP44: A | AQ44: P | AR44: P | AS44: A | AT44: P | AU44: P | AV44: A | AW44: P | AX44: P | AY44: A | AZ44: P | BA44: P | BB44: A | BC44: P | BD44: P | BE44: A | BF44: P | BG44: P | BH44: A | BI44: P | BJ44: P | BK44: A | BL44: P | BM44: P | BN44: A | BO44: P | BP44: P | BQ44: A | BR44: P | BS44: P | BT44: A | BU44: P | BV44: P | BW44: A | BX44: P | BY44: P | BZ44: A | CA44: P | CB44: P | CC44: A | CD44: P | CE44: P | CF44: A | CG44: P | CI44: 0 | CJ44: 0 | CK44: 0 | CL44: 0 | CM44: 0 | CN44: 0 | CO44: 1 | CP44: 0 | CQ44: 0 | CR44: 0 | CS44: 0 | CT44: 0 | CU44: 0 | CV44: 2 | CW44: 0 | CX44: 0 | CY44: 1 | CZ44: 0 | DA44: 1 | DB44: 0 | DC44: 0 | DD44: 1 | DE44: 1 | DF44: 0 | DG44: 0 | DH44: 0 | DI44: 2 | DJ44: 0 | DK44: 1 | DL44: 0 | DM44: 0
A45: WAGES | B45: DRIVER | C45: ROUF MONDAL | D45: TC 0420 | H45: 0 | J45: 300 | K45: 185 | L45: 21000 | O45: =Table4[[#This Row],[ESI FOOD]]+Table4[[#This Row],[ESI HRA]]+Table4[[#This Row],[ESI BASIC]] -> 21000 | P45: UCO BANK | Q45: UCBA0002550 | R45: 25500110040355 | T45: =COUNTIF(X45:CG45,"P") -> 43 | V45: =T45+U45 -> 43 | W45: =SUM(CI45:DM45) -> 14 | X45: P | Y45: P | Z45: A | AA45: P | AB45: P | AC45: A | AD45: P | AE45: P | AF45: A | AG45: P | AH45: P | AI45: A | AJ45: P | AK45: P | AL45: P | AM45: P | AN45: P | AO45: A | AP45: P | AQ45: P | AR45: A | AS45: P | AT45: P | AU45: A | AV45: P | AW45: P | AX45: A | AY45: P | AZ45: P | BA45: A | BB45: P | BC45: P | BD45: A | BE45: P | BF45: P | BG45: A | BH45: P | BI45: P | BJ45: A | BK45: P | BL45: P | BM45: A | BN45: P | BO45: P | BP45: A | BQ45: P | BR45: P | BS45: A | BT45: P | BU45: P | BV45: A | BW45: P | BX45: P | BY45: A | BZ45: P | CA45: P | CB45: A | CC45: P | CD45: P | CE45: A | CF45: P | CG45: P | CI45: 0 | CJ45: 0 | CK45: 0 | CL45: 0 | CM45: 1 | CN45: 0 | CO45: 0 | CP45: 1 | CQ45: 1 | CR45: 0 | CS45: 0 | CT45: 1 | CU45: 0 | CV45: 1 | CW45: 1 | CX45: 0 | CY45: 1 | CZ45: 1 | DA45: 0 | DB45: 0 | DC45: 0 | DD45: 1 | DE45: 1 | DF45: 0 | DG45: 1 | DH45: 0 | DI45: 2 | DJ45: 0 | DK45: 1 | DL45: 0 | DM45: 0
A46: CONTRACT | B46: HELPER | C46: JAMSHED ALI | H46: 0 | J46: 260 | K46: 80 | O46: =SUBTOTAL(9,Table4[[#This Row],[ESI BASIC]:[ESI FOOD]]) -> 0 | T46: =COUNTIF(X46:CG46,"P") -> 39 | V46: =T46+U46 -> 39 | W46: =SUM(CI46:DM46) -> 14 | X46: P | Y46: A | Z46: P | AA46: P | AB46: A | AC46: P | AD46: P | AE46: A | AF46: P | AG46: P | AH46: A | AI46: P | AJ46: P | AK46: A | AL46: P | AM46: P | AN46: A | AO46: P | AP46: P | AQ46: A | AR46: P | AS46: P | AT46: A | AU46: P | AV46: P | AW46: A | AX46: P | AY46: P | AZ46: A | BA46: P | BB46: P | BC46: A | BD46: P | BE46: P | BF46: A | BG46: P | BH46: P | BI46: A | BJ46: A | BK46: A | BL46: A | BM46: P | BN46: P | BO46: A | BP46: P | BQ46: P | BR46: A | BS46: P | BT46: P | BU46: A | BV46: P | BW46: P | BX46: A | BY46: P | BZ46: P | CA46: A | CB46: P | CC46: P | CD46: A | CE46: P | CF46: P | CG46: A | CI46: 0 | CJ46: 0 | CK46: 0 | CL46: 0 | CM46: 0 | CN46: 0 | CO46: 1 | CP46: 0 | CQ46: 1 | CR46: 0 | CS46: 1 | CT46: 0 | CU46: 0 | CV46: 3 | CW46: 2 | CX46: 0 | CY46: 0 | CZ46: 1 | DA46: 1 | DB46: 0 | DC46: 0 | DD46: 1 | DE46: 0 | DF46: 1 | DG46: 0 | DH46: 0 | DI46: 1 | DJ46: 0 | DK46: 1 | DL46: 0 | DM46: 0
A47: CONTRACT | B47: HELPER | C47: ABHIJIT MONDAL | H47: 0 | J47: 250 | K47: 70 | O47: =SUBTOTAL(9,Table4[[#This Row],[ESI BASIC]:[ESI FOOD]]) -> 0 | T47: =COUNTIF(X47:CG47,"P") -> 40 | V47: =T47+U47 -> 40 | W47: =SUM(CI47:DM47) -> 9 | X47: P | Y47: A | Z47: P | AA47: P | AB47: A | AC47: P | AD47: P | AE47: A | AF47: P | AG47: P | AH47: A | AI47: P | AJ47: P | AK47: A | AL47: P | AM47: P | AN47: A | AO47: P | AP47: P | AQ47: A | AR47: P | AS47: P | AT47: A | AU47: P | AV47: P | AW47: A | AX47: P | AY47: P | AZ47: A | BA47: P | BB47: P | BC47: A | BD47: P | BE47: P | BF47: A | BG47: P | BH47: P | BI47: A | BJ47: P | BK47: P | BL47: A | BM47: P | BN47: P | BO47: A | BP47: P | BQ47: P | BR47: A | BS47: A | BT47: P | BU47: A | BV47: P | BW47: P | BX47: A | BY47: P | BZ47: P | CA47: A | CB47: P | CC47: P | CD47: A | CE47: P | CF47: P | CG47: A | CI47: 0 | CJ47: 0 | CK47: 0 | CL47: 0 | CM47: 0 | CN47: 0 | CO47: 0 | CP47: 0 | CQ47: 1 | CR47: 0 | CS47: 1 | CT47: 0 | CU47: 0 | CV47: 3 | CW47: 1 | CX47: 0 | CY47: 0 | CZ47: 0 | DA47: 1 | DB47: 0 | DC47: 0 | DD47: 1 | DE47: 1 | DF47: 0 | DG47: 0 | DH47: 0 | DI47: 0 | DJ47: 0 | DK47: 0 | DL47: 0 | DM47: 0
A48: CONTRACT | B48: HELPER | C48: KHALEK DHALI | H48: 0 | J48: 260 | K48: 80 | O48: =SUBTOTAL(9,Table4[[#This Row],[ESI BASIC]:[ESI FOOD]]) -> 0 | T48: =COUNTIF(X48:CG48,"P") -> 40 | V48: =T48+U48 -> 40 | W48: =SUM(CI48:DM48) -> 13 | X48: P | Y48: P | Z48: A | AA48: P | AB48: P | AC48: A | AD48: P | AE48: P | AF48: A | AG48: P | AH48: P | AI48: A | AJ48: P | AK48: P | AL48: P | AM48: P | AN48: P | AO48: A | AP48: P | AQ48: P | AR48: A | AS48: P | AT48: P | AU48: A | AV48: P | AW48: P | AX48: A | AY48: P | AZ48: P | BA48: A | BB48: A | BC48: A | BD48: A | BE48: A | BF48: P | BG48: A | BH48: P | BI48: P | BJ48: A | BK48: P | BL48: P | BM48: A | BN48: P | BO48: P | BP48: A | BQ48: P | BR48: P | BS48: A | BT48: P | BU48: P | BV48: A | BW48: P | BX48: P | BY48: A | BZ48: P | CA48: P | CB48: A | CC48: P | CD48: P | CE48: A | CF48: P | CG48: P | CI48: 0 | CJ48: 0 | CK48: 0 | CL48: 0 | CM48: 1 | CN48: 0 | CO48: 0 | CP48: 1 | CQ48: 1 | CR48: 0 | CS48: 0 | CT48: 1 | CU48: 0 | CV48: 1 | CW48: 1 | CX48: 0 | CY48: 0 | CZ48: 1 | DA48: 0 | DB48: 0 | DC48: 0 | DD48: 1 | DE48: 1 | DF48: 0 | DG48: 1 | DH48: 0 | DI48: 2 | DJ48: 0 | DK48: 1 | DL48: 0 | DM48: 0
A49: CONTRACT | B49: HELPER | C49: JAMIR ALI | H49: 0 | J49: 260 | K49: 80 | O49: =SUBTOTAL(9,Table4[[#This Row],[ESI BASIC]:[ESI FOOD]]) -> 0 | T49: =COUNTIF(X49:CG49,"P") -> 31 | V49: =T49+U49 -> 31 | W49: =SUM(CI49:DM49) -> 7 | X49: P | Y49: A | Z49: P | AA49: P | AB49: A | AC49: A | AD49: A | AE49: A | AF49: A | AG49: A | AH49: A | AI49: A | AJ49: A | AK49: A | AL49: A | AM49: P | AN49: A | AO49: P | AP49: A | AQ49: A | AR49: P | AS49: P | AT49: A | AU49: P | AV49: P | AW49: A | AX49: P | AY49: P | AZ49: A | BA49: P | BB49: P | BC49: A | BD49: P | BE49: P | BF49: A | BG49: P | BH49: P | BI49: A | BJ49: P | BK49: P | BL49: A | BM49: P | BN49: P | BO49: A | BP49: P | BQ49: P | BR49: A | BS49: P | BT49: P | BU49: A | BV49: P | BW49: P | BX49: A | BY49: P | BZ49: P | CA49: A | CB49: A | CC49: A | CD49: A | CE49: P | CF49: P | CG49: A | CI49: 1 | CJ49: 0 | CK49: 0 | CL49: 0 | CM49: 0 | CN49: 0 | CO49: 0 | CP49: 0 | CQ49: 0 | CR49: 0 | CS49: 0 | CT49: 1 | CU49: 0 | CV49: 2 | CW49: 0 | CX49: 0 | CY49: 0 | CZ49: 0 | DA49: 1 | DB49: 0 | DC49: 0 | DD49: 1 | DE49: 1 | DF49: 0 | DG49: 0 | DH49: 0 | DI49: 0 | DJ49: 0 | DK49: 0 | DL49: 0 | DM49: 0
A50: WAGES | B50: LAB | C50: KANAK JANA | D50: TC0390 | H50: 0 | I50: 19500 | L50: 11620 | M50: 4000 | N50: 3880 | O50: =SUBTOTAL(9,Table4[[#This Row],[ESI BASIC]:[ESI FOOD]]) -> 0 | P50: BANK OF BARODA | Q50: BARB0VJSALT | R50: 77830100006691 | T50: =COUNTIF(X50:CG50,"P") -> 22 | U50: 3 | V50: =T50+U50 -> 25 | W50: =SUM(CI50:DM50) -> 0 | X50: P | Y50: A | Z50: A | AA50: A | AB50: P | AC50: A | AD50: A | AE50: A | AF50: A | AG50: A | AH50: P | AI50: A | AJ50: P | AK50: A | AL50: P | AM50: A | AN50: P | AO50: A | AP50: P | AQ50: A | AR50: P | AS50: A | AT50: P | AU50: A | AV50: P | AW50: A | AX50: P | AY50: A | AZ50: P | BA50: A | BB50: P | BC50: A | BD50: P | BE50: A | BF50: P | BG50: A | BH50: A | BI50: A | BJ50: A | BK50: A | BL50: A | BM50: P | BN50: A | BO50: P | BP50: P | BQ50: A | BR50: A | BS50: A | BT50: A | BU50: A | BV50: A | BW50: A | BX50: A | BY50: A | BZ50: A | CA50: P | CB50: A | CC50: P | CD50: A | CE50: P | CF50: A | CG50: P
A51: WAGES | B51: OTHERS | C51: SOUMEN GARAI | D51: TC0362 | H51: 0 | I51: 15000 | L51: 12777 | M51: 1127 | N51: 1096 | O51: =SUBTOTAL(9,Table4[[#This Row],[ESI BASIC]:[ESI FOOD]]) -> 0 | P51: UCO BANK | Q51: UCBA0001725 | R51: 17250110061947 | T51: =COUNTIF(X51:CG51,"P") -> 27 | U51: 4 | V51: =T51+U51 -> 31 | W51: =SUM(CI51:DM51) -> 0 | X51: P | Y51: A | Z51: P | AA51: A | AB51: P | AC51: A | AD51: P | AE51: A | AF51: P | AG51: A | AH51: P | AI51: A | AJ51: P | AK51: A | AL51: P | AM51: A | AN51: P | AO51: A | AP51: P | AQ51: A | AR51: P | AS51: A | AT51: A | AU51: A | AV51: A | AW51: A | AX51: A | AY51: A | AZ51: A | BA51: A | BB51: P | BC51: A | BD51: P | BE51: A | BF51: P | BG51: A | BH51: P | BI51: A | BJ51: P | BK51: A | BL51: P | BM51: A | BN51: P | BO51: A | BP51: P | BQ51: A | BR51: P | BS51: A | BT51: P | BU51: A | BV51: P | BW51: A | BX51: P | BY51: A | BZ51: P | CA51: A | CB51: P | CC51: A | CD51: P | CE51: A | CF51: P | CG51: A
A52: WAGES | B52: DRIVER | C52: ASHOK MONDAL | D52: TC 0428 | H52: 0 | J52: 300 | K52: 185 | L52: 21000 | O52: =SUBTOTAL(9,Table4[[#This Row],[ESI BASIC]:[ESI FOOD]]) -> 0 | P52: BANGIYA GRAMIN VIKASH BANK | Q52: PUNB0RRBBGB | R52: 5108010004050 | T52: =COUNTIF(X52:CG52,"P") -> 40 | V52: =T52+U52 -> 40 | W52: =SUM(CI52:DM52) -> 5 | X52: P | Y52: A | Z52: P | AA52: P | AB52: A | AC52: P | AD52: P | AE52: A | AF52: P | AG52: P | AH52: A | AI52: P | AJ52: P | AK52: A | AL52: P | AM52: P | AN52: A | AO52: P | AP52: P | AQ52: A | AR52: P | AS52: P | AT52: A | AU52: P | AV52: P | AW52: A | AX52: P | AY52: P | AZ52: A | BA52: P | BB52: P | BC52: A | BD52: P | BE52: P | BF52: A | BG52: P | BH52: P | BI52: A | BJ52: P | BK52: P | BL52: A | BM52: P | BN52: A | BO52: A | BP52: P | BQ52: P | BR52: A | BS52: P | BT52: P | BU52: A | BV52: P | BW52: P | BX52: A | BY52: P | BZ52: P | CA52: A | CB52: P | CC52: P | CD52: A | CE52: P | CF52: P | CG52: A | CI52: 0 | CJ52: 0 | CK52: 0 | CL52: 0 | CM52: 0 | CN52: 0 | CO52: 0 | CP52: 0 | CQ52: 0 | CR52: 0 | CS52: 0 | CT52: 0 | CU52: 0 | CV52: 1 | CW52: 0 | CX52: 1 | CY52: 0 | CZ52: 0 | DA52: 0 | DB52: 1 | DC52: 0 | DD52: 0 | DE52: 0 | DF52: 0 | DG52: 1 | DH52: 0 | DI52: 0 | DJ52: 1 | DK52: 0 | DL52: 0 | DM52: 0
A53: WAGES | B53: DRIVER | C53: ANSWAR ALI MOLLA | D53: TC 0395 | H53: 0 | J53: 300 | K53: 185 | L53: 21000 | O53: =SUBTOTAL(9,Table4[[#This Row],[ESI BASIC]:[ESI FOOD]]) -> 0 | P53: SBI | Q53: SBIN0014537 | R53: 34311568785 | T53: =COUNTIF(X53:CG53,"P") -> 38 | V53: =T53+U53 -> 38 | W53: =SUM(CI53:DM53) -> 10 | X53: P | Y53: P | Z53: A | AA53: P | AB53: P | AC53: A | AD53: P | AE53: P | AF53: A | AG53: P | AH53: A | AI53: A | AJ53: P | AK53: P | AL53: A | AM53: P | AN53: P | AO53: A | AP53: P | AQ53: P | AR53: A | AS53: P | AT53: P | AU53: A | AV53: P | AW53: P | AX53: A | AY53: P | AZ53: P | BA53: A | BB53: P | BC53: P | BD53: A | BE53: P | BF53: P | BG53: A | BH53: A | BI53: A | BJ53: A | BK53: P | BL53: P | BM53: A | BN53: P | BO53: P | BP53: A | BQ53: P | BR53: P | BS53: A | BT53: P | BU53: P | BV53: A | BW53: P | BX53: P | BY53: A | BZ53: P | CA53: P | CB53: A | CC53: P | CD53: P | CE53: A | CF53: A | CG53: P | CI53: 0 | CJ53: 0 | CK53: 0 | CL53: 0 | CM53: 0 | CN53: 0 | CO53: 1 | CP53: 0 | CQ53: 1 | CR53: 0 | CS53: 0 | CT53: 0 | CU53: 0 | CV53: 2 | CW53: 0 | CX53: 1 | CY53: 0 | CZ53: 1 | DA53: 0 | DB53: 0 | DC53: 0 | DD53: 1 | DE53: 0 | DF53: 0 | DG53: 0 | DH53: 0 | DI53: 1 | DJ53: 0 | DK53: 1 | DL53: 1 | DM53: 0
A54: CONTRACT | B54: HELPER | C54: MADAN | H54: 0 | J54: 260 | K54: 80 | O54: =SUBTOTAL(9,Table4[[#This Row],[ESI BASIC]:[ESI FOOD]]) -> 0 | T54: =COUNTIF(X54:CG54,"P") -> 41 | V54: =T54+U54 -> 41 | W54: =SUM(CI54:DM54) -> 9 | X54: P | Y54: P | Z54: A | AA54: P | AB54: P | AC54: A | AD54: P | AE54: P | AF54: A | AG54: P | AH54: P | AI54: A | AJ54: P | AK54: P | AL54: A | AM54: P | AN54: P | AO54: A | AP54: P | AQ54: P | AR54: A | AS54: P | AT54: A | AU54: A | AV54: P | AW54: P | AX54: P | AY54: P | AZ54: P | BA54: A | BB54: P | BC54: P | BD54: A | BE54: P | BF54: A | BG54: A | BH54: P | BI54: P | BJ54: A | BK54: P | BL54: P | BM54: A | BN54: P | BO54: P | BP54: A | BQ54: P | BR54: P | BS54: A | BT54: P | BU54: P | BV54: A | BW54: P | BX54: P | BY54: A | BZ54: P | CA54: P | CB54: A | CC54: P | CD54: P | CE54: A | CF54: P | CG54: P | CI54: 1 | CJ54: 0 | CK54: 0 | CL54: 0 | CM54: 0 | CN54: 0 | CO54: 0 | CP54: 0 | CQ54: 0 | CR54: 0 | CS54: 0 | CT54: 0 | CU54: 0 | CV54: 4 | CW54: 0 | CX54: 0 | CY54: 0 | CZ54: 0 | DA54: 0 | DB54: 0 | DC54: 0 | DD54: 1 | DE54: 0 | DF54: 0 | DG54: 1 | DH54: 0 | DI54: 1 | DJ54: 0 | DK54: 1 | DL54: 0 | DM54: 0
A55: CONTRACT | B55: HELPER | C55: SALAUDDIN SHAH | H55: 0 | J55: 260 | K55: 80 | O55: =SUBTOTAL(9,Table4[[#This Row],[ESI BASIC]:[ESI FOOD]]) -> 0 | T55: =COUNTIF(X55:CG55,"P") -> 41 | V55: =T55+U55 -> 41 | W55: =SUM(CI55:DM55) -> 12 | X55: A | Y55: P | Z55: P | AA55: A | AB55: P | AC55: P | AD55: A | AE55: P | AF55: P | AG55: A | AH55: P | AI55: P | AJ55: A | AK55: P | AL55: P | AM55: A | AN55: P | AO55: P | AP55: A | AQ55: P | AR55: P | AS55: A | AT55: P | AU55: P | AV55: A | AW55: P | AX55: P | AY55: A | AZ55: P | BA55: P | BB55: A | BC55: P | BD55: P | BE55: A | BF55: P | BG55: P | BH55: A | BI55: P | BJ55: P | BK55: A | BL55: P | BM55: P | BN55: A | BO55: P | BP55: P | BQ55: A | BR55: P | BS55: P | BT55: A | BU55: P | BV55: P | BW55: A | BX55: P | BY55: P | BZ55: A | CA55: P | CB55: P | CC55: A | CD55: P | CE55: P | CF55: A | CG55: P | CI55: 0 | CJ55: 0 | CK55: 0 | CL55: 1 | CM55: 0 | CN55: 0 | CO55: 2 | CP55: 0 | CQ55: 1 | CR55: 0 | CS55: 0 | CT55: 0 | CU55: 0 | CV55: 1 | CW55: 1 | CX55: 0 | CY55: 0 | CZ55: 0 | DA55: 0 | DB55: 1 | DC55: 0 | DD55: 0 | DE55: 1 | DF55: 0 | DG55: 0 | DH55: 0 | DI55: 1 | DJ55: 1 | DK55: 1 | DL55: 1 | DM55: 0
A56: CONTRACT | B56: DRIVER | C56: MOFIJUL ALI | H56: 0 | J56: 633.33 | T56: =COUNTIF(X56:CG56,"P") -> 31 | V56: =T56+U56 -> 31 | W56: =SUM(CI56:DM56) -> 0 | X56: P | Y56: A | Z56: P | AA56: A | AB56: P | AC56: A | AD56: P | AE56: A | AF56: P | AG56: A | AH56: P | AI56: A | AJ56: P | AK56: A | AL56: P | AM56: A | AN56: P | AO56: A | AP56: P | AQ56: A | AR56: P | AS56: A | AT56: P | AU56: A | AV56: P | AW56: A | AX56: P | AY56: A | AZ56: P | BA56: A | BB56: P | BC56: A | BD56: P | BE56: A | BF56: P | BG56: A | BH56: P | BI56: A | BJ56: P | BK56: A | BL56: P | BM56: A | BN56: P | BO56: A | BP56: P | BQ56: A | BR56: P | BS56: A | BT56: P | BU56: A | BV56: P | BW56: A | BX56: P | BY56: A | BZ56: P | CA56: A | CB56: P | CC56: A | CD56: P | CE56: A | CF56: P | CG56: A
A57: CONTRACT | B57: LAB | C57: ASHIK AHMED | H57: =SUBTOTAL(9,Table4[[#This Row],[BASIC]:[FOOD]]) -> 0 | I57: 12000 | O57: =SUBTOTAL(9,Table4[[#This Row],[ESI BASIC]:[ESI FOOD]]) -> 0 | T57: =COUNTIF(X57:CG57,"P") -> 21 | U57: 3 | V57: =T57+U57 -> 24 | W57: =SUM(CI57:DM57) -> 0 | AJ57: P | AK57: A | AL57: P | AM57: A | AN57: A | AO57: A | AP57: A | AQ57: A | AR57: P | AS57: A | AT57: P | AU57: A | AV57: P | AW57: A | AX57: P | AY57: P | AZ57: A | BA57: A | BB57: P | BC57: A | BD57: A | BE57: A | BF57: A | BG57: A | BH57: P | BI57: A | BJ57: P | BK57: A | BL57: A | BM57: P | BN57: A | BO57: P | BP57: A | BQ57: P | BR57: A | BS57: P | BT57: A | BU57: P | BV57: A | BW57: P | BX57: A | BY57: P | BZ57: P | CA57: A | CB57: P | CC57: A | CD57: P | CE57: A | CF57: P | CG57: A
A58: CONTRACT | B58: LAB | C58: SAMIT MONDAL | H58: 0 | I58: 12000 | T58: =COUNTIF(X58:CG58,"P") -> 24 | U58: 4 | V58: =T58+U58 -> 28 | W58: =SUM(CI58:DM58) -> 0 | AJ58: P | AK58: A | AL58: P | AM58: A | AN58: P | AO58: A | AP58: P | AQ58: A | AR58: P | AS58: A | AT58: P | AU58: A | AV58: P | AW58: A | AX58: P | AY58: A | AZ58: P | BA58: A | BB58: P | BC58: A | BD58: P | BE58: A | BF58: P | BG58: A | BH58: P | BI58: A | BJ58: P | BK58: A | BL58: P | BM58: A | BN58: A | BO58: A | BP58: P | BQ58: A | BR58: P | BS58: P | BT58: A | BU58: A | BV58: P | BW58: A | BX58: P | BY58: A | BZ58: P | CA58: A | CB58: P | CC58: A | CD58: P | CE58: A | CF58: P | CG58: A
A59: CONTRACT | B59: LAB | C59: SIDHARTHA MONDAL | H59: 0 | I59: 12000 | T59: =COUNTIF(X59:CG59,"P") -> 22 | U59: 3 | V59: =T59+U59 -> 25 | W59: =SUM(CI59:DM59) -> 0 | Z59: P | AA59: A | AB59: A | AC59: A | AD59: A | AE59: A | AF59: A | AG59: A | AH59: A | AI59: A | AJ59: P | AK59: A | AL59: P | AM59: A | AN59: A | AO59: A | AP59: A | AQ59: A | AR59: P | AS59: A | AT59: P | AU59: A | AV59: P | AW59: A | AX59: P | AY59: A | AZ59: P | BA59: A | BB59: P | BC59: A | BD59: P | BE59: A | BF59: P | BG59: A | BH59: A | BI59: A | BJ59: P | BK59: A | BL59: P | BM59: A | BN59: P | BO59: A | BP59: P | BQ59: A | BR59: P | BS59: A | BT59: P | BU59: P | BV59: A | BW59: A | BX59: P | BY59: A | BZ59: P | CA59: P | CB59: A | CC59: A | CD59: A | CE59: A | CF59: P | CG59: A
A60: SALARY | B60: OFFICE | C60: PROBIR GHOSH | D60: TC0271 | E60: 10560 | F60: 3940 | G60: 2000 | H60: =SUBTOTAL(9,Table4[[#This Row],[BASIC]:[FOOD]]) -> 16500 | P60: INDIAN BANK | Q60: IDIB000H550 | R60: 59049049476 | T60: =COUNTIF(X60:CG60,"P") -> 27 | U60: 4 | V60: =T60+U60 -> 31 | W60: =SUM(CI60:DM60) -> 0 | X60: P | Y60: A | Z60: P | AA60: P | AB60: A | AC60: A | AD60: P | AE60: A | AF60: A | AG60: A | AH60: P | AI60: A | AJ60: P | AK60: A | AL60: P | AM60: A | AN60: P | AO60: A | AP60: P | AQ60: A | AR60: P | AS60: A | AT60: P | AU60: A | AV60: A | AW60: A | AX60: P | AY60: A | AZ60: P | BA60: A | BB60: P | BC60: A | BD60: P | BE60: A | BF60: P | BG60: A | BH60: P | BI60: A | BJ60: A | BK60: A | BL60: P | BM60: A | BN60: P | BO60: A | BP60: P | BQ60: A | BR60: P | BS60: A | BT60: P | BU60: A | BV60: P | BW60: A | BX60: A | BY60: A | BZ60: P | CA60: A | CB60: P | CC60: A | CD60: P | CE60: A | CF60: P | CG60: A
A61: WAGES | B61: LAB | C61: MOMINUL HAQUE | D61: TC 0421 | H61: 0 | I61: 14700 | L61: 10560 | M61: 3000 | N61: 1140 | O61: =SUBTOTAL(9,Table4[[#This Row],[ESI BASIC]:[ESI FOOD]]) -> 0 | P61: PUNJAB NATIONAL BANK | Q61: PUNB0071920 | R61: 0719010235143 | T61: =COUNTIF(X61:CG61,"P") -> 30 | U61: 4 | V61: =T61+U61 -> 34 | W61: =SUM(CI61:DM61) -> 0 | X61: A | Y61: A | Z61: P | AA61: A | AB61: P | AC61: A | AD61: P | AE61: A | AF61: P | AG61: A | AH61: P | AI61: A | AJ61: P | AK61: A | AL61: P | AM61: A | AN61: P | AO61: A | AP61: A | AQ61: A | AR61: P | AS61: A | AT61: P | AU61: A | AV61: A | AW61: P | AX61: A | AY61: P | AZ61: A | BA61: P | BB61: A | BC61: P | BD61: A | BE61: P | BF61: A | BG61: P | BH61: A | BI61: P | BJ61: P | BK61: A | BL61: P | BM61: A | BN61: P | BO61: A | BP61: P | BQ61: A | BR61: P | BS61: A | BT61: P | BU61: A | BV61: P | BW61: A | BX61: P | BY61: A | BZ61: P | CA61: A | CB61: P | CC61: A | CD61: P | CE61: A | CF61: P | CG61: P
A62: CONTRACT | B62: HOPPER | C62: SUBRATA MONDAL | H62: 0 | I62: 15000 | O62: =SUBTOTAL(9,Table4[[#This Row],[ESI BASIC]:[ESI FOOD]]) -> 0 | T62: =COUNTIF(X62:CG62,"P") -> 32 | U62: 4 | V62: =T62+U62 -> 36 | W62: =SUM(CI62:DM62) -> 0 | X62: P | Y62: A | Z62: P | AA62: A | AB62: P | AC62: A | AD62: P | AE62: A | AF62: P | AG62: A | AH62: P | AI62: A | AJ62: P | AK62: A | AL62: P | AM62: A | AN62: P | AO62: A | AP62: P | AQ62: A | AR62: P | AS62: A | AT62: P | AU62: A | AV62: P | AW62: A | AX62: P | AY62: A | AZ62: P | BA62: A | BB62: P | BC62: P | BD62: P | BE62: A | BF62: P | BG62: A | BH62: P | BI62: A | BJ62: P | BK62: A | BL62: P | BM62: A | BN62: P | BO62: A | BP62: P | BQ62: A | BR62: P | BS62: A | BT62: P | BU62: A | BV62: P | BW62: A | BX62: P | BY62: A | BZ62: P | CA62: A | CB62: P | CC62: A | CD62: P | CE62: A | CF62: P | CG62: A
A63: WAGES | B63: HELPER | C63: EKRAMUL ALI | D63: TC 0422 | H63: 0 | J63: 260 | K63: 80 | L63: 10560 | M63: 700 | N63: 540 | O63: =SUBTOTAL(9,Table4[[#This Row],[ESI BASIC]:[ESI FOOD]]) -> 0 | P63: CENTRAL BANK OF INDIA | Q63: CBIN0281927 | R63: 5327086346 | T63: =COUNTIF(X63:CG63,"P") -> 40 | V63: =T63+U63 -> 40 | W63: =SUM(CI63:DM63) -> 11 | X63: A | Y63: P | Z63: P | AA63: A | AB63: P | AC63: P | AD63: A | AE63: P | AF63: P | AG63: A | AH63: P | AI63: P | AJ63: A | AK63: P | AL63: P | AM63: A | AN63: P | AO63: P | AP63: A | AQ63: P | AR63: P | AS63: A | AT63: P | AU63: P | AV63: A | AW63: P | AX63: A | AY63: A | AZ63: P | BA63: P | BB63: A | BC63: P | BD63: P | BE63: A | BF63: P | BG63: P | BH63: A | BI63: P | BJ63: P | BK63: A | BL63: P | BM63: P | BN63: A | BO63: P | BP63: P | BQ63: A | BR63: P | BS63: P | BT63: A | BU63: P | BV63: P | BW63: A | BX63: P | BY63: P | BZ63: A | CA63: P | CB63: P | CC63: A | CD63: P | CE63: P | CF63: A | CG63: P | CI63: 0 | CJ63: 0 | CK63: 0 | CL63: 0 | CM63: 1 | CN63: 0 | CO63: 1 | CP63: 1 | CQ63: 0 | CR63: 0 | CS63: 1 | CT63: 0 | CU63: 0 | CV63: 0 | CW63: 0 | CX63: 0 | CY63: 0 | CZ63: 1 | DA63: 1 | DB63: 1 | DC63: 0 | DD63: 1 | DE63: 1 | DF63: 0 | DG63: 0 | DH63: 0 | DI63: 2 | DJ63: 0 | DK63: 0 | DL63: 0 | DM63: 0
A64: CONTRACT | B64: HELPER | C64: REJJAK MONDAL | H64: 0 | J64: 260 | K64: 80 | O64: =SUBTOTAL(9,Table4[[#This Row],[ESI BASIC]:[ESI FOOD]]) -> 0 | T64: =COUNTIF(X64:CG64,"P") -> 41 | V64: =T64+U64 -> 41 | W64: =SUM(CI64:DM64) -> 12 | X64: P | Y64: P | Z64: A | AA64: P | AB64: P | AC64: A | AD64: P | AE64: P | AF64: A | AG64: P | AH64: P | AI64: A | AJ64: P | AK64: P | AL64: A | AM64: P | AN64: P | AO64: A | AP64: P | AQ64: P | AR64: A | AS64: P | AT64: P | AU64: A | AV64: P | AW64: P | AX64: A | AY64: P | AZ64: P | BA64: A | BB64: P | BC64: P | BD64: A | BE64: P | BF64: P | BG64: A | BH64: P | BI64: P | BJ64: A | BK64: P | BL64: P | BM64: A | BN64: P | BO64: P | BP64: A | BQ64: P | BR64: P | BS64: A | BT64: P | BU64: P | BV64: A | BW64: P | BX64: P | BY64: A | BZ64: P | CA64: P | CB64: A | CC64: P | CD64: A | CE64: A | CF64: P | CG64: P | CI64: 0 | CJ64: 1 | CK64: 0 | CL64: 0 | CM64: 0 | CN64: 0 | CO64: 0 | CP64: 0 | CQ64: 1 | CR64: 0 | CS64: 0 | CT64: 1 | CU64: 0 | CV64: 2 | CW64: 1 | CX64: 1 | CY64: 1 | CZ64: 0 | DA64: 1 | DB64: 0 | DC64: 0 | DD64: 1 | DE64: 1 | DF64: 0 | DG64: 0 | DH64: 0 | DI64: 1 | DJ64: 0 | DK64: 0 | DL64: 0 | DM64: 0
A65: WAGES | B65: DRIVER | C65: JULFIKAR DHALI | H65: 0 | J65: 300 | K65: 185 | L65: 19000 | O65: =SUBTOTAL(9,Table4[[#This Row],[ESI BASIC]:[ESI FOOD]]) -> 0 | P65: BANK OF INDIA | Q65: BKID0004382 | R65: 438218210001792 | T65: =COUNTIF(X65:CG65,"P") -> 41 | V65: =T65+U65 -> 41 | W65: =SUM(CI65:DM65) -> 8 | X65: A | Y65: P | Z65: P | AA65: A | AB65: P | AC65: P | AD65: A | AE65: P | AF65: P | AG65: A | AH65: P | AI65: P | AJ65: A | AK65: P | AL65: P | AM65: A | AN65: P | AO65: P | AP65: A | AQ65: P | AR65: P | AS65: A | AT65: P | AU65: P | AV65: A | AW65: P | AX65: P | AY65: A | AZ65: P | BA65: P | BB65: A | BC65: P | BD65: P | BE65: A | BF65: P | BG65: P | BH65: A | BI65: P | BJ65: P | BK65: A | BL65: P | BM65: P | BN65: A | BO65: P | BP65: P | BQ65: A | BR65: P | BS65: P | BT65: A | BU65: P | BV65: P | BW65: A | BX65: P | BY65: P | BZ65: A | CA65: P | CB65: P | CC65: A | CD65: P | CE65: P | CF65: A | CG65: P | CI65: 0 | CJ65: 0 | CK65: 0 | CL65: 0 | CM65: 0 | CN65: 0 | CO65: 1 | CP65: 0 | CQ65: 0 | CR65: 0 | CS65: 0 | CT65: 0 | CU65: 0 | CV65: 1 | CW65: 0 | CX65: 0 | CY65: 0 | CZ65: 1 | DA65: 0 | DB65: 0 | DC65: 1 | DD65: 1 | DE65: 0 | DF65: 0 | DG65: 0 | DH65: 0 | DI65: 1 | DJ65: 1 | DK65: 0 | DL65: 1 | DM65: 0
A66: CONTRACT | B66: DRIVER | C66: BISWANTH MONDAL | H66: 0 | J66: 300 | K66: 185 | O66: =SUBTOTAL(9,Table4[[#This Row],[ESI BASIC]:[ESI FOOD]]) -> 0 | T66: =COUNTIF(X66:CG66,"P") -> 32 | V66: =T66+U66 -> 32 | W66: =SUM(CI66:DM66) -> 8 | X66: P | Y66: A | Z66: P | AA66: P | AB66: A | AC66: P | AD66: P | AE66: A | AF66: P | AG66: P | AH66: A | AI66: A | AJ66: A | AK66: A | AL66: A | AM66: A | AN66: A | AO66: P | AP66: P | AQ66: A | AR66: P | AS66: P | AT66: A | AU66: P | AV66: P | AW66: A | AX66: P | AY66: P | AZ66: A | BA66: A | BB66: A | BC66: A | BD66: A | BE66: A | BF66: A | BG66: P | BH66: P | BI66: A | BJ66: P | BK66: P | BL66: A | BM66: P | BN66: P | BO66: A | BP66: P | BQ66: P | BR66: A | BS66: A | BT66: P | BU66: A | BV66: P | BW66: P | BX66: A | BY66: P | BZ66: P | CA66: A | CB66: P | CC66: P | CD66: A | CE66: P | CF66: P | CG66: A | CI66: 0 | CJ66: 0 | CK66: 0 | CL66: 0 | CM66: 0 | CN66: 0 | CO66: 0 | CP66: 0 | CQ66: 0 | CR66: 0 | CS66: 1 | CT66: 0 | CU66: 0 | CV66: 3 | CW66: 1 | CX66: 0 | CY66: 0 | CZ66: 0 | DA66: 1 | DB66: 0 | DC66: 0 | DD66: 1 | DE66: 1 | DF66: 0 | DG66: 0 | DH66: 0 | DI66: 0 | DJ66: 0 | DK66: 0 | DL66: 0 | DM66: 0
A67: WAGES | B67: LAB | C67: SUPRAKASH SAMANTO | D67: TC 0413 | H67: 0 | I67: 13650 | L67: 10560 | M67: 2000 | N67: 1090 | O67: =SUBTOTAL(9,Table4[[#This Row],[ESI BASIC]:[ESI FOOD]]) -> 0 | P67: PUNJAB NATIONAL BANK | Q67: PUNB0104620 | R67: 1046010656917 | T67: =COUNTIF(X67:CG67,"P") -> 24 | U67: 4 | V67: =T67+U67 -> 28 | W67: =SUM(CI67:DM67) -> 0 | X67: P | Y67: A | Z67: P | AA67: A | AB67: P | AC67: A | AD67: P | AE67: A | AF67: P | AG67: A | AH67: P | AI67: A | AJ67: P | AK67: A | AL67: P | AM67: A | AN67: P | AO67: A | AP67: P | AQ67: A | AR67: P | AS67: A | AT67: P | AU67: A | AV67: P | AW67: A | AX67: P | AY67: A | AZ67: A | BA67: A | BB67: A | BC67: A | BD67: A | BE67: A | BF67: A | BG67: A | BH67: A | BI67: A | BJ67: A | BK67: A | BL67: A | BM67: A | BN67: P | BO67: A | BP67: P | BQ67: P | BR67: A | BS67: A | BT67: P | BU67: A | BV67: P | BW67: A | BX67: P | BY67: A | BZ67: P | CA67: P | CB67: A | CC67: A | CD67: P | CE67: A | CF67: P | CG67: A
A68: WAGES | B68: DRIVER | C68: TANMOY MONDAL | H68: 0 | J68: 300 | K68: 185 | L68: 19000 | O68: =SUBTOTAL(9,Table4[[#This Row],[ESI BASIC]:[ESI FOOD]]) -> 0 | P68: BANK OF INDIA | Q68: BKID0004382 | R68: 438210110012523 | T68: =COUNTIF(X68:CG68,"P") -> 39 | V68: =T68+U68 -> 39 | W68: =SUM(CI68:DM68) -> 10 | X68: P | Y68: P | Z68: A | AA68: P | AB68: P | AC68: A | AD68: P | AE68: P | AF68: A | AG68: P | AH68: P | AI68: A | AJ68: P | AK68: P | AL68: A | AM68: A | AN68: P | AO68: A | AP68: A | AQ68: A | AR68: P | AS68: A | AT68: P | AU68: A | AV68: P | AW68: P | AX68: A | AY68: P | AZ68: P | BA68: A | BB68: P | BC68: P | BD68: A | BE68: P | BF68: P | BG68: A | BH68: P | BI68: P | BJ68: A | BK68: P | BL68: P | BM68: A | BN68: P | BO68: P | BP68: A | BQ68: P | BR68: P | BS68: A | BT68: P | BU68: P | BV68: A | BW68: P | BX68: P | BY68: A | BZ68: P | CA68: P | CB68: A | CC68: P | CD68: P | CE68: A | CF68: P | CG68: P | CI68: 0 | CJ68: 0 | CK68: 0 | CL68: 0 | CM68: 0 | CN68: 0 | CO68: 0 | CP68: 0 | CQ68: 1 | CR68: 0 | CS68: 0 | CT68: 1 | CU68: 0 | CV68: 1 | CW68: 1 | CX68: 1 | CY68: 0 | CZ68: 0 | DA68: 0 | DB68: 0 | DC68: 0 | DD68: 2 | DE68: 0 | DF68: 0 | DG68: 0 | DH68: 0 | DI68: 2 | DJ68: 0 | DK68: 1 | DL68: 0 | DM68: 0
A69: CONTRACT | B69: HELPER | C69: TAPAS MONDAL | H69: 0 | J69: 260 | K69: 80 | O69: =SUBTOTAL(9,Table4[[#This Row],[ESI BASIC]:[ESI FOOD]]) -> 0 | T69: =COUNTIF(X69:CG69,"P") -> 36 | V69: =T69+U69 -> 36 | W69: =SUM(CI69:DM69) -> 7 | X69: A | Y69: P | Z69: P | AA69: A | AB69: P | AC69: P | AD69: A | AE69: P | AF69: P | AG69: A | AH69: A | AI69: A | AJ69: A | AK69: P | AL69: P | AM69: A | AN69: P | AO69: P | AP69: A | AQ69: A | AR69: A | AS69: A | AT69: P | AU69: P | AV69: A | AW69: P | AX69: P | AY69: A | AZ69: P | BA69: P | BB69: A | BC69: P | BD69: P | BE69: A | BF69: P | BG69: P | BH69: A | BI69: P | BJ69: P | BK69: A | BL69: P | BM69: P | BN69: A | BO69: P | BP69: P | BQ69: A | BR69: A | BS69: P | BT69: A | BU69: P | BV69: P | BW69: A | BX69: P | BY69: P | BZ69: A | CA69: P | CB69: P | CC69: A | CD69: P | CE69: P | CF69: A | CG69: P | CI69: 0 | CJ69: 0 | CK69: 0 | CL69: 0 | CM69: 0 | CN69: 0 | CO69: 0 | CP69: 0 | CQ69: 0 | CR69: 0 | CS69: 0 | CT69: 0 | CU69: 0 | CV69: 1 | CW69: 0 | CX69: 0 | CY69: 0 | CZ69: 1 | DA69: 0 | DB69: 0 | DC69: 1 | DD69: 1 | DE69: 0 | DF69: 0 | DG69: 0 | DH69: 0 | DI69: 1 | DJ69: 1 | DK69: 0 | DL69: 1 | DM69: 0
A70: SALARY | B70: OFFICE | C70: NABA KUMAR BISWAS | D70: TC0367 | E70: 25000 | F70: 0 | G70: 0 | H70: =SUBTOTAL(9,Table4[[#This Row],[BASIC]:[FOOD]]) -> 25000 | P70: UCO BANK | Q70: UCBA0001870 | R70: 18700110074961 | T70: =COUNTIF(X70:CG70,"P") -> 24 | U70: 4 | V70: =T70+U70 -> 28 | W70: =SUM(CI70:DM70) -> 0 | X70: P | Y70: A | Z70: P | AA70: A | AB70: P | AC70: A | AD70: P | AE70: A | AF70: A | AG70: A | AH70: P | AI70: A | AJ70: P | AK70: A | AL70: A | AM70: A | AN70: P | AO70: A | AP70: P | AQ70: A | AR70: P | AS70: A | AT70: A | AU70: A | AV70: P | AW70: A | AX70: P | AY70: A | AZ70: A | BA70: A | BB70: A | BC70: A | BD70: A | BE70: P | BF70: P | BG70: A | BH70: A | BI70: A | BJ70: P | BK70: A | BL70: P | BM70: A | BN70: P | BO70: A | BP70: P | BQ70: A | BR70: P | BS70: A | BT70: P | BU70: A | BV70: A | BW70: A | BX70: P | BY70: A | BZ70: P | CA70: A | CB70: P | CC70: A | CD70: P | CE70: A | CF70: P | CG70: A
A71: WAGES | B71: HELPER | C71: ALOK MONDAL | D71: TC 0414 | H71: =SUBTOTAL(9,Table4[[#This Row],[BASIC]:[FOOD]]) -> 0 | J71: 260 | K71: 80 | L71: 10560 | M71: 700 | N71: 540 | O71: =SUBTOTAL(9,Table4[[#This Row],[ESI BASIC]:[ESI FOOD]]) -> 0 | P71: BANK OF BARODA | Q71: BARB0DBRAJR | R71: 80858100003185 | T71: =COUNTIF(X71:CG71,"P") -> 37 | V71: =T71+U71 -> 37 | W71: =SUM(CI71:DM71) -> 9 | X71: P | Y71: P | Z71: A | AA71: P | AB71: P | AC71: A | AD71: P | AE71: P | AF71: A | AG71: P | AH71: P | AI71: A | AJ71: P | AK71: P | AL71: A | AM71: P | AN71: P | AO71: A | AP71: P | AQ71: P | AR71: A | AS71: P | AT71: P | AU71: A | AV71: P | AW71: A | AX71: A | AY71: P | AZ71: P | BA71: A | BB71: A | BC71: A | BD71: A | BE71: A | BF71: A | BG71: A | BH71: P | BI71: P | BJ71: A | BK71: P | BL71: P | BM71: A | BN71: P | BO71: P | BP71: A | BQ71: P | BR71: P | BS71: A | BT71: P | BU71: P | BV71: A | BW71: P | BX71: P | BY71: A | BZ71: P | CA71: P | CB71: A | CC71: P | CD71: P | CE71: A | CF71: P | CG71: P | CI71: 0 | CJ71: 0 | CK71: 0 | CL71: 0 | CM71: 1 | CN71: 0 | CO71: 0 | CP71: 0 | CQ71: 1 | CR71: 0 | CS71: 0 | CT71: 0 | CU71: 0 | CV71: 0 | CW71: 1 | CX71: 0 | CY71: 0 | CZ71: 0 | DA71: 0 | DB71: 0 | DC71: 0 | DD71: 1 | DE71: 1 | DF71: 0 | DG71: 1 | DH71: 0 | DI71: 2 | DJ71: 0 | DK71: 0 | DL71: 1 | DM71: 0
A72: CONTRACT | B72: HELPER | C72: RASHID MONDAL | H72: =SUBTOTAL(9,Table4[[#This Row],[BASIC]:[FOOD]]) -> 0 | J72: 250 | K72: 70 | O72: =SUBTOTAL(9,Table4[[#This Row],[ESI BASIC]:[ESI FOOD]]) -> 0 | T72: =COUNTIF(X72:CG72,"P") -> 42 | V72: =T72+U72 -> 42 | W72: =SUM(CI72:DM72) -> 10 | X72: P | Y72: P | Z72: A | AA72: P | AB72: P | AC72: A | AD72: P | AE72: P | AF72: A | AG72: P | AH72: P | AI72: A | AJ72: P | AK72: P | AL72: A | AM72: P | AN72: P | AO72: A | AP72: P | AQ72: P | AR72: A | AS72: P | AT72: P | AU72: A | AV72: P | AW72: P | AX72: A | AY72: P | AZ72: P | BA72: A | BB72: P | BC72: P | BD72: A | BE72: P | BF72: P | BG72: A | BH72: P | BI72: P | BJ72: A | BK72: P | BL72: P | BM72: A | BN72: P | BO72: P | BP72: A | BQ72: P | BR72: P | BS72: A | BT72: P | BU72: P | BV72: A | BW72: P | BX72: P | BY72: A | BZ72: P | CA72: P | CB72: A | CC72: P | CD72: P | CE72: A | CF72: P | CG72: P | CH72: P | CI72: 0 | CJ72: 0 | CK72: 0 | CL72: 0 | CM72: 0 | CN72: 0 | CO72: 1 | CP72: 0 | CQ72: 0 | CR72: 0 | CS72: 0 | CT72: 0 | CU72: 0 | CV72: 2 | CW72: 0 | CX72: 0 | CY72: 1 | CZ72: 1 | DA72: 0 | DB72: 0 | DC72: 0 | DD72: 1 | DE72: 0 | DF72: 0 | DG72: 1 | DH72: 0 | DI72: 1 | DJ72: 0 | DK72: 1 | DL72: 1 | DM72: 0
A73: CONTRACT | B73: HELPER | C73: RAJU MONDAL | H73: =SUBTOTAL(9,Table4[[#This Row],[BASIC]:[FOOD]]) -> 0 | J73: 260 | K73: 80 | O73: =SUBTOTAL(9,Table4[[#This Row],[ESI BASIC]:[ESI FOOD]]) -> 0 | T73: =COUNTIF(X73:CG73,"P") -> 41 | V73: =T73+U73 -> 41 | W73: =SUM(CI73:DM73) -> 7 | X73: P | Y73: A | Z73: P | AA73: P | AB73: A | AC73: P | AD73: P | AE73: A | AF73: P | AG73: P | AH73: A | AI73: P | AJ73: P | AK73: A | AL73: P | AM73: P | AN73: A | AO73: P | AP73: P | AQ73: A | AR73: P | AS73: P | AT73: A | AU73: P | AV73: P | AW73: A | AX73: P | AY73: P | AZ73: A | BA73: P | BB73: P | BC73: A | BD73: P | BE73: P | BF73: A | BG73: P | BH73: P | BI73: A | BJ73: P | BK73: P | BL73: A | BM73: P | BN73: P | BO73: A | BP73: P | BQ73: P | BR73: A | BS73: P | BT73: P | BU73: A | BV73: P | BW73: P | BX73: A | BY73: P | BZ73: P | CA73: A | CB73: P | CC73: P | CD73: A | CE73: P | CF73: P | CG73: A | CI73: 0 | CJ73: 0 | CK73: 0 | CL73: 0 | CM73: 0 | CN73: 0 | CO73: 0 | CP73: 0 | CQ73: 0 | CR73: 0 | CS73: 1 | CT73: 0 | CU73: 0 | CV73: 4 | CW73: 0 | CX73: 0 | CY73: 0 | CZ73: 0 | DA73: 0 | DB73: 0 | DC73: 0 | DD73: 1 | DE73: 1 | DF73: 0 | DG73: 0 | DH73: 0 | DI73: 0 | DJ73: 0 | DK73: 0 | DL73: 0 | DM73: 0
A74: WAGES | B74: LAB | C74: RAJESH BAR | D74: TC 0415 | H74: =SUBTOTAL(9,Table4[[#This Row],[BASIC]:[FOOD]]) -> 0 | I74: 15750 | L74: 11620 | M74: 2130 | N74: 2000 | O74: =SUBTOTAL(9,Table4[[#This Row],[ESI BASIC]:[ESI FOOD]]) -> 0 | P74: PUNJAB NATIONAL BANK | Q74: PUNB0182310 | R74: 18232282000362 | T74: =COUNTIF(X74:CG74,"P") -> 24 | U74: 4 | V74: =T74+U74 -> 28 | W74: =SUM(CI74:DM74) -> 0 | X74: P | Y74: A | Z74: P | AA74: A | AB74: P | AC74: A | AD74: P | AE74: A | AF74: P | AG74: A | AH74: P | AI74: A | AJ74: P | AK74: A | AL74: P | AM74: A | AN74: P | AO74: A | AP74: P | AQ74: A | AR74: P | AS74: A | AT74: P | AU74: A | AV74: P | AW74: A | AX74: P | AY74: A | AZ74: A | BA74: A | BB74: P | BC74: A | BD74: P | BE74: A | BF74: P | BG74: A | BH74: P | BI74: A | BJ74: P | BK74: A | BL74: P | BM74: A | BN74: P | BO74: A | BP74: P | BQ74: A | BR74: A | BS74: A | BT74: A | BU74: A | BV74: A | BW74: A | BX74: A | BY74: A | BZ74: A | CA74: A | CB74: A | CC74: A | CD74: P | CE74: A | CF74: P | CG74: A
A75: CONTRACT | B75: HELPER | C75: SUDIP MONDAL | H75: =SUBTOTAL(9,Table4[[#This Row],[BASIC]:[FOOD]]) -> 0 | J75: 260 | K75: 80 | O75: =SUBTOTAL(9,Table4[[#This Row],[ESI BASIC]:[ESI FOOD]]) -> 0 | T75: =COUNTIF(X75:CG75,"P") -> 41 | V75: =T75+U75 -> 41 | W75: =SUM(CI75:DM75) -> 14 | X75: P | Y75: A | Z75: P | AA75: P | AB75: A | AC75: P | AD75: P | AE75: A | AF75: P | AG75: P | AH75: A | AI75: P | AJ75: P | AK75: A | AL75: P | AM75: P | AN75: A | AO75: P | AP75: P | AQ75: A | AR75: P | AS75: P | AT75: A | AU75: P | AV75: P | AW75: A | AX75: P | AY75: P | AZ75: A | BA75: P | BB75: P | BC75: A | BD75: P | BE75: P | BF75: A | BG75: P | BH75: P | BI75: A | BJ75: P | BK75: P | BL75: A | BM75: P | BN75: P | BO75: A | BP75: P | BQ75: P | BR75: A | BS75: P | BT75: P | BU75: A | BV75: P | BW75: P | BX75: A | BY75: P | BZ75: P | CA75: A | CB75: P | CC75: P | CD75: A | CE75: P | CF75: P | CG75: A | CI75: 0 | CJ75: 0 | CK75: 0 | CL75: 0 | CM75: 0 | CN75: 0 | CO75: 0 | CP75: 0 | CQ75: 3 | CR75: 0 | CS75: 0 | CT75: 1 | CU75: 0 | CV75: 3 | CW75: 0 | CX75: 1 | CY75: 0 | CZ75: 1 | DA75: 0 | DB75: 1 | DC75: 0 | DD75: 1 | DE75: 1 | DF75: 0 | DG75: 1 | DH75: 0 | DI75: 0 | DJ75: 1 | DK75: 0 | DL75: 0 | DM75: 0
A76: WAGES | B76: LAB | C76: BIKRAM ROY | H76: =SUBTOTAL(9,Table4[[#This Row],[BASIC]:[FOOD]]) -> 0 | I76: 13650 | L76: 10560 | M76: 2000 | N76: 1090 | O76: =SUBTOTAL(9,Table4[[#This Row],[ESI BASIC]:[ESI FOOD]]) -> 0 | P76: STATE BANK OF INDIA | Q76: SBIN0006853 | R76: 40569447216 | T76: =COUNTIF(X76:CG76,"P") -> 31 | U76: 4 | V76: =T76+U76 -> 35 | W76: =SUM(CI76:DM76) -> 0 | X76: P | Y76: A | Z76: P | AA76: A | AB76: A | AC76: A | AD76: P | AE76: P | AF76: P | AG76: A | AH76: P | AI76: A | AJ76: P | AK76: A | AL76: P | AM76: A | AN76: P | AO76: A | AP76: P | AQ76: A | AR76: P | AS76: A | AT76: P | AU76: A | AV76: P | AW76: A | AX76: P | AY76: A | AZ76: P | BA76: A | BB76: P | BC76: A | BD76: P | BE76: A | BF76: P | BG76: A | BH76: P | BI76: A | BJ76: P | BK76: A | BL76: P | BM76: A | BN76: P | BO76: A | BP76: P | BQ76: A | BR76: P | BS76: A | BT76: P | BU76: A | BV76: P | BW76: A | BX76: P | BY76: A | BZ76: P | CA76: A | CB76: P | CC76: A | CD76: P | CE76: P | CF76: A | CG76: A
A77: CONTRACT | B77: OTHERS | C77: ALMIRAJ JHAN | H77: =SUBTOTAL(9,Table4[[#This Row],[BASIC]:[FOOD]]) -> 0 | I77: 17900 | T77: =COUNTIF(X77:CG77,"P") -> 2 | V77: =T77+U77 -> 2 | W77: =SUM(CI77:DM77) -> 0 | CD77: P | CE77: A | CF77: P | CG77: A
A78: WAGES | B78: DRIVER | C78: JITU MAHALI | H78: =SUBTOTAL(9,Table4[[#This Row],[BASIC]:[FOOD]]) -> 0 | J78: 300 | K78: 185 | L78: 19000 | O78: =SUBTOTAL(9,Table4[[#This Row],[ESI BASIC]:[ESI FOOD]]) -> 0 | P78: BANK OF INDIA | Q78: BKID0004382 | R78: 438210110001543 | T78: =COUNTIF(X78:CG78,"P") -> 40 | V78: =T78+U78 -> 40 | W78: =SUM(CI78:DM78) -> 8 | X78: P | Y78: P | Z78: A | AA78: P | AB78: P | AC78: A | AD78: P | AE78: P | AF78: A | AG78: P | AH78: P | AI78: A | AJ78: P | AK78: P | AL78: A | AM78: P | AN78: A | AO78: A | AP78: P | AQ78: P | AR78: A | AS78: A | AT78: P | AU78: A | AV78: P | AW78: P | AX78: A | AY78: P | AZ78: P | BA78: A | BB78: P | BC78: P | BD78: A | BE78: P | BF78: P | BG78: A | BH78: P | BI78: P | BJ78: A | BK78: P | BL78: P | BM78: A | BN78: P | BO78: P | BP78: A | BQ78: P | BR78: P | BS78: A | BT78: P | BU78: P | BV78: A | BW78: P | BX78: P | BY78: A | BZ78: P | CA78: P | CB78: A | CC78: P | CD78: P | CE78: A | CF78: P | CG78: P | CI78: 0 | CJ78: 1 | CK78: 0 | CL78: 0 | CM78: 0 | CN78: 0 | CO78: 0 | CP78: 0 | CQ78: 0 | CR78: 0 | CS78: 0 | CT78: 0 | CU78: 0 | CV78: 0 | CW78: 0 | CX78: 1 | CY78: 0 | CZ78: 1 | DA78: 0 | DB78: 0 | DC78: 0 | DD78: 1 | DE78: 0 | DF78: 0 | DG78: 1 | DH78: 0 | DI78: 2 | DJ78: 1 | DK78: 0 | DL78: 0 | DM78: 0
H79: =SUBTOTAL(9,Table4[[#This Row],[BASIC]:[FOOD]]) -> 0 | T79: =COUNTIF(X79:CG79,"P") -> 0 | V79: =T79+U79 -> 0 | W79: =SUM(CI79:DM79) -> 0
A80: SALARY | B80: OFFICE | C80: ASIM KHUNTIA | D80: TC 0213 | E80: 33000 | F80: 7000 | H80: =SUBTOTAL(9,Table4[[#This Row],[BASIC]:[FOOD]]) -> 40000 | P80: PNB | Q80: PUNB0213000 | R80: 2.1300001e+15 | T80: =COUNTIF(X80:CG80,"P") -> 28 | U80: 3 | V80: =T80+U80 -> 31 | W80: =SUM(CI80:DM80) -> 0 | X80: P | Y80: A | Z80: P | AA80: A | AB80: P | AC80: A | AD80: P | AE80: A | AF80: P | AG80: A | AH80: P | AI80: A | AJ80: P | AK80: A | AL80: P | AM80: A | AN80: P | AO80: A | AP80: P | AQ80: A | AR80: P | AS80: A | AT80: A | AU80: A | AV80: P | AW80: A | AX80: P | AY80: P | AZ80: A | BA80: A | BB80: P | BC80: A | BD80: P | BE80: A | BF80: P | BG80: A | BH80: A | BI80: A | BJ80: P | BK80: A | BL80: P | BM80: A | BN80: P | BO80: A | BP80: P | BQ80: A | BR80: P | BS80: A | BT80: P | BU80: A | BV80: A | BW80: A | BX80: P | BY80: A | BZ80: P | CA80: A | CB80: P | CC80: A | CD80: P | CE80: A | CF80: P | CG80: A
A81: CONTRACT | B81: HELPER | C81: SAMSUR | H81: =SUBTOTAL(9,Table4[[#This Row],[BASIC]:[FOOD]]) -> 0 | J81: 260 | K81: 80 | O81: =SUBTOTAL(9,Table4[[#This Row],[ESI BASIC]:[ESI FOOD]]) -> 0 | T81: =COUNTIF(X81:CG81,"P") -> 41 | V81: =T81+U81 -> 41 | W81: =SUM(CI81:DM81) -> 10 | X81: A | Y81: P | Z81: P | AA81: A | AB81: P | AC81: P | AD81: A | AE81: P | AF81: P | AG81: A | AH81: P | AI81: P | AJ81: A | AK81: P | AL81: P | AM81: A | AN81: P | AO81: P | AP81: A | AQ81: P | AR81: P | AS81: A | AT81: P | AU81: P | AV81: A | AW81: P | AX81: P | AY81: A | AZ81: P | BA81: P | BB81: A | BC81: P | BD81: P | BE81: A | BF81: P | BG81: P | BH81: A | BI81: P | BJ81: P | BK81: A | BL81: P | BM81: P | BN81: A | BO81: P | BP81: P | BQ81: A | BR81: P | BS81: P | BT81: A | BU81: P | BV81: P | BW81: A | BX81: P | BY81: P | BZ81: A | CA81: P | CB81: P | CC81: A | CD81: P | CE81: P | CF81: A | CG81: P | CI81: 0 | CJ81: 0 | CK81: 0 | CL81: 0 | CM81: 0 | CN81: 0 | CO81: 1 | CP81: 0 | CQ81: 0 | CR81: 0 | CS81: 0 | CT81: 0 | CU81: 0 | CV81: 2 | CW81: 1 | CX81: 0 | CY81: 1 | CZ81: 0 | DA81: 1 | DB81: 0 | DC81: 0 | DD81: 1 | DE81: 1 | DF81: 0 | DG81: 0 | DH81: 0 | DI81: 1 | DJ81: 0 | DK81: 1 | DL81: 0 | DM81: 0
A82: CONTRACT | B82: LAB | C82: BALAI CHAND ROY | H82: =SUBTOTAL(9,Table4[[#This Row],[BASIC]:[FOOD]]) -> 0 | I82: 14700 | O82: =SUBTOTAL(9,Table4[[#This Row],[ESI BASIC]:[ESI FOOD]]) -> 0 | T82: =COUNTIF(X82:CG82,"P") -> 26 | U82: 4 | V82: =T82+U82 -> 30 | W82: =SUM(CI82:DM82) -> 0 | X82: P | Y82: A | Z82: P | AA82: A | AB82: P | AC82: A | AD82: P | AE82: A | AF82: A | AG82: A | AH82: P | AI82: A | AJ82: P | AK82: P | AL82: A | AM82: A | AN82: P | AO82: A | AP82: P | AQ82: A | AR82: P | AS82: P | AT82: A | AU82: A | AV82: P | AW82: A | AX82: P | AY82: A | AZ82: P | BA82: A | BB82: A | BC82: A | BD82: A | BE82: A | BF82: A | BG82: A | BH82: A | BI82: A | BJ82: A | BK82: P | BL82: P | BM82: A | BN82: P | BO82: A | BP82: P | BQ82: A | BR82: P | BS82: P | BT82: A | BU82: A | BV82: P | BW82: A | BX82: P | BY82: P | BZ82: A | CA82: A | CB82: A | CC82: P | CD82: A | CE82: P | CF82: A | CG82: P
H83: =SUBTOTAL(9,Table4[[#This Row],[BASIC]:[FOOD]]) -> 0 | T83: =COUNTIF(X83:CG83,"P") -> 0 | V83: =T83+U83 -> 0 | W83: =SUM(CI83:DM83) -> 0
H84: =SUBTOTAL(9,Table4[[#This Row],[BASIC]:[FOOD]]) -> 0 | O84: =SUBTOTAL(9,Table4[[#This Row],[ESI BASIC]:[ESI FOOD]]) -> 0 | T84: =COUNTIF(X84:CG84,"P") -> 0 | V84: =T84+U84 -> 0 | W84: =SUM(CI84:DM84) -> 0
H85: =SUBTOTAL(9,Table4[[#This Row],[BASIC]:[FOOD]]) -> 0 | T85: =COUNTIF(X85:CG85,"P") -> 0 | V85: =T85+U85 -> 0 | W85: =SUM(CI85:DM85) -> 0
A86: SALARY | B86: OFFICE | C86: MANABINDU BISWAS | D86: TC 0398 | E86: 10560 | F86: 3940 | G86: 2000 | H86: =SUBTOTAL(9,Table4[[#This Row],[BASIC]:[FOOD]]) -> 16500 | P86: KOTAK MAHINDRA | Q86: KKBK0006575 | R86: 4449590771 | T86: =COUNTIF(X86:CG86,"P") -> 26 | U86: 4 | V86: =T86+U86 -> 30 | W86: =SUM(CI86:DM86) -> 0 | X86: P | Y86: A | Z86: P | AA86: A | AB86: A | AC86: A | AD86: P | AE86: A | AF86: P | AG86: A | AH86: P | AI86: A | AJ86: P | AK86: A | AL86: P | AM86: A | AN86: A | AO86: A | AP86: P | AQ86: A | AR86: P | AS86: A | AT86: P | AU86: A | AV86: P | AW86: A | AX86: P | AY86: A | AZ86: P | BA86: A | BB86: P | BC86: A | BD86: A | BE86: A | BF86: A | BG86: A | BH86: P | BI86: A | BJ86: P | BK86: A | BL86: P | BM86: A | BN86: P | BO86: A | BP86: A | BQ86: A | BR86: P | BS86: A | BT86: P | BU86: A | BV86: P | BW86: A | BX86: P | BY86: A | BZ86: P | CA86: A | CB86: P | CC86: A | CD86: P | CE86: A | CF86: P | CG86: A
H87: =SUBTOTAL(9,Table4[[#This Row],[BASIC]:[FOOD]]) -> 0 | O87: =SUBTOTAL(9,Table4[[#This Row],[ESI BASIC]:[ESI FOOD]]) -> 0 | T87: =COUNTIF(X87:CG87,"P") -> 0 | U87: 3 | V87: =T87+U87 -> 3 | W87: =SUM(CI87:DM87) -> 0
A88: WAGES | B88: LAB | C88: MILAN RUIDAS | H88: =SUBTOTAL(9,Table4[[#This Row],[BASIC]:[FOOD]]) -> 0 | I88: 12600 | L88: 10560 | M88: 1040 | N88: 1000 | O88: =SUBTOTAL(9,Table4[[#This Row],[ESI BASIC]:[ESI FOOD]]) -> 0 | P88: BANK OF BARODA | Q88: BARB0GHATAL | R88: 59290100005279 | T88: =COUNTIF(X88:CG88,"P") -> 26 | U88: 4 | V88: =T88+U88 -> 30 | W88: =SUM(CI88:DM88) -> 0 | X88: P | Y88: A | Z88: P | AA88: A | AB88: P | AC88: A | AD88: P | AE88: A | AF88: P | AG88: A | AH88: P | AI88: A | AJ88: P | AK88: A | AL88: P | AM88: A | AN88: P | AO88: A | AP88: P | AQ88: A | AR88: P | AS88: A | AT88: P | AU88: A | AV88: A | AW88: P | AX88: A | AY88: P | AZ88: A | BA88: P | BB88: A | BC88: P | BD88: A | BE88: P | BF88: A | BG88: P | BH88: P | BI88: A | BJ88: A | BK88: A | BL88: A | BM88: A | BN88: A | BO88: A | BP88: A | BQ88: A | BR88: A | BS88: A | BT88: A | BU88: A | BV88: P | BW88: A | BX88: P | BY88: A | BZ88: P | CA88: A | CB88: P | CC88: P | CD88: A | CE88: P | CF88: P | CG88: A
A89: WAGES | B89: LAB | C89: BABLU MONDAL | D89: TC0227 | H89: =SUBTOTAL(9,Table4[[#This Row],[BASIC]:[FOOD]]) -> 0 | I89: 18500 | L89: 11620 | M89: 4000 | N89: 2880 | O89: =SUBTOTAL(9,Table4[[#This Row],[ESI BASIC]:[ESI FOOD]]) -> 0 | P89: BANK OF INDIA | Q89: BKID0004382 | R89: 438210110009816 | T89: =COUNTIF(X89:CG89,"P") -> 22 | U89: 3 | V89: =T89+U89 -> 25 | W89: =SUM(CI89:DM89) -> 0 | X89: P | Y89: A | Z89: P | AA89: A | AB89: P | AC89: A | AD89: A | AE89: A | AF89: P | AG89: A | AH89: P | AI89: A | AJ89: P | AK89: A | AL89: P | AM89: A | AN89: P | AO89: A | AP89: A | AQ89: A | AR89: P | AS89: A | AT89: P | AU89: A | AV89: A | AW89: P | AX89: A | AY89: P | AZ89: A | BA89: P | BB89: A | BC89: P | BD89: A | BE89: P | BF89: A | BG89: P | BH89: A | BI89: P | BJ89: A | BK89: P | BL89: A | BM89: A | BN89: A | BO89: A | BP89: A | BQ89: A | BR89: A | BS89: A | BT89: A | BU89: A | BV89: A | BW89: A | BX89: A | BY89: A | BZ89: P | CA89: A | CB89: P | CC89: A | CD89: P | CE89: A | CF89: P | CG89: A
H90: =SUBTOTAL(9,Table4[[#This Row],[BASIC]:[FOOD]]) -> 0 | T90: =COUNTIF(X90:CG90,"P") -> 0 | V90: =T90+U90 -> 0 | W90: =SUM(CI90:DM90) -> 0
H91: =SUBTOTAL(9,Table4[[#This Row],[BASIC]:[FOOD]]) -> 0 | O91: =SUBTOTAL(9,Table4[[#This Row],[ESI BASIC]:[ESI FOOD]]) -> 0 | T91: =COUNTIF(X91:CG91,"P") -> 0 | V91: =T91+U91 -> 0 | W91: =SUM(CI91:DM91) -> 0
H92: 0 | J92: 250 | K92: 70 | O92: =SUBTOTAL(9,Table4[[#This Row],[ESI BASIC]:[ESI FOOD]]) -> 0 | T92: =COUNTIF(X92:CG92,"P") -> 0 | V92: =T92+U92 -> 0 | W92: =SUM(CI92:DM92) -> 0
A93: SALARY | B93: OFFICE | C93: SUVANKAR SAMADDAR | D93: TC 0411 | E93: 23000 | H93: =SUBTOTAL(9,Table4[[#This Row],[BASIC]:[FOOD]]) -> 23000 | P93: BANK OF INDIA | Q93: BKID0004190 | R93: 419010110010170 | T93: =COUNTIF(X93:CG93,"P") -> 26 | U93: 4 | V93: =T93+U93 -> 30 | W93: =SUM(CI93:DM93) -> 0 | X93: A | Y93: A | Z93: P | AA93: A | AB93: P | AC93: A | AD93: P | AE93: A | AF93: P | AG93: A | AH93: A | AI93: A | AJ93: A | AK93: A | AL93: P | AM93: A | AN93: P | AO93: A | AP93: P | AQ93: A | AR93: P | AS93: A | AT93: A | AU93: A | AV93: P | AW93: A | AX93: P | AY93: A | AZ93: P | BA93: A | BB93: P | BC93: A | BD93: A | BE93: A | BF93: P | BG93: A | BH93: P | BI93: A | BJ93: P | BK93: A | BL93: P | BM93: A | BN93: P | BO93: A | BP93: P | BQ93: A | BR93: P | BS93: A | BT93: P | BU93: A | BV93: P | BW93: A | BX93: P | BY93: A | BZ93: P | CA93: A | CB93: P | CC93: A | CD93: P | CE93: A | CF93: P | CG93: A
H94: =SUBTOTAL(9,Table4[[#This Row],[BASIC]:[FOOD]]) -> 0 | O94: =Table4[[#This Row],[ESI FOOD]]+Table4[[#This Row],[ESI HRA]]+Table4[[#This Row],[ESI BASIC]] -> 0 | T94: =COUNTIF(X94:CG94,"P") -> 0 | V94: =T94+U94 -> 0 | W94: =SUM(CI94:DM94) -> 0
H95: =SUBTOTAL(9,Table4[[#This Row],[BASIC]:[FOOD]]) -> 0 | T95: =COUNTIF(X95:CG95,"P") -> 0 | V95: =T95+U95 -> 0 | W95: =SUM(CI95:DM95) -> 0
H96: =SUBTOTAL(9,Table4[[#This Row],[BASIC]:[FOOD]]) -> 0 | T96: =COUNTIF(X96:CG96,"P") -> 0 | V96: =T96+U96 -> 0 | W96: =SUM(CI96:DM96) -> 0
H97: =SUBTOTAL(9,Table4[[#This Row],[BASIC]:[FOOD]]) -> 0 | T97: =COUNTIF(X97:CG97,"P") -> 0 | V97: =T97+U97 -> 0 | W97: =SUM(CI97:DM97) -> 0
H98: =SUBTOTAL(9,Table4[[#This Row],[BASIC]:[FOOD]]) -> 0 | T98: =COUNTIF(X98:CG98,"P") -> 0 | V98: =T98+U98 -> 0 | W98: =SUM(CI98:DM98) -> 0
H99: =SUBTOTAL(9,Table4[[#This Row],[BASIC]:[FOOD]]) -> 0 | T99: =COUNTIF(X99:CG99,"P") -> 0 | V99: =T99+U99 -> 0 | W99: =SUM(CI99:DM99) -> 0
H100: =SUBTOTAL(9,Table4[[#This Row],[BASIC]:[FOOD]]) -> 0 | T100: =COUNTIF(X100:CG100,"P") -> 0 | V100: =T100+U100 -> 0 | W100: =SUM(CI100:DM100) -> 0
...

Sheet SALARY
A1: STAFF RJ SALARY REGISTER FOR THE MONTH OF | N1: =TEXT('RJ ATTENDENCE SHEET'!$A$1,"MMMM") -> July | P1: =YEAR('RJ ATTENDENCE SHEET'!$A$1) -> 2026
A2: SL. NO. | B2: EMP. CODE | C2: NAME | D2: BASIC | E2: HRA | F2: FOOD | G2: TOTAL PAYMENTS | H2: DAYS WORK | J2: GROSS AMT. | K2: DEDUCTIONS | O2: TOTAL DED. | P2: NET AMT.
H3: TOTAL DAYS | I3: WORK | K3: P.F | L3: ESIC | M3: P.TAX | N3: ADV.
A4: 1 | B4: =IFERROR(VLOOKUP(C4,'RJ ATTENDENCE SHEET'!$C:$D,2,0),"") -> TC 0005 | C4: ='DATA '!H3 -> ABED ALI | D4: =IFERROR(VLOOKUP(C4,'RJ ATTENDENCE SHEET'!$C:$L,3,0),"") -> 10560 | E4: =IFERROR(VLOOKUP(C4,'RJ ATTENDENCE SHEET'!$C:$L,4,0),"") -> 5000 | F4: =IFERROR(VLOOKUP(C4,'RJ ATTENDENCE SHEET'!$C:$L,5,0),"") -> 4440 | G4: =SUM(D4:F4) -> 20000 | H4: =DAY(EOMONTH('RJ ATTENDENCE SHEET'!$A$1,0)) -> 31 | I4: =IFERROR(VLOOKUP(C4,'RJ ATTENDENCE SHEET'!$C:$W,20,0),"") -> 31 | J4: =IFERROR(G4/H4*I4,"") -> 20000 | K4: =IFERROR(VLOOKUP(C4,'SALARY ESI (P)'!$C:$T,13,0),"") -> 1267 | L4: =IFERROR(VLOOKUP(C4,'SALARY ESI (P)'!$C:$T,14,0),"") -> 150 | M4: =IFERROR(VLOOKUP(C4,'SALARY ESI (P)'!$C:$T,15,0),"") -> 130 | N4: =IFERROR(VLOOKUP(C4,'RJ ATTENDENCE SHEET'!$C:$S,17,0),"") -> 0 | O4: =SUM(K4:N4) -> 1547 | P4: =IFERROR(J4-O4,"") -> 18453
A5: 2 | B5: =IFERROR(VLOOKUP(C5,'RJ ATTENDENCE SHEET'!$C:$D,2,0),"") -> TC 0003 | C5: ='DATA '!H4 -> ABHI MUKHERJEE | D5: =IFERROR(VLOOKUP(C5,'RJ ATTENDENCE SHEET'!$C:$L,3,0),"") -> 14300 | E5: =IFERROR(VLOOKUP(C5,'RJ ATTENDENCE SHEET'!$C:$L,4,0),"") -> 7000 | F5: =IFERROR(VLOOKUP(C5,'RJ ATTENDENCE SHEET'!$C:$L,5,0),"") -> 7200 | G5: =SUM(D5:F5) -> 28500 | H5: =DAY(EOMONTH('RJ ATTENDENCE SHEET'!$A$1,0)) -> 31 | I5: =IFERROR(VLOOKUP(C5,'RJ ATTENDENCE SHEET'!$C:$W,20,0),"") -> 31 | J5: =IFERROR(G5/H5*I5,"") -> 28500 | K5: =IFERROR(VLOOKUP(C5,'SALARY ESI (P)'!$C:$T,13,0),"") -> 1716 | L5: =IFERROR(VLOOKUP(C5,'SALARY ESI (P)'!$C:$T,14,0),"") -> 0 | M5: =IFERROR(VLOOKUP(C5,'SALARY ESI (P)'!$C:$T,15,0),"") -> 150 | N5: =IFERROR(VLOOKUP(C5,'RJ ATTENDENCE SHEET'!$C:$S,17,0),"") -> 0 | O5: =SUM(K5:N5) -> 1866 | P5: =IFERROR(J5-O5,"") -> 26634
A6: 3 | B6: =IFERROR(VLOOKUP(C6,'RJ ATTENDENCE SHEET'!$C:$D,2,0),"") -> TC 0001 | C6: ='DATA '!H5 -> ACHIN GUPTA | D6: =IFERROR(VLOOKUP(C6,'RJ ATTENDENCE SHEET'!$C:$L,3,0),"") -> 12000 | E6: =IFERROR(VLOOKUP(C6,'RJ ATTENDENCE SHEET'!$C:$L,4,0),"") -> 6000 | F6: =IFERROR(VLOOKUP(C6,'RJ ATTENDENCE SHEET'!$C:$L,5,0),"") -> 4500 | G6: =SUM(D6:F6) -> 22500 | H6: =DAY(EOMONTH('RJ ATTENDENCE SHEET'!$A$1,0)) -> 31 | I6: =IFERROR(VLOOKUP(C6,'RJ ATTENDENCE SHEET'!$C:$W,20,0),"") -> 31 | J6: =IFERROR(G6/H6*I6,"") -> 22500 | K6: =IFERROR(VLOOKUP(C6,'SALARY ESI (P)'!$C:$T,13,0),"") -> 1440 | L6: =IFERROR(VLOOKUP(C6,'SALARY ESI (P)'!$C:$T,14,0),"") -> 0 | M6: =IFERROR(VLOOKUP(C6,'SALARY ESI (P)'!$C:$T,15,0),"") -> 130 | N6: =IFERROR(VLOOKUP(C6,'RJ ATTENDENCE SHEET'!$C:$S,17,0),"") -> 0 | O6: =SUM(K6:N6) -> 1570 | P6: =IFERROR(J6-O6,"") -> 20930
A7: 4 | B7: =IFERROR(VLOOKUP(C7,'RJ ATTENDENCE SHEET'!$C:$D,2,0),"") -> TC 0006 | C7: ='DATA '!H6 -> AMIN YADAV | D7: =IFERROR(VLOOKUP(C7,'RJ ATTENDENCE SHEET'!$C:$L,3,0),"") -> 12780 | E7: =IFERROR(VLOOKUP(C7,'RJ ATTENDENCE SHEET'!$C:$L,4,0),"") -> 6000 | F7: =IFERROR(VLOOKUP(C7,'RJ ATTENDENCE SHEET'!$C:$L,5,0),"") -> 5720 | G7: =SUM(D7:F7) -> 24500 | H7: =DAY(EOMONTH('RJ ATTENDENCE SHEET'!$A$1,0)) -> 31 | I7: =IFERROR(VLOOKUP(C7,'RJ ATTENDENCE SHEET'!$C:$W,20,0),"") -> 31 | J7: =IFERROR(G7/H7*I7,"") -> 24500 | K7: =IFERROR(VLOOKUP(C7,'SALARY ESI (P)'!$C:$T,13,0),"") -> 1534 | L7: =IFERROR(VLOOKUP(C7,'SALARY ESI (P)'!$C:$T,14,0),"") -> 0 | M7: =IFERROR(VLOOKUP(C7,'SALARY ESI (P)'!$C:$T,15,0),"") -> 130 | N7: =IFERROR(VLOOKUP(C7,'RJ ATTENDENCE SHEET'!$C:$S,17,0),"") -> 0 | O7: =SUM(K7:N7) -> 1664 | P7: =IFERROR(J7-O7,"") -> 22836
A8: 5 | B8: =IFERROR(VLOOKUP(C8,'RJ ATTENDENCE SHEET'!$C:$D,2,0),"") -> TC 0185 | C8: ='DATA '!H7 -> ANOWAR MOLLA | D8: =IFERROR(VLOOKUP(C8,'RJ ATTENDENCE SHEET'!$C:$L,3,0),"") -> 10560 | E8: =IFERROR(VLOOKUP(C8,'RJ ATTENDENCE SHEET'!$C:$L,4,0),"") -> 2000 | F8: =IFERROR(VLOOKUP(C8,'RJ ATTENDENCE SHEET'!$C:$L,5,0),"") -> 1440 | G8: =SUM(D8:F8) -> 14000 | H8: =DAY(EOMONTH('RJ ATTENDENCE SHEET'!$A$1,0)) -> 31 | I8: =IFERROR(VLOOKUP(C8,'RJ ATTENDENCE SHEET'!$C:$W,20,0),"") -> 31 | J8: =IFERROR(G8/H8*I8,"") -> 14000 | K8: =IFERROR(VLOOKUP(C8,'SALARY ESI (P)'!$C:$T,13,0),"") -> 1267 | L8: =IFERROR(VLOOKUP(C8,'SALARY ESI (P)'!$C:$T,14,0),"") -> 105 | M8: =IFERROR(VLOOKUP(C8,'SALARY ESI (P)'!$C:$T,15,0),"") -> 110 | N8: =IFERROR(VLOOKUP(C8,'RJ ATTENDENCE SHEET'!$C:$S,17,0),"") -> 0 | O8: =SUM(K8:N8) -> 1482 | P8: =IFERROR(J8-O8,"") -> 12518
A9: 6 | B9: =IFERROR(VLOOKUP(C9,'RJ ATTENDENCE SHEET'!$C:$D,2,0),"") -> TC 0260 | C9: ='DATA '!H8 -> DIBAKAR MONDAL | D9: =IFERROR(VLOOKUP(C9,'RJ ATTENDENCE SHEET'!$C:$L,3,0),"") -> 10560 | E9: =IFERROR(VLOOKUP(C9,'RJ ATTENDENCE SHEET'!$C:$L,4,0),"") -> 4000 | F9: =IFERROR(VLOOKUP(C9,'RJ ATTENDENCE SHEET'!$C:$L,5,0),"") -> 3440 | G9: =SUM(D9:F9) -> 18000 | H9: =DAY(EOMONTH('RJ ATTENDENCE SHEET'!$A$1,0)) -> 31 | I9: =IFERROR(VLOOKUP(C9,'RJ ATTENDENCE SHEET'!$C:$W,20,0),"") -> 31 | J9: =IFERROR(G9/H9*I9,"") -> 18000 | K9: =IFERROR(VLOOKUP(C9,'SALARY ESI (P)'!$C:$T,13,0),"") -> 1267 | L9: =IFERROR(VLOOKUP(C9,'SALARY ESI (P)'!$C:$T,14,0),"") -> 135 | M9: =IFERROR(VLOOKUP(C9,'SALARY ESI (P)'!$C:$T,15,0),"") -> 130 | N9: =IFERROR(VLOOKUP(C9,'RJ ATTENDENCE SHEET'!$C:$S,17,0),"") -> 0 | O9: =SUM(K9:N9) -> 1532 | P9: =IFERROR(J9-O9,"") -> 16468
A10: 7 | B10: =IFERROR(VLOOKUP(C10,'RJ ATTENDENCE SHEET'!$C:$D,2,0),"") -> TC 0122 | C10: ='DATA '!H9 -> GOLAM SARWAR | D10: =IFERROR(VLOOKUP(C10,'RJ ATTENDENCE SHEET'!$C:$L,3,0),"") -> 26000 | E10: =IFERROR(VLOOKUP(C10,'RJ ATTENDENCE SHEET'!$C:$L,4,0),"") -> 0 | F10: =IFERROR(VLOOKUP(C10,'RJ ATTENDENCE SHEET'!$C:$L,5,0),"") -> 0 | G10: =SUM(D10:F10) -> 26000 | H10: =DAY(EOMONTH('RJ ATTENDENCE SHEET'!$A$1,0)) -> 31 | I10: =IFERROR(VLOOKUP(C10,'RJ ATTENDENCE SHEET'!$C:$W,20,0),"") -> 31 | J10: =IFERROR(G10/H10*I10,"") -> 26000 | K10: =IFERROR(VLOOKUP(C10,'SALARY ESI (P)'!$C:$T,13,0),"") -> 0 | L10: =IFERROR(VLOOKUP(C10,'SALARY ESI (P)'!$C:$T,14,0),"") -> 0 | M10: =IFERROR(VLOOKUP(C10,'SALARY ESI (P)'!$C:$T,15,0),"") -> 150 | N10: =IFERROR(VLOOKUP(C10,'RJ ATTENDENCE SHEET'!$C:$S,17,0),"") -> 0 | O10: =SUM(K10:N10) -> 150 | P10: =IFERROR(J10-O10,"") -> 25850
A11: 8 | B11: =IFERROR(VLOOKUP(C11,'RJ ATTENDENCE SHEET'!$C:$D,2,0),"") -> TC 0205 | C11: ='DATA '!H10 -> IMAN ALI MOLLA | D11: =IFERROR(VLOOKUP(C11,'RJ ATTENDENCE SHEET'!$C:$L,3,0),"") -> 10560 | E11: =IFERROR(VLOOKUP(C11,'RJ ATTENDENCE SHEET'!$C:$L,4,0),"") -> 4000 | F11: =IFERROR(VLOOKUP(C11,'RJ ATTENDENCE SHEET'!$C:$L,5,0),"") -> 2440 | G11: =SUM(D11:F11) -> 17000 | H11: =DAY(EOMONTH('RJ ATTENDENCE SHEET'!$A$1,0)) -> 31 | I11: =IFERROR(VLOOKUP(C11,'RJ ATTENDENCE SHEET'!$C:$W,20,0),"") -> 31 | J11: =IFERROR(G11/H11*I11,"") -> 17000 | K11: =IFERROR(VLOOKUP(C11,'SALARY ESI (P)'!$C:$T,13,0),"") -> 1267 | L11: =IFERROR(VLOOKUP(C11,'SALARY ESI (P)'!$C:$T,14,0),"") -> 128 | M11: =IFERROR(VLOOKUP(C11,'SALARY ESI (P)'!$C:$T,15,0),"") -> 130 | N11: =IFERROR(VLOOKUP(C11,'RJ ATTENDENCE SHEET'!$C:$S,17,0),"") -> 0 | O11: =SUM(K11:N11) -> 1525 | P11: =IFERROR(J11-O11,"") -> 15475
A12: 9 | B12: =IFERROR(VLOOKUP(C12,'RJ ATTENDENCE SHEET'!$C:$D,2,0),"") -> TC 0024 | C12: ='DATA '!H11 -> PULIN MONDAL | D12: =IFERROR(VLOOKUP(C12,'RJ ATTENDENCE SHEET'!$C:$L,3,0),"") -> 10560 | E12: =IFERROR(VLOOKUP(C12,'RJ ATTENDENCE SHEET'!$C:$L,4,0),"") -> 500 | F12: =IFERROR(VLOOKUP(C12,'RJ ATTENDENCE SHEET'!$C:$L,5,0),"") -> 440 | G12: =SUM(D12:F12) -> 11500 | H12: =DAY(EOMONTH('RJ ATTENDENCE SHEET'!$A$1,0)) -> 31 | I12: =IFERROR(VLOOKUP(C12,'RJ ATTENDENCE SHEET'!$C:$W,20,0),"") -> 31 | J12: =IFERROR(G12/H12*I12,"") -> 11500 | K12: =IFERROR(VLOOKUP(C12,'SALARY ESI (P)'!$C:$T,13,0),"") -> 1267 | L12: =IFERROR(VLOOKUP(C12,'SALARY ESI (P)'!$C:$T,14,0),"") -> 87 | M12: =IFERROR(VLOOKUP(C12,'SALARY ESI (P)'!$C:$T,15,0),"") -> 110 | N12: =IFERROR(VLOOKUP(C12,'RJ ATTENDENCE SHEET'!$C:$S,17,0),"") -> 0 | O12: =SUM(K12:N12) -> 1464 | P12: =IFERROR(J12-O12,"") -> 10036
A13: 10 | B13: =IFERROR(VLOOKUP(C13,'RJ ATTENDENCE SHEET'!$C:$D,2,0),"") -> TC 0040 | C13: ='DATA '!H12 -> RAJU PAL | D13: =IFERROR(VLOOKUP(C13,'RJ ATTENDENCE SHEET'!$C:$L,3,0),"") -> 11620 | E13: =IFERROR(VLOOKUP(C13,'RJ ATTENDENCE SHEET'!$C:$L,4,0),"") -> 5000 | F13: =IFERROR(VLOOKUP(C13,'RJ ATTENDENCE SHEET'!$C:$L,5,0),"") -> 3380 | G13: =SUM(D13:F13) -> 20000 | H13: =DAY(EOMONTH('RJ ATTENDENCE SHEET'!$A$1,0)) -> 31 | I13: =IFERROR(VLOOKUP(C13,'RJ ATTENDENCE SHEET'!$C:$W,20,0),"") -> 31 | J13: =IFERROR(G13/H13*I13,"") -> 20000 | K13: =IFERROR(VLOOKUP(C13,'SALARY ESI (P)'!$C:$T,13,0),"") -> 1394 | L13: =IFERROR(VLOOKUP(C13,'SALARY ESI (P)'!$C:$T,14,0),"") -> 150 | M13: =IFERROR(VLOOKUP(C13,'SALARY ESI (P)'!$C:$T,15,0),"") -> 130 | N13: =IFERROR(VLOOKUP(C13,'RJ ATTENDENCE SHEET'!$C:$S,17,0),"") -> 0 | O13: =SUM(K13:N13) -> 1674 | P13: =IFERROR(J13-O13,"") -> 18326
A14: 11 | B14: =IFERROR(VLOOKUP(C14,'RJ ATTENDENCE SHEET'!$C:$D,2,0),"") -> TC 0032 | C14: ='DATA '!H13 -> UJJAL MUKHERJEE | D14: =IFERROR(VLOOKUP(C14,'RJ ATTENDENCE SHEET'!$C:$L,3,0),"") -> 10560 | E14: =IFERROR(VLOOKUP(C14,'RJ ATTENDENCE SHEET'!$C:$L,4,0),"") -> 5000 | F14: =IFERROR(VLOOKUP(C14,'RJ ATTENDENCE SHEET'!$C:$L,5,0),"") -> 4440 | G14: =SUM(D14:F14) -> 20000 | H14: =DAY(EOMONTH('RJ ATTENDENCE SHEET'!$A$1,0)) -> 31 | I14: =IFERROR(VLOOKUP(C14,'RJ ATTENDENCE SHEET'!$C:$W,20,0),"") -> 31 | J14: =IFERROR(G14/H14*I14,"") -> 20000 | K14: =IFERROR(VLOOKUP(C14,'SALARY ESI (P)'!$C:$T,13,0),"") -> 1267 | L14: =IFERROR(VLOOKUP(C14,'SALARY ESI (P)'!$C:$T,14,0),"") -> 150 | M14: =IFERROR(VLOOKUP(C14,'SALARY ESI (P)'!$C:$T,15,0),"") -> 130 | N14: =IFERROR(VLOOKUP(C14,'RJ ATTENDENCE SHEET'!$C:$S,17,0),"") -> 0 | O14: =SUM(K14:N14) -> 1547 | P14: =IFERROR(J14-O14,"") -> 18453
A15: 12 | B15: =IFERROR(VLOOKUP(C15,'RJ ATTENDENCE SHEET'!$C:$D,2,0),"") -> TC0271 | C15: ='DATA '!H14 -> PROBIR GHOSH | D15: =IFERROR(VLOOKUP(C15,'RJ ATTENDENCE SHEET'!$C:$L,3,0),"") -> 10560 | E15: =IFERROR(VLOOKUP(C15,'RJ ATTENDENCE SHEET'!$C:$L,4,0),"") -> 3940 | F15: =IFERROR(VLOOKUP(C15,'RJ ATTENDENCE SHEET'!$C:$L,5,0),"") -> 2000 | G15: =SUM(D15:F15) -> 16500 | H15: =DAY(EOMONTH('RJ ATTENDENCE SHEET'!$A$1,0)) -> 31 | I15: =IFERROR(VLOOKUP(C15,'RJ ATTENDENCE SHEET'!$C:$W,20,0),"") -> 31 | J15: =IFERROR(G15/H15*I15,"") -> 16500 | K15: =IFERROR(VLOOKUP(C15,'SALARY ESI (P)'!$C:$T,13,0),"") -> 1267 | L15: =IFERROR(VLOOKUP(C15,'SALARY ESI (P)'!$C:$T,14,0),"") -> 124 | M15: =IFERROR(VLOOKUP(C15,'SALARY ESI (P)'!$C:$T,15,0),"") -> 130 | N15: =IFERROR(VLOOKUP(C15,'RJ ATTENDENCE SHEET'!$C:$S,17,0),"") -> 0 | O15: =SUM(K15:N15) -> 1521 | P15: =IFERROR(J15-O15,"") -> 14979
... A38: 35 | B38: =IFERROR(VLOOKUP(C38,'RJ ATTENDENCE SHEET'!$C:$D,2,0),"") | C38: ='DATA '!H37 | D38: =IFERROR(VLOOKUP(C38,'RJ ATTENDENCE SHEET'!$C:$L,3,0),"") | E38: =IFERROR(VLOOKUP(C38,'RJ ATTENDENCE SHEET'!$C:$L,4,0),"") | F38: =IFERROR(VLOOKUP(C38,'RJ ATTENDENCE SHEET'!$C:$L,5,0),"") | G38: =SUM(D38:F38) -> 0 | H38: =DAY(EOMONTH('RJ ATTENDENCE SHEET'!$A$1,0)) -> 31 | I38: =IFERROR(VLOOKUP(C38,'RJ ATTENDENCE SHEET'!$C:$W,20,0),"") | J38: =IFERROR(G38/H38*I38,"") | K38: =IFERROR(VLOOKUP(C38,'SALARY ESI (P)'!$C:$T,13,0),"") -> 0 | L38: =IFERROR(VLOOKUP(C38,'SALARY ESI (P)'!$C:$T,14,0),"") -> 0 | M38: =IFERROR(VLOOKUP(C38,'SALARY ESI (P)'!$C:$T,15,0),"") -> 0 | N38: =IFERROR(VLOOKUP(C38,'RJ ATTENDENCE SHEET'!$C:$S,17,0),"") | O38: =SUM(K38:N38) -> 0 | P38: =IFERROR(J38-O38,"")
A39: TOTAL | D39: =SUM(D4:D38) -> 242180 | E39: =SUM(E4:E38) -> 59380 | F39: =SUM(F4:F38) -> 41440 | G39: =SUM(G4:G38) -> 343000 | J39: =SUM(J4:J38) -> 339306.45 | K39: =SUM(K4:K38) -> 16179 | L39: =SUM(L4:L38) -> 1149 | M39: =SUM(M4:M38) -> 2100 | N39: =SUM(N4:N38) -> 0 | O39: =SUM(O4:O38) -> 19428 | P39: =SUM(P4:P38) -> 319878.45

Sheet WAGES
A1: WAGES WAGES REGISTER FOR THE MONTH OF | M1: =TEXT('RJ ATTENDENCE SHEET'!$A$1,"MMMM") -> July | O1: =YEAR('RJ ATTENDENCE SHEET'!$A$1) -> 2026
A2: SL. NO. | C2: NAME | D2: RATE | H2: DAYS WORK | J2: AMOUNT | L2: GROSS AMT. | M2: ADV. | N2: NET | O2: SIGNATURE
D3: MONTHLY | E3: DAILY | F3: DUTY | G3: TRIP | H3: DUTY | I3: TRIP | J3: DUTY AMNT. | K3: TRIP AMNT. | N3: AMT.
A4: 1 | B4: =VLOOKUP(C4,'DATA '!$K:$L,2,0) -> DRIVER | C4: ='DATA '!K3 -> ANISUR | D4: =IF(B4="DRIVER","",IF(B4="HELPER","",IF(B4="HOPPER",VLOOKUP(WAGES!C4,'RJ ATTENDENCE SHEET'!$C:$I,7,0),IF(B4="LAB",VLOOKUP(WAGES!C4,'RJ ATTENDENCE SHEET'!$C:$I,7,0),IF(B4="OTHERS",VLOOKUP(WAGES!C4,'RJ ATTENDENCE SHEET'!$C:$I,7,0),""))))) | E4: =IFERROR(D4/DAY(EOMONTH('RJ ATTENDENCE SHEET'!$A$1,0)),"") | F4: =IF(B4="DRIVER",VLOOKUP(WAGES!C4,'RJ ATTENDENCE SHEET'!$C:$W,8,0),IF(B4="HELPER",VLOOKUP(WAGES!C4,'RJ ATTENDENCE SHEET'!$C:$W,8,0),IF(B4="HOPPER","",IF(B4="LAB","",IF(B4="OTHERS","",""))))) -> 325 | G4: =IF(B4="DRIVER",VLOOKUP(WAGES!C4,'RJ ATTENDENCE SHEET'!$C:$W,9,0),IF(B4="HELPER",VLOOKUP(WAGES!C4,'RJ ATTENDENCE SHEET'!$C:$W,9,0),IF(B4="HOPPER","",IF(B4="LAB","",IF(B4="OTHERS","",""))))) -> 185 | H4: =IFERROR(VLOOKUP(C4,'RJ ATTENDENCE SHEET'!$C:$V,20,0),"") -> 40 | I4: =IFERROR(VLOOKUP(C4,'RJ ATTENDENCE SHEET'!$C:$W,21,0),"") -> 13 | J4: =IFERROR(F4*H4,"") -> 13000 | K4: =IFERROR(G4*I4,"") -> 2405 | L4: =IF(B4="DRIVER",(J4+K4),IF(B4="HELPER",(J4+K4),IF(B4="HOPPER",(E4*H4),IF(B4="LAB",(E4*H4),IF(B4="OTHERS",(E4*H4),""))))) -> 15405 | M4: =IFERROR(VLOOKUP(C4,'RJ ATTENDENCE SHEET'!$C:$S,17,0),"") -> 0 | N4: =IFERROR(L4-M4,"") -> 15405
A5: 2 | B5: =VLOOKUP(C5,'DATA '!$K:$L,2,0) -> DRIVER | C5: ='DATA '!K4 -> ARMAN ALI MONDAL | D5: =IF(B5="DRIVER","",IF(B5="HELPER","",IF(B5="HOPPER",VLOOKUP(WAGES!C5,'RJ ATTENDENCE SHEET'!$C:$I,7,0),IF(B5="LAB",VLOOKUP(WAGES!C5,'RJ ATTENDENCE SHEET'!$C:$I,7,0),IF(B5="OTHERS",VLOOKUP(WAGES!C5,'RJ ATTENDENCE SHEET'!$C:$I,7,0),""))))) | E5: =IFERROR(D5/DAY(EOMONTH('RJ ATTENDENCE SHEET'!$A$1,0)),"") | F5: =IF(B5="DRIVER",VLOOKUP(WAGES!C5,'RJ ATTENDENCE SHEET'!$C:$W,8,0),IF(B5="HELPER",VLOOKUP(WAGES!C5,'RJ ATTENDENCE SHEET'!$C:$W,8,0),IF(B5="HOPPER","",IF(B5="LAB","",IF(B5="OTHERS","",""))))) -> 320 | G5: =IF(B5="DRIVER",VLOOKUP(WAGES!C5,'RJ ATTENDENCE SHEET'!$C:$W,9,0),IF(B5="HELPER",VLOOKUP(WAGES!C5,'RJ ATTENDENCE SHEET'!$C:$W,9,0),IF(B5="HOPPER","",IF(B5="LAB","",IF(B5="OTHERS","",""))))) -> 185 | H5: =IFERROR(VLOOKUP(C5,'RJ ATTENDENCE SHEET'!$C:$V,20,0),"") -> 41 | I5: =IFERROR(VLOOKUP(C5,'RJ ATTENDENCE SHEET'!$C:$W,21,0),"") -> 8 | J5: =IFERROR(F5*H5,"") -> 13120 | K5: =IFERROR(G5*I5,"") -> 1480 | L5: =IF(B5="DRIVER",(J5+K5),IF(B5="HELPER",(J5+K5),IF(B5="HOPPER",(E5*H5),IF(B5="LAB",(E5*H5),IF(B5="OTHERS",(E5*H5),""))))) -> 14600 | M5: =IFERROR(VLOOKUP(C5,'RJ ATTENDENCE SHEET'!$C:$S,17,0),"") -> 0 | N5: =IFERROR(L5-M5,"") -> 14600
A6: 3 | B6: =VLOOKUP(C6,'DATA '!$K:$L,2,0) -> HELPER | C6: ='DATA '!K5 -> ASUTOSH SARDAR | D6: =IF(B6="DRIVER","",IF(B6="HELPER","",IF(B6="HOPPER",VLOOKUP(WAGES!C6,'RJ ATTENDENCE SHEET'!$C:$I,7,0),IF(B6="LAB",VLOOKUP(WAGES!C6,'RJ ATTENDENCE SHEET'!$C:$I,7,0),IF(B6="OTHERS",VLOOKUP(WAGES!C6,'RJ ATTENDENCE SHEET'!$C:$I,7,0),""))))) | E6: =IFERROR(D6/DAY(EOMONTH('RJ ATTENDENCE SHEET'!$A$1,0)),"") | F6: =IF(B6="DRIVER",VLOOKUP(WAGES!C6,'RJ ATTENDENCE SHEET'!$C:$W,8,0),IF(B6="HELPER",VLOOKUP(WAGES!C6,'RJ ATTENDENCE SHEET'!$C:$W,8,0),IF(B6="HOPPER","",IF(B6="LAB","",IF(B6="OTHERS","",""))))) -> 285 | G6: =IF(B6="DRIVER",VLOOKUP(WAGES!C6,'RJ ATTENDENCE SHEET'!$C:$W,9,0),IF(B6="HELPER",VLOOKUP(WAGES!C6,'RJ ATTENDENCE SHEET'!$C:$W,9,0),IF(B6="HOPPER","",IF(B6="LAB","",IF(B6="OTHERS","",""))))) -> 80 | H6: =IFERROR(VLOOKUP(C6,'RJ ATTENDENCE SHEET'!$C:$V,20,0),"") -> 40 | I6: =IFERROR(VLOOKUP(C6,'RJ ATTENDENCE SHEET'!$C:$W,21,0),"") -> 8 | J6: =IFERROR(F6*H6,"") -> 11400 | K6: =IFERROR(G6*I6,"") -> 640 | L6: =IF(B6="DRIVER",(J6+K6),IF(B6="HELPER",(J6+K6),IF(B6="HOPPER",(E6*H6),IF(B6="LAB",(E6*H6),IF(B6="OTHERS",(E6*H6),""))))) -> 12040 | M6: =IFERROR(VLOOKUP(C6,'RJ ATTENDENCE SHEET'!$C:$S,17,0),"") -> 0 | N6: =IFERROR(L6-M6,"") -> 12040
A7: 4 | B7: =VLOOKUP(C7,'DATA '!$K:$L,2,0) -> LAB | C7: ='DATA '!K6 -> BUDDHADEV SEAL | D7: =IF(B7="DRIVER","",IF(B7="HELPER","",IF(B7="HOPPER",VLOOKUP(WAGES!C7,'RJ ATTENDENCE SHEET'!$C:$I,7,0),IF(B7="LAB",VLOOKUP(WAGES!C7,'RJ ATTENDENCE SHEET'!$C:$I,7,0),IF(B7="OTHERS",VLOOKUP(WAGES!C7,'RJ ATTENDENCE SHEET'!$C:$I,7,0),""))))) -> 15225 | E7: =IFERROR(D7/DAY(EOMONTH('RJ ATTENDENCE SHEET'!$A$1,0)),"") -> 491.12903 | F7: =IF(B7="DRIVER",VLOOKUP(WAGES!C7,'RJ ATTENDENCE SHEET'!$C:$W,8,0),IF(B7="HELPER",VLOOKUP(WAGES!C7,'RJ ATTENDENCE SHEET'!$C:$W,8,0),IF(B7="HOPPER","",IF(B7="LAB","",IF(B7="OTHERS","",""))))) | G7: =IF(B7="DRIVER",VLOOKUP(WAGES!C7,'RJ ATTENDENCE SHEET'!$C:$W,9,0),IF(B7="HELPER",VLOOKUP(WAGES!C7,'RJ ATTENDENCE SHEET'!$C:$W,9,0),IF(B7="HOPPER","",IF(B7="LAB","",IF(B7="OTHERS","",""))))) | H7: =IFERROR(VLOOKUP(C7,'RJ ATTENDENCE SHEET'!$C:$V,20,0),"") -> 34 | I7: =IFERROR(VLOOKUP(C7,'RJ ATTENDENCE SHEET'!$C:$W,21,0),"") -> 0 | J7: =IFERROR(F7*H7,"") | K7: =IFERROR(G7*I7,"") | L7: =IF(B7="DRIVER",(J7+K7),IF(B7="HELPER",(J7+K7),IF(B7="HOPPER",(E7*H7),IF(B7="LAB",(E7*H7),IF(B7="OTHERS",(E7*H7),""))))) -> 16698.387 | M7: =IFERROR(VLOOKUP(C7,'RJ ATTENDENCE SHEET'!$C:$S,17,0),"") -> 0 | N7: =IFERROR(L7-M7,"") -> 16698.387
A8: 5 | B8: =VLOOKUP(C8,'DATA '!$K:$L,2,0) -> DRIVER | C8: ='DATA '!K7 -> FARUK ALI | D8: =IF(B8="DRIVER","",IF(B8="HELPER","",IF(B8="HOPPER",VLOOKUP(WAGES!C8,'RJ ATTENDENCE SHEET'!$C:$I,7,0),IF(B8="LAB",VLOOKUP(WAGES!C8,'RJ ATTENDENCE SHEET'!$C:$I,7,0),IF(B8="OTHERS",VLOOKUP(WAGES!C8,'RJ ATTENDENCE SHEET'!$C:$I,7,0),""))))) | E8: =IFERROR(D8/DAY(EOMONTH('RJ ATTENDENCE SHEET'!$A$1,0)),"") | F8: =IF(B8="DRIVER",VLOOKUP(WAGES!C8,'RJ ATTENDENCE SHEET'!$C:$W,8,0),IF(B8="HELPER",VLOOKUP(WAGES!C8,'RJ ATTENDENCE SHEET'!$C:$W,8,0),IF(B8="HOPPER","",IF(B8="LAB","",IF(B8="OTHERS","",""))))) -> 300 | G8: =IF(B8="DRIVER",VLOOKUP(WAGES!C8,'RJ ATTENDENCE SHEET'!$C:$W,9,0),IF(B8="HELPER",VLOOKUP(WAGES!C8,'RJ ATTENDENCE SHEET'!$C:$W,9,0),IF(B8="HOPPER","",IF(B8="LAB","",IF(B8="OTHERS","",""))))) -> 185 | H8: =IFERROR(VLOOKUP(C8,'RJ ATTENDENCE SHEET'!$C:$V,20,0),"") -> 41 | I8: =IFERROR(VLOOKUP(C8,'RJ ATTENDENCE SHEET'!$C:$W,21,0),"") -> 12 | J8: =IFERROR(F8*H8,"") -> 12300 | K8: =IFERROR(G8*I8,"") -> 2220 | L8: =IF(B8="DRIVER",(J8+K8),IF(B8="HELPER",(J8+K8),IF(B8="HOPPER",(E8*H8),IF(B8="LAB",(E8*H8),IF(B8="OTHERS",(E8*H8),""))))) -> 14520 | M8: =IFERROR(VLOOKUP(C8,'RJ ATTENDENCE SHEET'!$C:$S,17,0),"") -> 0 | N8: =IFERROR(L8-M8,"") -> 14520
A9: 6 | B9: =VLOOKUP(C9,'DATA '!$K:$L,2,0) -> HOPPER | C9: ='DATA '!K8 -> KUTUBUDDIN MOLLA | D9: =IF(B9="DRIVER","",IF(B9="HELPER","",IF(B9="HOPPER",VLOOKUP(WAGES!C9,'RJ ATTENDENCE SHEET'!$C:$I,7,0),IF(B9="LAB",VLOOKUP(WAGES!C9,'RJ ATTENDENCE SHEET'!$C:$I,7,0),IF(B9="OTHERS",VLOOKUP(WAGES!C9,'RJ ATTENDENCE SHEET'!$C:$I,7,0),""))))) -> 15000 | E9: =IFERROR(D9/DAY(EOMONTH('RJ ATTENDENCE SHEET'!$A$1,0)),"") -> 483.87097 | F9: =IF(B9="DRIVER",VLOOKUP(WAGES!C9,'RJ ATTENDENCE SHEET'!$C:$W,8,0),IF(B9="HELPER",VLOOKUP(WAGES!C9,'RJ ATTENDENCE SHEET'!$C:$W,8,0),IF(B9="HOPPER","",IF(B9="LAB","",IF(B9="OTHERS","",""))))) | G9: =IF(B9="DRIVER",VLOOKUP(WAGES!C9,'RJ ATTENDENCE SHEET'!$C:$W,9,0),IF(B9="HELPER",VLOOKUP(WAGES!C9,'RJ ATTENDENCE SHEET'!$C:$W,9,0),IF(B9="HOPPER","",IF(B9="LAB","",IF(B9="OTHERS","",""))))) | H9: =IFERROR(VLOOKUP(C9,'RJ ATTENDENCE SHEET'!$C:$V,20,0),"") -> 34 | I9: =IFERROR(VLOOKUP(C9,'RJ ATTENDENCE SHEET'!$C:$W,21,0),"") -> 0 | J9: =IFERROR(F9*H9,"") | K9: =IFERROR(G9*I9,"") | L9: =IF(B9="DRIVER",(J9+K9),IF(B9="HELPER",(J9+K9),IF(B9="HOPPER",(E9*H9),IF(B9="LAB",(E9*H9),IF(B9="OTHERS",(E9*H9),""))))) -> 16451.613 | M9: =IFERROR(VLOOKUP(C9,'RJ ATTENDENCE SHEET'!$C:$S,17,0),"") -> 0 | N9: =IFERROR(L9-M9,"") -> 16451.613
